Workbook
Name 物料编码: [1]产品信息!$A$3:$A$5000

Sheet 利润分析表
A1: 2026年6月广西利润分析表
A2: 附件表位置：
A3: 序号 | B3: 车牌 | D3: 负责人 | E3: 项目 | F3: 挂板车牌 | G3: 车型 | H3: 车辆趟数 | I3: 吨位 | J3: 运费产值收入 | M3: 油/电费实际金额 | N3: 油/电费占收入比% | P3: 司机工资 （提成+保底） | Q3: 司机工资占收入比% | R3: 车辆费 | AF3: 管理人员工资 | AH3: 均摊费元 | AJ3: 总车辆费用 合计 | AK3: 车贷 | AL3: 毛利 | AM3: 毛利率 | AN3: 挂板租金 | AO3: 保险费 | AP3: 毛利-租金-保险费=利润
C4: 司机 | K4: 货物险 | L4: 磅差金额 | O4: 单趟电耗 | R4: 维修费 | S4: 维修费占收入比% | T4: 配件 | U4: 配件费占收入比% | V4: 前期费用 | W4: 前期费用占收入比% | X4: 车辆费用 | Y4: 车辆费用占收入比% | Z4: 轮胎 | AA4: 轮胎费占收入比% | AB4: 罚款 | AC4: 罚款占收入比% | AD4: 税点 | AE4: 税点占收入比% | AG4: 管理人员工资占比 | AI4: 均摊占比
A5: 1 | B5: 赣J01379D | C5: 沈正元 | D5: 杨发明 | E5: 广西-玉溪 | F5: 桂LD735挂 | G5: 重型半挂牵引车 | H5: =COUNTIFS(磅单!E:E,B5) -> 1 | I5: =SUMIFS(磅单!L:L,磅单!E:E,B5) -> 41.74 | J5: =SUMIFS(磅单!O:O,磅单!E:E,B5) -> 2546.14 | K5: =SUMIFS(月汇总!Y:Y,月汇总!B:B,B5) -> 15 | L5: =SUMIFS(月汇总!I:I,月汇总!B:B,B5,月汇总!C:C,F5) -> 0 | M5: =SUMIFS(月汇总!J:J,月汇总!B:B,B5,月汇总!C:C,F5) -> 1091.9085 | N5: =M5/J5 -> 0.42884857 | O5: =M5/H5 -> 1091.9085 | P5: =SUMIFS(月汇总!R:R,月汇总!B:B,B5)+SUMIFS(月汇总!S:S,月汇总!B:B,B5) -> 600 | Q5: =P5/J5 -> 0.23565083 | R5: =SUMIFS(月汇总!Q:Q,月汇总!B:B,B5) -> 12500 | S5: =R5/J5 -> 4.9093923 | T5: =SUMIFS(月汇总!N:N,月汇总!B:B,B5) -> 220.88197 | V5: =SUMIFS(月汇总!X:X,月汇总!B:B,B5) -> 0 | W5: =V5/J5 -> 0 | X5: =SUMIFS(月汇总!U:U,月汇总!B:B,B5) -> 0 | Y5: =X5/J5 -> 0 | Z5: =SUMIFS(月汇总!O:O,月汇总!B:B,B5) -> 0 | AA5: =Z5/J5 -> 0 | AB5: =SUMIFS(月汇总!T:T,月汇总!B:B,B5) -> 0 | AC5: =AB5/J5 -> 0 | AD5: =SUMIFS(月汇总!Z:Z,月汇总!B:B,B5) -> 178.2298 | AE5: =AD5/J5 -> 0.07 | AF5: =SUMIFS(月汇总!AC:AC,月汇总!B:B,B5) -> 790.16393 | AG5: =AF5/J5 -> 0.31033798 | AH5: =SUMIFS(月汇总!V:V,月汇总!B:B,B5) -> 397.39246 | AI5: =AH5/J5 -> 0.15607644 | AJ5: =M5+P5+R5+T5+V5+X5+Z5+AB5+AD5+AF5+AH5 -> 15778.577 | AK5: =SUMIFS(月汇总!AA:AA,月汇总!B:B,B5) -> 10600 | AL5: =J5-K5-L5-AJ5-AK5 -> -23847.437 | AM5: =AL5/J5 -> -9.3661137 | AN5: =SUMIFS(月汇总!AB:AB,月汇总!B:B,B5) -> 3800 | AO5: =SUMIFS(月汇总!W:W,月汇总!B:B,B5) -> 2666 | AP5: =AL5-AN5-AO5 -> -30313.437
A6: 2 | B6: 赣J00236D | C6: 熊廷春 | D6: 杨发明 | E6: 广西-玉溪 | F6: 桂LA725挂 | G6: 重型半挂牵引车 | H6: =COUNTIFS(磅单!E:E,B6) -> 19 | I6: =SUMIFS(磅单!L:L,磅单!E:E,B6) -> 805.2 | J6: =SUMIFS(磅单!O:O,磅单!E:E,B6) -> 50229.42 | K6: =SUMIFS(月汇总!Y:Y,月汇总!B:B,B6) -> 285 | L6: =SUMIFS(月汇总!I:I,月汇总!B:B,B6,月汇总!C:C,F6) -> 0 | M6: =SUMIFS(月汇总!J:J,月汇总!B:B,B6,月汇总!C:C,F6) -> 16063.773 | N6: =M6/J6 -> 0.31980805 | O6: =M6/H6 -> 845.46174 | P6: =SUMIFS(月汇总!R:R,月汇总!B:B,B6)+SUMIFS(月汇总!S:S,月汇总!B:B,B6) -> 11800 | Q6: =P6/J6 -> 0.23492208 | R6: =SUMIFS(月汇总!Q:Q,月汇总!B:B,B6) -> 510 | S6: =R6/J6 -> 0.010153412 | T6: =SUMIFS(月汇总!N:N,月汇总!B:B,B6) -> 220.88197 | V6: =SUMIFS(月汇总!X:X,月汇总!B:B,B6) -> 0 | W6: =V6/J6 -> 0 | X6: =SUMIFS(月汇总!U:U,月汇总!B:B,B6) -> 467 | Y6: =X6/J6 -> 0.0092973401 | Z6: =SUMIFS(月汇总!O:O,月汇总!B:B,B6) -> 0 | AA6: =Z6/J6 -> 0 | AB6: =SUMIFS(月汇总!T:T,月汇总!B:B,B6) -> 120 | AC6: =AB6/J6 -> 0.0023890381 | AD6: =SUMIFS(月汇总!Z:Z,月汇总!B:B,B6) -> 3516.0594 | AE6: =AD6/J6 -> 0.07 | AF6: =SUMIFS(月汇总!AC:AC,月汇总!B:B,B6) -> 790.16393 | AG6: =AF6/J6 -> 0.015731098 | AH6: =SUMIFS(月汇总!V:V,月汇总!B:B,B6) -> 397.39246 | AI6: =AH6/J6 -> 0.0079115478 | AJ6: =M6+P6+R6+T6+V6+X6+Z6+AB6+AD6+AF6+AH6 -> 33885.271 | AK6: =SUMIFS(月汇总!AA:AA,月汇总!B:B,B6) -> 10600 | AL6: =J6-K6-L6-AJ6-AK6 -> 5459.1492 | AM6: =AL6/J6 -> 0.1086843 | AN6: =SUMIFS(月汇总!AB:AB,月汇总!B:B,B6) -> 3800 | AO6: =SUMIFS(月汇总!W:W,月汇总!B:B,B6) -> 2666 | AP6: =AL6-AN6-AO6 -> -1006.8508
A7: 3 | B7: 赣J05550D | C7: 任正勇 | D7: 杨发明 | E7: 广西-玉溪 | F7: 桂LD517挂 | G7: 重型半挂牵引车 | H7: =COUNTIFS(磅单!E:E,B7) -> 21 | I7: =SUMIFS(磅单!L:L,磅单!E:E,B7) -> 893.18 | J7: =SUMIFS(磅单!O:O,磅单!E:E,B7) -> 55301.38 | K7: =SUMIFS(月汇总!Y:Y,月汇总!B:B,B7) -> 315 | L7: =SUMIFS(月汇总!I:I,月汇总!B:B,B7,月汇总!C:C,F7) -> 0 | M7: =SUMIFS(月汇总!J:J,月汇总!B:B,B7,月汇总!C:C,F7) -> 17389.021 | N7: =M7/J7 -> 0.31444099 | O7: =M7/H7 -> 828.0486 | P7: =SUMIFS(月汇总!R:R,月汇总!B:B,B7)+SUMIFS(月汇总!S:S,月汇总!B:B,B7) -> 13200 | Q7: =P7/J7 -> 0.23869205 | R7: =SUMIFS(月汇总!Q:Q,月汇总!B:B,B7) -> 800 | S7: =R7/J7 -> 0.014466185 | T7: =SUMIFS(月汇总!N:N,月汇总!B:B,B7) -> 220.88197 | V7: =SUMIFS(月汇总!X:X,月汇总!B:B,B7) -> 0 | W7: =V7/J7 -> 0 | X7: =SUMIFS(月汇总!U:U,月汇总!B:B,B7) -> 544 | Y7: =X7/J7 -> 0.0098370059 | Z7: =SUMIFS(月汇总!O:O,月汇总!B:B,B7) -> 7130 | AA7: =Z7/J7 -> 0.12892987 | AB7: =SUMIFS(月汇总!T:T,月汇总!B:B,B7) -> 400 | AC7: =AB7/J7 -> 0.0072330926 | AD7: =SUMIFS(月汇总!Z:Z,月汇总!B:B,B7) -> 3871.0966 | AE7: =AD7/J7 -> 0.07 | AF7: =SUMIFS(月汇总!AC:AC,月汇总!B:B,B7) -> 790.16393 | AG7: =AF7/J7 -> 0.014288322 | AH7: =SUMIFS(月汇总!V:V,月汇总!B:B,B7) -> 397.39246 | AI7: =AH7/J7 -> 0.0071859411 | AJ7: =M7+P7+R7+T7+V7+X7+Z7+AB7+AD7+AF7+AH7 -> 44742.556 | AK7: =SUMIFS(月汇总!AA:AA,月汇总!B:B,B7) -> 10600 | AL7: =J7-K7-L7-AJ7-AK7 -> -356.17557 | AM7: =AL7/J7 -> -0.0064406272 | AN7: =SUMIFS(月汇总!AB:AB,月汇总!B:B,B7) -> 3800 | AO7: =SUMIFS(月汇总!W:W,月汇总!B:B,B7) -> 2666 | AP7: =AL7-AN7-AO7 -> -6822.1756
A8: 4 | B8: 赣J00607D | C8: 程大昌 | D8: 杨发明 | E8: 广西-玉溪 | F8: 桂LD396挂 | G8: 重型半挂牵引车 | H8: =COUNTIFS(磅单!E:E,B8) -> 19 | I8: =SUMIFS(磅单!L:L,磅单!E:E,B8) -> 782.99 | J8: =SUMIFS(磅单!O:O,磅单!E:E,B8) -> 46796.27 | K8: =SUMIFS(月汇总!Y:Y,月汇总!B:B,B8) -> 285 | L8: =SUMIFS(月汇总!I:I,月汇总!B:B,B8,月汇总!C:C,F8) -> 0 | M8: =SUMIFS(月汇总!J:J,月汇总!B:B,B8,月汇总!C:C,F8) -> 15004.904 | N8: =M8/J8 -> 0.32064315 | O8: =M8/H8 -> 789.73177 | P8: =SUMIFS(月汇总!R:R,月汇总!B:B,B8)+SUMIFS(月汇总!S:S,月汇总!B:B,B8) -> 11600 | Q8: =P8/J8 -> 0.247883 | R8: =SUMIFS(月汇总!Q:Q,月汇总!B:B,B8) -> 1120 | S8: =R8/J8 -> 0.023933531 | T8: =SUMIFS(月汇总!N:N,月汇总!B:B,B8) -> 220.88197 | V8: =SUMIFS(月汇总!X:X,月汇总!B:B,B8) -> 0 | W8: =V8/J8 -> 0 | X8: =SUMIFS(月汇总!U:U,月汇总!B:B,B8) -> 636 | Y8: =X8/J8 -> 0.013590827 | Z8: =SUMIFS(月汇总!O:O,月汇总!B:B,B8) -> 0 | AA8: =Z8/J8 -> 0 | AB8: =SUMIFS(月汇总!T:T,月汇总!B:B,B8) -> 440 | AC8: =AB8/J8 -> 0.0094024588 | AD8: =SUMIFS(月汇总!Z:Z,月汇总!B:B,B8) -> 3275.7389 | AE8: =AD8/J8 -> 0.07 | AF8: =SUMIFS(月汇总!AC:AC,月汇总!B:B,B8) -> 790.16393 | AG8: =AF8/J8 -> 0.016885191 | AH8: =SUMIFS(月汇总!V:V,月汇总!B:B,B8) -> 397.39246 | AI8: =AH8/J8 -> 0.0084919687 | AJ8: =M8+P8+R8+T8+V8+X8+Z8+AB8+AD8+AF8+AH8 -> 33485.081 | AK8: =SUMIFS(月汇总!AA:AA,月汇总!B:B,B8) -> 10600 | AL8: =J8-K8-L8-AJ8-AK8 -> 2426.1892 | AM8: =AL8/J8 -> 0.051845781 | AN8: =SUMIFS(月汇总!AB:AB,月汇总!B:B,B8) -> 3800 | AO8: =SUMIFS(月汇总!W:W,月汇总!B:B,B8) -> 2666 | AP8: =AL8-AN8-AO8 -> -4039.8108
A9: 5 | B9: 赣J00677D | C9: 付建东 | D9: 杨发明 | E9: 广西-玉溪 | F9: 桂LB829挂 | G9: 重型半挂牵引车 | H9: =COUNTIFS(磅单!E:E,B9) -> 20 | I9: =SUMIFS(磅单!L:L,磅单!E:E,B9) -> 820.18 | J9: =SUMIFS(磅单!O:O,磅单!E:E,B9) -> 50875.58 | K9: =SUMIFS(月汇总!Y:Y,月汇总!B:B,B9) -> 300 | L9: =SUMIFS(月汇总!I:I,月汇总!B:B,B9,月汇总!C:C,F9) -> 50 | M9: =SUMIFS(月汇总!J:J,月汇总!B:B,B9,月汇总!C:C,F9) -> 16613.933 | N9: =M9/J9 -> 0.32656006 | O9: =M9/H9 -> 830.69663 | P9: =SUMIFS(月汇总!R:R,月汇总!B:B,B9)+SUMIFS(月汇总!S:S,月汇总!B:B,B9) -> 12200 | Q9: =P9/J9 -> 0.23980071 | R9: =SUMIFS(月汇总!Q:Q,月汇总!B:B,B9) -> 670 | S9: =R9/J9 -> 0.013169383 | T9: =SUMIFS(月汇总!N:N,月汇总!B:B,B9) -> 220.88197 | V9: =SUMIFS(月汇总!X:X,月汇总!B:B,B9) -> 0 | W9: =V9/J9 -> 0 | X9: =SUMIFS(月汇总!U:U,月汇总!B:B,B9) -> 422 | Y9: =X9/J9 -> 0.0082947457 | Z9: =SUMIFS(月汇总!O:O,月汇总!B:B,B9) -> 7130 | AA9: =Z9/J9 -> 0.14014582 | AB9: =SUMIFS(月汇总!T:T,月汇总!B:B,B9) -> 200 | AC9: =AB9/J9 -> 0.0039311591 | AD9: =SUMIFS(月汇总!Z:Z,月汇总!B:B,B9) -> 3561.2906 | AE9: =AD9/J9 -> 0.07 | AF9: =SUMIFS(月汇总!AC:AC,月汇总!B:B,B9) -> 790.16393 | AG9: =AF9/J9 -> 0.015531301 | AH9: =SUMIFS(月汇总!V:V,月汇总!B:B,B9) -> 397.39246 | AI9: =AH9/J9 -> 0.0078110649 | AJ9: =M9+P9+R9+T9+V9+X9+Z9+AB9+AD9+AF9+AH9 -> 42205.661 | AK9: =SUMIFS(月汇总!AA:AA,月汇总!B:B,B9) -> 10600 | AL9: =J9-K9-L9-AJ9-AK9 -> -2280.0815 | AM9: =AL9/J9 -> -0.044816815 | AN9: =SUMIFS(月汇总!AB:AB,月汇总!B:B,B9) -> 3800 | AO9: =SUMIFS(月汇总!W:W,月汇总!B:B,B9) -> 2666 | AP9: =AL9-AN9-AO9 -> -8746.0815
A10: 6 | B10: 赣J01095D | C10: 张和平 | D10: 杨发明 | E10: 广西-玉溪 | F10: 桂LC705挂 | G10: 重型半挂牵引车 | H10: =COUNTIFS(磅单!E:E,B10) -> 19 | I10: =SUMIFS(磅单!L:L,磅单!E:E,B10) -> 769.79 | J10: =SUMIFS(磅单!O:O,磅单!E:E,B10) -> 48095.53 | K10: =SUMIFS(月汇总!Y:Y,月汇总!B:B,B10) -> 285 | L10: =SUMIFS(月汇总!I:I,月汇总!B:B,B10,月汇总!C:C,F10) -> 0 | M10: =SUMIFS(月汇总!J:J,月汇总!B:B,B10,月汇总!C:C,F10) -> 14132.489 | N10: =M10/J10 -> 0.29384204 | O10: =M10/H10 -> 743.81519 | P10: =SUMIFS(月汇总!R:R,月汇总!B:B,B10)+SUMIFS(月汇总!S:S,月汇总!B:B,B10) -> 11800 | Q10: =P10/J10 -> 0.24534505 | R10: =SUMIFS(月汇总!Q:Q,月汇总!B:B,B10) -> 415 | S10: =R10/J10 -> 0.0086286605 | T10: =SUMIFS(月汇总!N:N,月汇总!B:B,B10) -> 220.88197 | V10: =SUMIFS(月汇总!X:X,月汇总!B:B,B10) -> 0 | W10: =V10/J10 -> 0 | X10: =SUMIFS(月汇总!U:U,月汇总!B:B,B10) -> 581 | Y10: =X10/J10 -> 0.012080125 | Z10: =SUMIFS(月汇总!O:O,月汇总!B:B,B10) -> 900 | AA10: =Z10/J10 -> 0.018712758 | AB10: =SUMIFS(月汇总!T:T,月汇总!B:B,B10) -> 0 | AC10: =AB10/J10 -> 0 | AD10: =SUMIFS(月汇总!Z:Z,月汇总!B:B,B10) -> 3366.6871 | AE10: =AD10/J10 -> 0.07 | AF10: =SUMIFS(月汇总!AC:AC,月汇总!B:B,B10) -> 790.16393 | AG10: =AF10/J10 -> 0.016429051 | AH10: =SUMIFS(月汇总!V:V,月汇总!B:B,B10) -> 397.39246 | AI10: =AH10/J10 -> 0.0082625653 | AJ10: =M10+P10+R10+T10+V10+X10+Z10+AB10+AD10+AF10+AH10 -> 32603.614 | AK10: =SUMIFS(月汇总!AA:AA,月汇总!B:B,B10) -> 10600 | AL10: =J10-K10-L10-AJ10-AK10 -> 4606.9159 | AM10: =AL10/J10 -> 0.09578678 | AN10: =SUMIFS(月汇总!AB:AB,月汇总!B:B,B10) -> 3800 | AO10: =SUMIFS(月汇总!W:W,月汇总!B:B,B10) -> 2666 | AP10: =AL10-AN10-AO10 -> -1859.0841
A11: 7 | B11: 赣J03136D | C11: 朱家访 | D11: 杨发明 | E11: 广西-玉溪 | F11: 桂L9856挂 | G11: 重型半挂牵引车 | H11: =COUNTIFS(磅单!E:E,B11) -> 18 | I11: =SUMIFS(磅单!L:L,磅单!E:E,B11) -> 750.31 | J11: =SUMIFS(磅单!O:O,磅单!E:E,B11) -> 46013.89 | K11: =SUMIFS(月汇总!Y:Y,月汇总!B:B,B11) -> 270 | L11: =SUMIFS(月汇总!I:I,月汇总!B:B,B11,月汇总!C:C,F11) -> 0 | M11: =SUMIFS(月汇总!J:J,月汇总!B:B,B11,月汇总!C:C,F11) -> 15027.95 | N11: =M11/J11 -> 0.32659595 | O11: =M11/H11 -> 834.88612 | P11: =SUMIFS(月汇总!R:R,月汇总!B:B,B11)+SUMIFS(月汇总!S:S,月汇总!B:B,B11) -> 11800 | Q11: =P11/J11 -> 0.2564443 | R11: =SUMIFS(月汇总!Q:Q,月汇总!B:B,B11) -> 50 | S11: =R11/J11 -> 0.0010866284 | T11: =SUMIFS(月汇总!N:N,月汇总!B:B,B11) -> 220.88197 | V11: =SUMIFS(月汇总!X:X,月汇总!B:B,B11) -> 0 | W11: =V11/J11 -> 0 | X11: =SUMIFS(月汇总!U:U,月汇总!B:B,B11) -> 480 | Y11: =X11/J11 -> 0.010431633 | Z11: =SUMIFS(月汇总!O:O,月汇总!B:B,B11) -> 900 | AA11: =Z11/J11 -> 0.019559311 | AB11: =SUMIFS(月汇总!T:T,月汇总!B:B,B11) -> 210 | AC11: =AB11/J11 -> 0.0045638393 | AD11: =SUMIFS(月汇总!Z:Z,月汇总!B:B,B11) -> 3406.1335 | AE11: =AD11/J11 -> 0.074024028 | AF11: =SUMIFS(月汇总!AC:AC,月汇总!B:B,B11) -> 790.16393 | AG11: =AF11/J11 -> 0.017172292 | AH11: =SUMIFS(月汇总!V:V,月汇总!B:B,B11) -> 397.39246 | AI11: =AH11/J11 -> 0.0086363587 | AJ11: =M11+P11+R11+T11+V11+X11+Z11+AB11+AD11+AF11+AH11 -> 33282.522 | AK11: =SUMIFS(月汇总!AA:AA,月汇总!B:B,B11) -> 10600 | AL11: =J11-K11-L11-AJ11-AK11 -> 1861.368 | AM11: =AL11/J11 -> 0.040452308 | AN11: =SUMIFS(月汇总!AB:AB,月汇总!B:B,B11) -> 3800 | AO11: =SUMIFS(月汇总!W:W,月汇总!B:B,B11) -> 2666 | AP11: =AL11-AN11-AO11 -> -4604.632
A12: 8 | B12: 赣J03688D | C12: 刘小福 | D12: 杨发明 | E12: 广西-玉溪 | F12: 桂LA935挂 | G12: 重型半挂牵引车 | H12: =COUNTIFS(磅单!E:E,B12) -> 22 | I12: =SUMIFS(磅单!L:L,磅单!E:E,B12) -> 928.88 | J12: =SUMIFS(磅单!O:O,磅单!E:E,B12) -> 58792.78 | K12: =SUMIFS(月汇总!Y:Y,月汇总!B:B,B12) -> 330 | L12: =SUMIFS(月汇总!I:I,月汇总!B:B,B12,月汇总!C:C,F12) -> 0 | M12: =SUMIFS(月汇总!J:J,月汇总!B:B,B12,月汇总!C:C,F12) -> 16765.748 | N12: =M12/J12 -> 0.28516679 | O12: =M12/H12 -> 762.07948 | P12: =SUMIFS(月汇总!R:R,月汇总!B:B,B12)+SUMIFS(月汇总!S:S,月汇总!B:B,B12) -> 15000 | Q12: =P12/J12 -> 0.25513337 | R12: =SUMIFS(月汇总!Q:Q,月汇总!B:B,B12) -> 1203 | S12: =R12/J12 -> 0.020461696 | T12: =SUMIFS(月汇总!N:N,月汇总!B:B,B12) -> 220.88197 | V12: =SUMIFS(月汇总!X:X,月汇总!B:B,B12) -> 0 | W12: =V12/J12 -> 0 | X12: =SUMIFS(月汇总!U:U,月汇总!B:B,B12) -> 711 | Y12: =X12/J12 -> 0.012093322 | Z12: =SUMIFS(月汇总!O:O,月汇总!B:B,B12) -> 0 | AA12: =Z12/J12 -> 0 | AB12: =SUMIFS(月汇总!T:T,月汇总!B:B,B12) -> 420 | AC12: =AB12/J12 -> 0.0071437343 | AD12: =SUMIFS(月汇总!Z:Z,月汇总!B:B,B12) -> 4115.4946 | AE12: =AD12/J12 -> 0.07 | AF12: =SUMIFS(月汇总!AC:AC,月汇总!B:B,B12) -> 790.16393 | AG12: =AF12/J12 -> 0.013439812 | AH12: =SUMIFS(月汇总!V:V,月汇总!B:B,B12) -> 397.39246 | AI12: =AH12/J12 -> 0.0067592051 | AJ12: =M12+P12+R12+T12+V12+X12+Z12+AB12+AD12+AF12+AH12 -> 39623.681 | AK12: =SUMIFS(月汇总!AA:AA,月汇总!B:B,B12) -> 10600 | AL12: =J12-K12-L12-AJ12-AK12 -> 8239.0986 | AM12: =AL12/J12 -> 0.14013793 | AN12: =SUMIFS(月汇总!AB:AB,月汇总!B:B,B12) -> 3800 | AO12: =SUMIFS(月汇总!W:W,月汇总!B:B,B12) -> 2666 | AP12: =AL12-AN12-AO12 -> 1773.0986
A13: 9 | B13: 赣J07535D | C13: 李家宝 | D13: 杨发明 | E13: 广西-玉溪 | F13: 桂LB307挂 | G13: 重型半挂牵引车 | H13: =COUNTIFS(磅单!E:E,B13) -> 21 | I13: =SUMIFS(磅单!L:L,磅单!E:E,B13) -> 874.61 | J13: =SUMIFS(磅单!O:O,磅单!E:E,B13) -> 55429.23 | K13: =SUMIFS(月汇总!Y:Y,月汇总!B:B,B13) -> 315 | L13: =SUMIFS(月汇总!I:I,月汇总!B:B,B13,月汇总!C:C,F13) -> 0 | M13: =SUMIFS(月汇总!J:J,月汇总!B:B,B13,月汇总!C:C,F13) -> 14114.09 | N13: =M13/J13 -> 0.25463261 | O13: =M13/H13 -> 672.0995 | P13: =SUMIFS(月汇总!R:R,月汇总!B:B,B13)+SUMIFS(月汇总!S:S,月汇总!B:B,B13) -> 13000 | Q13: =P13/J13 -> 0.2345333 | R13: =SUMIFS(月汇总!Q:Q,月汇总!B:B,B13) -> 620 | S13: =R13/J13 -> 0.011185434 | T13: =SUMIFS(月汇总!N:N,月汇总!B:B,B13) -> 220.88197 | V13: =SUMIFS(月汇总!X:X,月汇总!B:B,B13) -> 0 | W13: =V13/J13 -> 0 | X13: =SUMIFS(月汇总!U:U,月汇总!B:B,B13) -> 613 | Y13: =X13/J13 -> 0.011059147 | Z13: =SUMIFS(月汇总!O:O,月汇总!B:B,B13) -> 0 | AA13: =Z13/J13 -> 0 | AB13: =SUMIFS(月汇总!T:T,月汇总!B:B,B13) -> 0 | AC13: =AB13/J13 -> 0 | AD13: =SUMIFS(月汇总!Z:Z,月汇总!B:B,B13) -> 3880.0461 | AE13: =AD13/J13 -> 0.07 | AF13: =SUMIFS(月汇总!AC:AC,月汇总!B:B,B13) -> 790.16393 | AG13: =AF13/J13 -> 0.014255366 | AH13: =SUMIFS(月汇总!V:V,月汇总!B:B,B13) -> 397.39246 | AI13: =AH13/J13 -> 0.0071693664 | AJ13: =M13+P13+R13+T13+V13+X13+Z13+AB13+AD13+AF13+AH13 -> 33635.574 | AK13: =SUMIFS(月汇总!AA:AA,月汇总!B:B,B13) -> 10600 | AL13: =J13-K13-L13-AJ13-AK13 -> 10878.656 | AM13: =AL13/J13 -> 0.19626208 | AN13: =SUMIFS(月汇总!AB:AB,月汇总!B:B,B13) -> 3800 | AO13: =SUMIFS(月汇总!W:W,月汇总!B:B,B13) -> 2666 | AP13: =AL13-AN13-AO13 -> 4412.656
A14: 10 | B14: 赣J08536D | C14: 李建祥 | D14: 杨发明 | E14: 广西-玉溪 | F14: 桂LD179挂 | G14: 重型半挂牵引车 | H14: =COUNTIFS(磅单!E:E,B14) -> 16 | I14: =SUMIFS(磅单!L:L,磅单!E:E,B14) -> 673.98 | J14: =SUMIFS(磅单!O:O,磅单!E:E,B14) -> 44638.62 | K14: =SUMIFS(月汇总!Y:Y,月汇总!B:B,B14) -> 240 | L14: =SUMIFS(月汇总!I:I,月汇总!B:B,B14,月汇总!C:C,F14) -> 0 | M14: =SUMIFS(月汇总!J:J,月汇总!B:B,B14,月汇总!C:C,F14) -> 15202.365 | N14: =M14/J14 -> 0.34056531 | O14: =M14/H14 -> 950.14784 | P14: =SUMIFS(月汇总!R:R,月汇总!B:B,B14)+SUMIFS(月汇总!S:S,月汇总!B:B,B14) -> 11400 | Q14: =P14/J14 -> 0.25538424 | R14: =SUMIFS(月汇总!Q:Q,月汇总!B:B,B14) -> 370 | S14: =R14/J14 -> 0.0082887867 | T14: =SUMIFS(月汇总!N:N,月汇总!B:B,B14) -> 220.88197 | V14: =SUMIFS(月汇总!X:X,月汇总!B:B,B14) -> 0 | W14: =V14/J14 -> 0 | X14: =SUMIFS(月汇总!U:U,月汇总!B:B,B14) -> 3194 | Y14: =X14/J14 -> 0.071552391 | Z14: =SUMIFS(月汇总!O:O,月汇总!B:B,B14) -> 0 | AA14: =Z14/J14 -> 0 | AB14: =SUMIFS(月汇总!T:T,月汇总!B:B,B14) -> 0 | AC14: =AB14/J14 -> 0 | AD14: =SUMIFS(月汇总!Z:Z,月汇总!B:B,B14) -> 3124.7034 | AE14: =AD14/J14 -> 0.07 | AF14: =SUMIFS(月汇总!AC:AC,月汇总!B:B,B14) -> 790.16393 | AG14: =AF14/J14 -> 0.017701352 | AH14: =SUMIFS(月汇总!V:V,月汇总!B:B,B14) -> 397.39246 | AI14: =AH14/J14 -> 0.008902436 | AJ14: =M14+P14+R14+T14+V14+X14+Z14+AB14+AD14+AF14+AH14 -> 34699.507 | AK14: =SUMIFS(月汇总!AA:AA,月汇总!B:B,B14) -> 10600 | AL14: =J14-K14-L14-AJ14-AK14 -> -900.88717 | AM14: =AL14/J14 -> -0.020181788 | AN14: =SUMIFS(月汇总!AB:AB,月汇总!B:B,B14) -> 3800 | AO14: =SUMIFS(月汇总!W:W,月汇总!B:B,B14) -> 2666 | AP14: =AL14-AN14-AO14 -> -7366.8872
A15: 11 | B15: 赣J05857D | C15: 高洪伟 | D15: 杨发明 | E15: 广西-玉溪 | F15: 桂LB659挂 | G15: 重型半挂牵引车 | H15: =COUNTIFS(磅单!E:E,B15) -> 19 | I15: =SUMIFS(磅单!L:L,磅单!E:E,B15) -> 798.41 | J15: =SUMIFS(磅单!O:O,磅单!E:E,B15) -> 48640.05 | K15: =SUMIFS(月汇总!Y:Y,月汇总!B:B,B15) -> 285 | L15: =SUMIFS(月汇总!I:I,月汇总!B:B,B15,月汇总!C:C,F15) -> 0 | M15: =SUMIFS(月汇总!J:J,月汇总!B:B,B15,月汇总!C:C,F15) -> 14817.425 | N15: =M15/J15 -> 0.30463425 | O15: =M15/H15 -> 779.86447 | P15: =SUMIFS(月汇总!R:R,月汇总!B:B,B15)+SUMIFS(月汇总!S:S,月汇总!B:B,B15) -> 11800 | Q15: =P15/J15 -> 0.24259843 | R15: =SUMIFS(月汇总!Q:Q,月汇总!B:B,B15) -> 2190 | S15: =R15/J15 -> 0.045024625 | T15: =SUMIFS(月汇总!N:N,月汇总!B:B,B15) -> 220.88197 | V15: =SUMIFS(月汇总!X:X,月汇总!B:B,B15) -> 0 | W15: =V15/J15 -> 0 | X15: =SUMIFS(月汇总!U:U,月汇总!B:B,B15) -> 395 | Y15: =X15/J15 -> 0.0081208798 | Z15: =SUMIFS(月汇总!O:O,月汇总!B:B,B15) -> 50 | AA15: =Z15/J15 -> 0.0010279595 | AB15: =SUMIFS(月汇总!T:T,月汇总!B:B,B15) -> 200 | AC15: =AB15/J15 -> 0.0041118379 | AD15: =SUMIFS(月汇总!Z:Z,月汇总!B:B,B15) -> 3404.8035 | AE15: =AD15/J15 -> 0.07 | AF15: =SUMIFS(月汇总!AC:AC,月汇总!B:B,B15) -> 790.16393 | AG15: =AF15/J15 -> 0.01624513 | AH15: =SUMIFS(月汇总!V:V,月汇总!B:B,B15) -> 397.39246 | AI15: =AH15/J15 -> 0.0081700668 | AJ15: =M15+P15+R15+T15+V15+X15+Z15+AB15+AD15+AF15+AH15 -> 34265.667 | AK15: =SUMIFS(月汇总!AA:AA,月汇总!B:B,B15) -> 10600 | AL15: =J15-K15-L15-AJ15-AK15 -> 3489.3831 | AM15: =AL15/J15 -> 0.071738889 | AN15: =SUMIFS(月汇总!AB:AB,月汇总!B:B,B15) -> 3800 | AO15: =SUMIFS(月汇总!W:W,月汇总!B:B,B15) -> 2666 | AP15: =AL15-AN15-AO15 -> -2976.6169
A16: 12 | B16: 赣J06519D | C16: 冯育柱 | D16: 杨发明 | E16: 广西-玉溪 | F16: 桂L5759挂 | G16: 重型半挂牵引车 | H16: =COUNTIFS(磅单!E:E,B16) -> 25 | I16: =SUMIFS(磅单!L:L,磅单!E:E,B16) -> 1015.87 | J16: =SUMIFS(磅单!O:O,磅单!E:E,B16) -> 64387.11 | K16: =SUMIFS(月汇总!Y:Y,月汇总!B:B,B16) -> 375 | L16: =SUMIFS(月汇总!I:I,月汇总!B:B,B16,月汇总!C:C,F16) -> 0 | M16: =SUMIFS(月汇总!J:J,月汇总!B:B,B16,月汇总!C:C,F16) -> 20084.735 | N16: =M16/J16 -> 0.3119372 | O16: =M16/H16 -> 803.3894 | P16: =SUMIFS(月汇总!R:R,月汇总!B:B,B16)+SUMIFS(月汇总!S:S,月汇总!B:B,B16) -> 15600 | Q16: =P16/J16 -> 0.24228452 | R16: =SUMIFS(月汇总!Q:Q,月汇总!B:B,B16) -> 2396 | S16: =R16/J16 -> 0.037212417 | T16: =SUMIFS(月汇总!N:N,月汇总!B:B,B16) -> 220.88197 | V16: =SUMIFS(月汇总!X:X,月汇总!B:B,B16) -> 0 | W16: =V16/J16 -> 0 | X16: =SUMIFS(月汇总!U:U,月汇总!B:B,B16) -> 606 | Y16: =X16/J16 -> 0.0094118217 | Z16: =SUMIFS(月汇总!O:O,月汇总!B:B,B16) -> 950 | AA16: =Z16/J16 -> 0.014754506 | AB16: =SUMIFS(月汇总!T:T,月汇总!B:B,B16) -> 220 | AC16: =AB16/J16 -> 0.003416833 | AD16: =SUMIFS(月汇总!Z:Z,月汇总!B:B,B16) -> 4507.0977 | AE16: =AD16/J16 -> 0.07 | AF16: =SUMIFS(月汇总!AC:AC,月汇总!B:B,B16) -> 790.16393 | AG16: =AF16/J16 -> 0.012272083 | AH16: =SUMIFS(月汇总!V:V,月汇总!B:B,B16) -> 397.39246 | AI16: =AH16/J16 -> 0.0061719257 | AJ16: =M16+P16+R16+T16+V16+X16+Z16+AB16+AD16+AF16+AH16 -> 45772.271 | AK16: =SUMIFS(月汇总!AA:AA,月汇总!B:B,B16) -> 10600 | AL16: =J16-K16-L16-AJ16-AK16 -> 7639.839 | AM16: =AL16/J16 -> 0.11865479 | AN16: =SUMIFS(月汇总!AB:AB,月汇总!B:B,B16) -> 3800 | AO16: =SUMIFS(月汇总!W:W,月汇总!B:B,B16) -> 2666 | AP16: =AL16-AN16-AO16 -> 1173.839
... A25: 21 | B25: 沪A04114D | C25: 李玉红 | D25: 杨发明 | E25: 广西-玉溪 | F25: 桂LB957挂 | G25: 重型半挂牵引车 | H25: =COUNTIFS(磅单!E:E,B25) -> 17 | I25: =SUMIFS(磅单!L:L,磅单!E:E,B25) -> 722.21 | J25: =SUMIFS(磅单!O:O,磅单!E:E,B25) -> 47707.93 | K25: =SUMIFS(月汇总!Y:Y,月汇总!B:B,B25) -> 255 | L25: =SUMIFS(月汇总!I:I,月汇总!B:B,B25,月汇总!C:C,F25) -> 0 | M25: =SUMIFS(月汇总!J:J,月汇总!B:B,B25,月汇总!C:C,F25) -> 13353.994 | N25: =M25/J25 -> 0.27991141 | O25: =M25/H25 -> 785.52906 | P25: =SUMIFS(月汇总!R:R,月汇总!B:B,B25)+SUMIFS(月汇总!S:S,月汇总!B:B,B25) -> 11200 | Q25: =P25/J25 -> 0.23476181 | R25: =SUMIFS(月汇总!Q:Q,月汇总!B:B,B25) -> 400 | S25: =R25/J25 -> 0.0083843504 | T25: =SUMIFS(月汇总!N:N,月汇总!B:B,B25) -> 220.88197 | V25: =SUMIFS(月汇总!X:X,月汇总!B:B,B25) -> 0 | W25: =V25/J25 -> 0 | X25: =SUMIFS(月汇总!U:U,月汇总!B:B,B25) -> 554 | Y25: =X25/J25 -> 0.011612325 | Z25: =SUMIFS(月汇总!O:O,月汇总!B:B,B25) -> 1000 | AA25: =Z25/J25 -> 0.020960876 | AB25: =SUMIFS(月汇总!T:T,月汇总!B:B,B25) -> 440 | AC25: =AB25/J25 -> 0.0092227854 | AD25: =SUMIFS(月汇总!Z:Z,月汇总!B:B,B25) -> 3339.5551 | AE25: =AD25/J25 -> 0.07 | AF25: =SUMIFS(月汇总!AC:AC,月汇总!B:B,B25) -> 790.16393 | AG25: =AF25/J25 -> 0.016562528 | AH25: =SUMIFS(月汇总!V:V,月汇总!B:B,B25) -> 397.39246 | AI25: =AH25/J25 -> 0.008329694 | AJ25: =M25+P25+R25+T25+V25+X25+Z25+AB25+AD25+AF25+AH25 -> 31695.987 | AK25: =SUMIFS(月汇总!AA:AA,月汇总!B:B,B25) -> 10600 | AL25: =J25-K25-L25-AJ25-AK25 -> 5156.9425 | AM25: =AL25/J25 -> 0.10809403 | AN25: =SUMIFS(月汇总!AB:AB,月汇总!B:B,B25) -> 3800 | AO25: =SUMIFS(月汇总!W:W,月汇总!B:B,B25) -> 2666 | AP25: =AL25-AN25-AO25 -> -1309.0575
A26: 22 | B26: 赣J08767D | C26: 何仕财 | D26: 杨发明 | E26: 广西-玉溪 | F26: 桂LA357挂 | G26: 重型半挂牵引车 | H26: =COUNTIFS(磅单!E:E,B26) -> 23 | I26: =SUMIFS(磅单!L:L,磅单!E:E,B26) -> 949.84 | J26: =SUMIFS(磅单!O:O,磅单!E:E,B26) -> 59389.6 | K26: =SUMIFS(月汇总!Y:Y,月汇总!B:B,B26) -> 345 | L26: =SUMIFS(月汇总!I:I,月汇总!B:B,B26,月汇总!C:C,F26) -> 0 | M26: =SUMIFS(月汇总!J:J,月汇总!B:B,B26,月汇总!C:C,F26) -> 19713.958 | N26: =M26/J26 -> 0.33194294 | O26: =M26/H26 -> 857.12862 | P26: =SUMIFS(月汇总!R:R,月汇总!B:B,B26)+SUMIFS(月汇总!S:S,月汇总!B:B,B26) -> 14400 | Q26: =P26/J26 -> 0.24246669 | R26: =SUMIFS(月汇总!Q:Q,月汇总!B:B,B26) -> 455 | S26: =R26/J26 -> 0.007661274 | T26: =SUMIFS(月汇总!N:N,月汇总!B:B,B26) -> 220.88197 | V26: =SUMIFS(月汇总!X:X,月汇总!B:B,B26) -> 0 | X26: =SUMIFS(月汇总!U:U,月汇总!B:B,B26) -> 568.6 | Y26: =X26/J26 -> 0.0095740668 | Z26: =SUMIFS(月汇总!O:O,月汇总!B:B,B26) -> 0 | AA26: =Z26/J26 -> 0 | AB26: =SUMIFS(月汇总!T:T,月汇总!B:B,B26) -> 260 | AC26: =AB26/J26 -> 0.0043778709 | AD26: =SUMIFS(月汇总!Z:Z,月汇总!B:B,B26) -> 4157.272 | AE26: =AD26/J26 -> 0.07 | AF26: =SUMIFS(月汇总!AC:AC,月汇总!B:B,B26) -> 790.16393 | AG26: =AF26/J26 -> 0.013304753 | AH26: =SUMIFS(月汇总!V:V,月汇总!B:B,B26) -> 397.39246 | AI26: =AH26/J26 -> 0.0066912803 | AJ26: =M26+P26+R26+T26+V26+X26+Z26+AB26+AD26+AF26+AH26 -> 40963.269 | AK26: =SUMIFS(月汇总!AA:AA,月汇总!B:B,B26) -> 10600 | AL26: =J26-K26-L26-AJ26-AK26 -> 7481.3314 | AM26: =AL26/J26 -> 0.1259704 | AN26: =SUMIFS(月汇总!AB:AB,月汇总!B:B,B26) -> 3800 | AO26: =SUMIFS(月汇总!W:W,月汇总!B:B,B26) -> 2666 | AP26: =AL26-AN26-AO26 -> 1015.3314
A27: 23 | B27: 赣J03528D | C27: 罗晶 | D27: 杨发明 | E27: 广西-玉溪 | F27: 桂LE308挂 | G27: 重型半挂牵引车 | H27: =COUNTIFS(磅单!E:E,B27) -> 21 | I27: =SUMIFS(磅单!L:L,磅单!E:E,B27) -> 888.56 | J27: =SUMIFS(磅单!O:O,磅单!E:E,B27) -> 57045.58 | K27: =SUMIFS(月汇总!Y:Y,月汇总!B:B,B27) -> 315 | L27: =SUMIFS(月汇总!I:I,月汇总!B:B,B27,月汇总!C:C,F27) -> 0 | M27: =SUMIFS(月汇总!J:J,月汇总!B:B,B27,月汇总!C:C,F27) -> 15543.134 | N27: =M27/J27 -> 0.27246869 | O27: =M27/H27 -> 740.14925 | P27: =SUMIFS(月汇总!R:R,月汇总!B:B,B27)+SUMIFS(月汇总!S:S,月汇总!B:B,B27) -> 13200 | Q27: =P27/J27 -> 0.23139391 | R27: =SUMIFS(月汇总!Q:Q,月汇总!B:B,B27) -> 570 | S27: =R27/J27 -> 0.0099920099 | T27: =SUMIFS(月汇总!N:N,月汇总!B:B,B27) -> 220.88197 | V27: =SUMIFS(月汇总!X:X,月汇总!B:B,B27) -> 0 | X27: =SUMIFS(月汇总!U:U,月汇总!B:B,B27) -> 608 | Y27: =X27/J27 -> 0.010658144 | Z27: =SUMIFS(月汇总!O:O,月汇总!B:B,B27) -> 0 | AA27: =Z27/J27 -> 0 | AB27: =SUMIFS(月汇总!T:T,月汇总!B:B,B27) -> 200 | AC27: =AB27/J27 -> 0.0035059684 | AD27: =SUMIFS(月汇总!Z:Z,月汇总!B:B,B27) -> 3993.1906 | AE27: =AD27/J27 -> 0.07 | AF27: =SUMIFS(月汇总!AC:AC,月汇总!B:B,B27) -> 790.16393 | AG27: =AF27/J27 -> 0.013851449 | AH27: =SUMIFS(月汇总!V:V,月汇总!B:B,B27) -> 397.39246 | AI27: =AH27/J27 -> 0.006966227 | AJ27: =M27+P27+R27+T27+V27+X27+Z27+AB27+AD27+AF27+AH27 -> 35522.763 | AK27: =SUMIFS(月汇总!AA:AA,月汇总!B:B,B27) -> 10600 | AL27: =J27-K27-L27-AJ27-AK27 -> 10607.817 | AM27: =AL27/J27 -> 0.18595335 | AN27: =SUMIFS(月汇总!AB:AB,月汇总!B:B,B27) -> 3800 | AO27: =SUMIFS(月汇总!W:W,月汇总!B:B,B27) -> 2666 | AP27: =AL27-AN27-AO27 -> 4141.8168
A28: 24 | B28: 赣J03373D | C28: 陆金城 | D28: 袁俊杰 | E28: 广西-玉溪 | F28: 桂LC575挂 | G28: 重型半挂牵引车 | H28: =COUNTIFS(磅单!E:E,B28) -> 4 | I28: =SUMIFS(磅单!L:L,磅单!E:E,B28) -> 167.72 | J28: =SUMIFS(磅单!O:O,磅单!E:E,B28) -> 11193.96 | K28: =SUMIFS(月汇总!Y:Y,月汇总!B:B,B28) -> 60 | L28: =SUMIFS(月汇总!I:I,月汇总!B:B,B28,月汇总!C:C,F28) -> 50 | M28: =SUMIFS(月汇总!J:J,月汇总!B:B,B28,月汇总!C:C,F28) -> 5252.5871 | N28: =M28/J28 -> 0.46923404 | O28: =M28/H28 -> 1313.1468 | P28: =SUMIFS(月汇总!R:R,月汇总!B:B,B28)+SUMIFS(月汇总!S:S,月汇总!B:B,B28) -> 3000 | Q28: =P28/J28 -> 0.26800167 | R28: =SUMIFS(月汇总!Q:Q,月汇总!B:B,B28) -> 295 | S28: =R28/J28 -> 0.026353498 | T28: =SUMIFS(月汇总!N:N,月汇总!B:B,B28) -> 220.88197 | V28: =SUMIFS(月汇总!X:X,月汇总!B:B,B28) -> 0 | X28: =SUMIFS(月汇总!U:U,月汇总!B:B,B28) -> 160 | Y28: =X28/J28 -> 0.014293423 | Z28: =SUMIFS(月汇总!O:O,月汇总!B:B,B28) -> 0 | AA28: =Z28/J28 -> 0 | AB28: =SUMIFS(月汇总!T:T,月汇总!B:B,B28) -> 200 | AC28: =AB28/J28 -> 0.017866778 | AD28: =SUMIFS(月汇总!Z:Z,月汇总!B:B,B28) -> 783.5772 | AE28: =AD28/J28 -> 0.07 | AF28: =SUMIFS(月汇总!AC:AC,月汇总!B:B,B28) -> 790.16393 | AG28: =AF28/J28 -> 0.070588419 | AH28: =SUMIFS(月汇总!V:V,月汇总!B:B,B28) -> 397.39246 | AI28: =AH28/J28 -> 0.035500615 | AJ28: =M28+P28+R28+T28+V28+X28+Z28+AB28+AD28+AF28+AH28 -> 11099.603 | AK28: =SUMIFS(月汇总!AA:AA,月汇总!B:B,B28) -> 10600 | AL28: =J28-K28-L28-AJ28-AK28 -> -10615.643 | AM28: =AL28/J28 -> -0.94833666 | AN28: =SUMIFS(月汇总!AB:AB,月汇总!B:B,B28) -> 3800 | AO28: =SUMIFS(月汇总!W:W,月汇总!B:B,B28) -> 2666 | AP28: =AL28-AN28-AO28 -> -17081.643
A29: 25 | B29: 赣J02525D | C29: 杨仁华 | D29: 杨发明 | E29: 广西-玉溪 | F29: 桂LB297挂 | G29: 重型半挂牵引车 | H29: =COUNTIFS(磅单!E:E,B29) -> 2 | I29: =SUMIFS(磅单!L:L,磅单!E:E,B29) -> 85.91 | J29: =SUMIFS(磅单!O:O,磅单!E:E,B29) -> 5499.59 | K29: =SUMIFS(月汇总!Y:Y,月汇总!B:B,B29) -> 30 | L29: =SUMIFS(月汇总!I:I,月汇总!B:B,B29,月汇总!C:C,F29) -> 0 | M29: =SUMIFS(月汇总!J:J,月汇总!B:B,B29,月汇总!C:C,F29) -> 2495.5028 | N29: =M29/J29 -> 0.45376161 | O29: =M29/H29 -> 1247.7514 | P29: =SUMIFS(月汇总!R:R,月汇总!B:B,B29)+SUMIFS(月汇总!S:S,月汇总!B:B,B29) -> 1200 | Q29: =P29/J29 -> 0.21819808 | R29: =SUMIFS(月汇总!Q:Q,月汇总!B:B,B29) -> 300 | S29: =R29/J29 -> 0.054549521 | T29: =SUMIFS(月汇总!N:N,月汇总!B:B,B29) -> 220.88197 | V29: =SUMIFS(月汇总!X:X,月汇总!B:B,B29) -> 0 | X29: =SUMIFS(月汇总!U:U,月汇总!B:B,B29) -> 417 | Y29: =X29/J29 -> 0.075823834 | Z29: =SUMIFS(月汇总!O:O,月汇总!B:B,B29) -> 0 | AA29: =Z29/J29 -> 0 | AB29: =SUMIFS(月汇总!T:T,月汇总!B:B,B29) -> 200 | AC29: =AB29/J29 -> 0.036366347 | AD29: =SUMIFS(月汇总!Z:Z,月汇总!B:B,B29) -> 384.9713 | AE29: =AD29/J29 -> 0.07 | AF29: =SUMIFS(月汇总!AC:AC,月汇总!B:B,B29) -> 790.16393 | AG29: =AF29/J29 -> 0.14367688 | AH29: =SUMIFS(月汇总!V:V,月汇总!B:B,B29) -> 397.39246 | AI29: =AH29/J29 -> 0.072258561 | AJ29: =M29+P29+R29+T29+V29+X29+Z29+AB29+AD29+AF29+AH29 -> 6405.9125 | AK29: =SUMIFS(月汇总!AA:AA,月汇总!B:B,B29) -> 10600 | AL29: =J29-K29-L29-AJ29-AK29 -> -11536.322 | AM29: =AL29/J29 -> -2.0976695 | AN29: =SUMIFS(月汇总!AB:AB,月汇总!B:B,B29) -> 3800 | AO29: =SUMIFS(月汇总!W:W,月汇总!B:B,B29) -> 2666 | AP29: =AL29-AN29-AO29 -> -18002.322
A30: 26 | B30: 赣J05379D | C30: 昝建伟 | D30: 杨发明 | E30: 广西-玉溪 | F30: 桂LC316挂 | G30: 重型半挂牵引车 | H30: =COUNTIFS(磅单!E:E,B30) -> 17 | I30: =SUMIFS(磅单!L:L,磅单!E:E,B30) -> 685.49 | J30: =SUMIFS(磅单!O:O,磅单!E:E,B30) -> 44813.27 | K30: =SUMIFS(月汇总!Y:Y,月汇总!B:B,B30) -> 255 | L30: =SUMIFS(月汇总!I:I,月汇总!B:B,B30,月汇总!C:C,F30) -> 50 | M30: =SUMIFS(月汇总!J:J,月汇总!B:B,B30,月汇总!C:C,F30) -> 14525.358 | N30: =M30/J30 -> 0.32413073 | O30: =M30/H30 -> 854.43282 | P30: =SUMIFS(月汇总!R:R,月汇总!B:B,B30)+SUMIFS(月汇总!S:S,月汇总!B:B,B30) -> 11000 | Q30: =P30/J30 -> 0.24546301 | R30: =SUMIFS(月汇总!Q:Q,月汇总!B:B,B30) -> 270 | S30: =R30/J30 -> 0.0060250011 | T30: =SUMIFS(月汇总!N:N,月汇总!B:B,B30) -> 220.88197 | V30: =SUMIFS(月汇总!X:X,月汇总!B:B,B30) -> 0 | X30: =SUMIFS(月汇总!U:U,月汇总!B:B,B30) -> 456 | Y30: =X30/J30 -> 0.010175557 | Z30: =SUMIFS(月汇总!O:O,月汇总!B:B,B30) -> 6080 | AA30: =Z30/J30 -> 0.1356741 | AB30: =SUMIFS(月汇总!T:T,月汇总!B:B,B30) -> 200 | AC30: =AB30/J30 -> 0.0044629638 | AD30: =SUMIFS(月汇总!Z:Z,月汇总!B:B,B30) -> 3136.9289 | AE30: =AD30/J30 -> 0.07 | AF30: =SUMIFS(月汇总!AC:AC,月汇总!B:B,B30) -> 790.16393 | AG30: =AF30/J30 -> 0.017632365 | AH30: =SUMIFS(月汇总!V:V,月汇总!B:B,B30) -> 397.39246 | AI30: =AH30/J30 -> 0.0088677407 | AJ30: =M30+P30+R30+T30+V30+X30+Z30+AB30+AD30+AF30+AH30 -> 37076.725 | AK30: =SUMIFS(月汇总!AA:AA,月汇总!B:B,B30) -> 10600 | AL30: =J30-K30-L30-AJ30-AK30 -> -3168.4553 | AM30: =AL30/J30 -> -0.070703505 | AN30: =SUMIFS(月汇总!AB:AB,月汇总!B:B,B30) -> 3800 | AO30: =SUMIFS(月汇总!W:W,月汇总!B:B,B30) -> 2666 | AP30: =AL30-AN30-AO30 -> -9634.4553
A31: 27 | B31: 赣J03535D | C31: 刘炳宏 | D31: 杨发明 | E31: 广西-玉溪 | F31: 桂LB917挂 | G31: 重型半挂牵引车 | H31: =COUNTIFS(磅单!E:E,B31) -> 16 | I31: =SUMIFS(磅单!L:L,磅单!E:E,B31) -> 649.14 | J31: =SUMIFS(磅单!O:O,磅单!E:E,B31) -> 41386.44 | K31: =SUMIFS(月汇总!Y:Y,月汇总!B:B,B31) -> 240 | L31: =SUMIFS(月汇总!I:I,月汇总!B:B,B31,月汇总!C:C,F31) -> 0 | M31: =SUMIFS(月汇总!J:J,月汇总!B:B,B31,月汇总!C:C,F31) -> 12909.952 | N31: =M31/J31 -> 0.31193676 | O31: =M31/H31 -> 806.872 | P31: =SUMIFS(月汇总!R:R,月汇总!B:B,B31)+SUMIFS(月汇总!S:S,月汇总!B:B,B31) -> 10000 | Q31: =P31/J31 -> 0.24162503 | R31: =SUMIFS(月汇总!Q:Q,月汇总!B:B,B31) -> 1405 | S31: =R31/J31 -> 0.033948317 | T31: =SUMIFS(月汇总!N:N,月汇总!B:B,B31) -> 220.88197 | V31: =SUMIFS(月汇总!X:X,月汇总!B:B,B31) -> 0 | X31: =SUMIFS(月汇总!U:U,月汇总!B:B,B31) -> 386 | Y31: =X31/J31 -> 0.0093267263 | Z31: =SUMIFS(月汇总!O:O,月汇总!B:B,B31) -> 8830 | AA31: =Z31/J31 -> 0.21335491 | AB31: =SUMIFS(月汇总!T:T,月汇总!B:B,B31) -> 220 | AC31: =AB31/J31 -> 0.0053157508 | AD31: =SUMIFS(月汇总!Z:Z,月汇总!B:B,B31) -> 2897.0508 | AE31: =AD31/J31 -> 0.07 | AF31: =SUMIFS(月汇总!AC:AC,月汇总!B:B,B31) -> 790.16393 | AG31: =AF31/J31 -> 0.019092339 | AH31: =SUMIFS(月汇总!V:V,月汇总!B:B,B31) -> 397.39246 | AI31: =AH31/J31 -> 0.0096019967 | AJ31: =M31+P31+R31+T31+V31+X31+Z31+AB31+AD31+AF31+AH31 -> 38056.441 | AK31: =SUMIFS(月汇总!AA:AA,月汇总!B:B,B31) -> 10600 | AL31: =J31-K31-L31-AJ31-AK31 -> -7510.0012 | AM31: =AL31/J31 -> -0.18146043 | AN31: =SUMIFS(月汇总!AB:AB,月汇总!B:B,B31) -> 3800 | AO31: =SUMIFS(月汇总!W:W,月汇总!B:B,B31) -> 2666 | AP31: =AL31-AN31-AO31 -> -13976.001
A32: 28 | B32: 赣J09206D | C32: 杨仁华 | D32: 杨发明 | E32: 广西-玉溪 | F32: 桂L9026挂 | G32: 重型半挂牵引车 | H32: =COUNTIFS(磅单!E:E,B32) -> 15 | I32: =SUMIFS(磅单!L:L,磅单!E:E,B32) -> 621.41 | J32: =SUMIFS(磅单!O:O,磅单!E:E,B32) -> 37840.85 | K32: =SUMIFS(月汇总!Y:Y,月汇总!B:B,B32) -> 225 | L32: =SUMIFS(月汇总!I:I,月汇总!B:B,B32,月汇总!C:C,F32) -> 0 | M32: =SUMIFS(月汇总!J:J,月汇总!B:B,B32,月汇总!C:C,F32) -> 13910.791 | N32: =M32/J32 -> 0.36761307 | O32: =M32/H32 -> 927.38607 | P32: =SUMIFS(月汇总!R:R,月汇总!B:B,B32)+SUMIFS(月汇总!S:S,月汇总!B:B,B32) -> 9980 | Q32: =P32/J32 -> 0.26373615 | R32: =SUMIFS(月汇总!Q:Q,月汇总!B:B,B32) -> 2260 | S32: =R32/J32 -> 0.059723817 | T32: =SUMIFS(月汇总!N:N,月汇总!B:B,B32) -> 220.88197 | V32: =SUMIFS(月汇总!X:X,月汇总!B:B,B32) -> 0 | W32: =V32/J32 -> 0 | X32: =SUMIFS(月汇总!U:U,月汇总!B:B,B32) -> 412 | Y32: =X32/J32 -> 0.010887705 | Z32: =SUMIFS(月汇总!O:O,月汇总!B:B,B32) -> 900 | AA32: =Z32/J32 -> 0.023783821 | AB32: =SUMIFS(月汇总!T:T,月汇总!B:B,B32) -> 400 | AC32: =AB32/J32 -> 0.010570587 | AD32: =SUMIFS(月汇总!Z:Z,月汇总!B:B,B32) -> 2648.8595 | AE32: =AD32/J32 -> 0.07 | AF32: =SUMIFS(月汇总!AC:AC,月汇总!B:B,B32) -> 790.16393 | AG32: =AF32/J32 -> 0.020881242 | AH32: =SUMIFS(月汇总!V:V,月汇总!B:B,B32) -> 397.39246 | AI32: =AH32/J32 -> 0.010501679 | AJ32: =M32+P32+R32+T32+V32+X32+Z32+AB32+AD32+AF32+AH32 -> 31920.089 | AK32: =SUMIFS(月汇总!AA:AA,月汇总!B:B,B32) -> 10600 | AL32: =J32-K32-L32-AJ32-AK32 -> -4904.2389 | AM32: =AL32/J32 -> -0.12960171 | AN32: =SUMIFS(月汇总!AB:AB,月汇总!B:B,B32) -> 3800 | AO32: =SUMIFS(月汇总!W:W,月汇总!B:B,B32) -> 2666 | AP32: =AL32-AN32-AO32 -> -11370.239
A33: 29 | B33: 粤B32450D | C33: 潘加松 | D33: 杨发明 | E33: 广西-玉溪 | F33: 桂LB675挂 | G33: 重型半挂牵引车 | H33: =COUNTIFS(磅单!E:E,B33) -> 18 | I33: =SUMIFS(磅单!L:L,磅单!E:E,B33) -> 746.48 | J33: =SUMIFS(磅单!O:O,磅单!E:E,B33) -> 47601.34 | K33: =SUMIFS(月汇总!Y:Y,月汇总!B:B,B33) -> 270 | L33: =SUMIFS(月汇总!I:I,月汇总!B:B,B33,月汇总!C:C,F35) -> 0 | M33: =SUMIFS(月汇总!J:J,月汇总!B:B,B33,月汇总!C:C,F33) -> 14021.364 | N33: =M33/J33 -> 0.29455818 | O33: =M33/H33 -> 778.96467 | P33: =SUMIFS(月汇总!R:R,月汇总!B:B,B33)+SUMIFS(月汇总!S:S,月汇总!B:B,B33) -> 11200 | Q33: =P33/J33 -> 0.23528749 | R33: =SUMIFS(月汇总!Q:Q,月汇总!B:B,B33) -> 352 | S33: =R33/J33 -> 0.0073947498 | T33: =SUMIFS(月汇总!N:N,月汇总!B:B,B33) -> 220.88197 | V33: =SUMIFS(月汇总!X:X,月汇总!B:B,B33) -> 3000 | W33: =V33/J33 -> 0.063023436 | X33: =SUMIFS(月汇总!U:U,月汇总!B:B,B33) -> 535 | Y33: =X33/J33 -> 0.011239179 | Z33: =SUMIFS(月汇总!O:O,月汇总!B:B,B33) -> 0 | AA33: =Z33/J33 -> 0 | AB33: =SUMIFS(月汇总!T:T,月汇总!B:B,B33) -> 200 | AC33: =AB33/J33 -> 0.0042015624 | AD33: =SUMIFS(月汇总!Z:Z,月汇总!B:B,B33) -> 3332.0938 | AE33: =AD33/J33 -> 0.07 | AF33: =SUMIFS(月汇总!AC:AC,月汇总!B:B,B33) -> 790.16393 | AG33: =AF33/J33 -> 0.016599615 | AH33: =SUMIFS(月汇总!V:V,月汇总!B:B,B33) -> 397.39246 | AI33: =AH33/J33 -> 0.0083483461 | AJ33: =M33+P33+R33+T33+V33+X33+Z33+AB33+AD33+AF33+AH33 -> 34048.896 | AK33: =SUMIFS(月汇总!AA:AA,月汇总!B:B,B33) -> 10600 | AL33: =J33-K33-L33-AJ33-AK33 -> 2682.4437 | AM33: =AL33/J33 -> 0.056352273 | AN33: =SUMIFS(月汇总!AB:AB,月汇总!B:B,B33) -> 3800 | AO33: =SUMIFS(月汇总!W:W,月汇总!B:B,B33) -> 2666 | AP33: =AL33-AN33-AO33 -> -3783.5563
A34: 30 | B34: 粤B95976D | C34: 侯开雄 | D34: 杨发明 | E34: 广西-玉溪 | F34: 桂LB629挂 | G34: 重型半挂牵引车 | H34: =COUNTIFS(磅单!E:E,B34) -> 17 | I34: =SUMIFS(磅单!L:L,磅单!E:E,B34) -> 707.89 | J34: =SUMIFS(磅单!O:O,磅单!E:E,B34) -> 45141.65 | K34: =SUMIFS(月汇总!Y:Y,月汇总!B:B,B34) -> 255 | L34: =SUMIFS(月汇总!I:I,月汇总!B:B,B34,月汇总!C:C,F36) -> 0 | M34: =SUMIFS(月汇总!J:J,月汇总!B:B,B34,月汇总!C:C,F34) -> 14959.372 | N34: =M34/J34 -> 0.33138736 | O34: =M34/H34 -> 879.96306 | P34: =SUMIFS(月汇总!R:R,月汇总!B:B,B34)+SUMIFS(月汇总!S:S,月汇总!B:B,B34) -> 10600 | Q34: =P34/J34 -> 0.23481641 | R34: =SUMIFS(月汇总!Q:Q,月汇总!B:B,B34) -> 17300 | S34: =R34/J34 -> 0.3832381 | T34: =SUMIFS(月汇总!N:N,月汇总!B:B,B34) -> 220.88197 | V34: =SUMIFS(月汇总!X:X,月汇总!B:B,B34) -> 3000 | W34: =V34/J34 -> 0.066457473 | X34: =SUMIFS(月汇总!U:U,月汇总!B:B,B34) -> 2989 | Y34: =X34/J34 -> 0.066213796 | Z34: =SUMIFS(月汇总!O:O,月汇总!B:B,B34) -> 0 | AA34: =Z34/J34 -> 0 | AB34: =SUMIFS(月汇总!T:T,月汇总!B:B,B34) -> 0 | AC34: =AB34/J34 -> 0 | AD34: =SUMIFS(月汇总!Z:Z,月汇总!B:B,B34) -> 3159.9155 | AE34: =AD34/J34 -> 0.07 | AF34: =SUMIFS(月汇总!AC:AC,月汇总!B:B,B34) -> 790.16393 | AG34: =AF34/J34 -> 0.0175041 | AH34: =SUMIFS(月汇总!V:V,月汇总!B:B,B34) -> 397.39246 | AI34: =AH34/J34 -> 0.0088032329 | AJ34: =M34+P34+R34+T34+V34+X34+Z34+AB34+AD34+AF34+AH34 -> 53416.726 | AK34: =SUMIFS(月汇总!AA:AA,月汇总!B:B,B34) -> 10600 | AL34: =J34-K34-L34-AJ34-AK34 -> -19130.076 | AM34: =AL34/J34 -> -0.42377884 | AN34: =SUMIFS(月汇总!AB:AB,月汇总!B:B,B34) -> 3800 | AO34: =SUMIFS(月汇总!W:W,月汇总!B:B,B34) -> 2666 | AP34: =AL34-AN34-AO34 -> -25596.076
A35: 31 | B35: 粤B79120D | C35: 周忠银 | D35: 杨发明 | E35: 广西-玉溪 | F35: 桂LD489挂 | G35: 重型半挂牵引车 | H35: =COUNTIFS(磅单!E:E,B35) -> 14 | I35: =SUMIFS(磅单!L:L,磅单!E:E,B35) -> 608.25 | J35: =SUMIFS(磅单!O:O,磅单!E:E,B35) -> 37988.71 | K35: =SUMIFS(月汇总!Y:Y,月汇总!B:B,B35) -> 210 | L35: =SUMIFS(月汇总!I:I,月汇总!B:B,B35,月汇总!C:C,F37) -> 0 | M35: =SUMIFS(月汇总!J:J,月汇总!B:B,B35,月汇总!C:C,F35) -> 13854.188 | N35: =M35/J35 -> 0.36469224 | O35: =M35/H35 -> 989.58483 | P35: =SUMIFS(月汇总!R:R,月汇总!B:B,B35)+SUMIFS(月汇总!S:S,月汇总!B:B,B35) -> 10000 | Q35: =P35/J35 -> 0.2632361 | R35: =SUMIFS(月汇总!Q:Q,月汇总!B:B,B35) -> 230 | S35: =R35/J35 -> 0.0060544304 | T35: =SUMIFS(月汇总!N:N,月汇总!B:B,B35) -> 220.88197 | V35: =SUMIFS(月汇总!X:X,月汇总!B:B,B35) -> 3000 | W35: =V35/J35 -> 0.078970831 | X35: =SUMIFS(月汇总!U:U,月汇总!B:B,B35) -> 466 | Y35: =X35/J35 -> 0.012266802 | Z35: =SUMIFS(月汇总!O:O,月汇总!B:B,B35) -> 0 | AA35: =Z35/J35 -> 0 | AB35: =SUMIFS(月汇总!T:T,月汇总!B:B,B35) -> 200 | AC35: =AB35/J35 -> 0.0052647221 | AD35: =SUMIFS(月汇总!Z:Z,月汇总!B:B,B35) -> 2659.2097 | AE35: =AD35/J35 -> 0.07 | AF35: =SUMIFS(月汇总!AC:AC,月汇总!B:B,B35) -> 790.16393 | AG35: =AF35/J35 -> 0.020799968 | AH35: =SUMIFS(月汇总!V:V,月汇总!B:B,B35) -> 397.39246 | AI35: =AH35/J35 -> 0.010460804 | AJ35: =M35+P35+R35+T35+V35+X35+Z35+AB35+AD35+AF35+AH35 -> 31817.836 | AK35: =SUMIFS(月汇总!AA:AA,月汇总!B:B,B35) -> 10600 | AL35: =J35-K35-L35-AJ35-AK35 -> -4639.1257 | AM35: =AL35/J35 -> -0.12211854 | AN35: =SUMIFS(月汇总!AB:AB,月汇总!B:B,B35) -> 0 | AO35: =SUMIFS(月汇总!W:W,月汇总!B:B,B35) -> 2666 | AP35: =AL35-AN35-AO35 -> -7305.1257
A36: 32 | B36: 粤B43551D | C36: 罗吴华 | D36: 杨发明 | E36: 广西-玉溪 | F36: 桂LC523挂 | G36: 重型半挂牵引车 | H36: =COUNTIFS(磅单!E:E,B36) -> 18 | I36: =SUMIFS(磅单!L:L,磅单!E:E,B36) -> 769.44 | J36: =SUMIFS(磅单!O:O,磅单!E:E,B36) -> 49469.5 | K36: =SUMIFS(月汇总!Y:Y,月汇总!B:B,B36) -> 270 | L36: =SUMIFS(月汇总!I:I,月汇总!B:B,B36,月汇总!C:C,F38) -> 0 | M36: =SUMIFS(月汇总!J:J,月汇总!B:B,B36,月汇总!C:C,F36) -> 19178.568 | N36: =M36/J36 -> 0.3876847 | O36: =M36/H36 -> 1065.476 | P36: =SUMIFS(月汇总!R:R,月汇总!B:B,B36)+SUMIFS(月汇总!S:S,月汇总!B:B,B36) -> 11200 | Q36: =P36/J36 -> 0.22640213 | R36: =SUMIFS(月汇总!Q:Q,月汇总!B:B,B36) -> 100 | S36: =R36/J36 -> 0.0020214476 | T36: =SUMIFS(月汇总!N:N,月汇总!B:B,B36) -> 220.88197 | V36: =SUMIFS(月汇总!X:X,月汇总!B:B,B36) -> 3000 | W36: =V36/J36 -> 0.060643427 | X36: =SUMIFS(月汇总!U:U,月汇总!B:B,B36) -> 424 | Y36: =X36/J36 -> 0.0085709376 | Z36: =SUMIFS(月汇总!O:O,月汇总!B:B,B36) -> 0 | AA36: =Z36/J36 -> 0 | AB36: =SUMIFS(月汇总!T:T,月汇总!B:B,B36) -> 220 | AC36: =AB36/J36 -> 0.0044471846 | AD36: =SUMIFS(月汇总!Z:Z,月汇总!B:B,B36) -> 3462.865 | AE36: =AD36/J36 -> 0.07 | AF36: =SUMIFS(月汇总!AC:AC,月汇总!B:B,B36) -> 790.16393 | AG36: =AF36/J36 -> 0.01597275 | AH36: =SUMIFS(月汇总!V:V,月汇总!B:B,B36) -> 397.39246 | AI36: =AH36/J36 -> 0.0080330802 | AJ36: =M36+P36+R36+T36+V36+X36+Z36+AB36+AD36+AF36+AH36 -> 38993.872 | AK36: =SUMIFS(月汇总!AA:AA,月汇总!B:B,B36) -> 10600 | AL36: =J36-K36-L36-AJ36-AK36 -> -394.37162 | AM36: =AL36/J36 -> -0.0079720155 | AN36: =SUMIFS(月汇总!AB:AB,月汇总!B:B,B36) -> 0 | AO36: =SUMIFS(月汇总!W:W,月汇总!B:B,B36) -> 2666 | AP36: =AL36-AN36-AO36 -> -3060.3716
A37: 33 | B37: 粤B98485D | C37: 覃胜猛 | D37: 陈金杰 | E37: 广西-玉溪 | F37: 桂L4036挂 | G37: 重型半挂牵引车 | H37: =COUNTIFS(磅单!E:E,B37) -> 17 | I37: =SUMIFS(磅单!L:L,磅单!E:E,B37) -> 740.58 | J37: =SUMIFS(磅单!O:O,磅单!E:E,B37) -> 48038.96 | K37: =SUMIFS(月汇总!Y:Y,月汇总!B:B,B37) -> 255 | L37: =SUMIFS(月汇总!I:I,月汇总!B:B,B37,月汇总!C:C,F39) -> 0 | M37: =SUMIFS(月汇总!J:J,月汇总!B:B,B37,月汇总!C:C,F37) -> 17792.421 | N37: =M37/J37 -> 0.37037482 | O37: =M37/H37 -> 1046.613 | P37: =SUMIFS(月汇总!R:R,月汇总!B:B,B37)+SUMIFS(月汇总!S:S,月汇总!B:B,B37) -> 10600 | Q37: =P37/J37 -> 0.22065424 | R37: =SUMIFS(月汇总!Q:Q,月汇总!B:B,B37) -> 50 | S37: =R37/J37 -> 0.0010408219 | T37: =SUMIFS(月汇总!N:N,月汇总!B:B,B37) -> 220.88197 | V37: =SUMIFS(月汇总!X:X,月汇总!B:B,B37) -> 3000 | W37: =V37/J37 -> 0.062449312 | X37: =SUMIFS(月汇总!U:U,月汇总!B:B,B37) -> 410 | Y37: =X37/J37 -> 0.0085347393 | Z37: =SUMIFS(月汇总!O:O,月汇总!B:B,B37) -> 0 | AA37: =Z37/J37 -> 0 | AB37: =SUMIFS(月汇总!T:T,月汇总!B:B,B37) -> 200 | AC37: =AB37/J37 -> 0.0041632875 | AD37: =SUMIFS(月汇总!Z:Z,月汇总!B:B,B37) -> 3362.7272 | AE37: =AD37/J37 -> 0.07 | AF37: =SUMIFS(月汇总!AC:AC,月汇总!B:B,B37) -> 790.16393 | AG37: =AF37/J37 -> 0.016448398 | AH37: =SUMIFS(月汇总!V:V,月汇总!B:B,B37) -> 397.39246 | AI37: =AH37/J37 -> 0.0082722952 | AJ37: =M37+P37+R37+T37+V37+X37+Z37+AB37+AD37+AF37+AH37 -> 36823.587 | AK37: =SUMIFS(月汇总!AA:AA,月汇总!B:B,B37) -> 10600 | AL37: =J37-K37-L37-AJ37-AK37 -> 360.37313 | AM37: =AL37/J37 -> 0.0075016846 | AN37: =SUMIFS(月汇总!AB:AB,月汇总!B:B,B37) -> 0 | AO37: =SUMIFS(月汇总!W:W,月汇总!B:B,B37) -> 2666 | AP37: =AL37-AN37-AO37 -> -2305.6269
A38: 34 | B38: 粤B93085D | C38: 盘靖 | D38: 袁俊杰 | E38: 广西-玉溪 | F38: 桂L13C55挂 | G38: 重型半挂牵引车 | H38: =COUNTIFS(磅单!E:E,B38) -> 9 | I38: =SUMIFS(磅单!L:L,磅单!E:E,B38) -> 393.24 | J38: =SUMIFS(磅单!O:O,磅单!E:E,B38) -> 27869.18 | K38: =SUMIFS(月汇总!Y:Y,月汇总!B:B,B38) -> 135 | L38: =SUMIFS(月汇总!I:I,月汇总!B:B,B38,月汇总!C:C,F40) -> 0 | M38: =SUMIFS(月汇总!J:J,月汇总!B:B,B38,月汇总!C:C,F38) -> 10008.92 | N38: =M38/J38 -> 0.35913938 | O38: =M38/H38 -> 1112.1022 | P38: =SUMIFS(月汇总!R:R,月汇总!B:B,B38)+SUMIFS(月汇总!S:S,月汇总!B:B,B38) -> 6400 | Q38: =P38/J38 -> 0.22964436 | R38: =SUMIFS(月汇总!Q:Q,月汇总!B:B,B38) -> 130 | S38: =R38/J38 -> 0.0046646511 | T38: =SUMIFS(月汇总!N:N,月汇总!B:B,B38) -> 220.88197 | V38: =SUMIFS(月汇总!X:X,月汇总!B:B,B38) -> 3100 | W38: =V38/J38 -> 0.11123399 | X38: =SUMIFS(月汇总!U:U,月汇总!B:B,B38) -> 337 | Y38: =X38/J38 -> 0.012092211 | Z38: =SUMIFS(月汇总!O:O,月汇总!B:B,B38) -> 0 | AA38: =Z38/J38 -> 0 | AB38: =SUMIFS(月汇总!T:T,月汇总!B:B,B38) -> 0 | AC38: =AB38/J38 -> 0 | AD38: =SUMIFS(月汇总!Z:Z,月汇总!B:B,B38) -> 1950.8426 | AE38: =AD38/J38 -> 0.07 | AF38: =SUMIFS(月汇总!AC:AC,月汇总!B:B,B38) -> 790.16393 | AG38: =AF38/J38 -> 0.028352608 | AH38: =SUMIFS(月汇总!V:V,月汇总!B:B,B38) -> 397.39246 | AI38: =AH38/J38 -> 0.014259209 | AJ38: =M38+P38+R38+T38+V38+X38+Z38+AB38+AD38+AF38+AH38 -> 23335.201 | AK38: =SUMIFS(月汇总!AA:AA,月汇总!B:B,B38) -> 10600 | AL38: =J38-K38-L38-AJ38-AK38 -> -6201.0209 | AM38: =AL38/J38 -> -0.2225046 | AN38: =SUMIFS(月汇总!AB:AB,月汇总!B:B,B38) -> 0 | AO38: =SUMIFS(月汇总!W:W,月汇总!B:B,B38) -> 2666 | AP38: =AL38-AN38-AO38 -> -8867.0209
A39: 35 | B39: 粤B85970D | C39: 陆世鹏 | D39: 陈金杰 | E39: 广西-玉溪 | F39: 桂L76464挂 | G39: 重型半挂牵引车 | H39: =COUNTIFS(磅单!E:E,B39) -> 11 | I39: =SUMIFS(磅单!L:L,磅单!E:E,B39) -> 476.11 | J39: =SUMIFS(磅单!O:O,磅单!E:E,B39) -> 31418.83 | K39: =SUMIFS(月汇总!Y:Y,月汇总!B:B,B39) -> 165 | L39: =SUMIFS(月汇总!I:I,月汇总!B:B,B39,月汇总!C:C,F41) -> 0 | M39: =SUMIFS(月汇总!J:J,月汇总!B:B,B39,月汇总!C:C,F39) -> 12396.287 | N39: =M39/J39 -> 0.39454959 | O39: =M39/H39 -> 1126.9351 | P39: =SUMIFS(月汇总!R:R,月汇总!B:B,B39)+SUMIFS(月汇总!S:S,月汇总!B:B,B39) -> 7400 | Q39: =P39/J39 -> 0.23552755 | R39: =SUMIFS(月汇总!Q:Q,月汇总!B:B,B39) -> 90 | S39: =R39/J39 -> 0.0028645242 | T39: =SUMIFS(月汇总!N:N,月汇总!B:B,B39) -> 220.88197 | V39: =SUMIFS(月汇总!X:X,月汇总!B:B,B39) -> 3100 | W39: =V39/J39 -> 0.098666946 | X39: =SUMIFS(月汇总!U:U,月汇总!B:B,B39) -> 328 | Y39: =X39/J39 -> 0.010439599 | Z39: =SUMIFS(月汇总!O:O,月汇总!B:B,B39) -> 0 | AA39: =Z39/J39 -> 0 | AB39: =SUMIFS(月汇总!T:T,月汇总!B:B,B39) -> 200 | AC39: =AB39/J39 -> 0.0063656094 | AD39: =SUMIFS(月汇总!Z:Z,月汇总!B:B,B39) -> 2199.3181 | AE39: =AD39/J39 -> 0.07 | AF39: =SUMIFS(月汇总!AC:AC,月汇总!B:B,B39) -> 790.16393 | AG39: =AF39/J39 -> 0.025149375 | AH39: =SUMIFS(月汇总!V:V,月汇总!B:B,B39) -> 397.39246 | AI39: =AH39/J39 -> 0.012648226 | AJ39: =M39+P39+R39+T39+V39+X39+Z39+AB39+AD39+AF39+AH39 -> 27122.043 | AK39: =SUMIFS(月汇总!AA:AA,月汇总!B:B,B39) -> 10600 | AL39: =J39-K39-L39-AJ39-AK39 -> -6468.2131 | AM39: =AL39/J39 -> -0.20587059 | AN39: =SUMIFS(月汇总!AB:AB,月汇总!B:B,B39) -> 0 | AO39: =SUMIFS(月汇总!W:W,月汇总!B:B,B39) -> 2666 | AP39: =AL39-AN39-AO39 -> -9134.2131
A40: 36 | B40: 粤B78432D | C40: 张俊 | D40: 陈金杰 | E40: 广西-玉溪 | F40: 桂L6429挂 | G40: 重型半挂牵引车 | H40: =COUNTIFS(磅单!E:E,B40) -> 13 | I40: =SUMIFS(磅单!L:L,磅单!E:E,B40) -> 564.55 | J40: =SUMIFS(磅单!O:O,磅单!E:E,B40) -> 40949.85 | K40: =SUMIFS(月汇总!Y:Y,月汇总!B:B,B40) -> 195 | L40: =SUMIFS(月汇总!I:I,月汇总!B:B,B40,月汇总!C:C,F42) -> 0 | M40: =SUMIFS(月汇总!J:J,月汇总!B:B,B40,月汇总!C:C,F40) -> 13245.676 | N40: =M40/J40 -> 0.3234609 | O40: =M40/H40 -> 1018.8981 | P40: =SUMIFS(月汇总!R:R,月汇总!B:B,B40)+SUMIFS(月汇总!S:S,月汇总!B:B,B40) -> 9200 | Q40: =P40/J40 -> 0.22466505 | R40: =SUMIFS(月汇总!Q:Q,月汇总!B:B,B40) -> 180 | S40: =R40/J40 -> 0.0043956205 | T40: =SUMIFS(月汇总!N:N,月汇总!B:B,B40) -> 220.88197 | V40: =SUMIFS(月汇总!X:X,月汇总!B:B,B40) -> 3200 | W40: =V40/J40 -> 0.078144364 | X40: =SUMIFS(月汇总!U:U,月汇总!B:B,B40) -> 229 | Y40: =X40/J40 -> 0.0055922061 | Z40: =SUMIFS(月汇总!O:O,月汇总!B:B,B40) -> 950 | AA40: =Z40/J40 -> 0.023199108 | AB40: =SUMIFS(月汇总!T:T,月汇总!B:B,B40) -> 200 | AC40: =AB40/J40 -> 0.0048840228 | AD40: =SUMIFS(月汇总!Z:Z,月汇总!B:B,B40) -> 2866.4895 | AE40: =AD40/J40 -> 0.07 | AF40: =SUMIFS(月汇总!AC:AC,月汇总!B:B,B40) -> 790.16393 | AG40: =AF40/J40 -> 0.019295893 | AH40: =SUMIFS(月汇总!V:V,月汇总!B:B,B40) -> 397.39246 | AI40: =AH40/J40 -> 0.0097043691 | AJ40: =M40+P40+R40+T40+V40+X40+Z40+AB40+AD40+AF40+AH40 -> 31479.603 | AK40: =SUMIFS(月汇总!AA:AA,月汇总!B:B,B40) -> 10600 | AL40: =J40-K40-L40-AJ40-AK40 -> -1324.7534 | AM40: =AL40/J40 -> -0.032350628 | AN40: =SUMIFS(月汇总!AB:AB,月汇总!B:B,B40) -> 0 | AO40: =SUMIFS(月汇总!W:W,月汇总!B:B,B40) -> 2666 | AP40: =AL40-AN40-AO40 -> -3990.7534
A41: 37 | B41: 粤B94650D | C41: 赵雄 | D41: 陈金杰 | E41: 广西-玉溪 | F41: 桂LD631挂 | G41: 重型半挂牵引车 | H41: =COUNTIFS(磅单!E:E,B41) -> 12 | I41: =SUMIFS(磅单!L:L,磅单!E:E,B41) -> 511.96 | J41: =SUMIFS(磅单!O:O,磅单!E:E,B41) -> 38347.32 | K41: =SUMIFS(月汇总!Y:Y,月汇总!B:B,B41) -> 180 | L41: =SUMIFS(月汇总!I:I,月汇总!B:B,B41,月汇总!C:C,F43) -> 0 | M41: =SUMIFS(月汇总!J:J,月汇总!B:B,B41,月汇总!C:C,F41) -> 13602.169 | N41: =M41/J41 -> 0.35470978 | O41: =M41/H41 -> 1133.5141 | P41: =SUMIFS(月汇总!R:R,月汇总!B:B,B41)+SUMIFS(月汇总!S:S,月汇总!B:B,B41) -> 8800 | Q41: =P41/J41 -> 0.22948149 | R41: =SUMIFS(月汇总!Q:Q,月汇总!B:B,B41) -> 760 | S41: =R41/J41 -> 0.019818856 | T41: =SUMIFS(月汇总!N:N,月汇总!B:B,B41) -> 220.88197 | V41: =SUMIFS(月汇总!X:X,月汇总!B:B,B41) -> 3200 | W41: =V41/J41 -> 0.083447813 | X41: =SUMIFS(月汇总!U:U,月汇总!B:B,B41) -> 210 | Y41: =X41/J41 -> 0.0054762627 | Z41: =SUMIFS(月汇总!O:O,月汇总!B:B,B41) -> 0 | AA41: =Z41/J41 -> 0 | AB41: =SUMIFS(月汇总!T:T,月汇总!B:B,B41) -> 200 | AC41: =AB41/J41 -> 0.0052154883 | AD41: =SUMIFS(月汇总!Z:Z,月汇总!B:B,B41) -> 2684.3124 | AE41: =AD41/J41 -> 0.07 | AF41: =SUMIFS(月汇总!AC:AC,月汇总!B:B,B41) -> 790.16393 | AG41: =AF41/J41 -> 0.020605454 | AH41: =SUMIFS(月汇总!V:V,月汇总!B:B,B41) -> 397.39246 | AI41: =AH41/J41 -> 0.010362979 | AJ41: =M41+P41+R41+T41+V41+X41+Z41+AB41+AD41+AF41+AH41 -> 30864.92 | AK41: =SUMIFS(月汇总!AA:AA,月汇总!B:B,B41) -> 10600 | AL41: =J41-K41-L41-AJ41-AK41 -> -3297.6001 | AM41: =AL41/J41 -> -0.085992973 | AN41: =SUMIFS(月汇总!AB:AB,月汇总!B:B,B41) -> 0 | AO41: =SUMIFS(月汇总!W:W,月汇总!B:B,B41) -> 2666 | AP41: =AL41-AN41-AO41 -> -5963.6001
A42: 38 | B42: 粤B47340D | C42: 曾龙龙 | D42: 陈金杰 | E42: 广西-玉溪 | F42: 桂L5748挂 | G42: 重型半挂牵引车 | H42: =COUNTIFS(磅单!E:E,B42) -> 11 | I42: =SUMIFS(磅单!L:L,磅单!E:E,B42) -> 471.26 | J42: =SUMIFS(磅单!O:O,磅单!E:E,B42) -> 34804.6 | K42: =SUMIFS(月汇总!Y:Y,月汇总!B:B,B42) -> 165 | L42: =SUMIFS(月汇总!I:I,月汇总!B:B,B42,月汇总!C:C,F44) -> 0 | M42: =SUMIFS(月汇总!J:J,月汇总!B:B,B42,月汇总!C:C,F42) -> 12537.759 | N42: =M42/J42 -> 0.3602328 | O42: =M42/H42 -> 1139.7962 | P42: =SUMIFS(月汇总!R:R,月汇总!B:B,B42)+SUMIFS(月汇总!S:S,月汇总!B:B,B42) -> 8000 | Q42: =P42/J42 -> 0.22985467 | R42: =SUMIFS(月汇总!Q:Q,月汇总!B:B,B42) -> 180 | S42: =R42/J42 -> 0.0051717302 | T42: =SUMIFS(月汇总!N:N,月汇总!B:B,B42) -> 220.88197 | V42: =SUMIFS(月汇总!X:X,月汇总!B:B,B42) -> 3200 | W42: =V42/J42 -> 0.09194187 | X42: =SUMIFS(月汇总!U:U,月汇总!B:B,B42) -> 207 | Y42: =X42/J42 -> 0.0059474897 | Z42: =SUMIFS(月汇总!O:O,月汇总!B:B,B42) -> 0 | AA42: =Z42/J42 -> 0 | AB42: =SUMIFS(月汇总!T:T,月汇总!B:B,B42) -> 220 | AC42: =AB42/J42 -> 0.0063210035 | AD42: =SUMIFS(月汇总!Z:Z,月汇总!B:B,B42) -> 2436.322 | AE42: =AD42/J42 -> 0.07 | AF42: =SUMIFS(月汇总!AC:AC,月汇总!B:B,B42) -> 790.16393 | AG42: =AF42/J42 -> 0.022702859 | AH42: =SUMIFS(月汇总!V:V,月汇总!B:B,B42) -> 397.39246 | AI42: =AH42/J42 -> 0.011417814 | AJ42: =M42+P42+R42+T42+V42+X42+Z42+AB42+AD42+AF42+AH42 -> 28189.519 | AK42: =SUMIFS(月汇总!AA:AA,月汇总!B:B,B42) -> 10600 | AL42: =J42-K42-L42-AJ42-AK42 -> -4149.9189 | AM42: =AL42/J42 -> -0.11923478 | AN42: =SUMIFS(月汇总!AB:AB,月汇总!B:B,B42) -> 0 | AO42: =SUMIFS(月汇总!W:W,月汇总!B:B,B42) -> 2666 | AP42: =AL42-AN42-AO42 -> -6815.9189
A43: 39 | B43: 粤B99322D | C43: 李昆 | D43: 陈金杰 | E43: 广西-玉溪 | F43: 桂L6249挂 | G43: 重型半挂牵引车 | H43: =COUNTIFS(磅单!E:E,B43) -> 11 | I43: =SUMIFS(磅单!L:L,磅单!E:E,B43) -> 466.22 | J43: =SUMIFS(磅单!O:O,磅单!E:E,B43) -> 34415.52 | K43: =SUMIFS(月汇总!Y:Y,月汇总!B:B,B43) -> 165 | L43: =SUMIFS(月汇总!I:I,月汇总!B:B,B43,月汇总!C:C,F45) -> 0 | M43: =SUMIFS(月汇总!J:J,月汇总!B:B,B43,月汇总!C:C,F43) -> 12805.259 | N43: =M43/J43 -> 0.37207802 | O43: =M43/H43 -> 1164.1144 | P43: =SUMIFS(月汇总!R:R,月汇总!B:B,B43)+SUMIFS(月汇总!S:S,月汇总!B:B,B43) -> 8000 | Q43: =P43/J43 -> 0.23245327 | R43: =SUMIFS(月汇总!Q:Q,月汇总!B:B,B43) -> 70 | S43: =R43/J43 -> 0.0020339661 | T43: =SUMIFS(月汇总!N:N,月汇总!B:B,B43) -> 220.88197 | V43: =SUMIFS(月汇总!X:X,月汇总!B:B,B43) -> 3200 | W43: =V43/J43 -> 0.092981306 | X43: =SUMIFS(月汇总!U:U,月汇总!B:B,B43) -> 197 | Y43: =X43/J43 -> 0.0057241617 | Z43: =SUMIFS(月汇总!O:O,月汇总!B:B,B43) -> 0 | AA43: =Z43/J43 -> 0 | AB43: =SUMIFS(月汇总!T:T,月汇总!B:B,B43) -> 0 | AC43: =AB43/J43 -> 0 | AD43: =SUMIFS(月汇总!Z:Z,月汇总!B:B,B43) -> 2409.0864 | AE43: =AD43/J43 -> 0.07 | AF43: =SUMIFS(月汇总!AC:AC,月汇总!B:B,B43) -> 790.16393 | AG43: =AF43/J43 -> 0.022959523 | AH43: =SUMIFS(月汇总!V:V,月汇总!B:B,B43) -> 397.39246 | AI43: =AH43/J43 -> 0.011546897 | AJ43: =M43+P43+R43+T43+V43+X43+Z43+AB43+AD43+AF43+AH43 -> 28089.783 | AK43: =SUMIFS(月汇总!AA:AA,月汇总!B:B,B43) -> 10600 | AL43: =J43-K43-L43-AJ43-AK43 -> -4439.2633 | AM43: =AL43/J43 -> -0.12899016 | AN43: =SUMIFS(月汇总!AB:AB,月汇总!B:B,B43) -> 0 | AO43: =SUMIFS(月汇总!W:W,月汇总!B:B,B43) -> 2666 | AP43: =AL43-AN43-AO43 -> -7105.2633
A44: 40 | B44: 粤B96406D | C44: 杨光傅 | D44: 陈金杰 | E44: 广西-玉溪 | F44: 桂L8626挂 | G44: 重型半挂牵引车 | H44: =COUNTIFS(磅单!E:E,B44) -> 13 | I44: =SUMIFS(磅单!L:L,磅单!E:E,B44) -> 565.56 | J44: =SUMIFS(磅单!O:O,磅单!E:E,B44) -> 40860.88 | K44: =SUMIFS(月汇总!Y:Y,月汇总!B:B,B44) -> 195 | L44: =SUMIFS(月汇总!I:I,月汇总!B:B,B44,月汇总!C:C,F46) -> 0 | M44: =SUMIFS(月汇总!J:J,月汇总!B:B,B44,月汇总!C:C,F44) -> 12702.374 | N44: =M44/J44 -> 0.31086882 | O44: =M44/H44 -> 977.10566 | P44: =SUMIFS(月汇总!R:R,月汇总!B:B,B44)+SUMIFS(月汇总!S:S,月汇总!B:B,B44) -> 9000 | Q44: =P44/J44 -> 0.22025957 | R44: =SUMIFS(月汇总!Q:Q,月汇总!B:B,B44) -> 20 | S44: =R44/J44 -> 0.00048946572 | T44: =SUMIFS(月汇总!N:N,月汇总!B:B,B44) -> 220.88197 | V44: =SUMIFS(月汇总!X:X,月汇总!B:B,B44) -> 3200 | W44: =V44/J44 -> 0.078314515 | X44: =SUMIFS(月汇总!U:U,月汇总!B:B,B44) -> 295 | Y44: =X44/J44 -> 0.0072196194 | Z44: =SUMIFS(月汇总!O:O,月汇总!B:B,B44) -> 0 | AA44: =Z44/J44 -> 0 | AB44: =SUMIFS(月汇总!T:T,月汇总!B:B,B44) -> 0 | AC44: =AB44/J44 -> 0 | AD44: =SUMIFS(月汇总!Z:Z,月汇总!B:B,B44) -> 2860.2616 | AE44: =AD44/J44 -> 0.07 | AF44: =SUMIFS(月汇总!AC:AC,月汇总!B:B,B44) -> 790.16393 | AG44: =AF44/J44 -> 0.019337908 | AH44: =SUMIFS(月汇总!V:V,月汇总!B:B,B44) -> 397.39246 | AI44: =AH44/J44 -> 0.0097254993 | AJ44: =M44+P44+R44+T44+V44+X44+Z44+AB44+AD44+AF44+AH44 -> 29486.074 | AK44: =SUMIFS(月汇总!AA:AA,月汇总!B:B,B44) -> 10600 | AL44: =J44-K44-L44-AJ44-AK44 -> 579.80643 | AM44: =AL44/J44 -> 0.014189769 | AN44: =SUMIFS(月汇总!AB:AB,月汇总!B:B,B44) -> 0 | AO44: =SUMIFS(月汇总!W:W,月汇总!B:B,B44) -> 2666 | AP44: =AL44-AN44-AO44 -> -2086.1936
A45: 41 | B45: 粤B95488D | C45: 赵洪凡 | D45: 陈金杰 | E45: 广西-玉溪 | F45: 桂L5939挂 | G45: 重型半挂牵引车 | H45: =COUNTIFS(磅单!E:E,B45) -> 10 | I45: =SUMIFS(磅单!L:L,磅单!E:E,B45) -> 433.28 | J45: =SUMIFS(磅单!O:O,磅单!E:E,B45) -> 30994.56 | K45: =SUMIFS(月汇总!Y:Y,月汇总!B:B,B45) -> 150 | L45: =SUMIFS(月汇总!I:I,月汇总!B:B,B45,月汇总!C:C,F66) -> 0 | M45: =SUMIFS(月汇总!J:J,月汇总!B:B,B45,月汇总!C:C,F45) -> 10634.231 | N45: =M45/J45 -> 0.34309992 | O45: =M45/H45 -> 1063.4231 | P45: =SUMIFS(月汇总!R:R,月汇总!B:B,B45)+SUMIFS(月汇总!S:S,月汇总!B:B,B45) -> 7000 | Q45: =P45/J45 -> 0.22584608 | R45: =SUMIFS(月汇总!Q:Q,月汇总!B:B,B45) -> 260 | S45: =R45/J45 -> 0.0083885688 | T45: =SUMIFS(月汇总!N:N,月汇总!B:B,B45) -> 220.88197 | V45: =SUMIFS(月汇总!X:X,月汇总!B:B,B45) -> 3200 | W45: =V45/J45 -> 0.10324392 | X45: =SUMIFS(月汇总!U:U,月汇总!B:B,B45) -> 175 | Y45: =X45/J45 -> 0.0056461521 | Z45: =SUMIFS(月汇总!O:O,月汇总!B:B,B45) -> 950 | AA45: =Z45/J45 -> 0.03065054 | AB45: =SUMIFS(月汇总!T:T,月汇总!B:B,B45) -> 0 | AC45: =AB45/J45 -> 0 | AD45: =SUMIFS(月汇总!Z:Z,月汇总!B:B,B45) -> 2169.6192 | AE45: =AD45/J45 -> 0.07 | AF45: =SUMIFS(月汇总!AC:AC,月汇总!B:B,B45) -> 790.16393 | AG45: =AF45/J45 -> 0.025493633 | AH45: =SUMIFS(月汇总!V:V,月汇总!B:B,B45) -> 397.39246 | AI45: =AH45/J45 -> 0.012821362 | AJ45: =M45+P45+R45+T45+V45+X45+Z45+AB45+AD45+AF45+AH45 -> 25797.288 | AK45: =SUMIFS(月汇总!AA:AA,月汇总!B:B,B45) -> 0 | AL45: =J45-K45-L45-AJ45-AK45 -> 5047.2715 | AM45: =AL45/J45 -> 0.16284379 | AN45: =SUMIFS(月汇总!AB:AB,月汇总!B:B,B45) -> 0 | AO45: =SUMIFS(月汇总!W:W,月汇总!B:B,B45) -> 2666 | AP45: =AL45-AN45-AO45 -> 2381.2715
A46: 42 | B46: 云F03990D | C46: 赵大云 | D46: 杨发明 | E46: 广西-玉溪 | F46: 桂LB629挂 | G46: 重型半挂牵引车 | H46: =COUNTIFS(磅单!E:E,B46) -> 7 | I46: =SUMIFS(磅单!L:L,磅单!E:E,B46) -> 288.78 | J46: =SUMIFS(磅单!O:O,磅单!E:E,B46) -> 16681.4 | K46: =SUMIFS(月汇总!Y:Y,月汇总!B:B,B46) -> 105 | L46: =SUMIFS(月汇总!I:I,月汇总!B:B,B46,月汇总!C:C,F67) -> 0 | M46: =SUMIFS(月汇总!J:J,月汇总!B:B,B46) -> 5341.5002 | N46: =M46/J46 -> 0.32020695 | O46: =M46/H46 -> 763.07146 | P46: =SUMIFS(月汇总!R:R,月汇总!B:B,B46)+SUMIFS(月汇总!S:S,月汇总!B:B,B46) -> 4200 | Q46: =P46/J46 -> 0.25177743 | R46: =SUMIFS(月汇总!Q:Q,月汇总!B:B,B46) -> 60 | S46: =R46/J46 -> 0.0035968204 | T46: =SUMIFS(月汇总!N:N,月汇总!B:B,B46) -> 220.88197 | V46: =SUMIFS(月汇总!X:X,月汇总!B:B,B46) -> 0 | W46: =V46/J46 -> 0 | X46: =SUMIFS(月汇总!U:U,月汇总!B:B,B46) -> 855.4 | Y46: =X46/J46 -> 0.05127867 | Z46: =SUMIFS(月汇总!O:O,月汇总!B:B,B46) -> 0 | AA46: =Z46/J46 -> 0 | AB46: =SUMIFS(月汇总!T:T,月汇总!B:B,B46) -> 0 | AC46: =AB46/J46 -> 0 | AD46: =SUMIFS(月汇总!Z:Z,月汇总!B:B,B46) -> 1167.698 | AE46: =AD46/J46 -> 0.07 | AF46: =SUMIFS(月汇总!AC:AC,月汇总!B:B,B46) -> 790.16393 | AG46: =AF46/J46 -> 0.047367963 | AH46: =SUMIFS(月汇总!V:V,月汇总!B:B,B46) -> 397.39246 | AI46: =AH46/J46 -> 0.023822488 | AJ46: =M46+P46+R46+T46+V46+X46+Z46+AB46+AD46+AF46+AH46 -> 13033.037 | AK46: =SUMIFS(月汇总!AA:AA,月汇总!B:B,B46) -> 0 | AL46: =J46-K46-L46-AJ46-AK46 -> 3543.3634 | AM46: =AL46/J46 -> 0.21241403 | AN46: =SUMIFS(月汇总!AB:AB,月汇总!B:B,B46) -> 2280 | AO46: =SUMIFS(月汇总!W:W,月汇总!B:B,B46) -> 0 | AP46: =AL46-AN46-AO46 -> 1263.3634
A47: 43 | B47: 粤B87855D | C47: 马辉 | D47: 陈金杰 | E47: 广西-玉溪 | F47: 桂LD762挂 | G47: 重型半挂牵引车 | H47: =COUNTIFS(磅单!E:E,B47) -> 10 | I47: =SUMIFS(磅单!L:L,磅单!E:E,B47) -> 427.61 | J47: =SUMIFS(磅单!O:O,磅单!E:E,B47) -> 31830.41 | K47: =SUMIFS(月汇总!Y:Y,月汇总!B:B,B47) -> 150 | L47: =SUMIFS(月汇总!I:I,月汇总!B:B,B47,月汇总!C:C,F68) -> 0 | M47: =SUMIFS(月汇总!J:J,月汇总!B:B,B47,月汇总!C:C,F47) -> 12209.052 | N47: =M47/J47 -> 0.38356566 | O47: =M47/H47 -> 1220.9052 | P47: =SUMIFS(月汇总!R:R,月汇总!B:B,B47)+SUMIFS(月汇总!S:S,月汇总!B:B,B47) -> 7200 | Q47: =P47/J47 -> 0.22619878 | R47: =SUMIFS(月汇总!Q:Q,月汇总!B:B,B47) -> 0 | S47: =R47/J47 -> 0 | T47: =SUMIFS(月汇总!N:N,月汇总!B:B,B47) -> 220.88197 | V47: =SUMIFS(月汇总!X:X,月汇总!B:B,B47) -> 3200 | W47: =V47/J47 -> 0.10053279 | X47: =SUMIFS(月汇总!U:U,月汇总!B:B,B47) -> 194 | Y47: =X47/J47 -> 0.0060948005 | Z47: =SUMIFS(月汇总!O:O,月汇总!B:B,B47) -> 0 | AA47: =Z47/J47 -> 0 | AB47: =SUMIFS(月汇总!T:T,月汇总!B:B,B47) -> 0 | AC47: =AB47/J47 -> 0 | AD47: =SUMIFS(月汇总!Z:Z,月汇总!B:B,B47) -> 2228.1287 | AE47: =AD47/J47 -> 0.07 | AF47: =SUMIFS(月汇总!AC:AC,月汇总!B:B,B47) -> 790.16393 | AG47: =AF47/J47 -> 0.024824183 | AH47: =SUMIFS(月汇总!V:V,月汇总!B:B,B47) -> 397.39246 | AI47: =AH47/J47 -> 0.012484679 | AJ47: =M47+P47+R47+T47+V47+X47+Z47+AB47+AD47+AF47+AH47 -> 26439.619 | AK47: =SUMIFS(月汇总!AA:AA,月汇总!B:B,B47) -> 0 | AL47: =J47-K47-L47-AJ47-AK47 -> 5240.7907 | AM47: =AL47/J47 -> 0.16464729 | AN47: =SUMIFS(月汇总!AB:AB,月汇总!B:B,B47) -> 0 | AO47: =SUMIFS(月汇总!W:W,月汇总!B:B,B47) -> 2666 | AP47: =AL47-AN47-AO47 -> 2574.7907
A48: 44 | B48: 粤B49365D | C48: 兰荣建 | D48: 陈金杰 | E48: 广西-玉溪 | F48: 桂LC671挂 | G48: 重型半挂牵引车 | H48: =COUNTIFS(磅单!E:E,B48) -> 11 | I48: =SUMIFS(磅单!L:L,磅单!E:E,B48) -> 463.5 | J48: =SUMIFS(磅单!O:O,磅单!E:E,B48) -> 34892.06 | K48: =SUMIFS(月汇总!Y:Y,月汇总!B:B,B48) -> 150 | L48: =SUMIFS(月汇总!I:I,月汇总!B:B,B48,月汇总!C:C,F69) -> 0 | M48: =SUMIFS(月汇总!J:J,月汇总!B:B,B48,月汇总!C:C,F48) -> 11158.452 | N48: =M48/J48 -> 0.31979916 | O48: =M48/H48 -> 1014.4047 | P48: =SUMIFS(月汇总!R:R,月汇总!B:B,B48)+SUMIFS(月汇总!S:S,月汇总!B:B,B48) -> 7800 | Q48: =P48/J48 -> 0.22354656 | R48: =SUMIFS(月汇总!Q:Q,月汇总!B:B,B48) -> 60 | S48: =R48/J48 -> 0.0017195889 | T48: =SUMIFS(月汇总!N:N,月汇总!B:B,B48) -> 220.88197 | V48: =SUMIFS(月汇总!X:X,月汇总!B:B,B48) -> 2800 | W48: =V48/J48 -> 0.080247483 | X48: =SUMIFS(月汇总!U:U,月汇总!B:B,B48) -> 173 | Y48: =X48/J48 -> 0.0049581481 | Z48: =SUMIFS(月汇总!O:O,月汇总!B:B,B48) -> 0 | AA48: =Z48/J48 -> 0 | AB48: =SUMIFS(月汇总!T:T,月汇总!B:B,B48) -> 0 | AC48: =AB48/J48 -> 0 | AD48: =SUMIFS(月汇总!Z:Z,月汇总!B:B,B48) -> 2442.4442 | AE48: =AD48/J48 -> 0.07 | AF48: =SUMIFS(月汇总!AC:AC,月汇总!B:B,B48) -> 790.16393 | AG48: =AF48/J48 -> 0.022645953 | AH48: =SUMIFS(月汇总!V:V,月汇总!B:B,B48) -> 397.39246 | AI48: =AH48/J48 -> 0.011389195 | AJ48: =M48+P48+R48+T48+V48+X48+Z48+AB48+AD48+AF48+AH48 -> 25842.334 | AK48: =SUMIFS(月汇总!AA:AA,月汇总!B:B,B48) -> 0 | AL48: =J48-K48-L48-AJ48-AK48 -> 8899.7259 | AM48: =AL48/J48 -> 0.2550645 | AN48: =SUMIFS(月汇总!AB:AB,月汇总!B:B,B48) -> 0 | AO48: =SUMIFS(月汇总!W:W,月汇总!B:B,B48) -> 2666 | AP48: =AL48-AN48-AO48 -> 6233.7259
A49: 45 | B49: 粤B93372D | C49: 玉圣杰 | D49: 陈金杰 | E49: 广西-玉溪 | F49: 桂L0466挂 | G49: 重型半挂牵引车 | H49: =COUNTIFS(磅单!E:E,B49) -> 12 | I49: =SUMIFS(磅单!L:L,磅单!E:E,B49) -> 507.05 | J49: =SUMIFS(磅单!O:O,磅单!E:E,B49) -> 38541.81 | K49: =SUMIFS(月汇总!Y:Y,月汇总!B:B,B49) -> 180 | L49: =SUMIFS(月汇总!I:I,月汇总!B:B,B49,月汇总!C:C,F70) -> 0 | M49: =SUMIFS(月汇总!J:J,月汇总!B:B,B49,月汇总!C:C,F49) -> 13784.637 | N49: =M49/J49 -> 0.3576541 | O49: =M49/H49 -> 1148.7197 | P49: =SUMIFS(月汇总!R:R,月汇总!B:B,B49)+SUMIFS(月汇总!S:S,月汇总!B:B,B49) -> 8800 | Q49: =P49/J49 -> 0.22832348 | R49: =SUMIFS(月汇总!Q:Q,月汇总!B:B,B49) -> 190 | S49: =R49/J49 -> 0.0049297114 | T49: =SUMIFS(月汇总!N:N,月汇总!B:B,B49) -> 220.88197 | V49: =SUMIFS(月汇总!X:X,月汇总!B:B,B49) -> 2800 | W49: =V49/J49 -> 0.072648378 | X49: =SUMIFS(月汇总!U:U,月汇总!B:B,B49) -> 340 | Y49: =X49/J49 -> 0.0088215888 | Z49: =SUMIFS(月汇总!O:O,月汇总!B:B,B49) -> 0 | AA49: =Z49/J49 -> 0 | AB49: =SUMIFS(月汇总!T:T,月汇总!B:B,B49) -> 200 | AC49: =AB49/J49 -> 0.0051891699 | AD49: =SUMIFS(月汇总!Z:Z,月汇总!B:B,B49) -> 2697.9267 | AE49: =AD49/J49 -> 0.07 | AF49: =SUMIFS(月汇总!AC:AC,月汇总!B:B,B49) -> 790.16393 | AG49: =AF49/J49 -> 0.020501474 | AH49: =SUMIFS(月汇总!V:V,月汇总!B:B,B49) -> 397.39246 | AI49: =AH49/J49 -> 0.010310685 | AJ49: =M49+P49+R49+T49+V49+X49+Z49+AB49+AD49+AF49+AH49 -> 30221.002 | AK49: =SUMIFS(月汇总!AA:AA,月汇总!B:B,B49) -> 0 | AL49: =J49-K49-L49-AJ49-AK49 -> 8140.8084 | AM49: =AL49/J49 -> 0.21122019 | AN49: =SUMIFS(月汇总!AB:AB,月汇总!B:B,B49) -> 0 | AO49: =SUMIFS(月汇总!W:W,月汇总!B:B,B49) -> 2666 | AP49: =AL49-AN49-AO49 -> 5474.8084
A50: 46 | B50: 粤B41547D | C50: 张克 | D50: 袁俊杰 | E50: 广西-玉溪 | F50: 桂LC701挂 | G50: 重型半挂牵引车 | H50: =COUNTIFS(磅单!E:E,B50) -> 7 | I50: =SUMIFS(磅单!L:L,磅单!E:E,B50) -> 306.91 | J50: =SUMIFS(磅单!O:O,磅单!E:E,B50) -> 22716.15 | K50: =SUMIFS(月汇总!Y:Y,月汇总!B:B,B50) -> 105 | L50: =SUMIFS(月汇总!I:I,月汇总!B:B,B50,月汇总!C:C,F71) -> 0 | M50: =SUMIFS(月汇总!J:J,月汇总!B:B,B50,月汇总!C:C,F50) -> 8633.0998 | N50: =M50/J50 -> 0.38004238 | O50: =M50/H50 -> 1233.3 | P50: =SUMIFS(月汇总!R:R,月汇总!B:B,B50)+SUMIFS(月汇总!S:S,月汇总!B:B,B50) -> 5200 | Q50: =P50/J50 -> 0.22891203 | R50: =SUMIFS(月汇总!Q:Q,月汇总!B:B,B50) -> 0 | S50: =R50/J50 -> 0 | T50: =SUMIFS(月汇总!N:N,月汇总!B:B,B50) -> 220.88197 | V50: =SUMIFS(月汇总!X:X,月汇总!B:B,B50) -> 2800 | W50: =V50/J50 -> 0.12326032 | X50: =SUMIFS(月汇总!U:U,月汇总!B:B,B50) -> 190 | Y50: =X50/J50 -> 0.0083640934 | Z50: =SUMIFS(月汇总!O:O,月汇总!B:B,B50) -> 0 | AA50: =Z50/J50 -> 0 | AB50: =SUMIFS(月汇总!T:T,月汇总!B:B,B50) -> 200 | AC50: =AB50/J50 -> 0.0088043088 | AD50: =SUMIFS(月汇总!Z:Z,月汇总!B:B,B50) -> 1590.1305 | AE50: =AD50/J50 -> 0.07 | AF50: =SUMIFS(月汇总!AC:AC,月汇总!B:B,B50) -> 790.16393 | AG50: =AF50/J50 -> 0.034784237 | AH50: =SUMIFS(月汇总!V:V,月汇总!B:B,B50) -> 397.39246 | AI50: =AH50/J50 -> 0.01749383 | AJ50: =M50+P50+R50+T50+V50+X50+Z50+AB50+AD50+AF50+AH50 -> 20021.669 | AK50: =SUMIFS(月汇总!AA:AA,月汇总!B:B,B50) -> 0 | AL50: =J50-K50-L50-AJ50-AK50 -> 2589.4813 | AM50: =AL50/J50 -> 0.11399297 | AN50: =SUMIFS(月汇总!AB:AB,月汇总!B:B,B50) -> 0 | AO50: =SUMIFS(月汇总!W:W,月汇总!B:B,B50) -> 2666 | AP50: =AL50-AN50-AO50 -> -76.518671
A51: 47 | B51: 粤B94652D | C51: 李张红 | D51: 陈金杰 | E51: 广西-玉溪 | F51: 桂L5408挂 | G51: 重型半挂牵引车 | H51: =COUNTIFS(磅单!E:E,B51) -> 7 | I51: =SUMIFS(磅单!L:L,磅单!E:E,B51) -> 304.92 | J51: =SUMIFS(磅单!O:O,磅单!E:E,B51) -> 20903.86 | K51: =SUMIFS(月汇总!Y:Y,月汇总!B:B,B51) -> 105 | L51: =SUMIFS(月汇总!I:I,月汇总!B:B,B51,月汇总!C:C,F72) -> 0 | M51: =SUMIFS(月汇总!J:J,月汇总!B:B,B51) -> 7254.3167 | N51: =M51/J51 -> 0.3470324 | O51: =M51/H51 -> 1036.331 | P51: =SUMIFS(月汇总!R:R,月汇总!B:B,B51)+SUMIFS(月汇总!S:S,月汇总!B:B,B51) -> 4600 | Q51: =P51/J51 -> 0.22005505 | R51: =SUMIFS(月汇总!Q:Q,月汇总!B:B,B51) -> 0 | S51: =R51/J51 -> 0 | T51: =SUMIFS(月汇总!N:N,月汇总!B:B,B51) -> 220.88197 | V51: =SUMIFS(月汇总!X:X,月汇总!B:B,B51) -> 2800 | W51: =V51/J51 -> 0.13394655 | X51: =SUMIFS(月汇总!U:U,月汇总!B:B,B51) -> 179 | Y51: =X51/J51 -> 0.0085630118 | Z51: =SUMIFS(月汇总!O:O,月汇总!B:B,B51) -> 0 | AA51: =Z51/J51 -> 0 | AB51: =SUMIFS(月汇总!T:T,月汇总!B:B,B51) -> 40 | AC51: =AB51/J51 -> 0.0019135222 | AD51: =SUMIFS(月汇总!Z:Z,月汇总!B:B,B51) -> 1463.2702 | AE51: =AD51/J51 -> 0.07 | AF51: =SUMIFS(月汇总!AC:AC,月汇总!B:B,B51) -> 790.16393 | AG51: =AF51/J51 -> 0.037799906 | AH51: =SUMIFS(月汇总!V:V,月汇总!B:B,B51) -> 397.39246 | AI51: =AH51/J51 -> 0.019010482 | AJ51: =M51+P51+R51+T51+V51+X51+Z51+AB51+AD51+AF51+AH51 -> 17745.025 | AK51: =SUMIFS(月汇总!AA:AA,月汇总!B:B,B51) -> 0 | AL51: =J51-K51-L51-AJ51-AK51 -> 3053.8347 | AM51: =AL51/J51 -> 0.14608951 | AN51: =SUMIFS(月汇总!AB:AB,月汇总!B:B,B51) -> 0 | AO51: =SUMIFS(月汇总!W:W,月汇总!B:B,B51) -> 2666 | AP51: =AL51-AN51-AO51 -> 387.83473
A52: 48 | B52: 粤B98145D | C52: 汪良友 | D52: 袁俊杰 | E52: 广西-玉溪 | F52: 桂L5163挂 | G52: 重型半挂牵引车 | H52: =COUNTIFS(磅单!E:E,B52) -> 6 | I52: =SUMIFS(磅单!L:L,磅单!E:E,B52) -> 264.06 | J52: =SUMIFS(磅单!O:O,磅单!E:E,B52) -> 18529.74 | K52: =SUMIFS(月汇总!Y:Y,月汇总!B:B,B52) -> 90 | L52: =SUMIFS(月汇总!I:I,月汇总!B:B,B52,月汇总!C:C,F73) -> 0 | M52: =SUMIFS(月汇总!J:J,月汇总!B:B,B52) -> 8196.1785 | N52: =M52/J52 -> 0.44232561 | O52: =M52/H52 -> 1366.0298 | P52: =SUMIFS(月汇总!R:R,月汇总!B:B,B52)+SUMIFS(月汇总!S:S,月汇总!B:B,B52) -> 4000 | Q52: =P52/J52 -> 0.21586919 | R52: =SUMIFS(月汇总!Q:Q,月汇总!B:B,B52) -> 60 | S52: =R52/J52 -> 0.0032380379 | T52: =SUMIFS(月汇总!N:N,月汇总!B:B,B52) -> 220.88197 | V52: =SUMIFS(月汇总!X:X,月汇总!B:B,B52) -> 2800 | W52: =V52/J52 -> 0.15110843 | X52: =SUMIFS(月汇总!U:U,月汇总!B:B,B52) -> 151 | Y52: =X52/J52 -> 0.008149062 | Z52: =SUMIFS(月汇总!O:O,月汇总!B:B,B52) -> 0 | AA52: =Z52/J52 -> 0 | AB52: =SUMIFS(月汇总!T:T,月汇总!B:B,B52) -> 20 | AC52: =AB52/J52 -> 0.001079346 | AD52: =SUMIFS(月汇总!Z:Z,月汇总!B:B,B52) -> 1297.0818 | AE52: =AD52/J52 -> 0.07 | AF52: =SUMIFS(月汇总!AC:AC,月汇总!B:B,B52) -> 790.16393 | AG52: =AF52/J52 -> 0.042643012 | AH52: =SUMIFS(月汇总!V:V,月汇总!B:B,B52) -> 397.39246 | AI52: =AH52/J52 -> 0.021446197 | AJ52: =M52+P52+R52+T52+V52+X52+Z52+AB52+AD52+AF52+AH52 -> 17932.699 | AK52: =SUMIFS(月汇总!AA:AA,月汇总!B:B,B52) -> 0 | AL52: =J52-K52-L52-AJ52-AK52 -> 507.04133 | AM52: =AL52/J52 -> 0.02736365 | AN52: =SUMIFS(月汇总!AB:AB,月汇总!B:B,B52) -> 0 | AO52: =SUMIFS(月汇总!W:W,月汇总!B:B,B52) -> 2666 | AP52: =AL52-AN52-AO52 -> -2158.9587
A53: 49 | B53: 粤B96063D | C53: 陆光锐 | D53: 袁俊杰 | E53: 广西-玉溪 | F53: 桂LB192挂 | G53: 重型半挂牵引车 | H53: =COUNTIFS(磅单!E:E,B53) -> 8 | I53: =SUMIFS(磅单!L:L,磅单!E:E,B53) -> 343.69 | J53: =SUMIFS(磅单!O:O,磅单!E:E,B53) -> 22105.89 | K53: =SUMIFS(月汇总!Y:Y,月汇总!B:B,B53) -> 120 | L53: =SUMIFS(月汇总!I:I,月汇总!B:B,B53,月汇总!C:C,F74) -> 0 | M53: =SUMIFS(月汇总!J:J,月汇总!B:B,B53) -> 7639.6485 | N53: =M53/J53 -> 0.34559335 | O53: =M53/H53 -> 954.95606 | P53: =SUMIFS(月汇总!R:R,月汇总!B:B,B53)+SUMIFS(月汇总!S:S,月汇总!B:B,B53) -> 5000 | Q53: =P53/J53 -> 0.22618406 | R53: =SUMIFS(月汇总!Q:Q,月汇总!B:B,B53) -> 0 | S53: =R53/J53 -> 0 | T53: =SUMIFS(月汇总!N:N,月汇总!B:B,B53) -> 220.88197 | V53: =SUMIFS(月汇总!X:X,月汇总!B:B,B53) -> 3600 | W53: =V53/J53 -> 0.16285252 | X53: =SUMIFS(月汇总!U:U,月汇总!B:B,B53) -> 90 | Y53: =X53/J53 -> 0.0040713131 | Z53: =SUMIFS(月汇总!O:O,月汇总!B:B,B53) -> 0 | AA53: =Z53/J53 -> 0 | AB53: =SUMIFS(月汇总!T:T,月汇总!B:B,B53) -> 0 | AC53: =AB53/J53 -> 0 | AD53: =SUMIFS(月汇总!Z:Z,月汇总!B:B,B53) -> 1547.4123 | AE53: =AD53/J53 -> 0.07 | AF53: =SUMIFS(月汇总!AC:AC,月汇总!B:B,B53) -> 790.16393 | AG53: =AF53/J53 -> 0.035744498 | AH53: =SUMIFS(月汇总!V:V,月汇总!B:B,B53) -> 397.39246 | AI53: =AH53/J53 -> 0.017976768 | AJ53: =M53+P53+R53+T53+V53+X53+Z53+AB53+AD53+AF53+AH53 -> 19285.499 | AK53: =SUMIFS(月汇总!AA:AA,月汇总!B:B,B53) -> 0 | AL53: =J53-K53-L53-AJ53-AK53 -> 2700.3908 | AM53: =AL53/J53 -> 0.12215707 | AN53: =SUMIFS(月汇总!AB:AB,月汇总!B:B,B53) -> 0 | AO53: =SUMIFS(月汇总!W:W,月汇总!B:B,B53) -> 2666 | AP53: =AL53-AN53-AO53 -> 34.390829
A54: 50 | B54: 粤B96373D | C54: 高克禹 | D54: 袁俊杰 | E54: 广西-玉溪 | F54: 桂LE571挂 | G54: 重型半挂牵引车 | H54: =COUNTIFS(磅单!E:E,B54) -> 7 | I54: =SUMIFS(磅单!L:L,磅单!E:E,B54) -> 300.53 | J54: =SUMIFS(磅单!O:O,磅单!E:E,B54) -> 22774.69 | K54: =SUMIFS(月汇总!Y:Y,月汇总!B:B,B54) -> 105 | L54: =SUMIFS(月汇总!I:I,月汇总!B:B,B54,月汇总!C:C,F75) -> 0 | M54: =SUMIFS(月汇总!J:J,月汇总!B:B,B54) -> 6947.4685 | N54: =M54/J54 -> 0.30505217 | O54: =M54/H54 -> 992.4955 | P54: =SUMIFS(月汇总!R:R,月汇总!B:B,B54)+SUMIFS(月汇总!S:S,月汇总!B:B,B54) -> 5000 | Q54: =P54/J54 -> 0.21954196 | R54: =SUMIFS(月汇总!Q:Q,月汇总!B:B,B54) -> 120 | S54: =R54/J54 -> 0.005269007 | T54: =SUMIFS(月汇总!N:N,月汇总!B:B,B54) -> 220.88197 | V54: =SUMIFS(月汇总!X:X,月汇总!B:B,B54) -> 3600 | W54: =V54/J54 -> 0.15807021 | X54: =SUMIFS(月汇总!U:U,月汇总!B:B,B54) -> 105 | Y54: =X54/J54 -> 0.0046103811 | Z54: =SUMIFS(月汇总!O:O,月汇总!B:B,B54) -> 0 | AA54: =Z54/J54 -> 0 | AB54: =SUMIFS(月汇总!T:T,月汇总!B:B,B54) -> 0 | AC54: =AB54/J54 -> 0 | AD54: =SUMIFS(月汇总!Z:Z,月汇总!B:B,B54) -> 1594.2283 | AE54: =AD54/J54 -> 0.07 | AF54: =SUMIFS(月汇总!AC:AC,月汇总!B:B,B54) -> 790.16393 | AG54: =AF54/J54 -> 0.034694827 | AH54: =SUMIFS(月汇总!V:V,月汇总!B:B,B54) -> 397.39246 | AI54: =AH54/J54 -> 0.017448864 | AJ54: =M54+P54+R54+T54+V54+X54+Z54+AB54+AD54+AF54+AH54 -> 18775.135 | AK54: =SUMIFS(月汇总!AA:AA,月汇总!B:B,B54) -> 0 | AL54: =J54-K54-L54-AJ54-AK54 -> 3894.5548 | AM54: =AL54/J54 -> 0.17100364 | AN54: =SUMIFS(月汇总!AB:AB,月汇总!B:B,B54) -> 0 | AO54: =SUMIFS(月汇总!W:W,月汇总!B:B,B54) -> 2666 | AP54: =AL54-AN54-AO54 -> 1228.5548
A55: 51 | B55: 粤B94050D | C55: 刘耀铭 | D55: 袁俊杰 | E55: 广西-玉溪 | F55: 桂LE017挂 | G55: 重型半挂牵引车 | H55: =COUNTIFS(磅单!E:E,B55) -> 4 | I55: =SUMIFS(磅单!L:L,磅单!E:E,B55) -> 172.36 | J55: =SUMIFS(磅单!O:O,磅单!E:E,B55) -> 12133.5 | K55: =SUMIFS(月汇总!Y:Y,月汇总!B:B,B55) -> 60 | L55: =SUMIFS(月汇总!I:I,月汇总!B:B,B55,月汇总!C:C,F76) -> 0 | M55: =SUMIFS(月汇总!J:J,月汇总!B:B,B55) -> 5978.9385 | N55: =M55/J55 -> 0.49276289 | O55: =M55/H55 -> 1494.7346 | P55: =SUMIFS(月汇总!R:R,月汇总!B:B,B55)+SUMIFS(月汇总!S:S,月汇总!B:B,B55) -> 2800 | Q55: =P55/J55 -> 0.23076606 | R55: =SUMIFS(月汇总!Q:Q,月汇总!B:B,B55) -> 50 | S55: =R55/J55 -> 0.0041208225 | T55: =SUMIFS(月汇总!N:N,月汇总!B:B,B55) -> 220.88197 | V55: =SUMIFS(月汇总!X:X,月汇总!B:B,B55) -> 3600 | W55: =V55/J55 -> 0.29669922 | X55: =SUMIFS(月汇总!U:U,月汇总!B:B,B55) -> 204 | Y55: =X55/J55 -> 0.016812956 | Z55: =SUMIFS(月汇总!O:O,月汇总!B:B,B55) -> 1050 | AA55: =Z55/J55 -> 0.086537273 | AB55: =SUMIFS(月汇总!T:T,月汇总!B:B,B55) -> 200 | AC55: =AB55/J55 -> 0.01648329 | AD55: =SUMIFS(月汇总!Z:Z,月汇总!B:B,B55) -> 849.345 | AE55: =AD55/J55 -> 0.07 | AF55: =SUMIFS(月汇总!AC:AC,月汇总!B:B,B55) -> 790.16393 | AG55: =AF55/J55 -> 0.065122507 | AH55: =SUMIFS(月汇总!V:V,月汇总!B:B,B55) -> 397.39246 | AI55: =AH55/J55 -> 0.032751676 | AJ55: =M55+P55+R55+T55+V55+X55+Z55+AB55+AD55+AF55+AH55 -> 16140.722 | AK55: =SUMIFS(月汇总!AA:AA,月汇总!B:B,B55) -> 0 | AL55: =J55-K55-L55-AJ55-AK55 -> -4067.2219 | AM55: =AL55/J55 -> -0.33520599 | AN55: =SUMIFS(月汇总!AB:AB,月汇总!B:B,B55) -> 0 | AO55: =SUMIFS(月汇总!W:W,月汇总!B:B,B55) -> 2666 | AP55: =AL55-AN55-AO55 -> -6733.2219
A56: 52 | B56: 粤B98382D | C56: 尹绍族 | D56: 陈金杰 | E56: 广西-玉溪 | F56: 桂L7502挂 | G56: 重型半挂牵引车 | H56: =COUNTIFS(磅单!E:E,B56) -> 4 | I56: =SUMIFS(磅单!L:L,磅单!E:E,B56) -> 179.06 | J56: =SUMIFS(磅单!O:O,磅单!E:E,B56) -> 11225.4 | K56: =SUMIFS(月汇总!Y:Y,月汇总!B:B,B56) -> 60 | L56: =SUMIFS(月汇总!I:I,月汇总!B:B,B56,月汇总!C:C,F77) -> 0 | M56: =SUMIFS(月汇总!J:J,月汇总!B:B,B56) -> 6039.1485 | N56: =M56/J56 -> 0.5379896 | O56: =M56/H56 -> 1509.7871 | P56: =SUMIFS(月汇总!R:R,月汇总!B:B,B56)+SUMIFS(月汇总!S:S,月汇总!B:B,B56) -> 2600 | Q56: =P56/J56 -> 0.23161758 | R56: =SUMIFS(月汇总!Q:Q,月汇总!B:B,B56) -> 0 | S56: =R56/J56 -> 0 | T56: =SUMIFS(月汇总!N:N,月汇总!B:B,B56) -> 220.88197 | V56: =SUMIFS(月汇总!X:X,月汇总!B:B,B56) -> 3600 | W56: =V56/J56 -> 0.32070127 | X56: =SUMIFS(月汇总!U:U,月汇总!B:B,B56) -> 183 | Y56: =X56/J56 -> 0.016302314 | Z56: =SUMIFS(月汇总!O:O,月汇总!B:B,B56) -> 0 | AA56: =Z56/J56 -> 0 | AB56: =SUMIFS(月汇总!T:T,月汇总!B:B,B56) -> 0 | AC56: =AB56/J56 -> 0 | AD56: =SUMIFS(月汇总!Z:Z,月汇总!B:B,B56) -> 785.778 | AE56: =AD56/J56 -> 0.07 | AF56: =SUMIFS(月汇总!AC:AC,月汇总!B:B,B56) -> 790.16393 | AG56: =AF56/J56 -> 0.070390715 | AH56: =SUMIFS(月汇总!V:V,月汇总!B:B,B56) -> 397.39246 | AI56: =AH56/J56 -> 0.035401185 | AJ56: =M56+P56+R56+T56+V56+X56+Z56+AB56+AD56+AF56+AH56 -> 14616.365 | AK56: =SUMIFS(月汇总!AA:AA,月汇总!B:B,B56) -> 0 | AL56: =J56-K56-L56-AJ56-AK56 -> -3450.9649 | AM56: =AL56/J56 -> -0.30742467 | AN56: =SUMIFS(月汇总!AB:AB,月汇总!B:B,B56) -> 0 | AO56: =SUMIFS(月汇总!W:W,月汇总!B:B,B56) -> 2666 | AP56: =AL56-AN56-AO56 -> -6116.9649
A57: 53 | B57: 粤B93345D | C57: 李云聪 | D57: 陈金杰 | E57: 广西-玉溪 | F57: 桂LE683挂 | G57: 重型半挂牵引车 | H57: =COUNTIFS(磅单!E:E,B57) -> 4 | I57: =SUMIFS(磅单!L:L,磅单!E:E,B57) -> 169.5 | J57: =SUMIFS(磅单!O:O,磅单!E:E,B57) -> 13067.94 | K57: =SUMIFS(月汇总!Y:Y,月汇总!B:B,B57) -> 60 | L57: =SUMIFS(月汇总!I:I,月汇总!B:B,B57,月汇总!C:C,F78) -> 0 | M57: =SUMIFS(月汇总!J:J,月汇总!B:B,B57) -> 5560.7085 | N57: =M57/J57 -> 0.42552296 | O57: =M57/H57 -> 1390.1771 | P57: =SUMIFS(月汇总!R:R,月汇总!B:B,B57)+SUMIFS(月汇总!S:S,月汇总!B:B,B57) -> 3000 | Q57: =P57/J57 -> 0.22956947 | R57: =SUMIFS(月汇总!Q:Q,月汇总!B:B,B57) -> 0 | S57: =R57/J57 -> 0 | T57: =SUMIFS(月汇总!N:N,月汇总!B:B,B57) -> 220.88197 | V57: =SUMIFS(月汇总!X:X,月汇总!B:B,B57) -> 3600 | W57: =V57/J57 -> 0.27548336 | X57: =SUMIFS(月汇总!U:U,月汇总!B:B,B57) -> 113 | Y57: =X57/J57 -> 0.0086471165 | Z57: =SUMIFS(月汇总!O:O,月汇总!B:B,B57) -> 0 | AA57: =Z57/J57 -> 0 | AB57: =SUMIFS(月汇总!T:T,月汇总!B:B,B57) -> 0 | AC57: =AB57/J57 -> 0 | AD57: =SUMIFS(月汇总!Z:Z,月汇总!B:B,B57) -> 914.7558 | AE57: =AD57/J57 -> 0.07 | AF57: =SUMIFS(月汇总!AC:AC,月汇总!B:B,B57) -> 790.16393 | AG57: =AF57/J57 -> 0.060465837 | AH57: =SUMIFS(月汇总!V:V,月汇总!B:B,B57) -> 397.39246 | AI57: =AH57/J57 -> 0.030409725 | AJ57: =M57+P57+R57+T57+V57+X57+Z57+AB57+AD57+AF57+AH57 -> 14596.903 | AK57: =SUMIFS(月汇总!AA:AA,月汇总!B:B,B57) -> 0 | AL57: =J57-K57-L57-AJ57-AK57 -> -1588.9627 | AM57: =AL57/J57 -> -0.12159244 | AN57: =SUMIFS(月汇总!AB:AB,月汇总!B:B,B57) -> 0 | AO57: =SUMIFS(月汇总!W:W,月汇总!B:B,B57) -> 2666 | AP57: =AL57-AN57-AO57 -> -4254.9627
A58: 54 | B58: 粤B98081D | C58: 唐四川 | D58: 陈金杰 | E58: 广西-玉溪 | F58: 贵LB763挂 | G58: 重型半挂牵引车 | H58: =COUNTIFS(磅单!E:E,B58) -> 4 | I58: =SUMIFS(磅单!L:L,磅单!E:E,B58) -> 169.46 | J58: =SUMIFS(磅单!O:O,磅单!E:E,B58) -> 13020.78 | K58: =SUMIFS(月汇总!Y:Y,月汇总!B:B,B58) -> 60 | L58: =SUMIFS(月汇总!I:I,月汇总!B:B,B58,月汇总!C:C,F79) -> 0 | M58: =SUMIFS(月汇总!J:J,月汇总!B:B,B58) -> 6333.0219 | N58: =M58/J58 -> 0.48637807 | O58: =M58/H58 -> 1583.2555 | P58: =SUMIFS(月汇总!R:R,月汇总!B:B,B58)+SUMIFS(月汇总!S:S,月汇总!B:B,B58) -> 3000 | Q58: =P58/J58 -> 0.23040094 | R58: =SUMIFS(月汇总!Q:Q,月汇总!B:B,B58) -> 70 | S58: =R58/J58 -> 0.005376022 | T58: =SUMIFS(月汇总!N:N,月汇总!B:B,B58) -> 220.88197 | V58: =SUMIFS(月汇总!X:X,月汇总!B:B,B58) -> 3600 | W58: =V58/J58 -> 0.27648113 | X58: =SUMIFS(月汇总!U:U,月汇总!B:B,B58) -> 122 | Y58: =X58/J58 -> 0.0093696384 | Z58: =SUMIFS(月汇总!O:O,月汇总!B:B,B58) -> 0 | AA58: =Z58/J58 -> 0 | AB58: =SUMIFS(月汇总!T:T,月汇总!B:B,B58) -> 0 | AC58: =AB58/J58 -> 0 | AD58: =SUMIFS(月汇总!Z:Z,月汇总!B:B,B58) -> 911.4546 | AE58: =AD58/J58 -> 0.07 | AF58: =SUMIFS(月汇总!AC:AC,月汇总!B:B,B58) -> 790.16393 | AG58: =AF58/J58 -> 0.060684839 | AH58: =SUMIFS(月汇总!V:V,月汇总!B:B,B58) -> 397.39246 | AI58: =AH58/J58 -> 0.030519866 | AJ58: =M58+P58+R58+T58+V58+X58+Z58+AB58+AD58+AF58+AH58 -> 15444.915 | AK58: =SUMIFS(月汇总!AA:AA,月汇总!B:B,B58) -> 0 | AL58: =J58-K58-L58-AJ58-AK58 -> -2484.1349 | AM58: =AL58/J58 -> -0.19078234 | AN58: =SUMIFS(月汇总!AB:AB,月汇总!B:B,B58) -> 0 | AO58: =SUMIFS(月汇总!W:W,月汇总!B:B,B58) -> 2666 | AP58: =AL58-AN58-AO58 -> -5150.1349
A59: 55 | B59: 粤B91025D | C59: 陆杰 | D59: 陈金杰 | E59: 广西-玉溪 | F59: 桂L8685挂 | G59: 重型半挂牵引车 | H59: =COUNTIFS(磅单!E:E,B59) -> 3 | I59: =SUMIFS(磅单!L:L,磅单!E:E,B59) -> 132.56 | J59: =SUMIFS(磅单!O:O,磅单!E:E,B59) -> 9437.6 | K59: =SUMIFS(月汇总!Y:Y,月汇总!B:B,B59) -> 45 | L59: =SUMIFS(月汇总!I:I,月汇总!B:B,B59,月汇总!C:C,F80) -> 0 | M59: =SUMIFS(月汇总!J:J,月汇总!B:B,B59) -> 5155.1585 | N59: =M59/J59 -> 0.54623617 | O59: =M59/H59 -> 1718.3862 | P59: =SUMIFS(月汇总!R:R,月汇总!B:B,B59)+SUMIFS(月汇总!S:S,月汇总!B:B,B59) -> 2000 | Q59: =P59/J59 -> 0.21191828 | R59: =SUMIFS(月汇总!Q:Q,月汇总!B:B,B59) -> 0 | S59: =R59/J59 -> 0 | T59: =SUMIFS(月汇总!N:N,月汇总!B:B,B59) -> 220.88197 | V59: =SUMIFS(月汇总!X:X,月汇总!B:B,B59) -> 3600 | W59: =V59/J59 -> 0.38145291 | X59: =SUMIFS(月汇总!U:U,月汇总!B:B,B59) -> 52 | Y59: =X59/J59 -> 0.0055098754 | Z59: =SUMIFS(月汇总!O:O,月汇总!B:B,B59) -> 0 | AA59: =Z59/J59 -> 0 | AB59: =SUMIFS(月汇总!T:T,月汇总!B:B,B59) -> 0 | AC59: =AB59/J59 -> 0 | AD59: =SUMIFS(月汇总!Z:Z,月汇总!B:B,B59) -> 660.632 | AE59: =AD59/J59 -> 0.07 | AF59: =SUMIFS(月汇总!AC:AC,月汇总!B:B,B59) -> 790.16393 | AG59: =AF59/J59 -> 0.083725093 | AH59: =SUMIFS(月汇总!V:V,月汇总!B:B,B59) -> 397.39246 | AI59: =AH59/J59 -> 0.042107364 | AJ59: =M59+P59+R59+T59+V59+X59+Z59+AB59+AD59+AF59+AH59 -> 12876.229 | AK59: =SUMIFS(月汇总!AA:AA,月汇总!B:B,B59) -> 0 | AL59: =J59-K59-L59-AJ59-AK59 -> -3483.6289 | AM59: =AL59/J59 -> -0.36912233 | AN59: =SUMIFS(月汇总!AB:AB,月汇总!B:B,B59) -> 0 | AO59: =SUMIFS(月汇总!W:W,月汇总!B:B,B59) -> 2666 | AP59: =AL59-AN59-AO59 -> -6149.6289
A60: 56 | B60: 粤B94092D | C60: 马全伟 | D60: 陈金杰 | E60: 广西-玉溪 | F60: 桂L6496挂 | G60: 重型半挂牵引车 | H60: =COUNTIFS(磅单!E:E,B60) -> 5 | I60: =SUMIFS(磅单!L:L,磅单!E:E,B60) -> 217.46 | J60: =SUMIFS(磅单!O:O,磅单!E:E,B60) -> 14219.62 | K60: =SUMIFS(月汇总!Y:Y,月汇总!B:B,B60) -> 75 | L60: =SUMIFS(月汇总!I:I,月汇总!B:B,B60,月汇总!C:C,F81) -> 0 | M60: =SUMIFS(月汇总!J:J,月汇总!B:B,B60) -> 4658.5885 | N60: =M60/J60 -> 0.32761695 | O60: =M60/H60 -> 931.7177 | P60: =SUMIFS(月汇总!R:R,月汇总!B:B,B60)+SUMIFS(月汇总!S:S,月汇总!B:B,B60) -> 3200 | Q60: =P60/J60 -> 0.22504118 | R60: =SUMIFS(月汇总!Q:Q,月汇总!B:B,B60) -> 15 | S60: =R60/J60 -> 0.0010548805 | T60: =SUMIFS(月汇总!N:N,月汇总!B:B,B60) -> 220.88197 | V60: =SUMIFS(月汇总!X:X,月汇总!B:B,B60) -> 3600 | W60: =V60/J60 -> 0.25317132 | X60: =SUMIFS(月汇总!U:U,月汇总!B:B,B60) -> 111 | Y60: =X60/J60 -> 0.0078061158 | Z60: =SUMIFS(月汇总!O:O,月汇总!B:B,B60) -> 0 | AA60: =Z60/J60 -> 0 | AB60: =SUMIFS(月汇总!T:T,月汇总!B:B,B60) -> 0 | AC60: =AB60/J60 -> 0 | AD60: =SUMIFS(月汇总!Z:Z,月汇总!B:B,B60) -> 995.3734 | AE60: =AD60/J60 -> 0.07 | AF60: =SUMIFS(月汇总!AC:AC,月汇总!B:B,B60) -> 790.16393 | AG60: =AF60/J60 -> 0.055568569 | AH60: =SUMIFS(月汇总!V:V,月汇总!B:B,B60) -> 397.39246 | AI60: =AH60/J60 -> 0.027946771 | AJ60: =M60+P60+R60+T60+V60+X60+Z60+AB60+AD60+AF60+AH60 -> 13988.4 | AK60: =SUMIFS(月汇总!AA:AA,月汇总!B:B,B60) -> 0 | AL60: =J60-K60-L60-AJ60-AK60 -> 156.21973 | AM60: =AL60/J60 -> 0.01098621 | AN60: =SUMIFS(月汇总!AB:AB,月汇总!B:B,B60) -> 0 | AO60: =SUMIFS(月汇总!W:W,月汇总!B:B,B60) -> 2666 | AP60: =AL60-AN60-AO60 -> -2509.7803
A61: 57 | B61: 粤B95241D | C61: 纳存江 | D61: 陈金杰 | E61: 广西-玉溪 | F61: 桂LC873挂 | G61: 重型半挂牵引车 | H61: =COUNTIFS(磅单!E:E,B61) -> 5 | I61: =SUMIFS(磅单!L:L,磅单!E:E,B61) -> 213.55 | J61: =SUMIFS(磅单!O:O,磅单!E:E,B61) -> 14014.69 | K61: =SUMIFS(月汇总!Y:Y,月汇总!B:B,B61) -> 75 | L61: =SUMIFS(月汇总!I:I,月汇总!B:B,B61,月汇总!C:C,F82) -> 0 | M61: =SUMIFS(月汇总!J:J,月汇总!B:B,B61) -> 4891.6085 | N61: =M61/J61 -> 0.34903437 | O61: =M61/H61 -> 978.3217 | P61: =SUMIFS(月汇总!R:R,月汇总!B:B,B61)+SUMIFS(月汇总!S:S,月汇总!B:B,B61) -> 3200 | Q61: =P61/J61 -> 0.22833184 | R61: =SUMIFS(月汇总!Q:Q,月汇总!B:B,B61) -> 10 | S61: =R61/J61 -> 0.00071353701 | T61: =SUMIFS(月汇总!N:N,月汇总!B:B,B61) -> 220.88197 | V61: =SUMIFS(月汇总!X:X,月汇总!B:B,B61) -> 3600 | W61: =V61/J61 -> 0.25687332 | X61: =SUMIFS(月汇总!U:U,月汇总!B:B,B61) -> 141 | Y61: =X61/J61 -> 0.010060872 | Z61: =SUMIFS(月汇总!O:O,月汇总!B:B,B61) -> 0 | AA61: =Z61/J61 -> 0 | AB61: =SUMIFS(月汇总!T:T,月汇总!B:B,B61) -> 0 | AC61: =AB61/J61 -> 0 | AD61: =SUMIFS(月汇总!Z:Z,月汇总!B:B,B61) -> 981.0283 | AE61: =AD61/J61 -> 0.07 | AF61: =SUMIFS(月汇总!AC:AC,月汇总!B:B,B61) -> 790.16393 | AG61: =AF61/J61 -> 0.056381121 | AH61: =SUMIFS(月汇总!V:V,月汇总!B:B,B61) -> 397.39246 | AI61: =AH61/J61 -> 0.028355423 | AJ61: =M61+P61+R61+T61+V61+X61+Z61+AB61+AD61+AF61+AH61 -> 14232.075 | AK61: =SUMIFS(月汇总!AA:AA,月汇总!B:B,B61) -> 0 | AL61: =J61-K61-L61-AJ61-AK61 -> -292.38517 | AM61: =AL61/J61 -> -0.020862764 | AN61: =SUMIFS(月汇总!AB:AB,月汇总!B:B,B61) -> 0 | AO61: =SUMIFS(月汇总!W:W,月汇总!B:B,B61) -> 2666 | AP61: =AL61-AN61-AO61 -> -2958.3852
A62: 58 | B62: 粤B92439D | E62: 广西-玉溪 | F62: 桂L7761挂 | G62: 重型半挂牵引车 | H62: =COUNTIFS(磅单!E:E,B62) -> 1 | I62: =SUMIFS(磅单!L:L,磅单!E:E,B62) -> 44.38 | J62: =SUMIFS(磅单!O:O,磅单!E:E,B62) -> 2973.46 | K62: =SUMIFS(月汇总!Y:Y,月汇总!B:B,B62) -> 15 | L62: =SUMIFS(月汇总!I:I,月汇总!B:B,B62,月汇总!C:C,F83) -> 0 | M62: =SUMIFS(月汇总!J:J,月汇总!B:B,B62) -> 1830.1877 | N62: =M62/J62 -> 0.61550776 | O62: =M62/H62 -> 1830.1877 | P62: =SUMIFS(月汇总!R:R,月汇总!B:B,B62)+SUMIFS(月汇总!S:S,月汇总!B:B,B62) -> 600 | Q62: =P62/J62 -> 0.20178513 | R62: =SUMIFS(月汇总!Q:Q,月汇总!B:B,B62) -> 0 | S62: =R62/J62 -> 0 | T62: =SUMIFS(月汇总!N:N,月汇总!B:B,B62) -> 220.88197 | V62: =SUMIFS(月汇总!X:X,月汇总!B:B,B62) -> 3600 | W62: =V62/J62 -> 1.2107108 | X62: =SUMIFS(月汇总!U:U,月汇总!B:B,B62) -> 15 | Y62: =X62/J62 -> 0.0050446281 | Z62: =SUMIFS(月汇总!O:O,月汇总!B:B,B62) -> 0 | AA62: =Z62/J62 -> 0 | AB62: =SUMIFS(月汇总!T:T,月汇总!B:B,B62) -> 0 | AC62: =AB62/J62 -> 0 | AD62: =SUMIFS(月汇总!Z:Z,月汇总!B:B,B62) -> 208.1422 | AE62: =AD62/J62 -> 0.07 | AF62: =SUMIFS(月汇总!AC:AC,月汇总!B:B,B62) -> 790.16393 | AG62: =AF62/J62 -> 0.26573888 | AH62: =SUMIFS(月汇总!V:V,月汇总!B:B,B62) -> 397.39246 | AI62: =AH62/J62 -> 0.13364648 | AJ62: =M62+P62+R62+T62+V62+X62+Z62+AB62+AD62+AF62+AH62 -> 7661.7683 | AK62: =SUMIFS(月汇总!AA:AA,月汇总!B:B,B62) -> 0 | AL62: =J62-K62-L62-AJ62-AK62 -> -4703.3083 | AM62: =AL62/J62 -> -1.5817628 | AN62: =SUMIFS(月汇总!AB:AB,月汇总!B:B,B62) -> 0 | AO62: =SUMIFS(月汇总!W:W,月汇总!B:B,B62) -> 2666 | AP62: =AL62-AN62-AO62 -> -7369.3083
A63: 59 | B63: 粤B98790D | E63: 广西-玉溪 | F63: 桂L5346挂 | G63: 重型半挂牵引车 | H63: =COUNTIFS(磅单!E:E,B63) -> 4 | I63: =SUMIFS(磅单!L:L,磅单!E:E,B63) -> 168.56 | J63: =SUMIFS(磅单!O:O,磅单!E:E,B63) -> 12051.06 | K63: =SUMIFS(月汇总!Y:Y,月汇总!B:B,B63) -> 60 | L63: =SUMIFS(月汇总!I:I,月汇总!B:B,B63,月汇总!C:C,F84) -> 0 | M63: =SUMIFS(月汇总!J:J,月汇总!B:B,B63) -> 5765.5309 | N63: =M63/J63 -> 0.47842521 | O63: =M63/H63 -> 1441.3827 | P63: =SUMIFS(月汇总!R:R,月汇总!B:B,B63)+SUMIFS(月汇总!S:S,月汇总!B:B,B63) -> 2800 | Q63: =P63/J63 -> 0.23234471 | R63: =SUMIFS(月汇总!Q:Q,月汇总!B:B,B63) -> 60 | S63: =R63/J63 -> 0.0049788151 | T63: =SUMIFS(月汇总!N:N,月汇总!B:B,B63) -> 220.88197 | V63: =SUMIFS(月汇总!X:X,月汇总!B:B,B63) -> 3600 | W63: =V63/J63 -> 0.29872891 | X63: =SUMIFS(月汇总!U:U,月汇总!B:B,B63) -> 105.5 | Y63: =X63/J63 -> 0.0087544166 | Z63: =SUMIFS(月汇总!O:O,月汇总!B:B,B63) -> 950 | AA63: =Z63/J63 -> 0.07883124 | AB63: =SUMIFS(月汇总!T:T,月汇总!B:B,B63) -> 0 | AC63: =AB63/J63 -> 0 | AD63: =SUMIFS(月汇总!Z:Z,月汇总!B:B,B63) -> 843.5742 | AE63: =AD63/J63 -> 0.07 | AF63: =SUMIFS(月汇总!AC:AC,月汇总!B:B,B63) -> 790.16393 | AG63: =AF63/J63 -> 0.065568003 | AH63: =SUMIFS(月汇总!V:V,月汇总!B:B,B63) -> 397.39246 | AI63: =AH63/J63 -> 0.032975727 | AJ63: =M63+P63+R63+T63+V63+X63+Z63+AB63+AD63+AF63+AH63 -> 15533.043 | AK63: =SUMIFS(月汇总!AA:AA,月汇总!B:B,B63) -> 0 | AL63: =J63-K63-L63-AJ63-AK63 -> -3541.9835 | AM63: =AL63/J63 -> -0.29391468 | AN63: =SUMIFS(月汇总!AB:AB,月汇总!B:B,B63) -> 0 | AO63: =SUMIFS(月汇总!W:W,月汇总!B:B,B63) -> 2666 | AP63: =AL63-AN63-AO63 -> -6207.9835
A64: 60 | B64: 粤B95641D | E64: 广西-玉溪 | F64: 桂L2510挂 | G64: 重型半挂牵引车 | H64: =COUNTIFS(磅单!E:E,B64) -> 3 | I64: =SUMIFS(磅单!L:L,磅单!E:E,B64) -> 124.5 | J64: =SUMIFS(磅单!O:O,磅单!E:E,B64) -> 9134.22 | K64: =SUMIFS(月汇总!Y:Y,月汇总!B:B,B64) -> 45 | L64: =SUMIFS(月汇总!I:I,月汇总!B:B,B64,月汇总!C:C,F85) -> 0 | M64: =SUMIFS(月汇总!J:J,月汇总!B:B,B64) -> 5409.4885 | N64: =M64/J64 -> 0.59222227 | O64: =M64/H64 -> 1803.1628 | P64: =SUMIFS(月汇总!R:R,月汇总!B:B,B64)+SUMIFS(月汇总!S:S,月汇总!B:B,B64) -> 2200 | Q64: =P64/J64 -> 0.24085253 | R64: =SUMIFS(月汇总!Q:Q,月汇总!B:B,B64) -> 150 | S64: =R64/J64 -> 0.016421763 | T64: =SUMIFS(月汇总!N:N,月汇总!B:B,B64) -> 220.88197 | V64: =SUMIFS(月汇总!X:X,月汇总!B:B,B64) -> 3600 | W64: =V64/J64 -> 0.39412232 | X64: =SUMIFS(月汇总!U:U,月汇总!B:B,B64) -> 90.5 | Y64: =X64/J64 -> 0.0099077973 | Z64: =SUMIFS(月汇总!O:O,月汇总!B:B,B64) -> 0 | AA64: =Z64/J64 -> 0 | AB64: =SUMIFS(月汇总!T:T,月汇总!B:B,B64) -> 0 | AC64: =AB64/J64 -> 0 | AD64: =SUMIFS(月汇总!Z:Z,月汇总!B:B,B64) -> 639.3954 | AE64: =AD64/J64 -> 0.07 | AF64: =SUMIFS(月汇总!AC:AC,月汇总!B:B,B64) -> 790.16393 | AG64: =AF64/J64 -> 0.086505901 | AH64: =SUMIFS(月汇总!V:V,月汇总!B:B,B64) -> 397.39246 | AI64: =AH64/J64 -> 0.0435059 | AJ64: =M64+P64+R64+T64+V64+X64+Z64+AB64+AD64+AF64+AH64 -> 13497.822 | AK64: =SUMIFS(月汇总!AA:AA,月汇总!B:B,B64) -> 0 | AL64: =J64-K64-L64-AJ64-AK64 -> -4408.6023 | AM64: =AL64/J64 -> -0.48264682 | AN64: =SUMIFS(月汇总!AB:AB,月汇总!B:B,B64) -> 0 | AO64: =SUMIFS(月汇总!W:W,月汇总!B:B,B64) -> 2666 | AP64: =AL64-AN64-AO64 -> -7074.6023
A65: 61 | B65: 粤B94058D | E65: 广西-玉溪 | G65: 重型半挂牵引车 | H65: =COUNTIFS(磅单!E:E,B65) -> 0 | I65: =SUMIFS(磅单!L:L,磅单!E:E,B65) -> 0 | J65: =SUMIFS(磅单!O:O,磅单!E:E,B65) -> 0 | K65: =SUMIFS(月汇总!Y:Y,月汇总!B:B,B65) -> 0 | L65: =SUMIFS(月汇总!I:I,月汇总!B:B,B65,月汇总!C:C,F86) -> 0 | M65: =SUMIFS(月汇总!J:J,月汇总!B:B,B65) -> 800.29851 | N65: =M65/J65 -> #DIV/0! | O65: =M65/H65 -> #DIV/0! | P65: =SUMIFS(月汇总!R:R,月汇总!B:B,B65)+SUMIFS(月汇总!S:S,月汇总!B:B,B65) -> 0 | Q65: =P65/J65 -> #DIV/0! | R65: =SUMIFS(月汇总!Q:Q,月汇总!B:B,B65) -> 0 | S65: =R65/J65 -> #DIV/0! | T65: =SUMIFS(月汇总!N:N,月汇总!B:B,B65) -> 220.88197 | V65: =SUMIFS(月汇总!X:X,月汇总!B:B,B65) -> 0 | W65: =V65/J65 -> #DIV/0! | X65: =SUMIFS(月汇总!U:U,月汇总!B:B,B65) -> 0 | Y65: =X65/J65 -> #DIV/0! | Z65: =SUMIFS(月汇总!O:O,月汇总!B:B,B65) -> 0 | AA65: =Z65/J65 -> #DIV/0! | AB65: =SUMIFS(月汇总!T:T,月汇总!B:B,B65) -> 0 | AC65: =AB65/J65 -> #DIV/0! | AD65: =SUMIFS(月汇总!Z:Z,月汇总!B:B,B65) -> 0 | AE65: =AD65/J65 -> #DIV/0! | AF65: =SUMIFS(月汇总!AC:AC,月汇总!B:B,B65) -> 790.16393 | AG65: =AF65/J65 -> #DIV/0! | AH65: =SUMIFS(月汇总!V:V,月汇总!B:B,B65) -> 397.39246 | AI65: =AH65/J65 -> #DIV/0! | AJ65: =M65+P65+R65+T65+V65+X65+Z65+AB65+AD65+AF65+AH65 -> 2208.7369 | AK65: =SUMIFS(月汇总!AA:AA,月汇总!B:B,B65) -> 0 | AL65: =J65-K65-L65-AJ65-AK65 -> -2208.7369 | AM65: =AL65/J65 -> #DIV/0! | AN65: =SUMIFS(月汇总!AB:AB,月汇总!B:B,B65) -> 0 | AO65: =SUMIFS(月汇总!W:W,月汇总!B:B,B65) -> 0 | AP65: =AL65-AN65-AO65 -> -2208.7369
A66: 总计 | H66: =SUM(H5:H65) -> 773 | I66: =SUM(I5:I65) -> 32439.31 | J66: =SUM(J5:J65) -> 2116578 | K66: =SUM(K5:K65) -> 11580 | L66: =SUM(L5:L65) -> 350 | M66: =SUM(M5:M65) -> 707281.99 | N66: =SUM(N5:N65) -> #DIV/0! | O66: =SUM(O5:O65) -> #DIV/0! | ... AP66: =SUM(AP5:AP65) -> -275779.4

Sheet 6月
A1: 应收汇总表
A2: 序号 | B2: 客户 | C2: 前期应收 | D2: 3月应收 | E2: 3月已收 | F2: 合计未收
A3: 1 | B3: 广西华银铝业有限公司 | C3: 160255.36 | D3: =SUMIFS(磅单!O:O,磅单!D:D,B:B) -> 664162.44 | E3: 300000 | F3: =D3-E3+C3 -> 524417.8
A4: 2 | B4: 广西信发物流有限公司(铝粉) | C4: 70646.72 | D4: =SUMIFS(磅单!O:O,磅单!D:D,B:B) -> 27568.26 | F4: =D4-E4+C4 -> 98214.98
A5: 3 | B5: 云南省煤炭交易（储配）中心有限公司 | C5: 193999.82 | D5: =SUMIFS(磅单!O:O,磅单!D:D,B:B) -> 820260.91 | E5: 224870.3 | F5: =D5-E5+C5 -> 789390.43
A6: 4 | B6: 靖西天桂铝业有限公司 | C6: 127283.62 | D6: =SUMIFS(磅单!O:O,磅单!D:D,B:B) -> 194197.36 | F6: =D6-E6+C6 -> 321480.98
A7: 5 | B7: 广西田东锦鑫化工有限公司 | D7: =SUMIFS(磅单!O:O,磅单!D:D,B:B) -> 413034.24 | F7: =D7-E7+C7 -> 413034.24
A8: 合计 | C8: =SUM(C3:C7)-27315.22 -> 524870.3 | D8: =SUM(D3:D7)-月汇总!Y63-月汇总!Y68-月汇总!I63-月汇总!I68 -> 2107293.2 | E8: =SUM(E3:E7) -> 524870.3 | F8: =C8+D8-E8 -> 2107293.2
A10: 二、应付账款
A11: 应付汇总表
A12: 序号 | B12: 客户 | C12: 前期未付 | D12: 4月应付 | E12: 4月已付 | F12: 合计未付
A13: 1 | B13: 充电费 | C13: -122541.36 | D13: =月汇总!J63+月汇总!J68 -> 707281.99 | E13: =SUMIFS(农行卡!#REF!,农行卡!#REF!,B13)+SUMIFS(微信!#REF!,微信!#REF!,B13)+SUMIFS(骏恒对公户!#REF!,骏恒对公户!#REF!,B13) -> #REF! | F13: =C13+D13-E13 -> #REF!
A14: 2 | B14: 配件费 | C14: 0 | D14: =月汇总!N63+月汇总!N68 -> 13473.8 | E14: =SUMIFS(微信!#REF!,微信!#REF!,B14)+SUMIFS(骏恒对公户!#REF!,骏恒对公户!#REF!,B14)+6300 -> #REF! | F14: =C14+D14-E14 -> #REF!
A15: 3 | B15: 轮胎费 | C15: 780 | D15: =月汇总!O63+月汇总!O68 -> 46150 | E15: =SUMIFS(农行卡!#REF!,农行卡!#REF!,B15)+SUMIFS(微信!#REF!,微信!#REF!,B15)+SUMIFS(骏恒对公户!#REF!,骏恒对公户!#REF!,B15) -> #REF! | F15: =C15+D15-E15 -> #REF!
A16: 4 | B16: 高速费 | C16: 0 | D16: =月汇总!P63 -> 0 | E16: =SUMIFS(农行卡!#REF!,农行卡!#REF!,B16)+SUMIFS(微信!#REF!,微信!#REF!,B16)+SUMIFS(骏恒对公户!#REF!,骏恒对公户!#REF!,B16) -> #REF! | F16: =C16+D16-E16 -> #REF!
A17: 5 | B17: 车队-司机工资 | C17: 380100 | D17: =月汇总!R63+月汇总!S63+月汇总!S68+月汇总!R68 -> 504580 | E17: =SUMIFS(农行卡!#REF!,农行卡!#REF!,B17)+SUMIFS(微信!#REF!,微信!#REF!,B17)+SUMIFS(骏恒对公户!#REF!,骏恒对公户!#REF!,B17) -> #REF! | F17: =C17+D17-E17 -> #REF!
A18: 6 | B18: 维修费 | C18: 37586.08 | D18: =月汇总!Q63+月汇总!Q68 -> 55270 | E18: =SUMIFS(农行卡!#REF!,农行卡!#REF!,B18)+SUMIFS(微信!#REF!,微信!#REF!,B18)+SUMIFS(骏恒对公户!#REF!,骏恒对公户!#REF!,B18) -> #REF! | F18: =C18+D18-E18 -> #REF!
A19: 7 | B19: 车辆费用 | C19: 135 | D19: =月汇总!U63+月汇总!U68 -> 26221.1 | E19: =SUMIFS(农行卡!#REF!,农行卡!#REF!,B19)+SUMIFS(微信!#REF!,微信!#REF!,B19)+SUMIFS(骏恒对公户!#REF!,骏恒对公户!#REF!,B19) -> #REF! | F19: =C19+D19-E19 -> #REF!
A20: 8 | B20: 综合费用 | C20: 12903.072 | D20: =月汇总!V63+月汇总!V68+月汇总!X63+月汇总!X68 -> 125040.94 | E20: =SUMIFS(农行卡!#REF!,农行卡!#REF!,B20)+SUMIFS(微信!#REF!,微信!#REF!,B20)+SUMIFS(骏恒对公户!#REF!,骏恒对公户!#REF!,B20) -> #REF! | F20: =C20+D20-E20 -> #REF!
A21: 9 | B21: 车头利息 | C21: 285858.06 | D21: =月汇总!AA63 -> 424000 | E21: =SUMIFS(农行卡!#REF!,农行卡!#REF!,B21)+SUMIFS(微信!#REF!,微信!#REF!,B21)+SUMIFS(骏恒对公户!#REF!,骏恒对公户!#REF!,B21)+285858.06 -> #REF! | F21: =C21+D21-E21 -> #REF!
A22: 10 | B22: 挂板租金 | C22: 111401.3 | D22: =月汇总!AB63+月汇总!AB68 -> 116280 | E22: =SUMIFS(农行卡!#REF!,农行卡!#REF!,B22)+SUMIFS(微信!#REF!,微信!#REF!,B22)+SUMIFS(骏恒对公户!#REF!,骏恒对公户!#REF!,B22) -> #REF! | F22: =C22+D22-E22 -> #REF!
A23: 11 | B23: 保险 | C23: 71895.997 | D23: =月汇总!W63 -> 157294 | E23: =SUMIFS(农行卡!#REF!,农行卡!#REF!,B23)+SUMIFS(微信!#REF!,微信!#REF!,B23)+SUMIFS(骏恒对公户!#REF!,骏恒对公户!#REF!,B23)+71896 -> #REF! | F23: =C23+D23-E23 -> #REF!
A24: 12 | B24: 管理人员工资 | C24: 28029.099 | D24: =月汇总!AC63+月汇总!AC68 -> 48200 | E24: =SUMIFS(农行卡!#REF!,农行卡!#REF!,B24)+SUMIFS(微信!#REF!,微信!#REF!,B24)+SUMIFS(骏恒对公户!#REF!,骏恒对公户!#REF!,B24) -> #REF! | F24: =C24+D24-E24 -> #REF!
A25: 13 | B25: 车队-罚款 | C25: 0 | D25: =月汇总!T63+月汇总!T68 -> 8290 | E25: =SUMIFS(农行卡!#REF!,农行卡!#REF!,B25)+SUMIFS(微信!#REF!,微信!#REF!,B25)+SUMIFS(骏恒对公户!#REF!,骏恒对公户!#REF!,B25) -> #REF! | F25: =C25+D25-E25 -> #REF!
A26: 14 | B26: 税点费用 | C26: 212217.93 | D26: =月汇总!Z63+月汇总!Z68 -> 148345.62 | E26: =SUMIFS(农行卡!#REF!,农行卡!#REF!,B26)+SUMIFS(微信!#REF!,微信!#REF!,B26)+SUMIFS(骏恒对公户!#REF!,骏恒对公户!#REF!,B26) -> #REF! | F26: =C26+D26-E26 -> #REF!
A27: 合计 | C27: =SUM(C13:C26) -> 1018365.2 | D27: =SUM(D13:D26) -> 2380427.5 | E27: =SUM(E13:E26) -> #REF! | F27: =SUM(F13:F26) -> #REF!
C28: 应收-应付 | D28: =D8-D27 -> -273134.24
C29: 利润 | D29: =月汇总!AD63+月汇总!AD68 -> -273134.24
D30: =D28-D29 -> -1.2223609e-09
A31: 三、其他应收
A32: 序号 | B32: 应收账款 | C32: 前期未收 | D32: 6月应收 | E32: 6月已收 | F32: 未收
A33: 1 | B33: 借款（联合重卡） | C33: 0
A34: 2 | B34: 借款（高彩云） | C34: 0
A35: 3 | B35: 其他应收款-房租押金 | C35: 4000 | F35: =C35+D35-E35 -> 4000
A36: 4 | B36: 其他应收款-代付联合重卡前期费用 | C36: 49830.99 | F36: =C36+D36-E36 -> 49830.99
A37: 5 | B37: 陈庆 | C37: 0 | F37: =C37+D37-E37 -> 0
A38: 6 | B38: 其他应收款-赫荣 | C38: 0 | F38: =C38+D38-E38 -> 0
A39: 7 | B39: 江西同欣达汽车贸易有限公司 | C39: 650000 | E39: 650000 | F39: =C39+D39-E39 -> 0
A40: 8 | B40: 杨发明 | D40: 25000 | F40: =C40+D40-E40 -> 25000
A41: 9 | B41: 赣J03373D配件款 | D41: 2050 | F41: =C41+D41-E41 -> 2050
A42: 10 | B42: 粤B94092D后视镜配件款 | D42: 570 | F42: =C42+D42-E42 -> 570
A43: 合计 | C43: =SUM(C35:C40) -> 703830.99 | D43: =SUM(D35:D42) -> 27620 | E43: =SUM(E35:E42) -> 650000 | F43: =SUM(F35:F42) -> 81450.99
A45: 四、其他应付
A46: 序号 | B46: 应付账款 | C46: 前期未付 | D46: 6月应付 | E46: 6月已付 | F46: 未付
A47: 1 | B47: 借款（联合重卡） | C47: 0
A48: 2 | B48: 借款（高彩云） | C48: 6000 | D48: =2000+2000 -> 4000 | E48: 2000 | F48: =C48+D48-E48 -> 8000
A49: 3 | B49: 林超车辆运费 | C49: 37230.722 | D49: =月汇总!AD68 -> 1263.3634 | E49: 30000 | F49: =C49+D49-E49 -> 8494.0855
A50: 4 | B50: 长沙海安供应链 | C50: 0 | D50: =120000+150000 -> 270000 | F50: =C50+D50-E50 -> 270000
A51: 5 | B51: 借款（陈庆） | C51: 6000 | E51: 6000 | F51: =C51+D51-E51 -> 0
A52: 6 | B52: 江西同欣达汽车贸易有限公司 | D52: 100000 | F52: =C52+D52-E52 -> 100000
A53: 7 | B53: 赣J03373D配件款 | D53: 2050 | F53: =C53+D53-E53 -> 2050
A54: 8 | B54: 粤B94092D后视镜配件款 | D54: 570 | F54: =C54+D54-E54 -> 570
A55: 合计 | D55: =SUM(D47:D54) -> 377883.36 | E55: =SUM(E47:E54) -> 38000 | F55: =SUM(F47:F54) -> 389114.09
A57: 四、收支平衡
A58: 序号 | B58: 资产类科目 | C58: 金额 | D58: 序号 | E58: 负债类科目 | F58: 金额
A59: 1 | B59: 农行卡余额 | C59: 2.24 | D59: 1 | E59: 车头利息 | F59: =F21 -> #REF!
A60: 2 | B60: 微信余额 | C60: =微信!#REF! -> #REF! | D60: 2 | E60: 车挂租金 | F60: =F22 -> #REF!
A61: 3 | B61: 骏恒公户 | C61: =骏恒对公户!#REF! -> #REF! | D61: 3 | E61: 保险 | F61: =F23 -> #REF!
A62: 4 | B62: 马队公户 | C62: 0 | D62: 4 | E62: 车队-充电 | F62: =F13 -> #REF!
A63: 5 | B63: 应收账款 | C63: =F8 -> 2107293.2 | D63: 5 | E63: 车队-配件 | F63: =F14 -> #REF!
A64: 6 | B64: 其他应收款 | C64: =F43 -> 81450.99 | D64: 6 | E64: 车队-轮胎 | F64: =F15 -> #REF!
A65: 7 | B65: 固定资产-前期车辆投资 | C65: =600000-37840.03 -> 562159.97 | D65: 7 | E65: 车队-高速费 | F65: =F16 -> #REF!
A66: 8 | D66: 8 | E66: 车队-司机工资 | F66: =F17 -> #REF!
A67: 9 | D67: 9 | E67: 车队-工时费 | F67: =F18 -> #REF!
A68: 10 | D68: 10 | E68: 车队-车辆费用 | F68: =F19 -> #REF!
D69: 11 | E69: 综合费用 | F69: =F20 -> #REF!
D70: 12 | E70: 其他应付 | F70: =F55 -> 389114.09
D71: 13 | E71: 管理工资 | F71: =F24 -> #REF!
D72: 14 | E72: 罚款 | F72: =F25 -> #REF!
D73: 15 | E73: 税点 | F73: =F26 -> #REF!
D74: 负债合计 | F74: =SUM(F59:F73) -> #REF!
D75: 1 | E75: 实收资本 | F75: =100000+600000-37840.03 -> 662159.97 | I75: 2月利润 | J75: -4973.1183
D76: 2 | E76: 未分配利润 | F76: =J75+J76-19298.41-18541.61+J77+月汇总!AD63-37840.03+J78 -> -184907.88 | I76: 3月利润 | J76: 80653.171
D77: 权益合计 | F77: =SUM(F75:F76) -> 477252.09 | I77: 4月利润 | J77: 23214.773
A78: 资产合计 | C78: =SUM(C59:C77) -> #REF! | D78: 负债+权益 | F78: =F74+F77 -> #REF! | I78: 5月利润 | J78: 66274.952
F79: =C78-F78 -> #REF!

Sheet 月汇总
A1: 2026年玉溪广西6月报汇总表
A2: 序号 | B2: 车牌 | C2: 挂板 | D2: 司机 | E2: 车辆状态 | F2: 趟数 | G2: 卸货吨位 | H2: 含税产值 | I2: 磅差和罚款金额 | J2: 电费 | K2: 电费占比 | L2: 单趟电耗 | M2: 电费税点 | N2: 配件费 | O2: 轮胎费 | P2: 高速费 | Q2: 维修费 | R2: 提成工资 | S2: 补助 | T2: 罚款 | U2: 车辆费用 | V2: 均摊 | W2: 车辆保险 | X2: 前期费用 | Y2: 货物险 | Z2: 税点 | AA2: 贷款 | AB2: 挂板租金/贷款 | AC2: 管理人员工资 | AD2: 利润
A3: 1 | B3: 赣J01379D | C3: 桂LD735挂 | D3: 陆光锐 | E3: 正常 | F3: =COUNTIFS(磅单!E:E,B3) -> 1 | G3: =SUMIFS(磅单!L:L,磅单!F:F,B3) -> 41.74 | H3: =SUMIFS(磅单!O:O,磅单!F:F,B3) -> 2546.14 | J3: =SUMIFS(现金充电明细!L:L,现金充电明细!B:B,B3)+SUMIFS('华瑞-曙光，大水井，老水井充电站'!L:L,'华瑞-曙光，大水井，老水井充电站'!B:B,B3)+SUMIFS('银盛-青龙坪充电站'!L:L,'银盛-青龙坪充电站'!B:B,B3)+SUMIFS('砚山锦佳-砚山充电站'!K:K,'砚山锦佳-砚山充电站'!B:B,B3)+SUMIFS(中石油广西百色靖西市龙临加油充电站!K:K,中石油广西百色靖西市龙临加油充电站!B:B,B3)+SUMIFS(德保众擎充电站!L:L,德保众擎充电站!B:B,B3)+SUMIFS(南网八宝充电站!K:K,南网八宝充电站!B:B,B3)+SUMIFS(南屏充电站!K:K,南屏充电站!B:B,B3)+SUMIFS(鑫鸿充电站!K:K,鑫鸿充电站!B:B,B3)+SUMIFS('锦田-百色田东充电站'!K:K,'锦田-百色田东充电站'!B:B,B3)+37.06/47+SUMIFS(平远充电站!K:K,平远充电站!B:B,B3) -> 1091.9085 | K3: =J3/(H3) -> 0.42884857 | L3: =J3/F3 -> 1091.9085 | N3: =13473.8/61 -> 220.88197 | O3: =SUMIFS(轮胎!H:H,轮胎!D:D,B3)+SUMIFS(轮胎!H:H,轮胎!D:D,C3) -> 0 | P3: 0 | Q3: =SUMIFS(维修费!E:E,维修费!C:C,B3)+SUMIFS(维修费!E:E,维修费!C:C,C3) -> 12500 | R3: =SUMIFS(磅单!R:R,磅单!F:F,B3) -> 600 | S3: =SUMIFS(司机工资表!E:E,司机工资表!B:B,D3)+SUMIFS(司机工资表!N:N,司机工资表!B:B,D3) -> 0 | T3: =SUMIFS(付款明细!G:G,付款明细!D:D,B3,付款明细!B:B,"车队-罚款") -> 0 | U3: =SUMIFS(付款明细!G:G,付款明细!D:D,B3,付款明细!B:B,"车辆费用")+SUMIFS(付款明细!G:G,付款明细!D:D,C3,付款明细!B:B,"车辆费用") -> 0 | V3: =SUMIFS(付款明细!G:G,付款明细!B:B,"综合费用")/61 -> 397.39246 | W3: 2666 | Y3: =SUMIFS(磅单!P:P,磅单!E:E,B3) -> 15 | Z3: =H3*0.07-M3 -> 178.2298 | AA3: 10600 | AB3: =3800 -> 3800 | AC3: =(管理人员工资!$D$10+管理人员工资!$E$10)/61 -> 790.16393 | AD3: =H3-I3-J3-N3-O3-R3-S3-T3-U3-V3-W3-AA3-AB3-AC3-Q3-P3-Z3-Y3-X3 -> -30313.437
A4: 2 | B4: 赣J00236D | C4: 桂LA725挂 | D4: 熊廷春 | E4: 正常 | F4: =COUNTIFS(磅单!E:E,B4) -> 19 | G4: =SUMIFS(磅单!L:L,磅单!F:F,B4) -> 805.2 | H4: =SUMIFS(磅单!O:O,磅单!F:F,B4) -> 50229.42 | J4: =SUMIFS(现金充电明细!L:L,现金充电明细!B:B,B4)+SUMIFS('华瑞-曙光，大水井，老水井充电站'!L:L,'华瑞-曙光，大水井，老水井充电站'!B:B,B4)+SUMIFS('银盛-青龙坪充电站'!L:L,'银盛-青龙坪充电站'!B:B,B4)+SUMIFS('砚山锦佳-砚山充电站'!K:K,'砚山锦佳-砚山充电站'!B:B,B4)+SUMIFS(中石油广西百色靖西市龙临加油充电站!K:K,中石油广西百色靖西市龙临加油充电站!B:B,B4)+SUMIFS(德保众擎充电站!L:L,德保众擎充电站!B:B,B4)+SUMIFS(南网八宝充电站!K:K,南网八宝充电站!B:B,B4)+SUMIFS(南屏充电站!K:K,南屏充电站!B:B,B4)+SUMIFS(鑫鸿充电站!K:K,鑫鸿充电站!B:B,B4)+SUMIFS('锦田-百色田东充电站'!K:K,'锦田-百色田东充电站'!B:B,B4)+37.06/47+SUMIFS(平远充电站!K:K,平远充电站!B:B,B4) -> 16063.773 | K4: =J4/(H4) -> 0.31980805 | L4: =J4/F4 -> 845.46174 | N4: =13473.8/61 -> 220.88197 | O4: =SUMIFS(轮胎!H:H,轮胎!D:D,B4)+SUMIFS(轮胎!H:H,轮胎!D:D,C4) -> 0 | P4: 0 | Q4: =SUMIFS(维修费!E:E,维修费!C:C,B4)+SUMIFS(维修费!E:E,维修费!C:C,C4) -> 510 | R4: =SUMIFS(磅单!R:R,磅单!F:F,B4) -> 11800 | S4: =SUMIFS(司机工资表!E:E,司机工资表!B:B,D4)+SUMIFS(司机工资表!N:N,司机工资表!B:B,D4) -> 0 | T4: =SUMIFS(付款明细!G:G,付款明细!D:D,B4,付款明细!B:B,"车队-罚款") -> 120 | U4: =SUMIFS(付款明细!G:G,付款明细!D:D,B4,付款明细!B:B,"车辆费用")+SUMIFS(付款明细!G:G,付款明细!D:D,C4,付款明细!B:B,"车辆费用") -> 467 | V4: =SUMIFS(付款明细!G:G,付款明细!B:B,"综合费用")/61 -> 397.39246 | W4: 2666 | Y4: =SUMIFS(磅单!P:P,磅单!E:E,B4) -> 285 | Z4: =H4*0.07-M4 -> 3516.0594 | AA4: 10600 | AB4: =3800 -> 3800 | AC4: =(管理人员工资!$D$10+管理人员工资!$E$10)/61 -> 790.16393 | AD4: =H4-I4-J4-N4-O4-R4-S4-T4-U4-V4-W4-AA4-AB4-AC4-Q4-P4-Z4-Y4-X4 -> -1006.8508
A5: 3 | B5: 赣J05550D | C5: 桂LD517挂 | D5: 任正勇 | E5: 正常 | F5: =COUNTIFS(磅单!E:E,B5) -> 21 | G5: =SUMIFS(磅单!L:L,磅单!F:F,B5) -> 893.18 | H5: =SUMIFS(磅单!O:O,磅单!F:F,B5) -> 55301.38 | J5: =SUMIFS(现金充电明细!L:L,现金充电明细!B:B,B5)+SUMIFS('华瑞-曙光，大水井，老水井充电站'!L:L,'华瑞-曙光，大水井，老水井充电站'!B:B,B5)+SUMIFS('银盛-青龙坪充电站'!L:L,'银盛-青龙坪充电站'!B:B,B5)+SUMIFS('砚山锦佳-砚山充电站'!K:K,'砚山锦佳-砚山充电站'!B:B,B5)+SUMIFS(中石油广西百色靖西市龙临加油充电站!K:K,中石油广西百色靖西市龙临加油充电站!B:B,B5)+SUMIFS(德保众擎充电站!L:L,德保众擎充电站!B:B,B5)+SUMIFS(南网八宝充电站!K:K,南网八宝充电站!B:B,B5)+SUMIFS(南屏充电站!K:K,南屏充电站!B:B,B5)+SUMIFS(鑫鸿充电站!K:K,鑫鸿充电站!B:B,B5)+SUMIFS('锦田-百色田东充电站'!K:K,'锦田-百色田东充电站'!B:B,B5)+37.06/47+SUMIFS(平远充电站!K:K,平远充电站!B:B,B5) -> 17389.021 | K5: =J5/(H5) -> 0.31444099 | L5: =J5/F5 -> 828.0486 | N5: =13473.8/61 -> 220.88197 | O5: =SUMIFS(轮胎!H:H,轮胎!D:D,B5)+SUMIFS(轮胎!H:H,轮胎!D:D,C5) -> 7130 | P5: 0 | Q5: =SUMIFS(维修费!E:E,维修费!C:C,B5)+SUMIFS(维修费!E:E,维修费!C:C,C5) -> 800 | R5: =SUMIFS(磅单!R:R,磅单!F:F,B5) -> 13000 | S5: =SUMIFS(司机工资表!E:E,司机工资表!B:B,D5)+SUMIFS(司机工资表!N:N,司机工资表!B:B,D5) -> 200 | T5: =SUMIFS(付款明细!G:G,付款明细!D:D,B5,付款明细!B:B,"车队-罚款") -> 400 | U5: =SUMIFS(付款明细!G:G,付款明细!D:D,B5,付款明细!B:B,"车辆费用")+SUMIFS(付款明细!G:G,付款明细!D:D,C5,付款明细!B:B,"车辆费用") -> 544 | V5: =SUMIFS(付款明细!G:G,付款明细!B:B,"综合费用")/61 -> 397.39246 | W5: 2666 | Y5: =SUMIFS(磅单!P:P,磅单!E:E,B5) -> 315 | Z5: =H5*0.07-M5 -> 3871.0966 | AA5: 10600 | AB5: =3800 -> 3800 | AC5: =(管理人员工资!$D$10+管理人员工资!$E$10)/61 -> 790.16393 | AD5: =H5-I5-J5-N5-O5-R5-S5-T5-U5-V5-W5-AA5-AB5-AC5-Q5-P5-Z5-Y5-X5 -> -6822.1756
A6: 4 | B6: 赣J00607D | C6: 桂LD396挂 | D6: 程大昌 | E6: 正常 | F6: =COUNTIFS(磅单!E:E,B6) -> 19 | G6: =SUMIFS(磅单!L:L,磅单!F:F,B6) -> 782.99 | H6: =SUMIFS(磅单!O:O,磅单!F:F,B6) -> 46796.27 | J6: =SUMIFS(现金充电明细!L:L,现金充电明细!B:B,B6)+SUMIFS('华瑞-曙光，大水井，老水井充电站'!L:L,'华瑞-曙光，大水井，老水井充电站'!B:B,B6)+SUMIFS('银盛-青龙坪充电站'!L:L,'银盛-青龙坪充电站'!B:B,B6)+SUMIFS('砚山锦佳-砚山充电站'!K:K,'砚山锦佳-砚山充电站'!B:B,B6)+SUMIFS(中石油广西百色靖西市龙临加油充电站!K:K,中石油广西百色靖西市龙临加油充电站!B:B,B6)+SUMIFS(德保众擎充电站!L:L,德保众擎充电站!B:B,B6)+SUMIFS(南网八宝充电站!K:K,南网八宝充电站!B:B,B6)+SUMIFS(南屏充电站!K:K,南屏充电站!B:B,B6)+SUMIFS(鑫鸿充电站!K:K,鑫鸿充电站!B:B,B6)+SUMIFS('锦田-百色田东充电站'!K:K,'锦田-百色田东充电站'!B:B,B6)+37.06/47+SUMIFS(平远充电站!K:K,平远充电站!B:B,B6) -> 15004.904 | K6: =J6/(H6) -> 0.32064315 | L6: =J6/F6 -> 789.73177 | N6: =13473.8/61 -> 220.88197 | O6: =SUMIFS(轮胎!H:H,轮胎!D:D,B6)+SUMIFS(轮胎!H:H,轮胎!D:D,C6) -> 0 | P6: 0 | Q6: =SUMIFS(维修费!E:E,维修费!C:C,B6)+SUMIFS(维修费!E:E,维修费!C:C,C6) -> 1120 | R6: =SUMIFS(磅单!R:R,磅单!F:F,B6) -> 11400 | S6: =SUMIFS(司机工资表!E:E,司机工资表!B:B,D6)+SUMIFS(司机工资表!N:N,司机工资表!B:B,D6) -> 200 | T6: =SUMIFS(付款明细!G:G,付款明细!D:D,B6,付款明细!B:B,"车队-罚款") -> 440 | U6: =SUMIFS(付款明细!G:G,付款明细!D:D,B6,付款明细!B:B,"车辆费用")+SUMIFS(付款明细!G:G,付款明细!D:D,C6,付款明细!B:B,"车辆费用") -> 636 | V6: =SUMIFS(付款明细!G:G,付款明细!B:B,"综合费用")/61 -> 397.39246 | W6: 2666 | Y6: =SUMIFS(磅单!P:P,磅单!E:E,B6) -> 285 | Z6: =H6*0.07-M6 -> 3275.7389 | AA6: 10600 | AB6: =3800 -> 3800 | AC6: =(管理人员工资!$D$10+管理人员工资!$E$10)/61 -> 790.16393 | AD6: =H6-I6-J6-N6-O6-R6-S6-T6-U6-V6-W6-AA6-AB6-AC6-Q6-P6-Z6-Y6-X6 -> -4039.8108
A7: 5 | B7: 赣J00677D | C7: 桂LB829挂 | D7: 付建东 | E7: 正常 | F7: =COUNTIFS(磅单!E:E,B7) -> 20 | G7: =SUMIFS(磅单!L:L,磅单!F:F,B7) -> 820.18 | H7: =SUMIFS(磅单!O:O,磅单!F:F,B7) -> 50875.58 | I7: 50 | J7: =SUMIFS(现金充电明细!L:L,现金充电明细!B:B,B7)+SUMIFS('华瑞-曙光，大水井，老水井充电站'!L:L,'华瑞-曙光，大水井，老水井充电站'!B:B,B7)+SUMIFS('银盛-青龙坪充电站'!L:L,'银盛-青龙坪充电站'!B:B,B7)+SUMIFS('砚山锦佳-砚山充电站'!K:K,'砚山锦佳-砚山充电站'!B:B,B7)+SUMIFS(中石油广西百色靖西市龙临加油充电站!K:K,中石油广西百色靖西市龙临加油充电站!B:B,B7)+SUMIFS(德保众擎充电站!L:L,德保众擎充电站!B:B,B7)+SUMIFS(南网八宝充电站!K:K,南网八宝充电站!B:B,B7)+SUMIFS(南屏充电站!K:K,南屏充电站!B:B,B7)+SUMIFS(鑫鸿充电站!K:K,鑫鸿充电站!B:B,B7)+SUMIFS('锦田-百色田东充电站'!K:K,'锦田-百色田东充电站'!B:B,B7)+37.06/47+SUMIFS(平远充电站!K:K,平远充电站!B:B,B7) -> 16613.933 | K7: =J7/(H7) -> 0.32656006 | L7: =J7/F7 -> 830.69663 | N7: =13473.8/61 -> 220.88197 | O7: =SUMIFS(轮胎!H:H,轮胎!D:D,B7)+SUMIFS(轮胎!H:H,轮胎!D:D,C7) -> 7130 | P7: 0 | Q7: =SUMIFS(维修费!E:E,维修费!C:C,B7)+SUMIFS(维修费!E:E,维修费!C:C,C7) -> 670 | R7: =SUMIFS(磅单!R:R,磅单!F:F,B7) -> 12200 | S7: =SUMIFS(司机工资表!E:E,司机工资表!B:B,D7)+SUMIFS(司机工资表!N:N,司机工资表!B:B,D7) -> 0 | T7: =SUMIFS(付款明细!G:G,付款明细!D:D,B7,付款明细!B:B,"车队-罚款") -> 200 | U7: =SUMIFS(付款明细!G:G,付款明细!D:D,B7,付款明细!B:B,"车辆费用")+SUMIFS(付款明细!G:G,付款明细!D:D,C7,付款明细!B:B,"车辆费用") -> 422 | V7: =SUMIFS(付款明细!G:G,付款明细!B:B,"综合费用")/61 -> 397.39246 | W7: 2666 | Y7: =SUMIFS(磅单!P:P,磅单!E:E,B7) -> 300 | Z7: =H7*0.07-M7 -> 3561.2906 | AA7: 10600 | AB7: =3800 -> 3800 | AC7: =(管理人员工资!$D$10+管理人员工资!$E$10)/61 -> 790.16393 | AD7: =H7-I7-J7-N7-O7-R7-S7-T7-U7-V7-W7-AA7-AB7-AC7-Q7-P7-Z7-Y7-X7 -> -8746.0815
A8: 6 | B8: 赣J01095D | C8: 桂LC705挂 | D8: 柏万云 | E8: 正常 | F8: =COUNTIFS(磅单!E:E,B8) -> 19 | G8: =SUMIFS(磅单!L:L,磅单!F:F,B8) -> 769.79 | H8: =SUMIFS(磅单!O:O,磅单!F:F,B8) -> 48095.53 | J8: =SUMIFS(现金充电明细!L:L,现金充电明细!B:B,B8)+SUMIFS('华瑞-曙光，大水井，老水井充电站'!L:L,'华瑞-曙光，大水井，老水井充电站'!B:B,B8)+SUMIFS('银盛-青龙坪充电站'!L:L,'银盛-青龙坪充电站'!B:B,B8)+SUMIFS('砚山锦佳-砚山充电站'!K:K,'砚山锦佳-砚山充电站'!B:B,B8)+SUMIFS(中石油广西百色靖西市龙临加油充电站!K:K,中石油广西百色靖西市龙临加油充电站!B:B,B8)+SUMIFS(德保众擎充电站!L:L,德保众擎充电站!B:B,B8)+SUMIFS(南网八宝充电站!K:K,南网八宝充电站!B:B,B8)+SUMIFS(南屏充电站!K:K,南屏充电站!B:B,B8)+SUMIFS(鑫鸿充电站!K:K,鑫鸿充电站!B:B,B8)+SUMIFS('锦田-百色田东充电站'!K:K,'锦田-百色田东充电站'!B:B,B8)+37.06/47+SUMIFS(平远充电站!K:K,平远充电站!B:B,B8) -> 14132.489 | K8: =J8/(H8) -> 0.29384204 | L8: =J8/F8 -> 743.81519 | N8: =13473.8/61 -> 220.88197 | O8: =SUMIFS(轮胎!H:H,轮胎!D:D,B8)+SUMIFS(轮胎!H:H,轮胎!D:D,C8) -> 900 | P8: 0 | Q8: =SUMIFS(维修费!E:E,维修费!C:C,B8)+SUMIFS(维修费!E:E,维修费!C:C,C8) -> 415 | R8: =SUMIFS(磅单!R:R,磅单!F:F,B8) -> 11800 | S8: =SUMIFS(司机工资表!E:E,司机工资表!B:B,D8)+SUMIFS(司机工资表!N:N,司机工资表!B:B,D8) -> 0 | T8: =SUMIFS(付款明细!G:G,付款明细!D:D,B8,付款明细!B:B,"车队-罚款") -> 0 | U8: =SUMIFS(付款明细!G:G,付款明细!D:D,B8,付款明细!B:B,"车辆费用")+SUMIFS(付款明细!G:G,付款明细!D:D,C8,付款明细!B:B,"车辆费用") -> 581 | V8: =SUMIFS(付款明细!G:G,付款明细!B:B,"综合费用")/61 -> 397.39246 | W8: 2666 | Y8: =SUMIFS(磅单!P:P,磅单!E:E,B8) -> 285 | Z8: =H8*0.07-M8 -> 3366.6871 | AA8: 10600 | AB8: =3800 -> 3800 | AC8: =(管理人员工资!$D$10+管理人员工资!$E$10)/61 -> 790.16393 | AD8: =H8-I8-J8-N8-O8-R8-S8-T8-U8-V8-W8-AA8-AB8-AC8-Q8-P8-Z8-Y8-X8 -> -1859.0841
A9: 7 | B9: 赣J03136D | C9: 桂L9856挂 | D9: 朱家访 | E9: 正常 | F9: =COUNTIFS(磅单!E:E,B9) -> 18 | G9: =SUMIFS(磅单!L:L,磅单!F:F,B9) -> 789.79 | H9: =SUMIFS(磅单!O:O,磅单!F:F,B9) -> 48659.05 | J9: =SUMIFS(现金充电明细!L:L,现金充电明细!B:B,B9)+SUMIFS('华瑞-曙光，大水井，老水井充电站'!L:L,'华瑞-曙光，大水井，老水井充电站'!B:B,B9)+SUMIFS('银盛-青龙坪充电站'!L:L,'银盛-青龙坪充电站'!B:B,B9)+SUMIFS('砚山锦佳-砚山充电站'!K:K,'砚山锦佳-砚山充电站'!B:B,B9)+SUMIFS(中石油广西百色靖西市龙临加油充电站!K:K,中石油广西百色靖西市龙临加油充电站!B:B,B9)+SUMIFS(德保众擎充电站!L:L,德保众擎充电站!B:B,B9)+SUMIFS(南网八宝充电站!K:K,南网八宝充电站!B:B,B9)+SUMIFS(南屏充电站!K:K,南屏充电站!B:B,B9)+SUMIFS(鑫鸿充电站!K:K,鑫鸿充电站!B:B,B9)+SUMIFS('锦田-百色田东充电站'!K:K,'锦田-百色田东充电站'!B:B,B9)+37.06/47+SUMIFS(平远充电站!K:K,平远充电站!B:B,B9) -> 15027.95 | K9: =J9/(H9) -> 0.30884183 | L9: =J9/F9 -> 834.88612 | N9: =13473.8/61 -> 220.88197 | O9: =SUMIFS(轮胎!H:H,轮胎!D:D,B9)+SUMIFS(轮胎!H:H,轮胎!D:D,C9) -> 900 | P9: 0 | Q9: =SUMIFS(维修费!E:E,维修费!C:C,B9)+SUMIFS(维修费!E:E,维修费!C:C,C9) -> 50 | R9: =SUMIFS(磅单!R:R,磅单!F:F,B9) -> 11600 | S9: =SUMIFS(司机工资表!E:E,司机工资表!B:B,D9)+SUMIFS(司机工资表!N:N,司机工资表!B:B,D9) -> 200 | T9: =SUMIFS(付款明细!G:G,付款明细!D:D,B9,付款明细!B:B,"车队-罚款") -> 210 | U9: =SUMIFS(付款明细!G:G,付款明细!D:D,B9,付款明细!B:B,"车辆费用")+SUMIFS(付款明细!G:G,付款明细!D:D,C9,付款明细!B:B,"车辆费用") -> 480 | V9: =SUMIFS(付款明细!G:G,付款明细!B:B,"综合费用")/61 -> 397.39246 | W9: 2666 | Y9: =SUMIFS(磅单!P:P,磅单!E:E,B9) -> 270 | Z9: =H9*0.07-M9 -> 3406.1335 | AA9: 10600 | AB9: =3800 -> 3800 | AC9: =(管理人员工资!$D$10+管理人员工资!$E$10)/61 -> 790.16393 | AD9: =H9-I9-J9-N9-O9-R9-S9-T9-U9-V9-W9-AA9-AB9-AC9-Q9-P9-Z9-Y9-X9 -> -1959.472
A10: 8 | B10: 赣J03688D | C10: 桂LA935挂 | D10: 刘小福 | E10: 正常 | F10: =COUNTIFS(磅单!E:E,B10) -> 22 | G10: =SUMIFS(磅单!L:L,磅单!F:F,B10) -> 928.88 | H10: =SUMIFS(磅单!O:O,磅单!F:F,B10) -> 58792.78 | J10: =SUMIFS(现金充电明细!L:L,现金充电明细!B:B,B10)+SUMIFS('华瑞-曙光，大水井，老水井充电站'!L:L,'华瑞-曙光，大水井，老水井充电站'!B:B,B10)+SUMIFS('银盛-青龙坪充电站'!L:L,'银盛-青龙坪充电站'!B:B,B10)+SUMIFS('砚山锦佳-砚山充电站'!K:K,'砚山锦佳-砚山充电站'!B:B,B10)+SUMIFS(中石油广西百色靖西市龙临加油充电站!K:K,中石油广西百色靖西市龙临加油充电站!B:B,B10)+SUMIFS(德保众擎充电站!L:L,德保众擎充电站!B:B,B10)+SUMIFS(南网八宝充电站!K:K,南网八宝充电站!B:B,B10)+SUMIFS(南屏充电站!K:K,南屏充电站!B:B,B10)+SUMIFS(鑫鸿充电站!K:K,鑫鸿充电站!B:B,B10)+SUMIFS('锦田-百色田东充电站'!K:K,'锦田-百色田东充电站'!B:B,B10)+37.06/47+SUMIFS(平远充电站!K:K,平远充电站!B:B,B10) -> 16765.748 | K10: =J10/(H10) -> 0.28516679 | L10: =J10/F10 -> 762.07948 | N10: =13473.8/61 -> 220.88197 | O10: =SUMIFS(轮胎!H:H,轮胎!D:D,B10)+SUMIFS(轮胎!H:H,轮胎!D:D,C10) -> 0 | P10: 0 | Q10: =SUMIFS(维修费!E:E,维修费!C:C,B10)+SUMIFS(维修费!E:E,维修费!C:C,C10) -> 1203 | R10: =SUMIFS(磅单!R:R,磅单!F:F,B10) -> 13800 | S10: =SUMIFS(司机工资表!E:E,司机工资表!B:B,D10)+SUMIFS(司机工资表!N:N,司机工资表!B:B,D10) -> 1200 | T10: =SUMIFS(付款明细!G:G,付款明细!D:D,B10,付款明细!B:B,"车队-罚款") -> 420 | U10: =SUMIFS(付款明细!G:G,付款明细!D:D,B10,付款明细!B:B,"车辆费用")+SUMIFS(付款明细!G:G,付款明细!D:D,C10,付款明细!B:B,"车辆费用") -> 711 | V10: =SUMIFS(付款明细!G:G,付款明细!B:B,"综合费用")/61 -> 397.39246 | W10: 2666 | Y10: =SUMIFS(磅单!P:P,磅单!E:E,B10) -> 330 | Z10: =H10*0.07-M10 -> 4115.4946 | AA10: 10600 | AB10: =3800 -> 3800 | AC10: =(管理人员工资!$D$10+管理人员工资!$E$10)/61 -> 790.16393 | AD10: =H10-I10-J10-N10-O10-R10-S10-T10-U10-V10-W10-AA10-AB10-AC10-Q10-P10-Z10-Y10-X10 -> 1773.0986
A11: 9 | B11: 赣J07535D | C11: 桂LB307挂 | D11: 李家宝 | E11: 正常 | F11: =COUNTIFS(磅单!E:E,B11) -> 21 | G11: =SUMIFS(磅单!L:L,磅单!F:F,B11) -> 874.61 | H11: =SUMIFS(磅单!O:O,磅单!F:F,B11) -> 55429.23 | J11: =SUMIFS(现金充电明细!L:L,现金充电明细!B:B,B11)+SUMIFS('华瑞-曙光，大水井，老水井充电站'!L:L,'华瑞-曙光，大水井，老水井充电站'!B:B,B11)+SUMIFS('银盛-青龙坪充电站'!L:L,'银盛-青龙坪充电站'!B:B,B11)+SUMIFS('砚山锦佳-砚山充电站'!K:K,'砚山锦佳-砚山充电站'!B:B,B11)+SUMIFS(中石油广西百色靖西市龙临加油充电站!K:K,中石油广西百色靖西市龙临加油充电站!B:B,B11)+SUMIFS(德保众擎充电站!L:L,德保众擎充电站!B:B,B11)+SUMIFS(南网八宝充电站!K:K,南网八宝充电站!B:B,B11)+SUMIFS(南屏充电站!K:K,南屏充电站!B:B,B11)+SUMIFS(鑫鸿充电站!K:K,鑫鸿充电站!B:B,B11)+SUMIFS('锦田-百色田东充电站'!K:K,'锦田-百色田东充电站'!B:B,B11)+37.06/47+SUMIFS(平远充电站!K:K,平远充电站!B:B,B11) -> 14114.09 | K11: =J11/(H11) -> 0.25463261 | L11: =J11/F11 -> 672.0995 | N11: =13473.8/61 -> 220.88197 | O11: =SUMIFS(轮胎!H:H,轮胎!D:D,B11)+SUMIFS(轮胎!H:H,轮胎!D:D,C11) -> 0 | P11: 0 | Q11: =SUMIFS(维修费!E:E,维修费!C:C,B11)+SUMIFS(维修费!E:E,维修费!C:C,C11) -> 620 | R11: =SUMIFS(磅单!R:R,磅单!F:F,B11) -> 13000 | S11: =SUMIFS(司机工资表!E:E,司机工资表!B:B,D11)+SUMIFS(司机工资表!N:N,司机工资表!B:B,D11) -> 0 | T11: =SUMIFS(付款明细!G:G,付款明细!D:D,B11,付款明细!B:B,"车队-罚款") -> 0 | U11: =SUMIFS(付款明细!G:G,付款明细!D:D,B11,付款明细!B:B,"车辆费用")+SUMIFS(付款明细!G:G,付款明细!D:D,C11,付款明细!B:B,"车辆费用") -> 613 | V11: =SUMIFS(付款明细!G:G,付款明细!B:B,"综合费用")/61 -> 397.39246 | W11: 2666 | Y11: =SUMIFS(磅单!P:P,磅单!E:E,B11) -> 315 | Z11: =H11*0.07-M11 -> 3880.0461 | AA11: 10600 | AB11: =3800 -> 3800 | AC11: =(管理人员工资!$D$10+管理人员工资!$E$10)/61 -> 790.16393 | AD11: =H11-I11-J11-N11-O11-R11-S11-T11-U11-V11-W11-AA11-AB11-AC11-Q11-P11-Z11-Y11-X11 -> 4412.656
A12: 10 | B12: 赣J08536D | C12: 桂LD179挂 | D12: 李建祥 | E12: 正常 | F12: =COUNTIFS(磅单!E:E,B12) -> 16 | G12: =SUMIFS(磅单!L:L,磅单!F:F,B12) -> 673.98 | H12: =SUMIFS(磅单!O:O,磅单!F:F,B12) -> 44638.62 | J12: =SUMIFS(现金充电明细!L:L,现金充电明细!B:B,B12)+SUMIFS('华瑞-曙光，大水井，老水井充电站'!L:L,'华瑞-曙光，大水井，老水井充电站'!B:B,B12)+SUMIFS('银盛-青龙坪充电站'!L:L,'银盛-青龙坪充电站'!B:B,B12)+SUMIFS('砚山锦佳-砚山充电站'!K:K,'砚山锦佳-砚山充电站'!B:B,B12)+SUMIFS(中石油广西百色靖西市龙临加油充电站!K:K,中石油广西百色靖西市龙临加油充电站!B:B,B12)+SUMIFS(德保众擎充电站!L:L,德保众擎充电站!B:B,B12)+SUMIFS(南网八宝充电站!K:K,南网八宝充电站!B:B,B12)+SUMIFS(南屏充电站!K:K,南屏充电站!B:B,B12)+SUMIFS(鑫鸿充电站!K:K,鑫鸿充电站!B:B,B12)+SUMIFS('锦田-百色田东充电站'!K:K,'锦田-百色田东充电站'!B:B,B12)+37.06/47+SUMIFS(平远充电站!K:K,平远充电站!B:B,B12) -> 15202.365 | K12: =J12/(H12) -> 0.34056531 | L12: =J12/F12 -> 950.14784 | N12: =13473.8/61 -> 220.88197 | O12: =SUMIFS(轮胎!H:H,轮胎!D:D,B12)+SUMIFS(轮胎!H:H,轮胎!D:D,C12) -> 0 | P12: 0 | Q12: =SUMIFS(维修费!E:E,维修费!C:C,B12)+SUMIFS(维修费!E:E,维修费!C:C,C12) -> 370 | R12: =SUMIFS(磅单!R:R,磅单!F:F,B12) -> 10400 | S12: =SUMIFS(司机工资表!E:E,司机工资表!B:B,D12)+SUMIFS(司机工资表!N:N,司机工资表!B:B,D12) -> 1000 | T12: =SUMIFS(付款明细!G:G,付款明细!D:D,B12,付款明细!B:B,"车队-罚款") -> 0 | U12: =SUMIFS(付款明细!G:G,付款明细!D:D,B12,付款明细!B:B,"车辆费用")+SUMIFS(付款明细!G:G,付款明细!D:D,C12,付款明细!B:B,"车辆费用") -> 3194 | V12: =SUMIFS(付款明细!G:G,付款明细!B:B,"综合费用")/61 -> 397.39246 | W12: 2666 | Y12: =SUMIFS(磅单!P:P,磅单!E:E,B12) -> 240 | Z12: =H12*0.07-M12 -> 3124.7034 | AA12: 10600 | AB12: =3800 -> 3800 | AC12: =(管理人员工资!$D$10+管理人员工资!$E$10)/61 -> 790.16393 | AD12: =H12-I12-J12-N12-O12-R12-S12-T12-U12-V12-W12-AA12-AB12-AC12-Q12-P12-Z12-Y12-X12 -> -7366.8872
A13: 11 | B13: 赣J05857D | C13: 桂LB659挂 | D13: 高洪伟 | E13: 正常 | F13: =COUNTIFS(磅单!E:E,B13) -> 19 | G13: =SUMIFS(磅单!L:L,磅单!F:F,B13) -> 798.41 | H13: =SUMIFS(磅单!O:O,磅单!F:F,B13) -> 48640.05 | J13: =SUMIFS(现金充电明细!L:L,现金充电明细!B:B,B13)+SUMIFS('华瑞-曙光，大水井，老水井充电站'!L:L,'华瑞-曙光，大水井，老水井充电站'!B:B,B13)+SUMIFS('银盛-青龙坪充电站'!L:L,'银盛-青龙坪充电站'!B:B,B13)+SUMIFS('砚山锦佳-砚山充电站'!K:K,'砚山锦佳-砚山充电站'!B:B,B13)+SUMIFS(中石油广西百色靖西市龙临加油充电站!K:K,中石油广西百色靖西市龙临加油充电站!B:B,B13)+SUMIFS(德保众擎充电站!L:L,德保众擎充电站!B:B,B13)+SUMIFS(南网八宝充电站!K:K,南网八宝充电站!B:B,B13)+SUMIFS(南屏充电站!K:K,南屏充电站!B:B,B13)+SUMIFS(鑫鸿充电站!K:K,鑫鸿充电站!B:B,B13)+SUMIFS('锦田-百色田东充电站'!K:K,'锦田-百色田东充电站'!B:B,B13)+37.06/47+SUMIFS(平远充电站!K:K,平远充电站!B:B,B13) -> 14817.425 | K13: =J13/(H13) -> 0.30463425 | L13: =J13/F13 -> 779.86447 | N13: =13473.8/61 -> 220.88197 | O13: =SUMIFS(轮胎!H:H,轮胎!D:D,B13)+SUMIFS(轮胎!H:H,轮胎!D:D,C13) -> 50 | P13: 0 | Q13: =SUMIFS(维修费!E:E,维修费!C:C,B13)+SUMIFS(维修费!E:E,维修费!C:C,C13) -> 2190 | R13: =SUMIFS(磅单!R:R,磅单!F:F,B13) -> 11600 | S13: =SUMIFS(司机工资表!E:E,司机工资表!B:B,D13)+SUMIFS(司机工资表!N:N,司机工资表!B:B,D13) -> 200 | T13: =SUMIFS(付款明细!G:G,付款明细!D:D,B13,付款明细!B:B,"车队-罚款") -> 200 | U13: =SUMIFS(付款明细!G:G,付款明细!D:D,B13,付款明细!B:B,"车辆费用")+SUMIFS(付款明细!G:G,付款明细!D:D,C13,付款明细!B:B,"车辆费用") -> 395 | V13: =SUMIFS(付款明细!G:G,付款明细!B:B,"综合费用")/61 -> 397.39246 | W13: 2666 | Y13: =SUMIFS(磅单!P:P,磅单!E:E,B13) -> 285 | Z13: =H13*0.07-M13 -> 3404.8035 | AA13: 10600 | AB13: =3800 -> 3800 | AC13: =(管理人员工资!$D$10+管理人员工资!$E$10)/61 -> 790.16393 | AD13: =H13-I13-J13-N13-O13-R13-S13-T13-U13-V13-W13-AA13-AB13-AC13-Q13-P13-Z13-Y13-X13 -> -2976.6169
A14: 12 | B14: 赣J06519D | C14: 桂L5759挂 | D14: 冯育柱 | E14: 正常 | F14: =COUNTIFS(磅单!E:E,B14) -> 25 | G14: =SUMIFS(磅单!L:L,磅单!F:F,B14) -> 1015.87 | H14: =SUMIFS(磅单!O:O,磅单!F:F,B14) -> 64387.11 | J14: =SUMIFS(现金充电明细!L:L,现金充电明细!B:B,B14)+SUMIFS('华瑞-曙光，大水井，老水井充电站'!L:L,'华瑞-曙光，大水井，老水井充电站'!B:B,B14)+SUMIFS('银盛-青龙坪充电站'!L:L,'银盛-青龙坪充电站'!B:B,B14)+SUMIFS('砚山锦佳-砚山充电站'!K:K,'砚山锦佳-砚山充电站'!B:B,B14)+SUMIFS(中石油广西百色靖西市龙临加油充电站!K:K,中石油广西百色靖西市龙临加油充电站!B:B,B14)+SUMIFS(德保众擎充电站!L:L,德保众擎充电站!B:B,B14)+SUMIFS(南网八宝充电站!K:K,南网八宝充电站!B:B,B14)+SUMIFS(南屏充电站!K:K,南屏充电站!B:B,B14)+SUMIFS(鑫鸿充电站!K:K,鑫鸿充电站!B:B,B14)+SUMIFS('锦田-百色田东充电站'!K:K,'锦田-百色田东充电站'!B:B,B14)+37.06/47+SUMIFS(平远充电站!K:K,平远充电站!B:B,B14) -> 20084.735 | K14: =J14/(H14) -> 0.3119372 | L14: =J14/F14 -> 803.3894 | N14: =13473.8/61 -> 220.88197 | O14: =SUMIFS(轮胎!H:H,轮胎!D:D,B14)+SUMIFS(轮胎!H:H,轮胎!D:D,C14) -> 950 | P14: 0 | Q14: =SUMIFS(维修费!E:E,维修费!C:C,B14)+SUMIFS(维修费!E:E,维修费!C:C,C14) -> 2396 | R14: =SUMIFS(磅单!R:R,磅单!F:F,B14) -> 15400 | S14: =SUMIFS(司机工资表!E:E,司机工资表!B:B,D14)+SUMIFS(司机工资表!N:N,司机工资表!B:B,D14) -> 200 | T14: =SUMIFS(付款明细!G:G,付款明细!D:D,B14,付款明细!B:B,"车队-罚款") -> 220 | U14: =SUMIFS(付款明细!G:G,付款明细!D:D,B14,付款明细!B:B,"车辆费用")+SUMIFS(付款明细!G:G,付款明细!D:D,C14,付款明细!B:B,"车辆费用") -> 606 | V14: =SUMIFS(付款明细!G:G,付款明细!B:B,"综合费用")/61 -> 397.39246 | W14: 2666 | Y14: =SUMIFS(磅单!P:P,磅单!E:E,B14) -> 375 | Z14: =H14*0.07-M14 -> 4507.0977 | AA14: 10600 | AB14: =3800 -> 3800 | AC14: =(管理人员工资!$D$10+管理人员工资!$E$10)/61 -> 790.16393 | AD14: =H14-I14-J14-N14-O14-R14-S14-T14-U14-V14-W14-AA14-AB14-AC14-Q14-P14-Z14-Y14-X14 -> 1173.839
A15: 13 | B15: 赣J09113D | C15: 桂LE938挂 | D15: 赵云江 | E15: 正常 | F15: =COUNTIFS(磅单!E:E,B15) -> 18 | G15: =SUMIFS(磅单!L:L,磅单!F:F,B15) -> 736.31 | H15: =SUMIFS(磅单!O:O,磅单!F:F,B15) -> 45586.49 | J15: =SUMIFS(现金充电明细!L:L,现金充电明细!B:B,B15)+SUMIFS('华瑞-曙光，大水井，老水井充电站'!L:L,'华瑞-曙光，大水井，老水井充电站'!B:B,B15)+SUMIFS('银盛-青龙坪充电站'!L:L,'银盛-青龙坪充电站'!B:B,B15)+SUMIFS('砚山锦佳-砚山充电站'!K:K,'砚山锦佳-砚山充电站'!B:B,B15)+SUMIFS(中石油广西百色靖西市龙临加油充电站!K:K,中石油广西百色靖西市龙临加油充电站!B:B,B15)+SUMIFS(德保众擎充电站!L:L,德保众擎充电站!B:B,B15)+SUMIFS(南网八宝充电站!K:K,南网八宝充电站!B:B,B15)+SUMIFS(南屏充电站!K:K,南屏充电站!B:B,B15)+SUMIFS(鑫鸿充电站!K:K,鑫鸿充电站!B:B,B15)+SUMIFS('锦田-百色田东充电站'!K:K,'锦田-百色田东充电站'!B:B,B15)+37.06/47+SUMIFS(平远充电站!K:K,平远充电站!B:B,B15) -> 14244.524 | K15: =J15/(H15) -> 0.31247248 | L15: =J15/F15 -> 791.36243 | N15: =13473.8/61 -> 220.88197 | O15: =SUMIFS(轮胎!H:H,轮胎!D:D,B15)+SUMIFS(轮胎!H:H,轮胎!D:D,C15) -> 0 | P15: 0 | Q15: =SUMIFS(维修费!E:E,维修费!C:C,B15)+SUMIFS(维修费!E:E,维修费!C:C,C15) -> 720 | R15: =SUMIFS(磅单!R:R,磅单!F:F,B15) -> 11000 | S15: =SUMIFS(司机工资表!E:E,司机工资表!B:B,D15)+SUMIFS(司机工资表!N:N,司机工资表!B:B,D15) -> 200 | T15: =SUMIFS(付款明细!G:G,付款明细!D:D,B15,付款明细!B:B,"车队-罚款") -> 20 | U15: =SUMIFS(付款明细!G:G,付款明细!D:D,B15,付款明细!B:B,"车辆费用")+SUMIFS(付款明细!G:G,付款明细!D:D,C15,付款明细!B:B,"车辆费用") -> 370.5 | V15: =SUMIFS(付款明细!G:G,付款明细!B:B,"综合费用")/61 -> 397.39246 | W15: 2666 | Y15: =SUMIFS(磅单!P:P,磅单!E:E,B15) -> 270 | Z15: =H15*0.07-M15 -> 3191.0543 | AA15: 10600 | AB15: =3800 -> 3800 | AC15: =(管理人员工资!$D$10+管理人员工资!$E$10)/61 -> 790.16393 | AD15: =H15-I15-J15-N15-O15-R15-S15-T15-U15-V15-W15-AA15-AB15-AC15-Q15-P15-Z15-Y15-X15 -> -2904.0264
A16: 14 | B16: 赣J05805D | C16: 桂L5676挂 | D16: 邱红志 | E16: 正常 | F16: =COUNTIFS(磅单!E:E,B16) -> 19 | G16: =SUMIFS(磅单!L:L,磅单!F:F,B16) -> 799.74 | H16: =SUMIFS(磅单!O:O,磅单!F:F,B16) -> 52459.52 | J16: =SUMIFS(现金充电明细!L:L,现金充电明细!B:B,B16)+SUMIFS('华瑞-曙光，大水井，老水井充电站'!L:L,'华瑞-曙光，大水井，老水井充电站'!B:B,B16)+SUMIFS('银盛-青龙坪充电站'!L:L,'银盛-青龙坪充电站'!B:B,B16)+SUMIFS('砚山锦佳-砚山充电站'!K:K,'砚山锦佳-砚山充电站'!B:B,B16)+SUMIFS(中石油广西百色靖西市龙临加油充电站!K:K,中石油广西百色靖西市龙临加油充电站!B:B,B16)+SUMIFS(德保众擎充电站!L:L,德保众擎充电站!B:B,B16)+SUMIFS(南网八宝充电站!K:K,南网八宝充电站!B:B,B16)+SUMIFS(南屏充电站!K:K,南屏充电站!B:B,B16)+SUMIFS(鑫鸿充电站!K:K,鑫鸿充电站!B:B,B16)+SUMIFS('锦田-百色田东充电站'!K:K,'锦田-百色田东充电站'!B:B,B16)+37.06/47+SUMIFS(平远充电站!K:K,平远充电站!B:B,B16) -> 14653.406 | K16: =J16/(H16) -> 0.27932787 | L16: =J16/F16 -> 771.2319 | N16: =13473.8/61 -> 220.88197 | O16: =SUMIFS(轮胎!H:H,轮胎!D:D,B16)+SUMIFS(轮胎!H:H,轮胎!D:D,C16) -> 6080 | P16: 0 | Q16: =SUMIFS(维修费!E:E,维修费!C:C,B16)+SUMIFS(维修费!E:E,维修费!C:C,C16) -> 1350 | R16: =SUMIFS(磅单!R:R,磅单!F:F,B16) -> 12200 | S16: =SUMIFS(司机工资表!E:E,司机工资表!B:B,D16)+SUMIFS(司机工资表!N:N,司机工资表!B:B,D16) -> 0 | T16: =SUMIFS(付款明细!G:G,付款明细!D:D,B16,付款明细!B:B,"车队-罚款") -> 20 | U16: =SUMIFS(付款明细!G:G,付款明细!D:D,B16,付款明细!B:B,"车辆费用")+SUMIFS(付款明细!G:G,付款明细!D:D,C16,付款明细!B:B,"车辆费用") -> 355 | V16: =SUMIFS(付款明细!G:G,付款明细!B:B,"综合费用")/61 -> 397.39246 | W16: 2666 | Y16: =SUMIFS(磅单!P:P,磅单!E:E,B16) -> 285 | Z16: =H16*0.07-M16 -> 3672.1664 | AA16: 10600 | AB16: =3800 -> 3800 | AC16: =(管理人员工资!$D$10+管理人员工资!$E$10)/61 -> 790.16393 | AD16: =H16-I16-J16-N16-O16-R16-S16-T16-U16-V16-W16-AA16-AB16-AC16-Q16-P16-Z16-Y16-X16 -> -4630.4909
A17: 15 | B17: 赣J05389D | C17: 桂LA778挂 | D17: 蒋永平 | E17: 正常 | F17: =COUNTIFS(磅单!E:E,B17) -> 19 | G17: =SUMIFS(磅单!L:L,磅单!F:F,B17) -> 776.1 | H17: =SUMIFS(磅单!O:O,磅单!F:F,B17) -> 48410.34 | J17: =SUMIFS(现金充电明细!L:L,现金充电明细!B:B,B17)+SUMIFS('华瑞-曙光，大水井，老水井充电站'!L:L,'华瑞-曙光，大水井，老水井充电站'!B:B,B17)+SUMIFS('银盛-青龙坪充电站'!L:L,'银盛-青龙坪充电站'!B:B,B17)+SUMIFS('砚山锦佳-砚山充电站'!K:K,'砚山锦佳-砚山充电站'!B:B,B17)+SUMIFS(中石油广西百色靖西市龙临加油充电站!K:K,中石油广西百色靖西市龙临加油充电站!B:B,B17)+SUMIFS(德保众擎充电站!L:L,德保众擎充电站!B:B,B17)+SUMIFS(南网八宝充电站!K:K,南网八宝充电站!B:B,B17)+SUMIFS(南屏充电站!K:K,南屏充电站!B:B,B17)+SUMIFS(鑫鸿充电站!K:K,鑫鸿充电站!B:B,B17)+SUMIFS('锦田-百色田东充电站'!K:K,'锦田-百色田东充电站'!B:B,B17)+37.06/47+SUMIFS(平远充电站!K:K,平远充电站!B:B,B17) -> 14095.548 | K17: =J17/(H17) -> 0.29116813 | L17: =J17/F17 -> 741.87095 | N17: =13473.8/61 -> 220.88197 | O17: =SUMIFS(轮胎!H:H,轮胎!D:D,B17)+SUMIFS(轮胎!H:H,轮胎!D:D,C17) -> 0 | P17: 0 | Q17: =SUMIFS(维修费!E:E,维修费!C:C,B17)+SUMIFS(维修费!E:E,维修费!C:C,C17) -> 1530 | R17: =SUMIFS(磅单!R:R,磅单!F:F,B17) -> 11800 | S17: =SUMIFS(司机工资表!E:E,司机工资表!B:B,D17)+SUMIFS(司机工资表!N:N,司机工资表!B:B,D17) -> 400 | T17: =SUMIFS(付款明细!G:G,付款明细!D:D,B17,付款明细!B:B,"车队-罚款") -> 720 | U17: =SUMIFS(付款明细!G:G,付款明细!D:D,B17,付款明细!B:B,"车辆费用")+SUMIFS(付款明细!G:G,付款明细!D:D,C17,付款明细!B:B,"车辆费用") -> 487 | V17: =SUMIFS(付款明细!G:G,付款明细!B:B,"综合费用")/61 -> 397.39246 | W17: 2666 | Y17: =SUMIFS(磅单!P:P,磅单!E:E,B17) -> 285 | Z17: =H17*0.07-M17 -> 3388.7238 | AA17: 10600 | AB17: =3800 -> 3800 | AC17: =(管理人员工资!$D$10+管理人员工资!$E$10)/61 -> 790.16393 | AD17: =H17-I17-J17-N17-O17-R17-S17-T17-U17-V17-W17-AA17-AB17-AC17-Q17-P17-Z17-Y17-X17 -> -2770.3703
A18: 16 | B18: 赣J02906D | C18: 桂LD096挂 | D18: 胡俊 | E18: 正常 | F18: =COUNTIFS(磅单!E:E,B18) -> 20 | G18: =SUMIFS(磅单!L:L,磅单!F:F,B18) -> 821.3 | H18: =SUMIFS(磅单!O:O,磅单!F:F,B18) -> 50943.24 | I18: 200 | J18: =SUMIFS(现金充电明细!L:L,现金充电明细!B:B,B18)+SUMIFS('华瑞-曙光，大水井，老水井充电站'!L:L,'华瑞-曙光，大水井，老水井充电站'!B:B,B18)+SUMIFS('银盛-青龙坪充电站'!L:L,'银盛-青龙坪充电站'!B:B,B18)+SUMIFS('砚山锦佳-砚山充电站'!K:K,'砚山锦佳-砚山充电站'!B:B,B18)+SUMIFS(中石油广西百色靖西市龙临加油充电站!K:K,中石油广西百色靖西市龙临加油充电站!B:B,B18)+SUMIFS(德保众擎充电站!L:L,德保众擎充电站!B:B,B18)+SUMIFS(南网八宝充电站!K:K,南网八宝充电站!B:B,B18)+SUMIFS(南屏充电站!K:K,南屏充电站!B:B,B18)+SUMIFS(鑫鸿充电站!K:K,鑫鸿充电站!B:B,B18)+SUMIFS('锦田-百色田东充电站'!K:K,'锦田-百色田东充电站'!B:B,B18)+37.06/47+SUMIFS(平远充电站!K:K,平远充电站!B:B,B18) -> 16407.35 | K18: =J18/(H18) -> 0.32207119 | L18: =J18/F18 -> 820.36749 | N18: =13473.8/61 -> 220.88197 | O18: =SUMIFS(轮胎!H:H,轮胎!D:D,B18)+SUMIFS(轮胎!H:H,轮胎!D:D,C18) -> 0 | P18: 0 | Q18: =SUMIFS(维修费!E:E,维修费!C:C,B18)+SUMIFS(维修费!E:E,维修费!C:C,C18) -> 680 | R18: =SUMIFS(磅单!R:R,磅单!F:F,B18) -> 12200 | S18: =SUMIFS(司机工资表!E:E,司机工资表!B:B,D18)+SUMIFS(司机工资表!N:N,司机工资表!B:B,D18) -> 0 | T18: =SUMIFS(付款明细!G:G,付款明细!D:D,B18,付款明细!B:B,"车队-罚款") -> 20 | U18: =SUMIFS(付款明细!G:G,付款明细!D:D,B18,付款明细!B:B,"车辆费用")+SUMIFS(付款明细!G:G,付款明细!D:D,C18,付款明细!B:B,"车辆费用") -> 574 | V18: =SUMIFS(付款明细!G:G,付款明细!B:B,"综合费用")/61 -> 397.39246 | W18: 2666 | Y18: =SUMIFS(磅单!P:P,磅单!E:E,B18) -> 300 | Z18: =H18*0.07-M18 -> 3566.0268 | AA18: 10600 | AB18: =3800 -> 3800 | AC18: =(管理人员工资!$D$10+管理人员工资!$E$10)/61 -> 790.16393 | AD18: =H18-I18-J18-N18-O18-R18-S18-T18-U18-V18-W18-AA18-AB18-AC18-Q18-P18-Z18-Y18-X18 -> -1478.5749
A19: 17 | B19: 赣J07957D | C19: 桂LB367挂 | D19: 徐天鹏 | E19: 正常 | F19: =COUNTIFS(磅单!E:E,B19) -> 20 | G19: =SUMIFS(磅单!L:L,磅单!F:F,B19) -> 814.94 | H19: =SUMIFS(磅单!O:O,磅单!F:F,B19) -> 50288.08 | J19: =SUMIFS(现金充电明细!L:L,现金充电明细!B:B,B19)+SUMIFS('华瑞-曙光，大水井，老水井充电站'!L:L,'华瑞-曙光，大水井，老水井充电站'!B:B,B19)+SUMIFS('银盛-青龙坪充电站'!L:L,'银盛-青龙坪充电站'!B:B,B19)+SUMIFS('砚山锦佳-砚山充电站'!K:K,'砚山锦佳-砚山充电站'!B:B,B19)+SUMIFS(中石油广西百色靖西市龙临加油充电站!K:K,中石油广西百色靖西市龙临加油充电站!B:B,B19)+SUMIFS(德保众擎充电站!L:L,德保众擎充电站!B:B,B19)+SUMIFS(南网八宝充电站!K:K,南网八宝充电站!B:B,B19)+SUMIFS(南屏充电站!K:K,南屏充电站!B:B,B19)+SUMIFS(鑫鸿充电站!K:K,鑫鸿充电站!B:B,B19)+SUMIFS('锦田-百色田东充电站'!K:K,'锦田-百色田东充电站'!B:B,B19)+37.06/47+SUMIFS(平远充电站!K:K,平远充电站!B:B,B19) -> 16655.431 | K19: =J19/(H19) -> 0.33120037 | L19: =J19/F19 -> 832.77154 | N19: =13473.8/61 -> 220.88197 | O19: =SUMIFS(轮胎!H:H,轮胎!D:D,B19)+SUMIFS(轮胎!H:H,轮胎!D:D,C19) -> 1300 | P19: 0 | Q19: =SUMIFS(维修费!E:E,维修费!C:C,B19)+SUMIFS(维修费!E:E,维修费!C:C,C19) -> 550 | R19: =SUMIFS(磅单!R:R,磅单!F:F,B19) -> 12400 | S19: =SUMIFS(司机工资表!E:E,司机工资表!B:B,D19)+SUMIFS(司机工资表!N:N,司机工资表!B:B,D19) -> 0 | T19: =SUMIFS(付款明细!G:G,付款明细!D:D,B19,付款明细!B:B,"车队-罚款") -> 260 | U19: =SUMIFS(付款明细!G:G,付款明细!D:D,B19,付款明细!B:B,"车辆费用")+SUMIFS(付款明细!G:G,付款明细!D:D,C19,付款明细!B:B,"车辆费用") -> 636 | V19: =SUMIFS(付款明细!G:G,付款明细!B:B,"综合费用")/61 -> 397.39246 | W19: 2666 | Y19: =SUMIFS(磅单!P:P,磅单!E:E,B19) -> 300 | Z19: =H19*0.07-M19 -> 3520.1656 | AA19: 10600 | AB19: =3800 -> 3800 | AC19: =(管理人员工资!$D$10+管理人员工资!$E$10)/61 -> 790.16393 | AD19: =H19-I19-J19-N19-O19-R19-S19-T19-U19-V19-W19-AA19-AB19-AC19-Q19-P19-Z19-Y19-X19 -> -3807.9548
A20: 18 | B20: 赣J06039D | C20: 桂LE795挂 | D20: 朱勋玉 | E20: 正常 | F20: =COUNTIFS(磅单!E:E,B20) -> 19 | G20: =SUMIFS(磅单!L:L,磅单!F:F,B20) -> 779.92 | H20: =SUMIFS(磅单!O:O,磅单!F:F,B20) -> 47588.88 | J20: =SUMIFS(现金充电明细!L:L,现金充电明细!B:B,B20)+SUMIFS('华瑞-曙光，大水井，老水井充电站'!L:L,'华瑞-曙光，大水井，老水井充电站'!B:B,B20)+SUMIFS('银盛-青龙坪充电站'!L:L,'银盛-青龙坪充电站'!B:B,B20)+SUMIFS('砚山锦佳-砚山充电站'!K:K,'砚山锦佳-砚山充电站'!B:B,B20)+SUMIFS(中石油广西百色靖西市龙临加油充电站!K:K,中石油广西百色靖西市龙临加油充电站!B:B,B20)+SUMIFS(德保众擎充电站!L:L,德保众擎充电站!B:B,B20)+SUMIFS(南网八宝充电站!K:K,南网八宝充电站!B:B,B20)+SUMIFS(南屏充电站!K:K,南屏充电站!B:B,B20)+SUMIFS(鑫鸿充电站!K:K,鑫鸿充电站!B:B,B20)+SUMIFS('锦田-百色田东充电站'!K:K,'锦田-百色田东充电站'!B:B,B20)+37.06/47+SUMIFS(平远充电站!K:K,平远充电站!B:B,B20) -> 16710.588 | K20: =J20/(H20) -> 0.35114481 | L20: =J20/F20 -> 879.50465 | N20: =13473.8/61 -> 220.88197 | O20: =SUMIFS(轮胎!H:H,轮胎!D:D,B20)+SUMIFS(轮胎!H:H,轮胎!D:D,C20) -> 0 | P20: 0 | Q20: =SUMIFS(维修费!E:E,维修费!C:C,B20)+SUMIFS(维修费!E:E,维修费!C:C,C20) -> 120 | R20: =SUMIFS(磅单!R:R,磅单!F:F,B20) -> 11600 | S20: =SUMIFS(司机工资表!E:E,司机工资表!B:B,D20)+SUMIFS(司机工资表!N:N,司机工资表!B:B,D20) -> 1200 | T20: =SUMIFS(付款明细!G:G,付款明细!D:D,B20,付款明细!B:B,"车队-罚款") -> 220 | U20: =SUMIFS(付款明细!G:G,付款明细!D:D,B20,付款明细!B:B,"车辆费用")+SUMIFS(付款明细!G:G,付款明细!D:D,C20,付款明细!B:B,"车辆费用") -> 555 | V20: =SUMIFS(付款明细!G:G,付款明细!B:B,"综合费用")/61 -> 397.39246 | W20: 2666 | Y20: =SUMIFS(磅单!P:P,磅单!E:E,B20) -> 285 | Z20: =H20*0.07-M20 -> 3331.2216 | AA20: 10600 | AB20: =3800 -> 3800 | AC20: =(管理人员工资!$D$10+管理人员工资!$E$10)/61 -> 790.16393 | AD20: =H20-I20-J20-N20-O20-R20-S20-T20-U20-V20-W20-AA20-AB20-AC20-Q20-P20-Z20-Y20-X20 -> -4907.3683
A21: 19 | B21: 赣J05617D | C21: 桂LE999挂 | D21: 徐进林 | E21: 正常 | F21: =COUNTIFS(磅单!E:E,B21) -> 18 | G21: =SUMIFS(磅单!L:L,磅单!F:F,B21) -> 745.35 | H21: =SUMIFS(磅单!O:O,磅单!F:F,B21) -> 45725.11 | J21: =SUMIFS(现金充电明细!L:L,现金充电明细!B:B,B21)+SUMIFS('华瑞-曙光，大水井，老水井充电站'!L:L,'华瑞-曙光，大水井，老水井充电站'!B:B,B21)+SUMIFS('银盛-青龙坪充电站'!L:L,'银盛-青龙坪充电站'!B:B,B21)+SUMIFS('砚山锦佳-砚山充电站'!K:K,'砚山锦佳-砚山充电站'!B:B,B21)+SUMIFS(中石油广西百色靖西市龙临加油充电站!K:K,中石油广西百色靖西市龙临加油充电站!B:B,B21)+SUMIFS(德保众擎充电站!L:L,德保众擎充电站!B:B,B21)+SUMIFS(南网八宝充电站!K:K,南网八宝充电站!B:B,B21)+SUMIFS(南屏充电站!K:K,南屏充电站!B:B,B21)+SUMIFS(鑫鸿充电站!K:K,鑫鸿充电站!B:B,B21)+SUMIFS('锦田-百色田东充电站'!K:K,'锦田-百色田东充电站'!B:B,B21)+37.06/47+SUMIFS(平远充电站!K:K,平远充电站!B:B,B21) -> 15247.842 | K21: =J21/(H21) -> 0.33346759 | L21: =J21/F21 -> 847.10235 | N21: =13473.8/61 -> 220.88197 | O21: =SUMIFS(轮胎!H:H,轮胎!D:D,B21)+SUMIFS(轮胎!H:H,轮胎!D:D,C21) -> 1000 | P21: 0 | Q21: =SUMIFS(维修费!E:E,维修费!C:C,B21)+SUMIFS(维修费!E:E,维修费!C:C,C21) -> 954 | R21: =SUMIFS(磅单!R:R,磅单!F:F,B21) -> 11200 | S21: =SUMIFS(司机工资表!E:E,司机工资表!B:B,D21)+SUMIFS(司机工资表!N:N,司机工资表!B:B,D21)+200 -> 200 | T21: =SUMIFS(付款明细!G:G,付款明细!D:D,B21,付款明细!B:B,"车队-罚款") -> 300 | U21: =SUMIFS(付款明细!G:G,付款明细!D:D,B21,付款明细!B:B,"车辆费用")+SUMIFS(付款明细!G:G,付款明细!D:D,C21,付款明细!B:B,"车辆费用") -> 390 | V21: =SUMIFS(付款明细!G:G,付款明细!B:B,"综合费用")/61 -> 397.39246 | W21: 2666 | Y21: =SUMIFS(磅单!P:P,磅单!E:E,B21) -> 270 | Z21: =H21*0.07-M21 -> 3200.7577 | AA21: 10600 | AB21: =3800 -> 3800 | AC21: =(管理人员工资!$D$10+管理人员工资!$E$10)/61 -> 790.16393 | AD21: =H21-I21-J21-N21-O21-R21-S21-T21-U21-V21-W21-AA21-AB21-AC21-Q21-P21-Z21-Y21-X21 -> -5511.9283
A22: 20 | B22: 赣J05067D | C22: 桂L0439挂 | D22: 杨咏富 | E22: 正常 | F22: =COUNTIFS(磅单!E:E,B22) -> 19 | G22: =SUMIFS(磅单!L:L,磅单!F:F,B22) -> 786.97 | H22: =SUMIFS(磅单!O:O,磅单!F:F,B22) -> 50797.99 | J22: =SUMIFS(现金充电明细!L:L,现金充电明细!B:B,B22)+SUMIFS('华瑞-曙光，大水井，老水井充电站'!L:L,'华瑞-曙光，大水井，老水井充电站'!B:B,B22)+SUMIFS('银盛-青龙坪充电站'!L:L,'银盛-青龙坪充电站'!B:B,B22)+SUMIFS('砚山锦佳-砚山充电站'!K:K,'砚山锦佳-砚山充电站'!B:B,B22)+SUMIFS(中石油广西百色靖西市龙临加油充电站!K:K,中石油广西百色靖西市龙临加油充电站!B:B,B22)+SUMIFS(德保众擎充电站!L:L,德保众擎充电站!B:B,B22)+SUMIFS(南网八宝充电站!K:K,南网八宝充电站!B:B,B22)+SUMIFS(南屏充电站!K:K,南屏充电站!B:B,B22)+SUMIFS(鑫鸿充电站!K:K,鑫鸿充电站!B:B,B22)+SUMIFS('锦田-百色田东充电站'!K:K,'锦田-百色田东充电站'!B:B,B22)+37.06/47+SUMIFS(平远充电站!K:K,平远充电站!B:B,B22) -> 13928.066 | K22: =J22/(H22) -> 0.27418537 | L22: =J22/F22 -> 733.05608 | N22: =13473.8/61 -> 220.88197 | O22: =SUMIFS(轮胎!H:H,轮胎!D:D,B22)+SUMIFS(轮胎!H:H,轮胎!D:D,C22) -> 0 | P22: 0 | Q22: =SUMIFS(维修费!E:E,维修费!C:C,B22)+SUMIFS(维修费!E:E,维修费!C:C,C22) -> 0 | R22: =SUMIFS(磅单!R:R,磅单!F:F,B22) -> 11800 | S22: =SUMIFS(司机工资表!E:E,司机工资表!B:B,D22)+SUMIFS(司机工资表!N:N,司机工资表!B:B,D22) -> 0 | T22: =SUMIFS(付款明细!G:G,付款明细!D:D,B22,付款明细!B:B,"车队-罚款") -> 100 | U22: =SUMIFS(付款明细!G:G,付款明细!D:D,B22,付款明细!B:B,"车辆费用")+SUMIFS(付款明细!G:G,付款明细!D:D,C22,付款明细!B:B,"车辆费用") -> 426.6 | V22: =SUMIFS(付款明细!G:G,付款明细!B:B,"综合费用")/61 -> 397.39246 | W22: 2666 | Y22: =SUMIFS(磅单!P:P,磅单!E:E,B22) -> 285 | Z22: =H22*0.07-M22 -> 3555.8593 | AA22: 10600 | AB22: =3800 -> 3800 | AC22: =(管理人员工资!$D$10+管理人员工资!$E$10)/61 -> 790.16393 | AD22: =H22-I22-J22-N22-O22-R22-S22-T22-U22-V22-W22-AA22-AB22-AC22-Q22-P22-Z22-Y22-X22 -> 2228.0268
A23: 21 | B23: 沪A04114D | C23: 桂LB957挂 | D23: 李玉红 | E23: 正常 | F23: =COUNTIFS(磅单!E:E,B23) -> 17 | G23: =SUMIFS(磅单!L:L,磅单!F:F,B23) -> 722.21 | H23: =SUMIFS(磅单!O:O,磅单!F:F,B23) -> 47707.93 | J23: =SUMIFS(现金充电明细!L:L,现金充电明细!B:B,B23)+SUMIFS('华瑞-曙光，大水井，老水井充电站'!L:L,'华瑞-曙光，大水井，老水井充电站'!B:B,B23)+SUMIFS('银盛-青龙坪充电站'!L:L,'银盛-青龙坪充电站'!B:B,B23)+SUMIFS('砚山锦佳-砚山充电站'!K:K,'砚山锦佳-砚山充电站'!B:B,B23)+SUMIFS(中石油广西百色靖西市龙临加油充电站!K:K,中石油广西百色靖西市龙临加油充电站!B:B,B23)+SUMIFS(德保众擎充电站!L:L,德保众擎充电站!B:B,B23)+SUMIFS(南网八宝充电站!K:K,南网八宝充电站!B:B,B23)+SUMIFS(南屏充电站!K:K,南屏充电站!B:B,B23)+SUMIFS(鑫鸿充电站!K:K,鑫鸿充电站!B:B,B23)+SUMIFS('锦田-百色田东充电站'!K:K,'锦田-百色田东充电站'!B:B,B23)+37.06/47+SUMIFS(平远充电站!K:K,平远充电站!B:B,B23) -> 13353.994 | K23: =J23/(H23) -> 0.27991141 | L23: =J23/F23 -> 785.52906 | N23: =13473.8/61 -> 220.88197 | O23: =SUMIFS(轮胎!H:H,轮胎!D:D,B23)+SUMIFS(轮胎!H:H,轮胎!D:D,C23) -> 1000 | P23: 0 | Q23: =SUMIFS(维修费!E:E,维修费!C:C,B23)+SUMIFS(维修费!E:E,维修费!C:C,C23) -> 400 | R23: =SUMIFS(磅单!R:R,磅单!F:F,B23) -> 11000 | S23: =SUMIFS(司机工资表!E:E,司机工资表!B:B,D23)+SUMIFS(司机工资表!N:N,司机工资表!B:B,D23) -> 200 | T23: =SUMIFS(付款明细!G:G,付款明细!D:D,B23,付款明细!B:B,"车队-罚款") -> 440 | U23: =SUMIFS(付款明细!G:G,付款明细!D:D,B23,付款明细!B:B,"车辆费用")+SUMIFS(付款明细!G:G,付款明细!D:D,C23,付款明细!B:B,"车辆费用") -> 554 | V23: =SUMIFS(付款明细!G:G,付款明细!B:B,"综合费用")/61 -> 397.39246 | W23: 2666 | Y23: =SUMIFS(磅单!P:P,磅单!E:E,B23) -> 255 | Z23: =H23*0.07-M23 -> 3339.5551 | AA23: 10600 | AB23: =3800 -> 3800 | AC23: =(管理人员工资!$D$10+管理人员工资!$E$10)/61 -> 790.16393 | AD23: =H23-I23-J23-N23-O23-R23-S23-T23-U23-V23-W23-AA23-AB23-AC23-Q23-P23-Z23-Y23-X23 -> -1309.0575
A24: 22 | B24: 赣J08767D | C24: 桂LA357挂 | D24: 何仕财 | E24: 正常 | F24: =COUNTIFS(磅单!E:E,B24) -> 23 | G24: =SUMIFS(磅单!L:L,磅单!F:F,B24) -> 949.84 | H24: =SUMIFS(磅单!O:O,磅单!F:F,B24) -> 59389.6 | J24: =SUMIFS(现金充电明细!L:L,现金充电明细!B:B,B24)+SUMIFS('华瑞-曙光，大水井，老水井充电站'!L:L,'华瑞-曙光，大水井，老水井充电站'!B:B,B24)+SUMIFS('银盛-青龙坪充电站'!L:L,'银盛-青龙坪充电站'!B:B,B24)+SUMIFS('砚山锦佳-砚山充电站'!K:K,'砚山锦佳-砚山充电站'!B:B,B24)+SUMIFS(中石油广西百色靖西市龙临加油充电站!K:K,中石油广西百色靖西市龙临加油充电站!B:B,B24)+SUMIFS(德保众擎充电站!L:L,德保众擎充电站!B:B,B24)+SUMIFS(南网八宝充电站!K:K,南网八宝充电站!B:B,B24)+SUMIFS(南屏充电站!K:K,南屏充电站!B:B,B24)+SUMIFS(鑫鸿充电站!K:K,鑫鸿充电站!B:B,B24)+SUMIFS('锦田-百色田东充电站'!K:K,'锦田-百色田东充电站'!B:B,B24)+37.06/47+SUMIFS(平远充电站!K:K,平远充电站!B:B,B24) -> 19713.958 | K24: =J24/(H24) -> 0.33194294 | L24: =J24/F24 -> 857.12862 | N24: =13473.8/61 -> 220.88197 | O24: =SUMIFS(轮胎!H:H,轮胎!D:D,B24)+SUMIFS(轮胎!H:H,轮胎!D:D,C24) -> 0 | P24: 0 | Q24: =SUMIFS(维修费!E:E,维修费!C:C,B24)+SUMIFS(维修费!E:E,维修费!C:C,C24) -> 455 | R24: =SUMIFS(磅单!R:R,磅单!F:F,B24) -> 14200 | S24: =SUMIFS(司机工资表!E:E,司机工资表!B:B,D24)+SUMIFS(司机工资表!N:N,司机工资表!B:B,D24) -> 200 | T24: =SUMIFS(付款明细!G:G,付款明细!D:D,B24,付款明细!B:B,"车队-罚款") -> 260 | U24: =SUMIFS(付款明细!G:G,付款明细!D:D,B24,付款明细!B:B,"车辆费用")+SUMIFS(付款明细!G:G,付款明细!D:D,C24,付款明细!B:B,"车辆费用") -> 568.6 | V24: =SUMIFS(付款明细!G:G,付款明细!B:B,"综合费用")/61 -> 397.39246 | W24: 2666 | Y24: =SUMIFS(磅单!P:P,磅单!E:E,B24) -> 345 | Z24: =H24*0.07-M24 -> 4157.272 | AA24: 10600 | AB24: =3800 -> 3800 | AC24: =(管理人员工资!$D$10+管理人员工资!$E$10)/61 -> 790.16393 | AD24: =H24-I24-J24-N24-O24-R24-S24-T24-U24-V24-W24-AA24-AB24-AC24-Q24-P24-Z24-Y24-X24 -> 1015.3314
A25: 23 | B25: 赣J03528D | C25: 桂LE308挂 | D25: 罗晶 | E25: 正常 | F25: =COUNTIFS(磅单!E:E,B25) -> 21 | G25: =SUMIFS(磅单!L:L,磅单!F:F,B25) -> 888.56 | H25: =SUMIFS(磅单!O:O,磅单!F:F,B25) -> 57045.58 | J25: =SUMIFS(现金充电明细!L:L,现金充电明细!B:B,B25)+SUMIFS('华瑞-曙光，大水井，老水井充电站'!L:L,'华瑞-曙光，大水井，老水井充电站'!B:B,B25)+SUMIFS('银盛-青龙坪充电站'!L:L,'银盛-青龙坪充电站'!B:B,B25)+SUMIFS('砚山锦佳-砚山充电站'!K:K,'砚山锦佳-砚山充电站'!B:B,B25)+SUMIFS(中石油广西百色靖西市龙临加油充电站!K:K,中石油广西百色靖西市龙临加油充电站!B:B,B25)+SUMIFS(德保众擎充电站!L:L,德保众擎充电站!B:B,B25)+SUMIFS(南网八宝充电站!K:K,南网八宝充电站!B:B,B25)+SUMIFS(南屏充电站!K:K,南屏充电站!B:B,B25)+SUMIFS(鑫鸿充电站!K:K,鑫鸿充电站!B:B,B25)+SUMIFS('锦田-百色田东充电站'!K:K,'锦田-百色田东充电站'!B:B,B25)+37.06/47+SUMIFS(平远充电站!K:K,平远充电站!B:B,B25) -> 15543.134 | K25: =J25/(H25) -> 0.27246869 | L25: =J25/F25 -> 740.14925 | N25: =13473.8/61 -> 220.88197 | O25: =SUMIFS(轮胎!H:H,轮胎!D:D,B25)+SUMIFS(轮胎!H:H,轮胎!D:D,C25) -> 0 | P25: 0 | Q25: =SUMIFS(维修费!E:E,维修费!C:C,B25)+SUMIFS(维修费!E:E,维修费!C:C,C25) -> 570 | R25: =SUMIFS(磅单!R:R,磅单!F:F,B25) -> 13200 | S25: =SUMIFS(司机工资表!E:E,司机工资表!B:B,D25)+SUMIFS(司机工资表!N:N,司机工资表!B:B,D25) -> 0 | T25: =SUMIFS(付款明细!G:G,付款明细!D:D,B25,付款明细!B:B,"车队-罚款") -> 200 | U25: =SUMIFS(付款明细!G:G,付款明细!D:D,B25,付款明细!B:B,"车辆费用")+SUMIFS(付款明细!G:G,付款明细!D:D,C25,付款明细!B:B,"车辆费用") -> 608 | V25: =SUMIFS(付款明细!G:G,付款明细!B:B,"综合费用")/61 -> 397.39246 | W25: 2666 | Y25: =SUMIFS(磅单!P:P,磅单!E:E,B25) -> 315 | Z25: =H25*0.07-M25 -> 3993.1906 | AA25: 10600 | AB25: =3800 -> 3800 | AC25: =(管理人员工资!$D$10+管理人员工资!$E$10)/61 -> 790.16393 | AD25: =H25-I25-J25-N25-O25-R25-S25-T25-U25-V25-W25-AA25-AB25-AC25-Q25-P25-Z25-Y25-X25 -> 4141.8168
A26: 24 | B26: 赣J03373D | C26: 桂LC575挂 | D26: 陆金城 | E26: 正常 | F26: =COUNTIFS(磅单!E:E,B26) -> 4 | G26: =SUMIFS(磅单!L:L,磅单!F:F,B26) -> 167.72 | H26: =SUMIFS(磅单!O:O,磅单!F:F,B26) -> 11193.96 | I26: 50 | J26: =SUMIFS(现金充电明细!L:L,现金充电明细!B:B,B26)+SUMIFS('华瑞-曙光，大水井，老水井充电站'!L:L,'华瑞-曙光，大水井，老水井充电站'!B:B,B26)+SUMIFS('银盛-青龙坪充电站'!L:L,'银盛-青龙坪充电站'!B:B,B26)+SUMIFS('砚山锦佳-砚山充电站'!K:K,'砚山锦佳-砚山充电站'!B:B,B26)+SUMIFS(中石油广西百色靖西市龙临加油充电站!K:K,中石油广西百色靖西市龙临加油充电站!B:B,B26)+SUMIFS(德保众擎充电站!L:L,德保众擎充电站!B:B,B26)+SUMIFS(南网八宝充电站!K:K,南网八宝充电站!B:B,B26)+SUMIFS(南屏充电站!K:K,南屏充电站!B:B,B26)+SUMIFS(鑫鸿充电站!K:K,鑫鸿充电站!B:B,B26)+SUMIFS('锦田-百色田东充电站'!K:K,'锦田-百色田东充电站'!B:B,B26)+37.06/47+SUMIFS(平远充电站!K:K,平远充电站!B:B,B26) -> 5252.5871 | K26: =J26/(H26) -> 0.46923404 | L26: =J26/F26 -> 1313.1468 | N26: =13473.8/61 -> 220.88197 | O26: =SUMIFS(轮胎!H:H,轮胎!D:D,B26)+SUMIFS(轮胎!H:H,轮胎!D:D,C26) -> 0 | P26: 0 | Q26: =SUMIFS(维修费!E:E,维修费!C:C,B26)+SUMIFS(维修费!E:E,维修费!C:C,C26) -> 295 | R26: =SUMIFS(磅单!R:R,磅单!F:F,B26) -> 2800 | S26: =SUMIFS(司机工资表!E:E,司机工资表!B:B,D26)+SUMIFS(司机工资表!N:N,司机工资表!B:B,D26) -> 200 | T26: =SUMIFS(付款明细!G:G,付款明细!D:D,B26,付款明细!B:B,"车队-罚款") -> 200 | U26: =SUMIFS(付款明细!G:G,付款明细!D:D,B26,付款明细!B:B,"车辆费用")+SUMIFS(付款明细!G:G,付款明细!D:D,C26,付款明细!B:B,"车辆费用") -> 160 | V26: =SUMIFS(付款明细!G:G,付款明细!B:B,"综合费用")/61 -> 397.39246 | W26: 2666 | Y26: =SUMIFS(磅单!P:P,磅单!E:E,B26) -> 60 | Z26: =H26*0.07-M26 -> 783.5772 | AA26: 10600 | AB26: =3800 -> 3800 | AC26: =(管理人员工资!$D$10+管理人员工资!$E$10)/61 -> 790.16393 | AD26: =H26-I26-J26-N26-O26-R26-S26-T26-U26-V26-W26-AA26-AB26-AC26-Q26-P26-Z26-Y26-X26 -> -17081.643
A27: 25 | B27: 赣J02525D | C27: 桂LB297挂 | E27: 事故侧翻维修中 | F27: =COUNTIFS(磅单!E:E,B27) -> 2 | G27: =SUMIFS(磅单!L:L,磅单!F:F,B27) -> 85.91 | H27: =SUMIFS(磅单!O:O,磅单!F:F,B27) -> 5499.59 | J27: =SUMIFS(现金充电明细!L:L,现金充电明细!B:B,B27)+SUMIFS('华瑞-曙光，大水井，老水井充电站'!L:L,'华瑞-曙光，大水井，老水井充电站'!B:B,B27)+SUMIFS('银盛-青龙坪充电站'!L:L,'银盛-青龙坪充电站'!B:B,B27)+SUMIFS('砚山锦佳-砚山充电站'!K:K,'砚山锦佳-砚山充电站'!B:B,B27)+SUMIFS(中石油广西百色靖西市龙临加油充电站!K:K,中石油广西百色靖西市龙临加油充电站!B:B,B27)+SUMIFS(德保众擎充电站!L:L,德保众擎充电站!B:B,B27)+SUMIFS(南网八宝充电站!K:K,南网八宝充电站!B:B,B27)+SUMIFS(南屏充电站!K:K,南屏充电站!B:B,B27)+SUMIFS(鑫鸿充电站!K:K,鑫鸿充电站!B:B,B27)+SUMIFS('锦田-百色田东充电站'!K:K,'锦田-百色田东充电站'!B:B,B27)+37.06/47+SUMIFS(平远充电站!K:K,平远充电站!B:B,B27) -> 2495.5028 | K27: =J27/(H27) -> 0.45376161 | L27: =J27/F27 -> 1247.7514 | N27: =13473.8/61 -> 220.88197 | O27: =SUMIFS(轮胎!H:H,轮胎!D:D,B27)+SUMIFS(轮胎!H:H,轮胎!D:D,C27) -> 0 | P27: 0 | Q27: =SUMIFS(维修费!E:E,维修费!C:C,B27)+SUMIFS(维修费!E:E,维修费!C:C,C27) -> 300 | R27: =SUMIFS(磅单!R:R,磅单!F:F,B27) -> 1200 | S27: =SUMIFS(司机工资表!E:E,司机工资表!B:B,D27)+SUMIFS(司机工资表!N:N,司机工资表!B:B,D27) -> 0 | T27: =SUMIFS(付款明细!G:G,付款明细!D:D,B27,付款明细!B:B,"车队-罚款") -> 200 | U27: =SUMIFS(付款明细!G:G,付款明细!D:D,B27,付款明细!B:B,"车辆费用")+SUMIFS(付款明细!G:G,付款明细!D:D,C27,付款明细!B:B,"车辆费用") -> 417 | V27: =SUMIFS(付款明细!G:G,付款明细!B:B,"综合费用")/61 -> 397.39246 | W27: 2666 | Y27: =SUMIFS(磅单!P:P,磅单!E:E,B27) -> 30 | Z27: =H27*0.07-M27 -> 384.9713 | AA27: 10600 | AB27: =3800 -> 3800 | AC27: =(管理人员工资!$D$10+管理人员工资!$E$10)/61 -> 790.16393 | AD27: =H27-I27-J27-N27-O27-R27-S27-T27-U27-V27-W27-AA27-AB27-AC27-Q27-P27-Z27-Y27-X27 -> -18002.322
A28: 26 | B28: 赣J05379D | C28: 桂LC316挂 | D28: 昝建伟 | E28: 正常 | F28: =COUNTIFS(磅单!E:E,B28) -> 17 | G28: =SUMIFS(磅单!L:L,磅单!F:F,B28) -> 685.49 | H28: =SUMIFS(磅单!O:O,磅单!F:F,B28) -> 44813.27 | I28: 50 | J28: =SUMIFS(现金充电明细!L:L,现金充电明细!B:B,B28)+SUMIFS('华瑞-曙光，大水井，老水井充电站'!L:L,'华瑞-曙光，大水井，老水井充电站'!B:B,B28)+SUMIFS('银盛-青龙坪充电站'!L:L,'银盛-青龙坪充电站'!B:B,B28)+SUMIFS('砚山锦佳-砚山充电站'!K:K,'砚山锦佳-砚山充电站'!B:B,B28)+SUMIFS(中石油广西百色靖西市龙临加油充电站!K:K,中石油广西百色靖西市龙临加油充电站!B:B,B28)+SUMIFS(德保众擎充电站!L:L,德保众擎充电站!B:B,B28)+SUMIFS(南网八宝充电站!K:K,南网八宝充电站!B:B,B28)+SUMIFS(南屏充电站!K:K,南屏充电站!B:B,B28)+SUMIFS(鑫鸿充电站!K:K,鑫鸿充电站!B:B,B28)+SUMIFS('锦田-百色田东充电站'!K:K,'锦田-百色田东充电站'!B:B,B28)+37.06/47+SUMIFS(平远充电站!K:K,平远充电站!B:B,B28) -> 14525.358 | K28: =J28/(H28) -> 0.32413073 | L28: =J28/F28 -> 854.43282 | N28: =13473.8/61 -> 220.88197 | O28: =SUMIFS(轮胎!H:H,轮胎!D:D,B28)+SUMIFS(轮胎!H:H,轮胎!D:D,C28) -> 6080 | P28: 0 | Q28: =SUMIFS(维修费!E:E,维修费!C:C,B28)+SUMIFS(维修费!E:E,维修费!C:C,C28) -> 270 | R28: =SUMIFS(磅单!R:R,磅单!F:F,B28) -> 10600 | S28: =SUMIFS(司机工资表!E:E,司机工资表!B:B,D28)+SUMIFS(司机工资表!N:N,司机工资表!B:B,D28) -> 400 | T28: =SUMIFS(付款明细!G:G,付款明细!D:D,B28,付款明细!B:B,"车队-罚款") -> 200 | U28: =SUMIFS(付款明细!G:G,付款明细!D:D,B28,付款明细!B:B,"车辆费用")+SUMIFS(付款明细!G:G,付款明细!D:D,C28,付款明细!B:B,"车辆费用") -> 456 | V28: =SUMIFS(付款明细!G:G,付款明细!B:B,"综合费用")/61 -> 397.39246 | W28: 2666 | Y28: =SUMIFS(磅单!P:P,磅单!E:E,B28) -> 255 | Z28: =H28*0.07-M28 -> 3136.9289 | AA28: 10600 | AB28: =3800 -> 3800 | AC28: =(管理人员工资!$D$10+管理人员工资!$E$10)/61 -> 790.16393 | AD28: =H28-I28-J28-N28-O28-R28-S28-T28-U28-V28-W28-AA28-AB28-AC28-Q28-P28-Z28-Y28-X28 -> -9634.4553
A29: 27 | B29: 赣J03535D | C29: 桂LB917挂 | D29: 刘炳宏 | E29: 正常 | F29: =COUNTIFS(磅单!E:E,B29) -> 16 | G29: =SUMIFS(磅单!L:L,磅单!F:F,B29) -> 649.14 | H29: =SUMIFS(磅单!O:O,磅单!F:F,B29) -> 41386.44 | J29: =SUMIFS(现金充电明细!L:L,现金充电明细!B:B,B29)+SUMIFS('华瑞-曙光，大水井，老水井充电站'!L:L,'华瑞-曙光，大水井，老水井充电站'!B:B,B29)+SUMIFS('银盛-青龙坪充电站'!L:L,'银盛-青龙坪充电站'!B:B,B29)+SUMIFS('砚山锦佳-砚山充电站'!K:K,'砚山锦佳-砚山充电站'!B:B,B29)+SUMIFS(中石油广西百色靖西市龙临加油充电站!K:K,中石油广西百色靖西市龙临加油充电站!B:B,B29)+SUMIFS(德保众擎充电站!L:L,德保众擎充电站!B:B,B29)+SUMIFS(南网八宝充电站!K:K,南网八宝充电站!B:B,B29)+SUMIFS(南屏充电站!K:K,南屏充电站!B:B,B29)+SUMIFS(鑫鸿充电站!K:K,鑫鸿充电站!B:B,B29)+SUMIFS('锦田-百色田东充电站'!K:K,'锦田-百色田东充电站'!B:B,B29)+37.06/47+SUMIFS(平远充电站!K:K,平远充电站!B:B,B29) -> 12909.952 | K29: =J29/(H29) -> 0.31193676 | L29: =J29/F29 -> 806.872 | N29: =13473.8/61 -> 220.88197 | O29: =SUMIFS(轮胎!H:H,轮胎!D:D,B29)+SUMIFS(轮胎!H:H,轮胎!D:D,C29) -> 8830 | P29: 0 | Q29: =SUMIFS(维修费!E:E,维修费!C:C,B29)+SUMIFS(维修费!E:E,维修费!C:C,C29) -> 1405 | R29: =SUMIFS(磅单!R:R,磅单!F:F,B29) -> 10000 | S29: =SUMIFS(司机工资表!E:E,司机工资表!B:B,D29)+SUMIFS(司机工资表!N:N,司机工资表!B:B,D29) -> 0 | T29: =SUMIFS(付款明细!G:G,付款明细!D:D,B29,付款明细!B:B,"车队-罚款") -> 220 | U29: =SUMIFS(付款明细!G:G,付款明细!D:D,B29,付款明细!B:B,"车辆费用")+SUMIFS(付款明细!G:G,付款明细!D:D,C29,付款明细!B:B,"车辆费用") -> 386 | V29: =SUMIFS(付款明细!G:G,付款明细!B:B,"综合费用")/61 -> 397.39246 | W29: 2666 | Y29: =SUMIFS(磅单!P:P,磅单!E:E,B29) -> 240 | Z29: =H29*0.07-M29 -> 2897.0508 | AA29: 10600 | AB29: =3800 -> 3800 | AC29: =(管理人员工资!$D$10+管理人员工资!$E$10)/61 -> 790.16393 | AD29: =H29-I29-J29-N29-O29-R29-S29-T29-U29-V29-W29-AA29-AB29-AC29-Q29-P29-Z29-Y29-X29 -> -13976.001
A30: 28 | B30: 赣J09206D | C30: 桂L9026挂 | D30: 杨仁华 | E30: 正常 | F30: =COUNTIFS(磅单!E:E,B30) -> 15 | G30: =SUMIFS(磅单!L:L,磅单!F:F,B30) -> 621.41 | H30: =SUMIFS(磅单!O:O,磅单!F:F,B30) -> 37840.85 | J30: =SUMIFS(现金充电明细!L:L,现金充电明细!B:B,B30)+SUMIFS('华瑞-曙光，大水井，老水井充电站'!L:L,'华瑞-曙光，大水井，老水井充电站'!B:B,B30)+SUMIFS('银盛-青龙坪充电站'!L:L,'银盛-青龙坪充电站'!B:B,B30)+SUMIFS('砚山锦佳-砚山充电站'!K:K,'砚山锦佳-砚山充电站'!B:B,B30)+SUMIFS(中石油广西百色靖西市龙临加油充电站!K:K,中石油广西百色靖西市龙临加油充电站!B:B,B30)+SUMIFS(德保众擎充电站!L:L,德保众擎充电站!B:B,B30)+SUMIFS(南网八宝充电站!K:K,南网八宝充电站!B:B,B30)+SUMIFS(南屏充电站!K:K,南屏充电站!B:B,B30)+SUMIFS(鑫鸿充电站!K:K,鑫鸿充电站!B:B,B30)+SUMIFS('锦田-百色田东充电站'!K:K,'锦田-百色田东充电站'!B:B,B30)+37.06/47+SUMIFS(平远充电站!K:K,平远充电站!B:B,B30) -> 13910.791 | K30: =J30/(H30) -> 0.36761307 | L30: =J30/F30 -> 927.38607 | N30: =13473.8/61 -> 220.88197 | O30: =SUMIFS(轮胎!H:H,轮胎!D:D,B30)+SUMIFS(轮胎!H:H,轮胎!D:D,C30) -> 900 | P30: 0 | Q30: =SUMIFS(维修费!E:E,维修费!C:C,B30)+SUMIFS(维修费!E:E,维修费!C:C,C30) -> 2260 | R30: =SUMIFS(磅单!R:R,磅单!F:F,B30) -> 9200 | S30: =SUMIFS(司机工资表!E:E,司机工资表!B:B,D30)+SUMIFS(司机工资表!N:N,司机工资表!B:B,D30) -> 780 | T30: =SUMIFS(付款明细!G:G,付款明细!D:D,B30,付款明细!B:B,"车队-罚款") -> 400 | U30: =SUMIFS(付款明细!G:G,付款明细!D:D,B30,付款明细!B:B,"车辆费用")+SUMIFS(付款明细!G:G,付款明细!D:D,C30,付款明细!B:B,"车辆费用") -> 412 | V30: =SUMIFS(付款明细!G:G,付款明细!B:B,"综合费用")/61 -> 397.39246 | W30: 2666 | Y30: =SUMIFS(磅单!P:P,磅单!E:E,B30) -> 225 | Z30: =H30*0.07-M30 -> 2648.8595 | AA30: 10600 | AB30: =3800 -> 3800 | AC30: =(管理人员工资!$D$10+管理人员工资!$E$10)/61 -> 790.16393 | AD30: =H30-I30-J30-N30-O30-R30-S30-T30-U30-V30-W30-AA30-AB30-AC30-Q30-P30-Z30-Y30-X30 -> -11370.239
A31: 29 | B31: 粤B32450D | C31: 桂LB675挂 | D31: 潘加松 | E31: 正常 | F31: =COUNTIFS(磅单!E:E,B31) -> 18 | G31: =SUMIFS(磅单!L:L,磅单!F:F,B31) -> 746.48 | H31: =SUMIFS(磅单!O:O,磅单!F:F,B31) -> 47601.34 | J31: =SUMIFS(现金充电明细!L:L,现金充电明细!B:B,B31)+SUMIFS('华瑞-曙光，大水井，老水井充电站'!L:L,'华瑞-曙光，大水井，老水井充电站'!B:B,B31)+SUMIFS('银盛-青龙坪充电站'!L:L,'银盛-青龙坪充电站'!B:B,B31)+SUMIFS('砚山锦佳-砚山充电站'!K:K,'砚山锦佳-砚山充电站'!B:B,B31)+SUMIFS(中石油广西百色靖西市龙临加油充电站!K:K,中石油广西百色靖西市龙临加油充电站!B:B,B31)+SUMIFS(德保众擎充电站!L:L,德保众擎充电站!B:B,B31)+SUMIFS(南网八宝充电站!K:K,南网八宝充电站!B:B,B31)+SUMIFS(南屏充电站!K:K,南屏充电站!B:B,B31)+SUMIFS(鑫鸿充电站!K:K,鑫鸿充电站!B:B,B31)+SUMIFS('锦田-百色田东充电站'!K:K,'锦田-百色田东充电站'!B:B,B31)+37.06/47+SUMIFS(平远充电站!K:K,平远充电站!B:B,B31) -> 14021.364 | K31: =J31/(H31) -> 0.29455818 | L31: =J31/F31 -> 778.96467 | N31: =13473.8/61 -> 220.88197 | O31: =SUMIFS(轮胎!H:H,轮胎!D:D,B31)+SUMIFS(轮胎!H:H,轮胎!D:D,C31) -> 0 | P31: 0 | Q31: =SUMIFS(维修费!E:E,维修费!C:C,B31)+SUMIFS(维修费!E:E,维修费!C:C,C31) -> 352 | R31: =SUMIFS(磅单!R:R,磅单!F:F,B31) -> 11200 | S31: =SUMIFS(司机工资表!E:E,司机工资表!B:B,D31)+SUMIFS(司机工资表!N:N,司机工资表!B:B,D31) -> 0 | T31: =SUMIFS(付款明细!G:G,付款明细!D:D,B31,付款明细!B:B,"车队-罚款") -> 200 | U31: =SUMIFS(付款明细!G:G,付款明细!D:D,B31,付款明细!B:B,"车辆费用")+SUMIFS(付款明细!G:G,付款明细!D:D,C31,付款明细!B:B,"车辆费用") -> 535 | V31: =SUMIFS(付款明细!G:G,付款明细!B:B,"综合费用")/61 -> 397.39246 | W31: 2666 | X31: 3000 | Y31: =SUMIFS(磅单!P:P,磅单!E:E,B31) -> 270 | Z31: =H31*0.07-M31 -> 3332.0938 | AA31: 10600 | AB31: =3800 -> 3800 | AC31: =(管理人员工资!$D$10+管理人员工资!$E$10)/61 -> 790.16393 | AD31: =H31-I31-J31-N31-O31-R31-S31-T31-U31-V31-W31-AA31-AB31-AC31-Q31-P31-Z31-Y31-X31 -> -3783.5563
A32: 30 | B32: 粤B95976D | C32: 桂LB629挂 | D32: 侯开雄 | E32: 正常 | F32: =COUNTIFS(磅单!E:E,B32) -> 17 | G32: =SUMIFS(磅单!L:L,磅单!F:F,B32) -> 707.89 | H32: =SUMIFS(磅单!O:O,磅单!F:F,B32) -> 45141.65 | J32: =SUMIFS(现金充电明细!L:L,现金充电明细!B:B,B32)+SUMIFS('华瑞-曙光，大水井，老水井充电站'!L:L,'华瑞-曙光，大水井，老水井充电站'!B:B,B32)+SUMIFS('银盛-青龙坪充电站'!L:L,'银盛-青龙坪充电站'!B:B,B32)+SUMIFS('砚山锦佳-砚山充电站'!K:K,'砚山锦佳-砚山充电站'!B:B,B32)+SUMIFS(中石油广西百色靖西市龙临加油充电站!K:K,中石油广西百色靖西市龙临加油充电站!B:B,B32)+SUMIFS(德保众擎充电站!L:L,德保众擎充电站!B:B,B32)+SUMIFS(南网八宝充电站!K:K,南网八宝充电站!B:B,B32)+SUMIFS(南屏充电站!K:K,南屏充电站!B:B,B32)+SUMIFS(鑫鸿充电站!K:K,鑫鸿充电站!B:B,B32)+SUMIFS('锦田-百色田东充电站'!K:K,'锦田-百色田东充电站'!B:B,B32)+37.06/47+SUMIFS(平远充电站!K:K,平远充电站!B:B,B32) -> 14959.372 | K32: =J32/(H32) -> 0.33138736 | L32: =J32/F32 -> 879.96306 | N32: =13473.8/61 -> 220.88197 | O32: =SUMIFS(轮胎!H:H,轮胎!D:D,B32)+SUMIFS(轮胎!H:H,轮胎!D:D,C32) -> 0 | P32: 0 | Q32: =SUMIFS(维修费!E:E,维修费!C:C,B32)+SUMIFS(维修费!E:E,维修费!C:C,C32) -> 17300 | R32: =SUMIFS(磅单!R:R,磅单!F:F,B32) -> 10600 | S32: =SUMIFS(司机工资表!E:E,司机工资表!B:B,D32)+SUMIFS(司机工资表!N:N,司机工资表!B:B,D32) -> 0 | T32: =SUMIFS(付款明细!G:G,付款明细!D:D,B32,付款明细!B:B,"车队-罚款") -> 0 | U32: =SUMIFS(付款明细!G:G,付款明细!D:D,B32,付款明细!B:B,"车辆费用")+SUMIFS(付款明细!G:G,付款明细!D:D,C32,付款明细!B:B,"车辆费用") -> 2989 | V32: =SUMIFS(付款明细!G:G,付款明细!B:B,"综合费用")/61 -> 397.39246 | W32: 2666 | X32: 3000 | Y32: =SUMIFS(磅单!P:P,磅单!E:E,B32) -> 255 | Z32: =H32*0.07-M32 -> 3159.9155 | AA32: 10600 | AB32: =3800 -> 3800 | AC32: =(管理人员工资!$D$10+管理人员工资!$E$10)/61 -> 790.16393 | AD32: =H32-I32-J32-N32-O32-R32-S32-T32-U32-V32-W32-AA32-AB32-AC32-Q32-P32-Z32-Y32-X32 -> -25596.076
A33: 31 | B33: 粤B79120D | C33: 桂LD489挂 | D33: 周忠银 | E33: 正常 | F33: =COUNTIFS(磅单!E:E,B33) -> 14 | G33: =SUMIFS(磅单!L:L,磅单!F:F,B33) -> 608.25 | H33: =SUMIFS(磅单!O:O,磅单!F:F,B33) -> 37988.71 | J33: =SUMIFS(现金充电明细!L:L,现金充电明细!B:B,B33)+SUMIFS('华瑞-曙光，大水井，老水井充电站'!L:L,'华瑞-曙光，大水井，老水井充电站'!B:B,B33)+SUMIFS('银盛-青龙坪充电站'!L:L,'银盛-青龙坪充电站'!B:B,B33)+SUMIFS('砚山锦佳-砚山充电站'!K:K,'砚山锦佳-砚山充电站'!B:B,B33)+SUMIFS(中石油广西百色靖西市龙临加油充电站!K:K,中石油广西百色靖西市龙临加油充电站!B:B,B33)+SUMIFS(德保众擎充电站!L:L,德保众擎充电站!B:B,B33)+SUMIFS(南网八宝充电站!K:K,南网八宝充电站!B:B,B33)+SUMIFS(南屏充电站!K:K,南屏充电站!B:B,B33)+SUMIFS(鑫鸿充电站!K:K,鑫鸿充电站!B:B,B33)+SUMIFS('锦田-百色田东充电站'!K:K,'锦田-百色田东充电站'!B:B,B33)+37.06/47+SUMIFS(平远充电站!K:K,平远充电站!B:B,B33) -> 13854.188 | K33: =J33/(H33) -> 0.36469224 | L33: =J33/F33 -> 989.58483 | N33: =13473.8/61 -> 220.88197 | O33: =SUMIFS(轮胎!H:H,轮胎!D:D,B33)+SUMIFS(轮胎!H:H,轮胎!D:D,C33) -> 0 | P33: 0 | Q33: =SUMIFS(维修费!E:E,维修费!C:C,B33)+SUMIFS(维修费!E:E,维修费!C:C,C33) -> 230 | R33: =SUMIFS(磅单!R:R,磅单!F:F,B33) -> 8800 | S33: =SUMIFS(司机工资表!E:E,司机工资表!B:B,D33)+SUMIFS(司机工资表!N:N,司机工资表!B:B,D33)+400 -> 1200 | T33: =SUMIFS(付款明细!G:G,付款明细!D:D,B33,付款明细!B:B,"车队-罚款") -> 200 | U33: =SUMIFS(付款明细!G:G,付款明细!D:D,B33,付款明细!B:B,"车辆费用")+SUMIFS(付款明细!G:G,付款明细!D:D,C33,付款明细!B:B,"车辆费用") -> 466 | V33: =SUMIFS(付款明细!G:G,付款明细!B:B,"综合费用")/61 -> 397.39246 | W33: 2666 | X33: 3000 | Y33: =SUMIFS(磅单!P:P,磅单!E:E,B33) -> 210 | Z33: =H33*0.07-M33 -> 2659.2097 | AA33: 10600 | AC33: =(管理人员工资!$D$10+管理人员工资!$E$10)/61 -> 790.16393 | AD33: =H33-I33-J33-N33-O33-R33-S33-T33-U33-V33-W33-AA33-AB33-AC33-Q33-P33-Z33-Y33-X33 -> -7305.1257
A34: 32 | B34: 粤B43551D | C34: 桂LC523挂 | D34: 罗吴华 | E34: 正常 | F34: =COUNTIFS(磅单!E:E,B34) -> 18 | G34: =SUMIFS(磅单!L:L,磅单!F:F,B34) -> 769.44 | H34: =SUMIFS(磅单!O:O,磅单!F:F,B34) -> 49469.5 | J34: =SUMIFS(现金充电明细!L:L,现金充电明细!B:B,B34)+SUMIFS('华瑞-曙光，大水井，老水井充电站'!L:L,'华瑞-曙光，大水井，老水井充电站'!B:B,B34)+SUMIFS('银盛-青龙坪充电站'!L:L,'银盛-青龙坪充电站'!B:B,B34)+SUMIFS('砚山锦佳-砚山充电站'!K:K,'砚山锦佳-砚山充电站'!B:B,B34)+SUMIFS(中石油广西百色靖西市龙临加油充电站!K:K,中石油广西百色靖西市龙临加油充电站!B:B,B34)+SUMIFS(德保众擎充电站!L:L,德保众擎充电站!B:B,B34)+SUMIFS(南网八宝充电站!K:K,南网八宝充电站!B:B,B34)+SUMIFS(南屏充电站!K:K,南屏充电站!B:B,B34)+SUMIFS(鑫鸿充电站!K:K,鑫鸿充电站!B:B,B34)+SUMIFS('锦田-百色田东充电站'!K:K,'锦田-百色田东充电站'!B:B,B34)+37.06/47+SUMIFS(平远充电站!K:K,平远充电站!B:B,B34) -> 19178.568 | K34: =J34/(H34) -> 0.3876847 | L34: =J34/F34 -> 1065.476 | N34: =13473.8/61 -> 220.88197 | O34: =SUMIFS(轮胎!H:H,轮胎!D:D,B34)+SUMIFS(轮胎!H:H,轮胎!D:D,C34) -> 0 | P34: 0 | Q34: =SUMIFS(维修费!E:E,维修费!C:C,B34)+SUMIFS(维修费!E:E,维修费!C:C,C34) -> 100 | R34: =SUMIFS(磅单!R:R,磅单!F:F,B34) -> 11200 | S34: =SUMIFS(司机工资表!E:E,司机工资表!B:B,D34)+SUMIFS(司机工资表!N:N,司机工资表!B:B,D34) -> 0 | T34: =SUMIFS(付款明细!G:G,付款明细!D:D,B34,付款明细!B:B,"车队-罚款") -> 220 | U34: =SUMIFS(付款明细!G:G,付款明细!D:D,B34,付款明细!B:B,"车辆费用")+SUMIFS(付款明细!G:G,付款明细!D:D,C34,付款明细!B:B,"车辆费用") -> 424 | V34: =SUMIFS(付款明细!G:G,付款明细!B:B,"综合费用")/61 -> 397.39246 | W34: 2666 | X34: 3000 | Y34: =SUMIFS(磅单!P:P,磅单!E:E,B34) -> 270 | Z34: =H34*0.07-M34 -> 3462.865 | AA34: 10600 | AC34: =(管理人员工资!$D$10+管理人员工资!$E$10)/61 -> 790.16393 | AD34: =H34-I34-J34-N34-O34-R34-S34-T34-U34-V34-W34-AA34-AB34-AC34-Q34-P34-Z34-Y34-X34 -> -3060.3716
A35: 33 | B35: 粤B98485D | C35: 桂L4036挂 | D35: 覃胜猛 | E35: 正常 | F35: =COUNTIFS(磅单!E:E,B35) -> 17 | G35: =SUMIFS(磅单!L:L,磅单!F:F,B35) -> 740.58 | H35: =SUMIFS(磅单!O:O,磅单!F:F,B35) -> 48038.96 | J35: =SUMIFS(现金充电明细!L:L,现金充电明细!B:B,B35)+SUMIFS('华瑞-曙光，大水井，老水井充电站'!L:L,'华瑞-曙光，大水井，老水井充电站'!B:B,B35)+SUMIFS('银盛-青龙坪充电站'!L:L,'银盛-青龙坪充电站'!B:B,B35)+SUMIFS('砚山锦佳-砚山充电站'!K:K,'砚山锦佳-砚山充电站'!B:B,B35)+SUMIFS(中石油广西百色靖西市龙临加油充电站!K:K,中石油广西百色靖西市龙临加油充电站!B:B,B35)+SUMIFS(德保众擎充电站!L:L,德保众擎充电站!B:B,B35)+SUMIFS(南网八宝充电站!K:K,南网八宝充电站!B:B,B35)+SUMIFS(南屏充电站!K:K,南屏充电站!B:B,B35)+SUMIFS(鑫鸿充电站!K:K,鑫鸿充电站!B:B,B35)+SUMIFS('锦田-百色田东充电站'!K:K,'锦田-百色田东充电站'!B:B,B35)+37.06/47+SUMIFS(平远充电站!K:K,平远充电站!B:B,B35) -> 17792.421 | K35: =J35/(H35) -> 0.37037482 | L35: =J35/F35 -> 1046.613 | N35: =13473.8/61 -> 220.88197 | O35: =SUMIFS(轮胎!H:H,轮胎!D:D,B35)+SUMIFS(轮胎!H:H,轮胎!D:D,C35) -> 0 | P35: 0 | Q35: =SUMIFS(维修费!E:E,维修费!C:C,B35)+SUMIFS(维修费!E:E,维修费!C:C,C35) -> 50 | R35: =SUMIFS(磅单!R:R,磅单!F:F,B35) -> 10600 | S35: =SUMIFS(司机工资表!E:E,司机工资表!B:B,D35)+SUMIFS(司机工资表!N:N,司机工资表!B:B,D35) -> 0 | T35: =SUMIFS(付款明细!G:G,付款明细!D:D,B35,付款明细!B:B,"车队-罚款") -> 200 | U35: =SUMIFS(付款明细!G:G,付款明细!D:D,B35,付款明细!B:B,"车辆费用")+SUMIFS(付款明细!G:G,付款明细!D:D,C35,付款明细!B:B,"车辆费用") -> 410 | V35: =SUMIFS(付款明细!G:G,付款明细!B:B,"综合费用")/61 -> 397.39246 | W35: 2666 | X35: 3000 | Y35: =SUMIFS(磅单!P:P,磅单!E:E,B35) -> 255 | Z35: =H35*0.07-M35 -> 3362.7272 | AA35: 10600 | AC35: =(管理人员工资!$D$10+管理人员工资!$E$10)/61 -> 790.16393 | AD35: =H35-I35-J35-N35-O35-R35-S35-T35-U35-V35-W35-AA35-AB35-AC35-Q35-P35-Z35-Y35-X35 -> -2305.6269
A36: 34 | B36: 粤B93085D | C36: 桂L13C55挂 | D36: 盘靖 | E36: 正常 | F36: =COUNTIFS(磅单!E:E,B36) -> 9 | G36: =SUMIFS(磅单!L:L,磅单!F:F,B36) -> 393.24 | H36: =SUMIFS(磅单!O:O,磅单!F:F,B36) -> 27869.18 | J36: =SUMIFS(现金充电明细!L:L,现金充电明细!B:B,B36)+SUMIFS('华瑞-曙光，大水井，老水井充电站'!L:L,'华瑞-曙光，大水井，老水井充电站'!B:B,B36)+SUMIFS('银盛-青龙坪充电站'!L:L,'银盛-青龙坪充电站'!B:B,B36)+SUMIFS('砚山锦佳-砚山充电站'!K:K,'砚山锦佳-砚山充电站'!B:B,B36)+SUMIFS(中石油广西百色靖西市龙临加油充电站!K:K,中石油广西百色靖西市龙临加油充电站!B:B,B36)+SUMIFS(德保众擎充电站!L:L,德保众擎充电站!B:B,B36)+SUMIFS(南网八宝充电站!K:K,南网八宝充电站!B:B,B36)+SUMIFS(南屏充电站!K:K,南屏充电站!B:B,B36)+SUMIFS(鑫鸿充电站!K:K,鑫鸿充电站!B:B,B36)+SUMIFS('锦田-百色田东充电站'!K:K,'锦田-百色田东充电站'!B:B,B36)+37.06/47+SUMIFS(平远充电站!K:K,平远充电站!B:B,B36) -> 10008.92 | K36: =J36/(H36) -> 0.35913938 | L36: =J36/F36 -> 1112.1022 | N36: =13473.8/61 -> 220.88197 | O36: =SUMIFS(轮胎!H:H,轮胎!D:D,B36)+SUMIFS(轮胎!H:H,轮胎!D:D,C36) -> 0 | P36: 0 | Q36: =SUMIFS(维修费!E:E,维修费!C:C,B36)+SUMIFS(维修费!E:E,维修费!C:C,C36) -> 130 | R36: =SUMIFS(磅单!R:R,磅单!F:F,B36) -> 6400 | S36: =SUMIFS(司机工资表!E:E,司机工资表!B:B,D36)+SUMIFS(司机工资表!N:N,司机工资表!B:B,D36) -> 0 | T36: =SUMIFS(付款明细!G:G,付款明细!D:D,B36,付款明细!B:B,"车队-罚款") -> 0 | U36: =SUMIFS(付款明细!G:G,付款明细!D:D,B36,付款明细!B:B,"车辆费用")+SUMIFS(付款明细!G:G,付款明细!D:D,C36,付款明细!B:B,"车辆费用") -> 337 | V36: =SUMIFS(付款明细!G:G,付款明细!B:B,"综合费用")/61 -> 397.39246 | W36: 2666 | X36: 3100 | Y36: =SUMIFS(磅单!P:P,磅单!E:E,B36) -> 135 | Z36: =H36*0.07-M36 -> 1950.8426 | AA36: 10600 | AC36: =(管理人员工资!$D$10+管理人员工资!$E$10)/61 -> 790.16393 | AD36: =H36-I36-J36-N36-O36-R36-S36-T36-U36-V36-W36-AA36-AB36-AC36-Q36-P36-Z36-Y36-X36 -> -8867.0209
A37: 35 | B37: 粤B85970D | C37: 桂L76464挂 | D37: 陆世鹏 | E37: 正常 | F37: =COUNTIFS(磅单!E:E,B37) -> 11 | G37: =SUMIFS(磅单!L:L,磅单!F:F,B37) -> 476.11 | H37: =SUMIFS(磅单!O:O,磅单!F:F,B37) -> 31418.83 | J37: =SUMIFS(现金充电明细!L:L,现金充电明细!B:B,B37)+SUMIFS('华瑞-曙光，大水井，老水井充电站'!L:L,'华瑞-曙光，大水井，老水井充电站'!B:B,B37)+SUMIFS('银盛-青龙坪充电站'!L:L,'银盛-青龙坪充电站'!B:B,B37)+SUMIFS('砚山锦佳-砚山充电站'!K:K,'砚山锦佳-砚山充电站'!B:B,B37)+SUMIFS(中石油广西百色靖西市龙临加油充电站!K:K,中石油广西百色靖西市龙临加油充电站!B:B,B37)+SUMIFS(德保众擎充电站!L:L,德保众擎充电站!B:B,B37)+SUMIFS(南网八宝充电站!K:K,南网八宝充电站!B:B,B37)+SUMIFS(南屏充电站!K:K,南屏充电站!B:B,B37)+SUMIFS(鑫鸿充电站!K:K,鑫鸿充电站!B:B,B37)+SUMIFS('锦田-百色田东充电站'!K:K,'锦田-百色田东充电站'!B:B,B37)+37.06/47+SUMIFS(平远充电站!K:K,平远充电站!B:B,B37) -> 12396.287 | K37: =J37/(H37) -> 0.39454959 | L37: =J37/F37 -> 1126.9351 | N37: =13473.8/61 -> 220.88197 | O37: =SUMIFS(轮胎!H:H,轮胎!D:D,B37)+SUMIFS(轮胎!H:H,轮胎!D:D,C37) -> 0 | P37: 0 | Q37: =SUMIFS(维修费!E:E,维修费!C:C,B37)+SUMIFS(维修费!E:E,维修费!C:C,C37) -> 90 | R37: =SUMIFS(磅单!R:R,磅单!F:F,B37) -> 7200 | S37: =SUMIFS(司机工资表!E:E,司机工资表!B:B,D37)+SUMIFS(司机工资表!N:N,司机工资表!B:B,D37) -> 200 | T37: =SUMIFS(付款明细!G:G,付款明细!D:D,B37,付款明细!B:B,"车队-罚款") -> 200 | U37: =SUMIFS(付款明细!G:G,付款明细!D:D,B37,付款明细!B:B,"车辆费用")+SUMIFS(付款明细!G:G,付款明细!D:D,C37,付款明细!B:B,"车辆费用") -> 328 | V37: =SUMIFS(付款明细!G:G,付款明细!B:B,"综合费用")/61 -> 397.39246 | W37: 2666 | X37: 3100 | Y37: =SUMIFS(磅单!P:P,磅单!E:E,B37) -> 165 | Z37: =H37*0.07-M37 -> 2199.3181 | AA37: 10600 | AC37: =(管理人员工资!$D$10+管理人员工资!$E$10)/61 -> 790.16393 | AD37: =H37-I37-J37-N37-O37-R37-S37-T37-U37-V37-W37-AA37-AB37-AC37-Q37-P37-Z37-Y37-X37 -> -9134.2131
A38: 36 | B38: 粤B78432D | C38: 桂L6429挂 | D38: 张俊 | E38: 正常 | F38: =COUNTIFS(磅单!E:E,B38) -> 13 | G38: =SUMIFS(磅单!L:L,磅单!F:F,B38) -> 564.55 | H38: =SUMIFS(磅单!O:O,磅单!F:F,B38) -> 40949.85 | J38: =SUMIFS(现金充电明细!L:L,现金充电明细!B:B,B38)+SUMIFS('华瑞-曙光，大水井，老水井充电站'!L:L,'华瑞-曙光，大水井，老水井充电站'!B:B,B38)+SUMIFS('银盛-青龙坪充电站'!L:L,'银盛-青龙坪充电站'!B:B,B38)+SUMIFS('砚山锦佳-砚山充电站'!K:K,'砚山锦佳-砚山充电站'!B:B,B38)+SUMIFS(中石油广西百色靖西市龙临加油充电站!K:K,中石油广西百色靖西市龙临加油充电站!B:B,B38)+SUMIFS(德保众擎充电站!L:L,德保众擎充电站!B:B,B38)+SUMIFS(南网八宝充电站!K:K,南网八宝充电站!B:B,B38)+SUMIFS(南屏充电站!K:K,南屏充电站!B:B,B38)+SUMIFS(鑫鸿充电站!K:K,鑫鸿充电站!B:B,B38)+SUMIFS('锦田-百色田东充电站'!K:K,'锦田-百色田东充电站'!B:B,B38)+37.06/47+SUMIFS(平远充电站!K:K,平远充电站!B:B,B38) -> 13245.676 | K38: =J38/(H38) -> 0.3234609 | L38: =J38/F38 -> 1018.8981 | N38: =13473.8/61 -> 220.88197 | O38: =SUMIFS(轮胎!H:H,轮胎!D:D,B38)+SUMIFS(轮胎!H:H,轮胎!D:D,C38) -> 950 | P38: 0 | Q38: =SUMIFS(维修费!E:E,维修费!C:C,B38)+SUMIFS(维修费!E:E,维修费!C:C,C38) -> 180 | R38: =SUMIFS(磅单!R:R,磅单!F:F,B38) -> 9000 | S38: =SUMIFS(司机工资表!E:E,司机工资表!B:B,D38)+SUMIFS(司机工资表!N:N,司机工资表!B:B,D38) -> 200 | T38: =SUMIFS(付款明细!G:G,付款明细!D:D,B38,付款明细!B:B,"车队-罚款") -> 200 | U38: =SUMIFS(付款明细!G:G,付款明细!D:D,B38,付款明细!B:B,"车辆费用")+SUMIFS(付款明细!G:G,付款明细!D:D,C38,付款明细!B:B,"车辆费用") -> 229 | V38: =SUMIFS(付款明细!G:G,付款明细!B:B,"综合费用")/61 -> 397.39246 | W38: 2666 | X38: 3200 | Y38: =SUMIFS(磅单!P:P,磅单!E:E,B38) -> 195 | Z38: =H38*0.07-M38 -> 2866.4895 | AA38: 10600 | AC38: =(管理人员工资!$D$10+管理人员工资!$E$10)/61 -> 790.16393 | AD38: =H38-I38-J38-N38-O38-R38-S38-T38-U38-V38-W38-AA38-AB38-AC38-Q38-P38-Z38-Y38-X38 -> -3990.7534
A39: 37 | B39: 粤B94650D | C39: 桂LD631挂 | D39: 赵雄 | E39: 正常 | F39: =COUNTIFS(磅单!E:E,B39) -> 12 | G39: =SUMIFS(磅单!L:L,磅单!F:F,B39) -> 511.96 | H39: =SUMIFS(磅单!O:O,磅单!F:F,B39) -> 38347.32 | J39: =SUMIFS(现金充电明细!L:L,现金充电明细!B:B,B39)+SUMIFS('华瑞-曙光，大水井，老水井充电站'!L:L,'华瑞-曙光，大水井，老水井充电站'!B:B,B39)+SUMIFS('银盛-青龙坪充电站'!L:L,'银盛-青龙坪充电站'!B:B,B39)+SUMIFS('砚山锦佳-砚山充电站'!K:K,'砚山锦佳-砚山充电站'!B:B,B39)+SUMIFS(中石油广西百色靖西市龙临加油充电站!K:K,中石油广西百色靖西市龙临加油充电站!B:B,B39)+SUMIFS(德保众擎充电站!L:L,德保众擎充电站!B:B,B39)+SUMIFS(南网八宝充电站!K:K,南网八宝充电站!B:B,B39)+SUMIFS(南屏充电站!K:K,南屏充电站!B:B,B39)+SUMIFS(鑫鸿充电站!K:K,鑫鸿充电站!B:B,B39)+SUMIFS('锦田-百色田东充电站'!K:K,'锦田-百色田东充电站'!B:B,B39)+37.06/47+SUMIFS(平远充电站!K:K,平远充电站!B:B,B39) -> 13602.169 | K39: =J39/(H39) -> 0.35470978 | L39: =J39/F39 -> 1133.5141 | N39: =13473.8/61 -> 220.88197 | O39: =SUMIFS(轮胎!H:H,轮胎!D:D,B39)+SUMIFS(轮胎!H:H,轮胎!D:D,C39) -> 0 | P39: 0 | Q39: =SUMIFS(维修费!E:E,维修费!C:C,B39)+SUMIFS(维修费!E:E,维修费!C:C,C39) -> 760 | R39: =SUMIFS(磅单!R:R,磅单!F:F,B39) -> 8600 | S39: =SUMIFS(司机工资表!E:E,司机工资表!B:B,D39)+SUMIFS(司机工资表!N:N,司机工资表!B:B,D39) -> 200 | T39: =SUMIFS(付款明细!G:G,付款明细!D:D,B39,付款明细!B:B,"车队-罚款") -> 200 | U39: =SUMIFS(付款明细!G:G,付款明细!D:D,B39,付款明细!B:B,"车辆费用")+SUMIFS(付款明细!G:G,付款明细!D:D,C39,付款明细!B:B,"车辆费用") -> 210 | V39: =SUMIFS(付款明细!G:G,付款明细!B:B,"综合费用")/61 -> 397.39246 | W39: 2666 | X39: 3200 | Y39: =SUMIFS(磅单!P:P,磅单!E:E,B39) -> 180 | Z39: =H39*0.07-M39 -> 2684.3124 | AA39: 10600 | AC39: =(管理人员工资!$D$10+管理人员工资!$E$10)/61 -> 790.16393 | AD39: =H39-I39-J39-N39-O39-R39-S39-T39-U39-V39-W39-AA39-AB39-AC39-Q39-P39-Z39-Y39-X39 -> -5963.6001
A40: 38 | B40: 粤B47340D | C40: 桂L5748挂 | D40: 曾龙龙 | E40: 正常 | F40: =COUNTIFS(磅单!E:E,B40) -> 11 | G40: =SUMIFS(磅单!L:L,磅单!F:F,B40) -> 471.26 | H40: =SUMIFS(磅单!O:O,磅单!F:F,B40) -> 34804.6 | J40: =SUMIFS(现金充电明细!L:L,现金充电明细!B:B,B40)+SUMIFS('华瑞-曙光，大水井，老水井充电站'!L:L,'华瑞-曙光，大水井，老水井充电站'!B:B,B40)+SUMIFS('银盛-青龙坪充电站'!L:L,'银盛-青龙坪充电站'!B:B,B40)+SUMIFS('砚山锦佳-砚山充电站'!K:K,'砚山锦佳-砚山充电站'!B:B,B40)+SUMIFS(中石油广西百色靖西市龙临加油充电站!K:K,中石油广西百色靖西市龙临加油充电站!B:B,B40)+SUMIFS(德保众擎充电站!L:L,德保众擎充电站!B:B,B40)+SUMIFS(南网八宝充电站!K:K,南网八宝充电站!B:B,B40)+SUMIFS(南屏充电站!K:K,南屏充电站!B:B,B40)+SUMIFS(鑫鸿充电站!K:K,鑫鸿充电站!B:B,B40)+SUMIFS('锦田-百色田东充电站'!K:K,'锦田-百色田东充电站'!B:B,B40)+37.06/47+SUMIFS(平远充电站!K:K,平远充电站!B:B,B40) -> 12537.759 | K40: =J40/(H40) -> 0.3602328 | L40: =J40/F40 -> 1139.7962 | N40: =13473.8/61 -> 220.88197 | O40: =SUMIFS(轮胎!H:H,轮胎!D:D,B40)+SUMIFS(轮胎!H:H,轮胎!D:D,C40) -> 0 | P40: 0 | Q40: =SUMIFS(维修费!E:E,维修费!C:C,B40)+SUMIFS(维修费!E:E,维修费!C:C,C40) -> 180 | R40: =SUMIFS(磅单!R:R,磅单!F:F,B40) -> 7800 | S40: =SUMIFS(司机工资表!E:E,司机工资表!B:B,D40)+SUMIFS(司机工资表!N:N,司机工资表!B:B,D40) -> 200 | T40: =SUMIFS(付款明细!G:G,付款明细!D:D,B40,付款明细!B:B,"车队-罚款") -> 220 | U40: =SUMIFS(付款明细!G:G,付款明细!D:D,B40,付款明细!B:B,"车辆费用")+SUMIFS(付款明细!G:G,付款明细!D:D,C40,付款明细!B:B,"车辆费用") -> 207 | V40: =SUMIFS(付款明细!G:G,付款明细!B:B,"综合费用")/61 -> 397.39246 | W40: 2666 | X40: 3200 | Y40: =SUMIFS(磅单!P:P,磅单!E:E,B40) -> 165 | Z40: =H40*0.07-M40 -> 2436.322 | AA40: 10600 | AC40: =(管理人员工资!$D$10+管理人员工资!$E$10)/61 -> 790.16393 | AD40: =H40-I40-J40-N40-O40-R40-S40-T40-U40-V40-W40-AA40-AB40-AC40-Q40-P40-Z40-Y40-X40 -> -6815.9189
A41: 39 | B41: 粤B99322D | C41: 桂L6249挂 | D41: 李昆 | E41: 正常 | F41: =COUNTIFS(磅单!E:E,B41) -> 11 | G41: =SUMIFS(磅单!L:L,磅单!F:F,B41) -> 466.22 | H41: =SUMIFS(磅单!O:O,磅单!F:F,B41) -> 34415.52 | J41: =SUMIFS(现金充电明细!L:L,现金充电明细!B:B,B41)+SUMIFS('华瑞-曙光，大水井，老水井充电站'!L:L,'华瑞-曙光，大水井，老水井充电站'!B:B,B41)+SUMIFS('银盛-青龙坪充电站'!L:L,'银盛-青龙坪充电站'!B:B,B41)+SUMIFS('砚山锦佳-砚山充电站'!K:K,'砚山锦佳-砚山充电站'!B:B,B41)+SUMIFS(中石油广西百色靖西市龙临加油充电站!K:K,中石油广西百色靖西市龙临加油充电站!B:B,B41)+SUMIFS(德保众擎充电站!L:L,德保众擎充电站!B:B,B41)+SUMIFS(南网八宝充电站!K:K,南网八宝充电站!B:B,B41)+SUMIFS(南屏充电站!K:K,南屏充电站!B:B,B41)+SUMIFS(鑫鸿充电站!K:K,鑫鸿充电站!B:B,B41)+SUMIFS('锦田-百色田东充电站'!K:K,'锦田-百色田东充电站'!B:B,B41)+37.06/47+SUMIFS(平远充电站!K:K,平远充电站!B:B,B41) -> 12805.259 | K41: =J41/(H41) -> 0.37207802 | L41: =J41/F41 -> 1164.1144 | N41: =13473.8/61 -> 220.88197 | O41: =SUMIFS(轮胎!H:H,轮胎!D:D,B41)+SUMIFS(轮胎!H:H,轮胎!D:D,C41) -> 0 | P41: 0 | Q41: =SUMIFS(维修费!E:E,维修费!C:C,B41)+SUMIFS(维修费!E:E,维修费!C:C,C41) -> 70 | R41: =SUMIFS(磅单!R:R,磅单!F:F,B41) -> 7800 | S41: =SUMIFS(司机工资表!E:E,司机工资表!B:B,D41)+SUMIFS(司机工资表!N:N,司机工资表!B:B,D41) -> 200 | T41: =SUMIFS(付款明细!G:G,付款明细!D:D,B41,付款明细!B:B,"车队-罚款") -> 0 | U41: =SUMIFS(付款明细!G:G,付款明细!D:D,B41,付款明细!B:B,"车辆费用")+SUMIFS(付款明细!G:G,付款明细!D:D,C41,付款明细!B:B,"车辆费用") -> 197 | V41: =SUMIFS(付款明细!G:G,付款明细!B:B,"综合费用")/61 -> 397.39246 | W41: 2666 | X41: 3200 | Y41: =SUMIFS(磅单!P:P,磅单!E:E,B41) -> 165 | Z41: =H41*0.07-M41 -> 2409.0864 | AA41: 10600 | AC41: =(管理人员工资!$D$10+管理人员工资!$E$10)/61 -> 790.16393 | AD41: =H41-I41-J41-N41-O41-R41-S41-T41-U41-V41-W41-AA41-AB41-AC41-Q41-P41-Z41-Y41-X41 -> -7105.2633
A42: 40 | B42: 粤B96406D | C42: 桂L8626挂 | D42: 杨光傅 | E42: 正常 | F42: =COUNTIFS(磅单!E:E,B42) -> 13 | G42: =SUMIFS(磅单!L:L,磅单!F:F,B42) -> 565.56 | H42: =SUMIFS(磅单!O:O,磅单!F:F,B42) -> 40860.88 | J42: =SUMIFS(现金充电明细!L:L,现金充电明细!B:B,B42)+SUMIFS('华瑞-曙光，大水井，老水井充电站'!L:L,'华瑞-曙光，大水井，老水井充电站'!B:B,B42)+SUMIFS('银盛-青龙坪充电站'!L:L,'银盛-青龙坪充电站'!B:B,B42)+SUMIFS('砚山锦佳-砚山充电站'!K:K,'砚山锦佳-砚山充电站'!B:B,B42)+SUMIFS(中石油广西百色靖西市龙临加油充电站!K:K,中石油广西百色靖西市龙临加油充电站!B:B,B42)+SUMIFS(德保众擎充电站!L:L,德保众擎充电站!B:B,B42)+SUMIFS(南网八宝充电站!K:K,南网八宝充电站!B:B,B42)+SUMIFS(南屏充电站!K:K,南屏充电站!B:B,B42)+SUMIFS(鑫鸿充电站!K:K,鑫鸿充电站!B:B,B42)+SUMIFS('锦田-百色田东充电站'!K:K,'锦田-百色田东充电站'!B:B,B42)+37.06/47+SUMIFS(平远充电站!K:K,平远充电站!B:B,B42) -> 12702.374 | K42: =J42/(H42) -> 0.31086882 | L42: =J42/F42 -> 977.10566 | N42: =13473.8/61 -> 220.88197 | O42: =SUMIFS(轮胎!H:H,轮胎!D:D,B42)+SUMIFS(轮胎!H:H,轮胎!D:D,C42) -> 0 | P42: 0 | Q42: =SUMIFS(维修费!E:E,维修费!C:C,B42)+SUMIFS(维修费!E:E,维修费!C:C,C42) -> 20 | R42: =SUMIFS(磅单!R:R,磅单!F:F,B42) -> 9000 | S42: =SUMIFS(司机工资表!E:E,司机工资表!B:B,D42)+SUMIFS(司机工资表!N:N,司机工资表!B:B,D42) -> 0 | T42: =SUMIFS(付款明细!G:G,付款明细!D:D,B42,付款明细!B:B,"车队-罚款") -> 0 | U42: =SUMIFS(付款明细!G:G,付款明细!D:D,B42,付款明细!B:B,"车辆费用")+SUMIFS(付款明细!G:G,付款明细!D:D,C42,付款明细!B:B,"车辆费用") -> 295 | V42: =SUMIFS(付款明细!G:G,付款明细!B:B,"综合费用")/61 -> 397.39246 | W42: 2666 | X42: 3200 | Y42: =SUMIFS(磅单!P:P,磅单!E:E,B42) -> 195 | Z42: =H42*0.07-M42 -> 2860.2616 | AA42: 10600 | AC42: =(管理人员工资!$D$10+管理人员工资!$E$10)/61 -> 790.16393 | AD42: =H42-I42-J42-N42-O42-R42-S42-T42-U42-V42-W42-AA42-AB42-AC42-Q42-P42-Z42-Y42-X42 -> -2086.1936
A43: 41 | B43: 粤B95488D | C43: 桂L5939挂 | D43: 赵洪凡 | E43: 正常 | F43: =COUNTIFS(磅单!E:E,B43) -> 10 | G43: =SUMIFS(磅单!L:L,磅单!F:F,B43) -> 433.28 | H43: =SUMIFS(磅单!O:O,磅单!F:F,B43) -> 30994.56 | J43: =SUMIFS(现金充电明细!L:L,现金充电明细!B:B,B43)+SUMIFS('华瑞-曙光，大水井，老水井充电站'!L:L,'华瑞-曙光，大水井，老水井充电站'!B:B,B43)+SUMIFS('银盛-青龙坪充电站'!L:L,'银盛-青龙坪充电站'!B:B,B43)+SUMIFS('砚山锦佳-砚山充电站'!K:K,'砚山锦佳-砚山充电站'!B:B,B43)+SUMIFS(中石油广西百色靖西市龙临加油充电站!K:K,中石油广西百色靖西市龙临加油充电站!B:B,B43)+SUMIFS(德保众擎充电站!L:L,德保众擎充电站!B:B,B43)+SUMIFS(南网八宝充电站!K:K,南网八宝充电站!B:B,B43)+SUMIFS(南屏充电站!K:K,南屏充电站!B:B,B43)+SUMIFS(鑫鸿充电站!K:K,鑫鸿充电站!B:B,B43)+SUMIFS('锦田-百色田东充电站'!K:K,'锦田-百色田东充电站'!B:B,B43)+37.06/47+SUMIFS(平远充电站!K:K,平远充电站!B:B,B43) -> 10634.231 | K43: =J43/(H43) -> 0.34309992 | L43: =J43/F43 -> 1063.4231 | N43: =13473.8/61 -> 220.88197 | O43: =SUMIFS(轮胎!H:H,轮胎!D:D,B43)+SUMIFS(轮胎!H:H,轮胎!D:D,C43) -> 950 | P43: 0 | Q43: =SUMIFS(维修费!E:E,维修费!C:C,B43)+SUMIFS(维修费!E:E,维修费!C:C,C43) -> 260 | R43: =SUMIFS(磅单!R:R,磅单!F:F,B43) -> 7000 | S43: =SUMIFS(司机工资表!E:E,司机工资表!B:B,D43)+SUMIFS(司机工资表!N:N,司机工资表!B:B,D43) -> 0 | T43: =SUMIFS(付款明细!G:G,付款明细!D:D,B43,付款明细!B:B,"车队-罚款") -> 0 | U43: =SUMIFS(付款明细!G:G,付款明细!D:D,B43,付款明细!B:B,"车辆费用")+SUMIFS(付款明细!G:G,付款明细!D:D,C43,付款明细!B:B,"车辆费用") -> 175 | V43: =SUMIFS(付款明细!G:G,付款明细!B:B,"综合费用")/61 -> 397.39246 | W43: 2666 | X43: 3200 | Y43: =SUMIFS(磅单!P:P,磅单!E:E,B43) -> 150 | Z43: =H43*0.07-M43 -> 2169.6192 | AC43: =(管理人员工资!$D$10+管理人员工资!$E$10)/61 -> 790.16393 | AD43: =H43-I43-J43-N43-O43-R43-S43-T43-U43-V43-W43-AA43-AB43-AC43-Q43-P43-Z43-Y43-X43 -> 2381.2715
A44: 42 | B44: 粤B87855D | C44: 桂LD762挂 | D44: 马辉 | E44: 正常 | F44: =COUNTIFS(磅单!E:E,B44) -> 10 | G44: =SUMIFS(磅单!L:L,磅单!F:F,B44) -> 427.61 | H44: =SUMIFS(磅单!O:O,磅单!F:F,B44) -> 31830.41 | J44: =SUMIFS(现金充电明细!L:L,现金充电明细!B:B,B44)+SUMIFS('华瑞-曙光，大水井，老水井充电站'!L:L,'华瑞-曙光，大水井，老水井充电站'!B:B,B44)+SUMIFS('银盛-青龙坪充电站'!L:L,'银盛-青龙坪充电站'!B:B,B44)+SUMIFS('砚山锦佳-砚山充电站'!K:K,'砚山锦佳-砚山充电站'!B:B,B44)+SUMIFS(中石油广西百色靖西市龙临加油充电站!K:K,中石油广西百色靖西市龙临加油充电站!B:B,B44)+SUMIFS(德保众擎充电站!L:L,德保众擎充电站!B:B,B44)+SUMIFS(南网八宝充电站!K:K,南网八宝充电站!B:B,B44)+SUMIFS(南屏充电站!K:K,南屏充电站!B:B,B44)+SUMIFS(鑫鸿充电站!K:K,鑫鸿充电站!B:B,B44)+SUMIFS('锦田-百色田东充电站'!K:K,'锦田-百色田东充电站'!B:B,B44)+37.06/47+SUMIFS(平远充电站!K:K,平远充电站!B:B,B44) -> 12209.052 | K44: =J44/(H44) -> 0.38356566 | L44: =J44/F44 -> 1220.9052 | N44: =13473.8/61 -> 220.88197 | O44: =SUMIFS(轮胎!H:H,轮胎!D:D,B44)+SUMIFS(轮胎!H:H,轮胎!D:D,C44) -> 0 | P44: 0 | Q44: =SUMIFS(维修费!E:E,维修费!C:C,B44)+SUMIFS(维修费!E:E,维修费!C:C,C44) -> 0 | R44: =SUMIFS(磅单!R:R,磅单!F:F,B44) -> 7000 | S44: =SUMIFS(司机工资表!E:E,司机工资表!B:B,D44)+SUMIFS(司机工资表!N:N,司机工资表!B:B,D44) -> 200 | T44: =SUMIFS(付款明细!G:G,付款明细!D:D,B44,付款明细!B:B,"车队-罚款") -> 0 | U44: =SUMIFS(付款明细!G:G,付款明细!D:D,B44,付款明细!B:B,"车辆费用")+SUMIFS(付款明细!G:G,付款明细!D:D,C44,付款明细!B:B,"车辆费用") -> 194 | V44: =SUMIFS(付款明细!G:G,付款明细!B:B,"综合费用")/61 -> 397.39246 | W44: 2666 | X44: 3200 | Y44: =SUMIFS(磅单!P:P,磅单!E:E,B44) -> 150 | Z44: =H44*0.07-M44 -> 2228.1287 | AC44: =(管理人员工资!$D$10+管理人员工资!$E$10)/61 -> 790.16393 | AD44: =H44-I44-J44-N44-O44-R44-S44-T44-U44-V44-W44-AA44-AB44-AC44-Q44-P44-Z44-Y44-X44 -> 2574.7907
A45: 43 | B45: 粤B49365D | C45: 桂LC671挂 | D45: 兰荣建 | E45: 正常 | F45: =COUNTIFS(磅单!E:E,B45) -> 11 | G45: =SUMIFS(磅单!L:L,磅单!F:F,B45) -> 463.5 | H45: =SUMIFS(磅单!O:O,磅单!F:F,B45) -> 34892.06 | J45: =SUMIFS(现金充电明细!L:L,现金充电明细!B:B,B45)+SUMIFS('华瑞-曙光，大水井，老水井充电站'!L:L,'华瑞-曙光，大水井，老水井充电站'!B:B,B45)+SUMIFS('银盛-青龙坪充电站'!L:L,'银盛-青龙坪充电站'!B:B,B45)+SUMIFS('砚山锦佳-砚山充电站'!K:K,'砚山锦佳-砚山充电站'!B:B,B45)+SUMIFS(中石油广西百色靖西市龙临加油充电站!K:K,中石油广西百色靖西市龙临加油充电站!B:B,B45)+SUMIFS(德保众擎充电站!L:L,德保众擎充电站!B:B,B45)+SUMIFS(南网八宝充电站!K:K,南网八宝充电站!B:B,B45)+SUMIFS(南屏充电站!K:K,南屏充电站!B:B,B45)+SUMIFS(鑫鸿充电站!K:K,鑫鸿充电站!B:B,B45)+SUMIFS('锦田-百色田东充电站'!K:K,'锦田-百色田东充电站'!B:B,B45)+37.06/47+SUMIFS(平远充电站!K:K,平远充电站!B:B,B45) -> 11158.452 | K45: =J45/(H45) -> 0.31979916 | L45: =J45/F45 -> 1014.4047 | N45: =13473.8/61 -> 220.88197 | O45: =SUMIFS(轮胎!H:H,轮胎!D:D,B45)+SUMIFS(轮胎!H:H,轮胎!D:D,C45) -> 0 | P45: 0 | Q45: =SUMIFS(维修费!E:E,维修费!C:C,B45)+SUMIFS(维修费!E:E,维修费!C:C,C45) -> 60 | R45: =SUMIFS(磅单!R:R,磅单!F:F,B45) -> 7800 | S45: =SUMIFS(司机工资表!E:E,司机工资表!B:B,D45)+SUMIFS(司机工资表!N:N,司机工资表!B:B,D45) -> 0 | T45: =SUMIFS(付款明细!G:G,付款明细!D:D,B45,付款明细!B:B,"车队-罚款") -> 0 | U45: =SUMIFS(付款明细!G:G,付款明细!D:D,B45,付款明细!B:B,"车辆费用")+SUMIFS(付款明细!G:G,付款明细!D:D,C45,付款明细!B:B,"车辆费用") -> 173 | V45: =SUMIFS(付款明细!G:G,付款明细!B:B,"综合费用")/61 -> 397.39246 | W45: 2666 | X45: 2800 | Y45: =SUMIFS(磅单!P:P,磅单!E:E,B45) -> 150 | Z45: =H45*0.07-M45 -> 2442.4442 | AC45: =(管理人员工资!$D$10+管理人员工资!$E$10)/61 -> 790.16393 | AD45: =H45-I45-J45-N45-O45-R45-S45-T45-U45-V45-W45-AA45-AB45-AC45-Q45-P45-Z45-Y45-X45 -> 6233.7259
A46: 44 | B46: 粤B93372D | C46: 桂L0466挂 | D46: 玉圣杰 | E46: 正常 | F46: =COUNTIFS(磅单!E:E,B46) -> 12 | G46: =SUMIFS(磅单!L:L,磅单!F:F,B46) -> 507.05 | H46: =SUMIFS(磅单!O:O,磅单!F:F,B46) -> 38541.81 | J46: =SUMIFS(现金充电明细!L:L,现金充电明细!B:B,B46)+SUMIFS('华瑞-曙光，大水井，老水井充电站'!L:L,'华瑞-曙光，大水井，老水井充电站'!B:B,B46)+SUMIFS('银盛-青龙坪充电站'!L:L,'银盛-青龙坪充电站'!B:B,B46)+SUMIFS('砚山锦佳-砚山充电站'!K:K,'砚山锦佳-砚山充电站'!B:B,B46)+SUMIFS(中石油广西百色靖西市龙临加油充电站!K:K,中石油广西百色靖西市龙临加油充电站!B:B,B46)+SUMIFS(德保众擎充电站!L:L,德保众擎充电站!B:B,B46)+SUMIFS(南网八宝充电站!K:K,南网八宝充电站!B:B,B46)+SUMIFS(南屏充电站!K:K,南屏充电站!B:B,B46)+SUMIFS(鑫鸿充电站!K:K,鑫鸿充电站!B:B,B46)+SUMIFS('锦田-百色田东充电站'!K:K,'锦田-百色田东充电站'!B:B,B46)+37.06/47+SUMIFS(平远充电站!K:K,平远充电站!B:B,B46) -> 13784.637 | K46: =J46/(H46) -> 0.3576541 | L46: =J46/F46 -> 1148.7197 | N46: =13473.8/61 -> 220.88197 | O46: =SUMIFS(轮胎!H:H,轮胎!D:D,B46)+SUMIFS(轮胎!H:H,轮胎!D:D,C46) -> 0 | P46: 0 | Q46: =SUMIFS(维修费!E:E,维修费!C:C,B46)+SUMIFS(维修费!E:E,维修费!C:C,C46) -> 190 | R46: =SUMIFS(磅单!R:R,磅单!F:F,B46) -> 8600 | S46: =SUMIFS(司机工资表!E:E,司机工资表!B:B,D46)+SUMIFS(司机工资表!N:N,司机工资表!B:B,D46) -> 200 | T46: =SUMIFS(付款明细!G:G,付款明细!D:D,B46,付款明细!B:B,"车队-罚款") -> 200 | U46: =SUMIFS(付款明细!G:G,付款明细!D:D,B46,付款明细!B:B,"车辆费用")+SUMIFS(付款明细!G:G,付款明细!D:D,C46,付款明细!B:B,"车辆费用") -> 340 | V46: =SUMIFS(付款明细!G:G,付款明细!B:B,"综合费用")/61 -> 397.39246 | W46: 2666 | X46: 2800 | Y46: =SUMIFS(磅单!P:P,磅单!E:E,B46) -> 180 | Z46: =H46*0.07-M46 -> 2697.9267 | AC46: =(管理人员工资!$D$10+管理人员工资!$E$10)/61 -> 790.16393 | AD46: =H46-I46-J46-N46-O46-R46-S46-T46-U46-V46-W46-AA46-AB46-AC46-Q46-P46-Z46-Y46-X46 -> 5474.8084
A47: 45 | B47: 粤B41547D | C47: 桂LC701挂 | D47: 张克 | E47: 正常 | F47: =COUNTIFS(磅单!E:E,B47) -> 7 | G47: =SUMIFS(磅单!L:L,磅单!F:F,B47) -> 306.91 | H47: =SUMIFS(磅单!O:O,磅单!F:F,B47) -> 22716.15 | J47: =SUMIFS(现金充电明细!L:L,现金充电明细!B:B,B47)+SUMIFS('华瑞-曙光，大水井，老水井充电站'!L:L,'华瑞-曙光，大水井，老水井充电站'!B:B,B47)+SUMIFS('银盛-青龙坪充电站'!L:L,'银盛-青龙坪充电站'!B:B,B47)+SUMIFS('砚山锦佳-砚山充电站'!K:K,'砚山锦佳-砚山充电站'!B:B,B47)+SUMIFS(中石油广西百色靖西市龙临加油充电站!K:K,中石油广西百色靖西市龙临加油充电站!B:B,B47)+SUMIFS(德保众擎充电站!L:L,德保众擎充电站!B:B,B47)+SUMIFS(南网八宝充电站!K:K,南网八宝充电站!B:B,B47)+SUMIFS(南屏充电站!K:K,南屏充电站!B:B,B47)+SUMIFS(鑫鸿充电站!K:K,鑫鸿充电站!B:B,B47)+SUMIFS('锦田-百色田东充电站'!K:K,'锦田-百色田东充电站'!B:B,B47)+37.06/47+SUMIFS(平远充电站!K:K,平远充电站!B:B,B47) -> 8633.0998 | K47: =J47/(H47) -> 0.38004238 | L47: =J47/F47 -> 1233.3 | N47: =13473.8/61 -> 220.88197 | O47: =SUMIFS(轮胎!H:H,轮胎!D:D,B47)+SUMIFS(轮胎!H:H,轮胎!D:D,C47) -> 0 | P47: 0 | Q47: =SUMIFS(维修费!E:E,维修费!C:C,B47)+SUMIFS(维修费!E:E,维修费!C:C,C47) -> 0 | R47: =SUMIFS(磅单!R:R,磅单!F:F,B47) -> 5000 | S47: =SUMIFS(司机工资表!E:E,司机工资表!B:B,D47)+SUMIFS(司机工资表!N:N,司机工资表!B:B,D47) -> 200 | T47: =SUMIFS(付款明细!G:G,付款明细!D:D,B47,付款明细!B:B,"车队-罚款") -> 200 | U47: =SUMIFS(付款明细!G:G,付款明细!D:D,B47,付款明细!B:B,"车辆费用")+SUMIFS(付款明细!G:G,付款明细!D:D,C47,付款明细!B:B,"车辆费用") -> 190 | V47: =SUMIFS(付款明细!G:G,付款明细!B:B,"综合费用")/61 -> 397.39246 | W47: 2666 | X47: 2800 | Y47: =SUMIFS(磅单!P:P,磅单!E:E,B47) -> 105 | Z47: =H47*0.07-M47 -> 1590.1305 | AC47: =(管理人员工资!$D$10+管理人员工资!$E$10)/61 -> 790.16393 | AD47: =H47-I47-J47-N47-O47-R47-S47-T47-U47-V47-W47-AA47-AB47-AC47-Q47-P47-Z47-Y47-X47 -> -76.518671
A48: 46 | B48: 粤B94652D | C48: 桂L5408挂 | D48: 李张红 | E48: 正常 | F48: =COUNTIFS(磅单!E:E,B48) -> 7 | G48: =SUMIFS(磅单!L:L,磅单!F:F,B48) -> 304.92 | H48: =SUMIFS(磅单!O:O,磅单!F:F,B48) -> 20903.86 | J48: =SUMIFS(现金充电明细!L:L,现金充电明细!B:B,B48)+SUMIFS('华瑞-曙光，大水井，老水井充电站'!L:L,'华瑞-曙光，大水井，老水井充电站'!B:B,B48)+SUMIFS('银盛-青龙坪充电站'!L:L,'银盛-青龙坪充电站'!B:B,B48)+SUMIFS('砚山锦佳-砚山充电站'!K:K,'砚山锦佳-砚山充电站'!B:B,B48)+SUMIFS(中石油广西百色靖西市龙临加油充电站!K:K,中石油广西百色靖西市龙临加油充电站!B:B,B48)+SUMIFS(德保众擎充电站!L:L,德保众擎充电站!B:B,B48)+SUMIFS(南网八宝充电站!K:K,南网八宝充电站!B:B,B48)+SUMIFS(南屏充电站!K:K,南屏充电站!B:B,B48)+SUMIFS(鑫鸿充电站!K:K,鑫鸿充电站!B:B,B48)+SUMIFS('锦田-百色田东充电站'!K:K,'锦田-百色田东充电站'!B:B,B48)+37.06/47+SUMIFS(平远充电站!K:K,平远充电站!B:B,B48) -> 7254.3167 | K48: =J48/(H48) -> 0.3470324 | L48: =J48/F48 -> 1036.331 | N48: =13473.8/61 -> 220.88197 | O48: =SUMIFS(轮胎!H:H,轮胎!D:D,B48)+SUMIFS(轮胎!H:H,轮胎!D:D,C48) -> 0 | P48: 0 | Q48: =SUMIFS(维修费!E:E,维修费!C:C,B48)+SUMIFS(维修费!E:E,维修费!C:C,C48) -> 0 | R48: =SUMIFS(磅单!R:R,磅单!F:F,B48) -> 4600 | S48: =SUMIFS(司机工资表!E:E,司机工资表!B:B,D48)+SUMIFS(司机工资表!N:N,司机工资表!B:B,D48) -> 0 | T48: =SUMIFS(付款明细!G:G,付款明细!D:D,B48,付款明细!B:B,"车队-罚款") -> 40 | U48: =SUMIFS(付款明细!G:G,付款明细!D:D,B48,付款明细!B:B,"车辆费用")+SUMIFS(付款明细!G:G,付款明细!D:D,C48,付款明细!B:B,"车辆费用") -> 179 | V48: =SUMIFS(付款明细!G:G,付款明细!B:B,"综合费用")/61 -> 397.39246 | W48: 2666 | X48: 2800 | Y48: =SUMIFS(磅单!P:P,磅单!E:E,B48) -> 105 | Z48: =H48*0.07-M48 -> 1463.2702 | AC48: =(管理人员工资!$D$10+管理人员工资!$E$10)/61 -> 790.16393 | AD48: =H48-I48-J48-N48-O48-R48-S48-T48-U48-V48-W48-AA48-AB48-AC48-Q48-P48-Z48-Y48-X48 -> 387.83473
A49: 47 | B49: 粤B98145D | C49: 桂L5163挂 | D49: 汪良友 | E49: 正常 | F49: =COUNTIFS(磅单!E:E,B49) -> 6 | G49: =SUMIFS(磅单!L:L,磅单!F:F,B49) -> 264.06 | H49: =SUMIFS(磅单!O:O,磅单!F:F,B49) -> 18529.74 | J49: =SUMIFS(现金充电明细!L:L,现金充电明细!B:B,B49)+SUMIFS('华瑞-曙光，大水井，老水井充电站'!L:L,'华瑞-曙光，大水井，老水井充电站'!B:B,B49)+SUMIFS('银盛-青龙坪充电站'!L:L,'银盛-青龙坪充电站'!B:B,B49)+SUMIFS('砚山锦佳-砚山充电站'!K:K,'砚山锦佳-砚山充电站'!B:B,B49)+SUMIFS(中石油广西百色靖西市龙临加油充电站!K:K,中石油广西百色靖西市龙临加油充电站!B:B,B49)+SUMIFS(德保众擎充电站!L:L,德保众擎充电站!B:B,B49)+SUMIFS(南网八宝充电站!K:K,南网八宝充电站!B:B,B49)+SUMIFS(南屏充电站!K:K,南屏充电站!B:B,B49)+SUMIFS(鑫鸿充电站!K:K,鑫鸿充电站!B:B,B49)+SUMIFS('锦田-百色田东充电站'!K:K,'锦田-百色田东充电站'!B:B,B49)+37.06/47+SUMIFS(平远充电站!K:K,平远充电站!B:B,B49) -> 8196.1785 | K49: =J49/(H49) -> 0.44232561 | L49: =J49/F49 -> 1366.0298 | N49: =13473.8/61 -> 220.88197 | O49: =SUMIFS(轮胎!H:H,轮胎!D:D,B49)+SUMIFS(轮胎!H:H,轮胎!D:D,C49) -> 0 | P49: 0 | Q49: =SUMIFS(维修费!E:E,维修费!C:C,B49)+SUMIFS(维修费!E:E,维修费!C:C,C49) -> 60 | R49: =SUMIFS(磅单!R:R,磅单!F:F,B49) -> 4000 | S49: =SUMIFS(司机工资表!E:E,司机工资表!B:B,D49)+SUMIFS(司机工资表!N:N,司机工资表!B:B,D49) -> 0 | T49: =SUMIFS(付款明细!G:G,付款明细!D:D,B49,付款明细!B:B,"车队-罚款") -> 20 | U49: =SUMIFS(付款明细!G:G,付款明细!D:D,B49,付款明细!B:B,"车辆费用")+SUMIFS(付款明细!G:G,付款明细!D:D,C49,付款明细!B:B,"车辆费用") -> 151 | V49: =SUMIFS(付款明细!G:G,付款明细!B:B,"综合费用")/61 -> 397.39246 | W49: 2666 | X49: 2800 | Y49: =SUMIFS(磅单!P:P,磅单!E:E,B49) -> 90 | Z49: =H49*0.07-M49 -> 1297.0818 | AC49: =(管理人员工资!$D$10+管理人员工资!$E$10)/61 -> 790.16393 | AD49: =H49-I49-J49-N49-O49-R49-S49-T49-U49-V49-W49-AA49-AB49-AC49-Q49-P49-Z49-Y49-X49 -> -2158.9587
A50: 48 | B50: 粤B96063D | C50: 桂LB192挂 | D50: 陆光锐 | E50: 正常 | F50: =COUNTIFS(磅单!E:E,B50) -> 8 | G50: =SUMIFS(磅单!L:L,磅单!F:F,B50) -> 343.69 | H50: =SUMIFS(磅单!O:O,磅单!F:F,B50) -> 22105.89 | J50: =SUMIFS(现金充电明细!L:L,现金充电明细!B:B,B50)+SUMIFS('华瑞-曙光，大水井，老水井充电站'!L:L,'华瑞-曙光，大水井，老水井充电站'!B:B,B50)+SUMIFS('银盛-青龙坪充电站'!L:L,'银盛-青龙坪充电站'!B:B,B50)+SUMIFS('砚山锦佳-砚山充电站'!K:K,'砚山锦佳-砚山充电站'!B:B,B50)+SUMIFS(中石油广西百色靖西市龙临加油充电站!K:K,中石油广西百色靖西市龙临加油充电站!B:B,B50)+SUMIFS(德保众擎充电站!L:L,德保众擎充电站!B:B,B50)+SUMIFS(南网八宝充电站!K:K,南网八宝充电站!B:B,B50)+SUMIFS(南屏充电站!K:K,南屏充电站!B:B,B50)+SUMIFS(鑫鸿充电站!K:K,鑫鸿充电站!B:B,B50)+SUMIFS('锦田-百色田东充电站'!K:K,'锦田-百色田东充电站'!B:B,B50)+37.06/47+SUMIFS(平远充电站!K:K,平远充电站!B:B,B50) -> 7639.6485 | K50: =J50/(H50) -> 0.34559335 | L50: =J50/F50 -> 954.95606 | N50: =13473.8/61 -> 220.88197 | O50: =SUMIFS(轮胎!H:H,轮胎!D:D,B50)+SUMIFS(轮胎!H:H,轮胎!D:D,C50) -> 0 | P50: 0 | Q50: =SUMIFS(维修费!E:E,维修费!C:C,B50)+SUMIFS(维修费!E:E,维修费!C:C,C50) -> 0 | R50: =SUMIFS(磅单!R:R,磅单!F:F,B50) -> 5000 | S50: =SUMIFS(司机工资表!E:E,司机工资表!B:B,D50)+SUMIFS(司机工资表!N:N,司机工资表!B:B,D50) -> 0 | T50: =SUMIFS(付款明细!G:G,付款明细!D:D,B50,付款明细!B:B,"车队-罚款") -> 0 | U50: =SUMIFS(付款明细!G:G,付款明细!D:D,B50,付款明细!B:B,"车辆费用")+SUMIFS(付款明细!G:G,付款明细!D:D,C50,付款明细!B:B,"车辆费用") -> 90 | V50: =SUMIFS(付款明细!G:G,付款明细!B:B,"综合费用")/61 -> 397.39246 | W50: 2666 | X50: 3600 | Y50: =SUMIFS(磅单!P:P,磅单!E:E,B50) -> 120 | Z50: =H50*0.07-M50 -> 1547.4123 | AC50: =(管理人员工资!$D$10+管理人员工资!$E$10)/61 -> 790.16393 | AD50: =H50-I50-J50-N50-O50-R50-S50-T50-U50-V50-W50-AA50-AB50-AC50-Q50-P50-Z50-Y50-X50 -> 34.390829
A51: 49 | B51: 粤B96373D | C51: 桂LE571挂 | D51: 高克禹 | E51: 正常 | F51: =COUNTIFS(磅单!E:E,B51) -> 7 | G51: =SUMIFS(磅单!L:L,磅单!F:F,B51) -> 300.53 | H51: =SUMIFS(磅单!O:O,磅单!F:F,B51) -> 22774.69 | J51: =SUMIFS(现金充电明细!L:L,现金充电明细!B:B,B51)+SUMIFS('华瑞-曙光，大水井，老水井充电站'!L:L,'华瑞-曙光，大水井，老水井充电站'!B:B,B51)+SUMIFS('银盛-青龙坪充电站'!L:L,'银盛-青龙坪充电站'!B:B,B51)+SUMIFS('砚山锦佳-砚山充电站'!K:K,'砚山锦佳-砚山充电站'!B:B,B51)+SUMIFS(中石油广西百色靖西市龙临加油充电站!K:K,中石油广西百色靖西市龙临加油充电站!B:B,B51)+SUMIFS(德保众擎充电站!L:L,德保众擎充电站!B:B,B51)+SUMIFS(南网八宝充电站!K:K,南网八宝充电站!B:B,B51)+SUMIFS(南屏充电站!K:K,南屏充电站!B:B,B51)+SUMIFS(鑫鸿充电站!K:K,鑫鸿充电站!B:B,B51)+SUMIFS('锦田-百色田东充电站'!K:K,'锦田-百色田东充电站'!B:B,B51)+37.06/47+SUMIFS(平远充电站!K:K,平远充电站!B:B,B51) -> 6947.4685 | K51: =J51/(H51) -> 0.30505217 | L51: =J51/F51 -> 992.4955 | N51: =13473.8/61 -> 220.88197 | O51: =SUMIFS(轮胎!H:H,轮胎!D:D,B51)+SUMIFS(轮胎!H:H,轮胎!D:D,C51) -> 0 | P51: 0 | Q51: =SUMIFS(维修费!E:E,维修费!C:C,B51)+SUMIFS(维修费!E:E,维修费!C:C,C51) -> 120 | R51: =SUMIFS(磅单!R:R,磅单!F:F,B51) -> 5000 | S51: =SUMIFS(司机工资表!E:E,司机工资表!B:B,D51)+SUMIFS(司机工资表!N:N,司机工资表!B:B,D51) -> 0 | T51: =SUMIFS(付款明细!G:G,付款明细!D:D,B51,付款明细!B:B,"车队-罚款") -> 0 | U51: =SUMIFS(付款明细!G:G,付款明细!D:D,B51,付款明细!B:B,"车辆费用")+SUMIFS(付款明细!G:G,付款明细!D:D,C51,付款明细!B:B,"车辆费用") -> 105 | V51: =SUMIFS(付款明细!G:G,付款明细!B:B,"综合费用")/61 -> 397.39246 | W51: 2666 | X51: 3600 | Y51: =SUMIFS(磅单!P:P,磅单!E:E,B51) -> 105 | Z51: =H51*0.07-M51 -> 1594.2283 | AC51: =(管理人员工资!$D$10+管理人员工资!$E$10)/61 -> 790.16393 | AD51: =H51-I51-J51-N51-O51-R51-S51-T51-U51-V51-W51-AA51-AB51-AC51-Q51-P51-Z51-Y51-X51 -> 1228.5548
A52: 50 | B52: 粤B94050D | C52: 桂LE017挂 | D52: 周本兴 | E52: 正常 | F52: =COUNTIFS(磅单!E:E,B52) -> 4 | G52: =SUMIFS(磅单!L:L,磅单!F:F,B52) -> 172.36 | H52: =SUMIFS(磅单!O:O,磅单!F:F,B52) -> 12133.5 | J52: =SUMIFS(现金充电明细!L:L,现金充电明细!B:B,B52)+SUMIFS('华瑞-曙光，大水井，老水井充电站'!L:L,'华瑞-曙光，大水井，老水井充电站'!B:B,B52)+SUMIFS('银盛-青龙坪充电站'!L:L,'银盛-青龙坪充电站'!B:B,B52)+SUMIFS('砚山锦佳-砚山充电站'!K:K,'砚山锦佳-砚山充电站'!B:B,B52)+SUMIFS(中石油广西百色靖西市龙临加油充电站!K:K,中石油广西百色靖西市龙临加油充电站!B:B,B52)+SUMIFS(德保众擎充电站!L:L,德保众擎充电站!B:B,B52)+SUMIFS(南网八宝充电站!K:K,南网八宝充电站!B:B,B52)+SUMIFS(南屏充电站!K:K,南屏充电站!B:B,B52)+SUMIFS(鑫鸿充电站!K:K,鑫鸿充电站!B:B,B52)+SUMIFS('锦田-百色田东充电站'!K:K,'锦田-百色田东充电站'!B:B,B52)+37.06/47+SUMIFS(平远充电站!K:K,平远充电站!B:B,B52) -> 5978.9385 | K52: =J52/(H52) -> 0.49276289 | L52: =J52/F52 -> 1494.7346 | N52: =13473.8/61 -> 220.88197 | O52: =SUMIFS(轮胎!H:H,轮胎!D:D,B52)+SUMIFS(轮胎!H:H,轮胎!D:D,C52) -> 1050 | P52: 0 | Q52: =SUMIFS(维修费!E:E,维修费!C:C,B52)+SUMIFS(维修费!E:E,维修费!C:C,C52) -> 50 | R52: =SUMIFS(磅单!R:R,磅单!F:F,B52) -> 2800 | S52: =SUMIFS(司机工资表!E:E,司机工资表!B:B,D52)+SUMIFS(司机工资表!N:N,司机工资表!B:B,D52) -> 0 | T52: =SUMIFS(付款明细!G:G,付款明细!D:D,B52,付款明细!B:B,"车队-罚款") -> 200 | U52: =SUMIFS(付款明细!G:G,付款明细!D:D,B52,付款明细!B:B,"车辆费用")+SUMIFS(付款明细!G:G,付款明细!D:D,C52,付款明细!B:B,"车辆费用") -> 204 | V52: =SUMIFS(付款明细!G:G,付款明细!B:B,"综合费用")/61 -> 397.39246 | W52: 2666 | X52: 3600 | Y52: =SUMIFS(磅单!P:P,磅单!E:E,B52) -> 60 | Z52: =H52*0.07-M52 -> 849.345 | AC52: =(管理人员工资!$D$10+管理人员工资!$E$10)/61 -> 790.16393 | AD52: =H52-I52-J52-N52-O52-R52-S52-T52-U52-V52-W52-AA52-AB52-AC52-Q52-P52-Z52-Y52-X52 -> -6733.2219
A53: 51 | B53: 粤B98382D | C53: 桂L7502挂 | D53: 尹绍族 | E53: 正常 | F53: =COUNTIFS(磅单!E:E,B53) -> 4 | G53: =SUMIFS(磅单!L:L,磅单!F:F,B53) -> 179.06 | H53: =SUMIFS(磅单!O:O,磅单!F:F,B53) -> 11225.4 | J53: =SUMIFS(现金充电明细!L:L,现金充电明细!B:B,B53)+SUMIFS('华瑞-曙光，大水井，老水井充电站'!L:L,'华瑞-曙光，大水井，老水井充电站'!B:B,B53)+SUMIFS('银盛-青龙坪充电站'!L:L,'银盛-青龙坪充电站'!B:B,B53)+SUMIFS('砚山锦佳-砚山充电站'!K:K,'砚山锦佳-砚山充电站'!B:B,B53)+SUMIFS(中石油广西百色靖西市龙临加油充电站!K:K,中石油广西百色靖西市龙临加油充电站!B:B,B53)+SUMIFS(德保众擎充电站!L:L,德保众擎充电站!B:B,B53)+SUMIFS(南网八宝充电站!K:K,南网八宝充电站!B:B,B53)+SUMIFS(南屏充电站!K:K,南屏充电站!B:B,B53)+SUMIFS(鑫鸿充电站!K:K,鑫鸿充电站!B:B,B53)+SUMIFS('锦田-百色田东充电站'!K:K,'锦田-百色田东充电站'!B:B,B53)+37.06/47+SUMIFS(平远充电站!K:K,平远充电站!B:B,B53) -> 6039.1485 | K53: =J53/(H53) -> 0.5379896 | L53: =J53/F53 -> 1509.7871 | N53: =13473.8/61 -> 220.88197 | O53: =SUMIFS(轮胎!H:H,轮胎!D:D,B53)+SUMIFS(轮胎!H:H,轮胎!D:D,C53) -> 0 | P53: 0 | Q53: =SUMIFS(维修费!E:E,维修费!C:C,B53)+SUMIFS(维修费!E:E,维修费!C:C,C53) -> 0 | R53: =SUMIFS(磅单!R:R,磅单!F:F,B53) -> 2600 | S53: =SUMIFS(司机工资表!E:E,司机工资表!B:B,D53)+SUMIFS(司机工资表!N:N,司机工资表!B:B,D53) -> 0 | T53: =SUMIFS(付款明细!G:G,付款明细!D:D,B53,付款明细!B:B,"车队-罚款") -> 0 | U53: =SUMIFS(付款明细!G:G,付款明细!D:D,B53,付款明细!B:B,"车辆费用")+SUMIFS(付款明细!G:G,付款明细!D:D,C53,付款明细!B:B,"车辆费用") -> 183 | V53: =SUMIFS(付款明细!G:G,付款明细!B:B,"综合费用")/61 -> 397.39246 | W53: 2666 | X53: 3600 | Y53: =SUMIFS(磅单!P:P,磅单!E:E,B53) -> 60 | Z53: =H53*0.07-M53 -> 785.778 | AC53: =(管理人员工资!$D$10+管理人员工资!$E$10)/61 -> 790.16393 | AD53: =H53-I53-J53-N53-O53-R53-S53-T53-U53-V53-W53-AA53-AB53-AC53-Q53-P53-Z53-Y53-X53 -> -6116.9649
A54: 52 | B54: 粤B93345D | C54: 桂LE683挂 | D54: 李云聪 | E54: 正常 | F54: =COUNTIFS(磅单!E:E,B54) -> 4 | G54: =SUMIFS(磅单!L:L,磅单!F:F,B54) -> 169.5 | H54: =SUMIFS(磅单!O:O,磅单!F:F,B54) -> 13067.94 | J54: =SUMIFS(现金充电明细!L:L,现金充电明细!B:B,B54)+SUMIFS('华瑞-曙光，大水井，老水井充电站'!L:L,'华瑞-曙光，大水井，老水井充电站'!B:B,B54)+SUMIFS('银盛-青龙坪充电站'!L:L,'银盛-青龙坪充电站'!B:B,B54)+SUMIFS('砚山锦佳-砚山充电站'!K:K,'砚山锦佳-砚山充电站'!B:B,B54)+SUMIFS(中石油广西百色靖西市龙临加油充电站!K:K,中石油广西百色靖西市龙临加油充电站!B:B,B54)+SUMIFS(德保众擎充电站!L:L,德保众擎充电站!B:B,B54)+SUMIFS(南网八宝充电站!K:K,南网八宝充电站!B:B,B54)+SUMIFS(南屏充电站!K:K,南屏充电站!B:B,B54)+SUMIFS(鑫鸿充电站!K:K,鑫鸿充电站!B:B,B54)+SUMIFS('锦田-百色田东充电站'!K:K,'锦田-百色田东充电站'!B:B,B54)+37.06/47+SUMIFS(平远充电站!K:K,平远充电站!B:B,B54) -> 5560.7085 | K54: =J54/(H54) -> 0.42552296 | L54: =J54/F54 -> 1390.1771 | N54: =13473.8/61 -> 220.88197 | O54: =SUMIFS(轮胎!H:H,轮胎!D:D,B54)+SUMIFS(轮胎!H:H,轮胎!D:D,C54) -> 0 | P54: 0 | Q54: =SUMIFS(维修费!E:E,维修费!C:C,B54)+SUMIFS(维修费!E:E,维修费!C:C,C54) -> 0 | R54: =SUMIFS(磅单!R:R,磅单!F:F,B54) -> 3000 | S54: =SUMIFS(司机工资表!E:E,司机工资表!B:B,D54)+SUMIFS(司机工资表!N:N,司机工资表!B:B,D54) -> 0 | T54: =SUMIFS(付款明细!G:G,付款明细!D:D,B54,付款明细!B:B,"车队-罚款") -> 0 | U54: =SUMIFS(付款明细!G:G,付款明细!D:D,B54,付款明细!B:B,"车辆费用")+SUMIFS(付款明细!G:G,付款明细!D:D,C54,付款明细!B:B,"车辆费用") -> 113 | V54: =SUMIFS(付款明细!G:G,付款明细!B:B,"综合费用")/61 -> 397.39246 | W54: 2666 | X54: 3600 | Y54: =SUMIFS(磅单!P:P,磅单!E:E,B54) -> 60 | Z54: =H54*0.07-M54 -> 914.7558 | AC54: =(管理人员工资!$D$10+管理人员工资!$E$10)/61 -> 790.16393 | AD54: =H54-I54-J54-N54-O54-R54-S54-T54-U54-V54-W54-AA54-AB54-AC54-Q54-P54-Z54-Y54-X54 -> -4254.9627
... A56: 54 | B56: 粤B91025D | C56: 桂L8685挂 | D56: 陆杰 | E56: 正常 | F56: =COUNTIFS(磅单!E:E,B56) -> 3 | G56: =SUMIFS(磅单!L:L,磅单!F:F,B56) -> 132.56 | H56: =SUMIFS(磅单!O:O,磅单!F:F,B56) -> 9437.6 | J56: =SUMIFS(现金充电明细!L:L,现金充电明细!B:B,B56)+SUMIFS('华瑞-曙光，大水井，老水井充电站'!L:L,'华瑞-曙光，大水井，老水井充电站'!B:B,B56)+SUMIFS('银盛-青龙坪充电站'!L:L,'银盛-青龙坪充电站'!B:B,B56)+SUMIFS('砚山锦佳-砚山充电站'!K:K,'砚山锦佳-砚山充电站'!B:B,B56)+SUMIFS(中石油广西百色靖西市龙临加油充电站!K:K,中石油广西百色靖西市龙临加油充电站!B:B,B56)+SUMIFS(德保众擎充电站!L:L,德保众擎充电站!B:B,B56)+SUMIFS(南网八宝充电站!K:K,南网八宝充电站!B:B,B56)+SUMIFS(南屏充电站!K:K,南屏充电站!B:B,B56)+SUMIFS(鑫鸿充电站!K:K,鑫鸿充电站!B:B,B56)+SUMIFS('锦田-百色田东充电站'!K:K,'锦田-百色田东充电站'!B:B,B56)+37.06/47+SUMIFS(平远充电站!K:K,平远充电站!B:B,B56) -> 5155.1585 | K56: =J56/(H56) -> 0.54623617 | L56: =J56/F56 -> 1718.3862 | N56: =13473.8/61 -> 220.88197 | O56: =SUMIFS(轮胎!H:H,轮胎!D:D,B56)+SUMIFS(轮胎!H:H,轮胎!D:D,C56) -> 0 | P56: 0 | Q56: =SUMIFS(维修费!E:E,维修费!C:C,B56)+SUMIFS(维修费!E:E,维修费!C:C,C56) -> 0 | R56: =SUMIFS(磅单!R:R,磅单!F:F,B56) -> 2000 | S56: =SUMIFS(司机工资表!E:E,司机工资表!B:B,D56)+SUMIFS(司机工资表!N:N,司机工资表!B:B,D56) -> 0 | T56: =SUMIFS(付款明细!G:G,付款明细!D:D,B56,付款明细!B:B,"车队-罚款") -> 0 | U56: =SUMIFS(付款明细!G:G,付款明细!D:D,B56,付款明细!B:B,"车辆费用")+SUMIFS(付款明细!G:G,付款明细!D:D,C56,付款明细!B:B,"车辆费用") -> 52 | V56: =SUMIFS(付款明细!G:G,付款明细!B:B,"综合费用")/61 -> 397.39246 | W56: 2666 | X56: 3600 | Y56: =SUMIFS(磅单!P:P,磅单!E:E,B56) -> 45 | Z56: =H56*0.07-M56 -> 660.632 | AC56: =(管理人员工资!$D$10+管理人员工资!$E$10)/61 -> 790.16393 | AD56: =H56-I56-J56-N56-O56-R56-S56-T56-U56-V56-W56-AA56-AB56-AC56-Q56-P56-Z56-Y56-X56 -> -6149.6289
A57: 55 | B57: 粤B94092D | C57: 桂L6496挂 | D57: 马全伟 | E57: 整备 | F57: =COUNTIFS(磅单!E:E,B57) -> 5 | G57: =SUMIFS(磅单!L:L,磅单!F:F,B57) -> 217.46 | H57: =SUMIFS(磅单!O:O,磅单!F:F,B57) -> 14219.62 | J57: =SUMIFS(现金充电明细!L:L,现金充电明细!B:B,B57)+SUMIFS('华瑞-曙光，大水井，老水井充电站'!L:L,'华瑞-曙光，大水井，老水井充电站'!B:B,B57)+SUMIFS('银盛-青龙坪充电站'!L:L,'银盛-青龙坪充电站'!B:B,B57)+SUMIFS('砚山锦佳-砚山充电站'!K:K,'砚山锦佳-砚山充电站'!B:B,B57)+SUMIFS(中石油广西百色靖西市龙临加油充电站!K:K,中石油广西百色靖西市龙临加油充电站!B:B,B57)+SUMIFS(德保众擎充电站!L:L,德保众擎充电站!B:B,B57)+SUMIFS(南网八宝充电站!K:K,南网八宝充电站!B:B,B57)+SUMIFS(南屏充电站!K:K,南屏充电站!B:B,B57)+SUMIFS(鑫鸿充电站!K:K,鑫鸿充电站!B:B,B57)+SUMIFS('锦田-百色田东充电站'!K:K,'锦田-百色田东充电站'!B:B,B57)+37.06/47+SUMIFS(平远充电站!K:K,平远充电站!B:B,B57) -> 4658.5885 | N57: =13473.8/61 -> 220.88197 | O57: =SUMIFS(轮胎!H:H,轮胎!D:D,B57)+SUMIFS(轮胎!H:H,轮胎!D:D,C57) -> 0 | P57: 0 | Q57: =SUMIFS(维修费!E:E,维修费!C:C,B57)+SUMIFS(维修费!E:E,维修费!C:C,C57) -> 15 | R57: =SUMIFS(磅单!R:R,磅单!F:F,B57) -> 3200 | S57: =SUMIFS(司机工资表!E:E,司机工资表!B:B,D57)+SUMIFS(司机工资表!N:N,司机工资表!B:B,D57) -> 0 | T57: =SUMIFS(付款明细!G:G,付款明细!D:D,B57,付款明细!B:B,"车队-罚款") -> 0 | U57: =SUMIFS(付款明细!G:G,付款明细!D:D,B57,付款明细!B:B,"车辆费用")+SUMIFS(付款明细!G:G,付款明细!D:D,C57,付款明细!B:B,"车辆费用") -> 111 | V57: =SUMIFS(付款明细!G:G,付款明细!B:B,"综合费用")/61 -> 397.39246 | W57: 2666 | X57: 3600 | Y57: =SUMIFS(磅单!P:P,磅单!E:E,B57) -> 75 | Z57: =H57*0.07-M57 -> 995.3734 | AC57: =(管理人员工资!$D$10+管理人员工资!$E$10)/61 -> 790.16393 | AD57: =H57-I57-J57-N57-O57-R57-S57-T57-U57-V57-W57-AA57-AB57-AC57-Q57-P57-Z57-Y57-X57 -> -2509.7803
A58: 56 | B58: 粤B95241D | C58: 桂LC873挂 | D58: 纳存江 | E58: 整备 | F58: =COUNTIFS(磅单!E:E,B58) -> 5 | G58: =SUMIFS(磅单!L:L,磅单!F:F,B58) -> 213.55 | H58: =SUMIFS(磅单!O:O,磅单!F:F,B58) -> 14014.69 | J58: =SUMIFS(现金充电明细!L:L,现金充电明细!B:B,B58)+SUMIFS('华瑞-曙光，大水井，老水井充电站'!L:L,'华瑞-曙光，大水井，老水井充电站'!B:B,B58)+SUMIFS('银盛-青龙坪充电站'!L:L,'银盛-青龙坪充电站'!B:B,B58)+SUMIFS('砚山锦佳-砚山充电站'!K:K,'砚山锦佳-砚山充电站'!B:B,B58)+SUMIFS(中石油广西百色靖西市龙临加油充电站!K:K,中石油广西百色靖西市龙临加油充电站!B:B,B58)+SUMIFS(德保众擎充电站!L:L,德保众擎充电站!B:B,B58)+SUMIFS(南网八宝充电站!K:K,南网八宝充电站!B:B,B58)+SUMIFS(南屏充电站!K:K,南屏充电站!B:B,B58)+SUMIFS(鑫鸿充电站!K:K,鑫鸿充电站!B:B,B58)+SUMIFS('锦田-百色田东充电站'!K:K,'锦田-百色田东充电站'!B:B,B58)+37.06/47+SUMIFS(平远充电站!K:K,平远充电站!B:B,B58) -> 4891.6085 | N58: =13473.8/61 -> 220.88197 | O58: =SUMIFS(轮胎!H:H,轮胎!D:D,B58)+SUMIFS(轮胎!H:H,轮胎!D:D,C58) -> 0 | P58: 0 | Q58: =SUMIFS(维修费!E:E,维修费!C:C,B58)+SUMIFS(维修费!E:E,维修费!C:C,C58) -> 10 | R58: =SUMIFS(磅单!R:R,磅单!F:F,B58) -> 3200 | S58: =SUMIFS(司机工资表!E:E,司机工资表!B:B,D58)+SUMIFS(司机工资表!N:N,司机工资表!B:B,D58) -> 0 | T58: =SUMIFS(付款明细!G:G,付款明细!D:D,B58,付款明细!B:B,"车队-罚款") -> 0 | U58: =SUMIFS(付款明细!G:G,付款明细!D:D,B58,付款明细!B:B,"车辆费用")+SUMIFS(付款明细!G:G,付款明细!D:D,C58,付款明细!B:B,"车辆费用") -> 141 | V58: =SUMIFS(付款明细!G:G,付款明细!B:B,"综合费用")/61 -> 397.39246 | W58: 2666 | X58: 3600 | Y58: =SUMIFS(磅单!P:P,磅单!E:E,B58) -> 75 | Z58: =H58*0.07-M58 -> 981.0283 | AC58: =(管理人员工资!$D$10+管理人员工资!$E$10)/61 -> 790.16393 | AD58: =H58-I58-J58-N58-O58-R58-S58-T58-U58-V58-W58-AA58-AB58-AC58-Q58-P58-Z58-Y58-X58 -> -2958.3852
A59: 57 | B59: 粤B92439D | C59: 桂L7761挂 | E59: 整备 | F59: =COUNTIFS(磅单!E:E,B59) -> 1 | G59: =SUMIFS(磅单!L:L,磅单!F:F,B59) -> 44.38 | H59: =SUMIFS(磅单!O:O,磅单!F:F,B59) -> 2973.46 | J59: =SUMIFS(现金充电明细!L:L,现金充电明细!B:B,B59)+SUMIFS('华瑞-曙光，大水井，老水井充电站'!L:L,'华瑞-曙光，大水井，老水井充电站'!B:B,B59)+SUMIFS('银盛-青龙坪充电站'!L:L,'银盛-青龙坪充电站'!B:B,B59)+SUMIFS('砚山锦佳-砚山充电站'!K:K,'砚山锦佳-砚山充电站'!B:B,B59)+SUMIFS(中石油广西百色靖西市龙临加油充电站!K:K,中石油广西百色靖西市龙临加油充电站!B:B,B59)+SUMIFS(德保众擎充电站!L:L,德保众擎充电站!B:B,B59)+SUMIFS(南网八宝充电站!K:K,南网八宝充电站!B:B,B59)+SUMIFS(南屏充电站!K:K,南屏充电站!B:B,B59)+SUMIFS(鑫鸿充电站!K:K,鑫鸿充电站!B:B,B59)+SUMIFS('锦田-百色田东充电站'!K:K,'锦田-百色田东充电站'!B:B,B59)+37.06/47+SUMIFS(平远充电站!K:K,平远充电站!B:B,B59) -> 1830.1877 | N59: =13473.8/61 -> 220.88197 | O59: =SUMIFS(轮胎!H:H,轮胎!D:D,B59)+SUMIFS(轮胎!H:H,轮胎!D:D,C59) -> 0 | P59: 0 | Q59: =SUMIFS(维修费!E:E,维修费!C:C,B59)+SUMIFS(维修费!E:E,维修费!C:C,C59) -> 0 | R59: =SUMIFS(磅单!R:R,磅单!F:F,B59) -> 600 | S59: =SUMIFS(司机工资表!E:E,司机工资表!B:B,D59)+SUMIFS(司机工资表!N:N,司机工资表!B:B,D59) -> 0 | T59: =SUMIFS(付款明细!G:G,付款明细!D:D,B59,付款明细!B:B,"车队-罚款") -> 0 | U59: =SUMIFS(付款明细!G:G,付款明细!D:D,B59,付款明细!B:B,"车辆费用")+SUMIFS(付款明细!G:G,付款明细!D:D,C59,付款明细!B:B,"车辆费用") -> 15 | V59: =SUMIFS(付款明细!G:G,付款明细!B:B,"综合费用")/61 -> 397.39246 | W59: 2666 | X59: 3600 | Y59: =SUMIFS(磅单!P:P,磅单!E:E,B59) -> 15 | Z59: =H59*0.07-M59 -> 208.1422 | AC59: =(管理人员工资!$D$10+管理人员工资!$E$10)/61 -> 790.16393 | AD59: =H59-I59-J59-N59-O59-R59-S59-T59-U59-V59-W59-AA59-AB59-AC59-Q59-P59-Z59-Y59-X59 -> -7369.3083
A60: 58 | B60: 粤B98790D | C60: 桂L5346挂 | E60: 整备 | F60: =COUNTIFS(磅单!E:E,B60) -> 4 | G60: =SUMIFS(磅单!L:L,磅单!F:F,B60) -> 168.56 | H60: =SUMIFS(磅单!O:O,磅单!F:F,B60) -> 12051.06 | J60: =SUMIFS(现金充电明细!L:L,现金充电明细!B:B,B60)+SUMIFS('华瑞-曙光，大水井，老水井充电站'!L:L,'华瑞-曙光，大水井，老水井充电站'!B:B,B60)+SUMIFS('银盛-青龙坪充电站'!L:L,'银盛-青龙坪充电站'!B:B,B60)+SUMIFS('砚山锦佳-砚山充电站'!K:K,'砚山锦佳-砚山充电站'!B:B,B60)+SUMIFS(中石油广西百色靖西市龙临加油充电站!K:K,中石油广西百色靖西市龙临加油充电站!B:B,B60)+SUMIFS(德保众擎充电站!L:L,德保众擎充电站!B:B,B60)+SUMIFS(南网八宝充电站!K:K,南网八宝充电站!B:B,B60)+SUMIFS(南屏充电站!K:K,南屏充电站!B:B,B60)+SUMIFS(鑫鸿充电站!K:K,鑫鸿充电站!B:B,B60)+SUMIFS('锦田-百色田东充电站'!K:K,'锦田-百色田东充电站'!B:B,B60)+37.06/47+SUMIFS(平远充电站!K:K,平远充电站!B:B,B60) -> 5765.5309 | N60: =13473.8/61 -> 220.88197 | O60: =SUMIFS(轮胎!H:H,轮胎!D:D,B60)+SUMIFS(轮胎!H:H,轮胎!D:D,C60) -> 950 | P60: 0 | Q60: =SUMIFS(维修费!E:E,维修费!C:C,B60)+SUMIFS(维修费!E:E,维修费!C:C,C60) -> 60 | R60: =SUMIFS(磅单!R:R,磅单!F:F,B60) -> 2800 | S60: =SUMIFS(司机工资表!E:E,司机工资表!B:B,D60)+SUMIFS(司机工资表!N:N,司机工资表!B:B,D60) -> 0 | T60: =SUMIFS(付款明细!G:G,付款明细!D:D,B60,付款明细!B:B,"车队-罚款") -> 0 | U60: =SUMIFS(付款明细!G:G,付款明细!D:D,B60,付款明细!B:B,"车辆费用")+SUMIFS(付款明细!G:G,付款明细!D:D,C60,付款明细!B:B,"车辆费用") -> 105.5 | V60: =SUMIFS(付款明细!G:G,付款明细!B:B,"综合费用")/61 -> 397.39246 | W60: 2666 | X60: 3600 | Y60: =SUMIFS(磅单!P:P,磅单!E:E,B60) -> 60 | Z60: =H60*0.07-M60 -> 843.5742 | AC60: =(管理人员工资!$D$10+管理人员工资!$E$10)/61 -> 790.16393 | AD60: =H60-I60-J60-N60-O60-R60-S60-T60-U60-V60-W60-AA60-AB60-AC60-Q60-P60-Z60-Y60-X60 -> -6207.9835
A61: 59 | B61: 粤B95641D | C61: 桂L2510挂 | E61: 整备 | F61: =COUNTIFS(磅单!E:E,B61) -> 3 | G61: =SUMIFS(磅单!L:L,磅单!F:F,B61) -> 124.5 | H61: =SUMIFS(磅单!O:O,磅单!F:F,B61) -> 9134.22 | J61: =SUMIFS(现金充电明细!L:L,现金充电明细!B:B,B61)+SUMIFS('华瑞-曙光，大水井，老水井充电站'!L:L,'华瑞-曙光，大水井，老水井充电站'!B:B,B61)+SUMIFS('银盛-青龙坪充电站'!L:L,'银盛-青龙坪充电站'!B:B,B61)+SUMIFS('砚山锦佳-砚山充电站'!K:K,'砚山锦佳-砚山充电站'!B:B,B61)+SUMIFS(中石油广西百色靖西市龙临加油充电站!K:K,中石油广西百色靖西市龙临加油充电站!B:B,B61)+SUMIFS(德保众擎充电站!L:L,德保众擎充电站!B:B,B61)+SUMIFS(南网八宝充电站!K:K,南网八宝充电站!B:B,B61)+SUMIFS(南屏充电站!K:K,南屏充电站!B:B,B61)+SUMIFS(鑫鸿充电站!K:K,鑫鸿充电站!B:B,B61)+SUMIFS('锦田-百色田东充电站'!K:K,'锦田-百色田东充电站'!B:B,B61)+37.06/47+SUMIFS(平远充电站!K:K,平远充电站!B:B,B61) -> 5409.4885 | N61: =13473.8/61 -> 220.88197 | O61: =SUMIFS(轮胎!H:H,轮胎!D:D,B61)+SUMIFS(轮胎!H:H,轮胎!D:D,C61) -> 0 | P61: 0 | Q61: =SUMIFS(维修费!E:E,维修费!C:C,B61)+SUMIFS(维修费!E:E,维修费!C:C,C61) -> 150 | R61: =SUMIFS(磅单!R:R,磅单!F:F,B61) -> 2200 | S61: =SUMIFS(司机工资表!E:E,司机工资表!B:B,D61)+SUMIFS(司机工资表!N:N,司机工资表!B:B,D61) -> 0 | T61: =SUMIFS(付款明细!G:G,付款明细!D:D,B61,付款明细!B:B,"车队-罚款") -> 0 | U61: =SUMIFS(付款明细!G:G,付款明细!D:D,B61,付款明细!B:B,"车辆费用")+SUMIFS(付款明细!G:G,付款明细!D:D,C61,付款明细!B:B,"车辆费用") -> 90.5 | V61: =SUMIFS(付款明细!G:G,付款明细!B:B,"综合费用")/61 -> 397.39246 | W61: 2666 | X61: 3600 | Y61: =SUMIFS(磅单!P:P,磅单!E:E,B61) -> 45 | Z61: =H61*0.07-M61 -> 639.3954 | AC61: =(管理人员工资!$D$10+管理人员工资!$E$10)/61 -> 790.16393 | AD61: =H61-I61-J61-N61-O61-R61-S61-T61-U61-V61-W61-AA61-AB61-AC61-Q61-P61-Z61-Y61-X61 -> -7074.6023
A62: 60 | B62: 粤B94058D | E62: 整备 | F62: =COUNTIFS(磅单!E:E,B62) -> 0 | J62: =SUMIFS(现金充电明细!L:L,现金充电明细!B:B,B62)+SUMIFS('华瑞-曙光，大水井，老水井充电站'!L:L,'华瑞-曙光，大水井，老水井充电站'!B:B,B62)+SUMIFS('银盛-青龙坪充电站'!L:L,'银盛-青龙坪充电站'!B:B,B62)+SUMIFS('砚山锦佳-砚山充电站'!K:K,'砚山锦佳-砚山充电站'!B:B,B62)+SUMIFS(中石油广西百色靖西市龙临加油充电站!K:K,中石油广西百色靖西市龙临加油充电站!B:B,B62)+SUMIFS(德保众擎充电站!L:L,德保众擎充电站!B:B,B62)+SUMIFS(南网八宝充电站!K:K,南网八宝充电站!B:B,B62)+SUMIFS(南屏充电站!K:K,南屏充电站!B:B,B62)+SUMIFS(鑫鸿充电站!K:K,鑫鸿充电站!B:B,B62)+SUMIFS('锦田-百色田东充电站'!K:K,'锦田-百色田东充电站'!B:B,B62)+37.06/47+SUMIFS(平远充电站!K:K,平远充电站!B:B,B62) -> 800.29851 | N62: =13473.8/61 -> 220.88197 | O62: =SUMIFS(轮胎!H:H,轮胎!D:D,B62)+SUMIFS(轮胎!H:H,轮胎!D:D,C62) -> 0 | Q62: =SUMIFS(维修费!E:E,维修费!C:C,B62)+SUMIFS(维修费!E:E,维修费!C:C,C62) -> 0 | U62: =SUMIFS(付款明细!G:G,付款明细!D:D,B62,付款明细!B:B,"车辆费用")+SUMIFS(付款明细!G:G,付款明细!D:D,C62,付款明细!B:B,"车辆费用") -> 0 | V62: =SUMIFS(付款明细!G:G,付款明细!B:B,"综合费用")/61 -> 397.39246 | AC62: =(管理人员工资!$D$10+管理人员工资!$E$10)/61 -> 790.16393 | AD62: =H62-I62-J62-N62-O62-R62-S62-T62-U62-V62-W62-AA62-AB62-AC62-Q62-P62-Z62-Y62-X62 -> -2208.7369
A63: 合计 | F63: =SUM(F3:F62) -> 766 | G63: =SUM(G3:G62) -> 32190.01 | H63: =SUM(H3:H62) -> 2102541.8 | I63: =SUM(I3:I62) -> 350 | J63: =SUM(J3:J62) -> 701940.49 | K63: =SUM(K3:K62) -> 19.052749 | L63: =SUM(L3:L62) -> 54041.766 | M63: =SUM(M3:M62) -> 0 | ... AD63: =SUM(AD3:AD62) -> -274397.61
A66: 序号 | B66: 车牌 | C66: 挂板 | D66: 司机 | E66: 车辆状态 | F66: 趟数 | G66: 卸货吨位 | H66: 含税产值 | I66: 磅差金额 | J66: 电费 | K66: 电费占比 | L66: 单趟电耗 | M66: 电费税点 | N66: 配件费 | O66: 轮胎费 | P66: 高速费 | Q66: 维修费 | R66: 提成工资 | S66: 补助 | T66: 罚款 | U66: 车辆费用 | V66: 均摊 | W66: 车辆保险 | X66: 前期费用 | Y66: 货物险 | Z66: 税点 | AA66: 贷款 | AB66: 挂板租金/贷款 | AC66: 管理人员工资 | AD66: 利润
A67: 1 | B67: 云F03990D | E67: 正常 | F67: =COUNTIFS(磅单!E:E,B67) -> 7 | G67: =SUMIFS(磅单!L:L,磅单!F:F,B67) -> 288.78 | H67: =SUMIFS(磅单!O:O,磅单!F:F,B67) -> 16681.4 | J67: =SUMIFS(现金充电明细!L:L,现金充电明细!B:B,B67)+SUMIFS('华瑞-曙光，大水井，老水井充电站'!L:L,'华瑞-曙光，大水井，老水井充电站'!B:B,B67)+SUMIFS('银盛-青龙坪充电站'!L:L,'银盛-青龙坪充电站'!B:B,B67)+SUMIFS('砚山锦佳-砚山充电站'!K:K,'砚山锦佳-砚山充电站'!B:B,B67)+SUMIFS(中石油广西百色靖西市龙临加油充电站!K:K,中石油广西百色靖西市龙临加油充电站!B:B,B67)+SUMIFS(德保众擎充电站!L:L,德保众擎充电站!B:B,B67)+SUMIFS(南网八宝充电站!K:K,南网八宝充电站!B:B,B67)+SUMIFS(南屏充电站!K:K,南屏充电站!B:B,B67)+SUMIFS(鑫鸿充电站!K:K,鑫鸿充电站!B:B,B67)+SUMIFS('锦田-百色田东充电站'!K:K,'锦田-百色田东充电站'!B:B,B67)+37.06/47+SUMIFS(平远充电站!K:K,平远充电站!B:B,B67) -> 5341.5002 | K67: =J67/(H67) -> 0.32020695 | L67: =J67/F67 -> 763.07146 | N67: =13473.8/61 -> 220.88197 | O67: =SUMIFS(轮胎!H:H,轮胎!D:D,B67)+SUMIFS(轮胎!H:H,轮胎!C:C,C67) -> 0 | P67: 0 | Q67: =SUMIFS(维修费!E:E,维修费!C:C,B67)+SUMIFS(维修费!E:E,维修费!C:C,C67) -> 60 | R67: =SUMIFS(磅单!R:R,磅单!F:F,B67) -> 4200 | S67: =SUMIFS(司机工资表!E:E,司机工资表!B:B,D67)+SUMIFS(司机工资表!N:N,司机工资表!B:B,D67) -> 0 | T67: =SUMIFS(付款明细!G:G,付款明细!D:D,B67,付款明细!B:B,"车队-罚款") -> 0 | U67: =SUMIFS(付款明细!G:G,付款明细!D:D,B67,付款明细!B:B,"车辆费用")+SUMIFS(付款明细!G:G,付款明细!D:D,C67,付款明细!B:B,"车辆费用") -> 855.4 | V67: =SUMIFS(付款明细!G:G,付款明细!B:B,"综合费用")/61 -> 397.39246 | Y67: =SUMIFS(磅单!P:P,磅单!E:E,B67) -> 105 | Z67: =H67*0.07-M67 -> 1167.698 | AB67: =3800/30*18 -> 2280 | AC67: =(管理人员工资!$D$10+管理人员工资!$E$10)/61 -> 790.16393 | AD67: =H67+I67-J67-N67-O67-R67-S67-T67-U67-V67-W67-AA67-AB67-AC67-Q67-P67-Z67-Y67-X67-M67 -> 1263.3634
A68: 合计 | F68: =SUM(F67:F67) -> 7 | G68: =SUM(G67:G67) -> 288.78 | H68: =SUM(H67:H67) -> 16681.4 | I68: =SUM(I67:I67) -> 0 | J68: =SUM(J67:J67) -> 5341.5002 | K68: =SUM(K67:K67) -> 0.32020695 | L68: =SUM(L67:L67) -> 763.07146 | M68: =SUM(M67:M67) -> 0 | ... AD68: =SUM(AD67:AD67) -> 1263.3634
A70: 电耗比例
A71: 序号 | B71: 车牌 | C71: 挂板 | E71: 车辆状态 | F71: 趟数 | G71: 卸货吨位 | H71: 产值 | I71: 油/电费 | J71: 电费占比 | K71: 单趟电耗
A72: 1 | B72: 赣J01379D | E72: 正常 | F72: =F3 -> 1 | G72: =G3 -> 41.74 | H72: =I3+H3 -> 2546.14 | I72: =J3 -> 1091.9085 | J72: =I72/H72 -> 0.42884857 | K72: =I72/F72 -> 1091.9085
A73: 2 | B73: 赣J00236D | E73: 正常 | F73: =F4 -> 19 | G73: =G4 -> 805.2 | H73: =I4+H4 -> 50229.42 | I73: =J4 -> 16063.773 | J73: =I73/H73 -> 0.31980805 | K73: =I73/F73 -> 845.46174
A74: 3 | B74: 赣J05550D | E74: 正常 | F74: =F5 -> 21 | G74: =G5 -> 893.18 | H74: =I5+H5 -> 55301.38 | I74: =J5 -> 17389.021 | J74: =I74/H74 -> 0.31444099 | K74: =I74/F74 -> 828.0486
A75: 4 | B75: 赣J00607D | E75: 正常 | F75: =F6 -> 19 | G75: =G6 -> 782.99 | H75: =I6+H6 -> 46796.27 | I75: =J6 -> 15004.904 | J75: =I75/H75 -> 0.32064315 | K75: =I75/F75 -> 789.73177
A76: 5 | B76: 赣J00677D | E76: 正常 | F76: =F7 -> 20 | G76: =G7 -> 820.18 | H76: =I7+H7 -> 50925.58 | I76: =J7 -> 16613.933 | J76: =I76/H76 -> 0.32623944 | K76: =I76/F76 -> 830.69663
A77: 6 | B77: 赣J01095D | E77: 正常 | F77: =F8 -> 19 | G77: =G8 -> 769.79 | H77: =I8+H8 -> 48095.53 | I77: =J8 -> 14132.489 | J77: =I77/H77 -> 0.29384204 | K77: =I77/F77 -> 743.81519
A78: 7 | B78: 赣J03136D | E78: 正常 | F78: =F9 -> 18 | G78: =G9 -> 789.79 | H78: =I9+H9 -> 48659.05 | I78: =J9 -> 15027.95 | J78: =I78/H78 -> 0.30884183 | K78: =I78/F78 -> 834.88612
A79: 8 | B79: 赣J03688D | E79: 正常 | F79: =F10 -> 22 | G79: =G10 -> 928.88 | H79: =I10+H10 -> 58792.78 | I79: =J10 -> 16765.748 | J79: =I79/H79 -> 0.28516679 | K79: =I79/F79 -> 762.07948
A80: 9 | B80: 赣J07535D | E80: 正常 | F80: =F11 -> 21 | G80: =G11 -> 874.61 | H80: =I11+H11 -> 55429.23 | I80: =J11 -> 14114.09 | J80: =I80/H80 -> 0.25463261 | K80: =I80/F80 -> 672.0995
A81: 10 | B81: 赣J08536D | E81: 正常 | F81: =F12 -> 16 | G81: =G12 -> 673.98 | H81: =I12+H12 -> 44638.62 | I81: =J12 -> 15202.365 | J81: =I81/H81 -> 0.34056531 | K81: =I81/F81 -> 950.14784
A82: 11 | B82: 赣J05857D | E82: 正常 | F82: =F13 -> 19 | G82: =G13 -> 798.41 | H82: =I13+H13 -> 48640.05 | I82: =J13 -> 14817.425 | J82: =I82/H82 -> 0.30463425 | K82: =I82/F82 -> 779.86447
A83: 12 | B83: 赣J06519D | E83: 正常 | F83: =F14 -> 25 | G83: =G14 -> 1015.87 | H83: =I14+H14 -> 64387.11 | I83: =J14 -> 20084.735 | J83: =I83/H83 -> 0.3119372 | K83: =I83/F83 -> 803.3894
... A97: 26 | B97: 赣J05379D | E97: 正常 | F97: =F28 -> 17 | G97: =G28 -> 685.49 | H97: =I28+H28 -> 44863.27 | I97: =J28 -> 14525.358 | J97: =I97/H97 -> 0.32376949 | K97: =I97/F97 -> 854.43282
A98: 合计 | F98: =SUM(F72:F97) -> 456 | G98: =SUM(G72:G97) -> 18954.98 | H98: =SUM(H72:H97) -> 1192190.7 | I98: =SUM(I72:I97) -> 369135.63

Sheet 日报表
A1: =YEAR(Y2)&"年玉溪广西"&MONTH(Y2)&"月"&DAY(Y2)&"日报汇总表" -> 2026年玉溪广西6月28日报汇总表
A2: 序号 | B2: 车牌 | C2: 挂板 | D2: 日期 | E2: 趟数 | F2: 卸货吨位 | G2: 含税产值 | H2: 货物险 | I2: 电费 | J2: 配件费 | K2: 轮胎费 | L2: 高速费 | M2: 维修费 | N2: 提成工资 | O2: 基本工资 | P2: 罚款 | Q2: 车辆费用 | R2: 综合费用 | S2: 车辆保险 | T2: 挂板租金 | U2: 车头租金 | V2: 税点 | W2: 管理人员工资 | X2: 利润 | Y2: 46201
A3: 1 | B3: 赣J01379D | C3: 桂LD735挂 | D3: =$Y$2 -> 46201 | E3: =COUNTIFS(磅单!E:E,B:B,磅单!B:B,D:D) -> 0 | F3: =SUMIFS(磅单!L:L,磅单!F:F,B:B,磅单!B:B,D:D) -> 0 | G3: =SUMIFS(磅单!O:O,磅单!F:F,B3,磅单!B:B,D3) -> 0 | H3: =SUMIFS(磅单!P:P,磅单!F:F,B:B,磅单!B:B,D:D) -> 0 | I3: =SUMIFS(现金充电明细!L:L,现金充电明细!B:B,B:B,现金充电明细!A:A,D:D)+SUMIFS('华瑞-曙光，大水井，老水井充电站'!L:L,'华瑞-曙光，大水井，老水井充电站'!B:B,B:B,'华瑞-曙光，大水井，老水井充电站'!A:A,D:D)+SUMIFS('银盛-青龙坪充电站'!L:L,'银盛-青龙坪充电站'!B:B,B:B,'银盛-青龙坪充电站'!A:A,D:D)+SUMIFS('砚山锦佳-砚山充电站'!K:K,'砚山锦佳-砚山充电站'!B:B,B:B,'砚山锦佳-砚山充电站'!A:A,D:D)+SUMIFS(中石油广西百色靖西市龙临加油充电站!K:K,中石油广西百色靖西市龙临加油充电站!B:B,B:B,中石油广西百色靖西市龙临加油充电站!A:A,D:D)+SUMIFS(德保众擎充电站!L:L,德保众擎充电站!B:B,B:B,德保众擎充电站!A:A,D:D)+SUMIFS(南网八宝充电站!K:K,南网八宝充电站!B:B,B:B,南网八宝充电站!A:A,D:D)+SUMIFS(南屏充电站!K:K,南屏充电站!B:B,B:B,南屏充电站!A:A,D:D)+SUMIFS(鑫鸿充电站!K:K,鑫鸿充电站!B:B,B:B,鑫鸿充电站!A:A,D:D)+SUMIFS('锦田-百色田东充电站'!K:K,'锦田-百色田东充电站'!B:B,C:C,'锦田-百色田东充电站'!A:A,D:D)+SUMIFS(平远充电站!K:K,平远充电站!B:B,B3,平远充电站!A:A,D3) -> 0 | J3: =SUMIFS(付款明细!G:G,付款明细!D:D,B:B,付款明细!A:A,D:D,付款明细!B:B,J2) -> 0 | K3: =SUMIFS(轮胎!H:H,轮胎!C:C,B:B,轮胎!A:A,D:D) -> 0 | L3: 0 | M3: =SUMIFS(维修费!E:E,维修费!C:C,B:B,维修费!A:A,D:D) -> 0 | N3: =SUMIFS(磅单!R:R,磅单!F:F,B:B,磅单!B:B,D:D) -> 0 | O3: 0 | P3: =SUMIFS(付款明细!G:G,付款明细!D:D,B:B,付款明细!A:A,D:D,付款明细!B:B,"车队-罚款") -> 0 | Q3: =SUMIFS(付款明细!G:G,付款明细!D:D,B:B,付款明细!A:A,D:D,付款明细!B:B,"车辆费用") -> 0 | R3: =SUMIFS(付款明细!G:G,付款明细!A:A,D:D,付款明细!B:B,"综合费用")/61 -> 0 | S3: =32000/12/30 -> 88.888889 | T3: =3800/30 -> 126.66667 | U3: =10600/30 -> 353.33333 | V3: =G3*0.07 -> 0 | W3: =48200/30/61 -> 26.338798 | X3: =G3-I3-J3-K3-L3-M3-N3-O3-P3-Q3-R3-S3-U3-V3-W3-T3-H3 -> -595.22769
A4: 2 | B4: 赣J00236D | C4: 桂LA725挂 | D4: =$Y$2 -> 46201 | E4: =COUNTIFS(磅单!E:E,B:B,磅单!B:B,D:D) -> 1 | F4: =SUMIFS(磅单!L:L,磅单!F:F,B:B,磅单!B:B,D:D) -> 39.98 | G4: =SUMIFS(磅单!O:O,磅单!F:F,B4,磅单!B:B,D4) -> 3018.64 | H4: =SUMIFS(磅单!P:P,磅单!F:F,B:B,磅单!B:B,D:D) -> 15 | I4: =SUMIFS(现金充电明细!L:L,现金充电明细!B:B,B:B,现金充电明细!A:A,D:D)+SUMIFS('华瑞-曙光，大水井，老水井充电站'!L:L,'华瑞-曙光，大水井，老水井充电站'!B:B,B:B,'华瑞-曙光，大水井，老水井充电站'!A:A,D:D)+SUMIFS('银盛-青龙坪充电站'!L:L,'银盛-青龙坪充电站'!B:B,B:B,'银盛-青龙坪充电站'!A:A,D:D)+SUMIFS('砚山锦佳-砚山充电站'!K:K,'砚山锦佳-砚山充电站'!B:B,B:B,'砚山锦佳-砚山充电站'!A:A,D:D)+SUMIFS(中石油广西百色靖西市龙临加油充电站!K:K,中石油广西百色靖西市龙临加油充电站!B:B,B:B,中石油广西百色靖西市龙临加油充电站!A:A,D:D)+SUMIFS(德保众擎充电站!L:L,德保众擎充电站!B:B,B:B,德保众擎充电站!A:A,D:D)+SUMIFS(南网八宝充电站!K:K,南网八宝充电站!B:B,B:B,南网八宝充电站!A:A,D:D)+SUMIFS(南屏充电站!K:K,南屏充电站!B:B,B:B,南屏充电站!A:A,D:D)+SUMIFS(鑫鸿充电站!K:K,鑫鸿充电站!B:B,B:B,鑫鸿充电站!A:A,D:D)+SUMIFS('锦田-百色田东充电站'!K:K,'锦田-百色田东充电站'!B:B,C:C,'锦田-百色田东充电站'!A:A,D:D)+SUMIFS(平远充电站!K:K,平远充电站!B:B,B4,平远充电站!A:A,D4) -> 286.05 | J4: =SUMIFS(付款明细!G:G,付款明细!D:D,B:B,付款明细!A:A,D:D,付款明细!B:B,J3) -> 0 | K4: =SUMIFS(轮胎!H:H,轮胎!C:C,B:B,轮胎!A:A,D:D) -> 0 | L4: 0 | M4: =SUMIFS(维修费!E:E,维修费!C:C,B:B,维修费!A:A,D:D) -> 0 | N4: =SUMIFS(磅单!R:R,磅单!F:F,B:B,磅单!B:B,D:D) -> 800 | O4: 0 | P4: =SUMIFS(付款明细!G:G,付款明细!D:D,B:B,付款明细!A:A,D:D,付款明细!B:B,"车队-罚款") -> 0 | Q4: =SUMIFS(付款明细!G:G,付款明细!D:D,B:B,付款明细!A:A,D:D,付款明细!B:B,"车辆费用") -> 0 | R4: =SUMIFS(付款明细!G:G,付款明细!A:A,D:D,付款明细!B:B,"综合费用")/61 -> 0 | S4: =32000/12/30 -> 88.888889 | T4: =3800/30 -> 126.66667 | U4: =10600/30 -> 353.33333 | V4: =G4*0.07 -> 211.3048 | W4: =48200/30/61 -> 26.338798 | X4: =G4-I4-J4-K4-L4-M4-N4-O4-P4-Q4-R4-S4-U4-V4-W4-T4-H4 -> 1111.0575
A5: 3 | B5: 赣J05550D | C5: 桂LD517挂 | D5: =$Y$2 -> 46201 | E5: =COUNTIFS(磅单!E:E,B:B,磅单!B:B,D:D) -> 1 | F5: =SUMIFS(磅单!L:L,磅单!F:F,B:B,磅单!B:B,D:D) -> 40.94 | G5: =SUMIFS(磅单!O:O,磅单!F:F,B5,磅单!B:B,D5) -> 3042.98 | H5: =SUMIFS(磅单!P:P,磅单!F:F,B:B,磅单!B:B,D:D) -> 15 | I5: =SUMIFS(现金充电明细!L:L,现金充电明细!B:B,B:B,现金充电明细!A:A,D:D)+SUMIFS('华瑞-曙光，大水井，老水井充电站'!L:L,'华瑞-曙光，大水井，老水井充电站'!B:B,B:B,'华瑞-曙光，大水井，老水井充电站'!A:A,D:D)+SUMIFS('银盛-青龙坪充电站'!L:L,'银盛-青龙坪充电站'!B:B,B:B,'银盛-青龙坪充电站'!A:A,D:D)+SUMIFS('砚山锦佳-砚山充电站'!K:K,'砚山锦佳-砚山充电站'!B:B,B:B,'砚山锦佳-砚山充电站'!A:A,D:D)+SUMIFS(中石油广西百色靖西市龙临加油充电站!K:K,中石油广西百色靖西市龙临加油充电站!B:B,B:B,中石油广西百色靖西市龙临加油充电站!A:A,D:D)+SUMIFS(德保众擎充电站!L:L,德保众擎充电站!B:B,B:B,德保众擎充电站!A:A,D:D)+SUMIFS(南网八宝充电站!K:K,南网八宝充电站!B:B,B:B,南网八宝充电站!A:A,D:D)+SUMIFS(南屏充电站!K:K,南屏充电站!B:B,B:B,南屏充电站!A:A,D:D)+SUMIFS(鑫鸿充电站!K:K,鑫鸿充电站!B:B,B:B,鑫鸿充电站!A:A,D:D)+SUMIFS('锦田-百色田东充电站'!K:K,'锦田-百色田东充电站'!B:B,C:C,'锦田-百色田东充电站'!A:A,D:D)+SUMIFS(平远充电站!K:K,平远充电站!B:B,B5,平远充电站!A:A,D5) -> 300.96 | J5: =SUMIFS(付款明细!G:G,付款明细!D:D,B:B,付款明细!A:A,D:D,付款明细!B:B,J4) -> 0 | K5: =SUMIFS(轮胎!H:H,轮胎!C:C,B:B,轮胎!A:A,D:D) -> 0 | L5: 0 | M5: =SUMIFS(维修费!E:E,维修费!C:C,B:B,维修费!A:A,D:D) -> 0 | N5: =SUMIFS(磅单!R:R,磅单!F:F,B:B,磅单!B:B,D:D) -> 800 | O5: 0 | P5: =SUMIFS(付款明细!G:G,付款明细!D:D,B:B,付款明细!A:A,D:D,付款明细!B:B,"车队-罚款") -> 0 | Q5: =SUMIFS(付款明细!G:G,付款明细!D:D,B:B,付款明细!A:A,D:D,付款明细!B:B,"车辆费用") -> 0 | R5: =SUMIFS(付款明细!G:G,付款明细!A:A,D:D,付款明细!B:B,"综合费用")/61 -> 0 | S5: =32000/12/30 -> 88.888889 | T5: =3800/30 -> 126.66667 | U5: =10600/30 -> 353.33333 | V5: =G5*0.07 -> 213.0086 | W5: =48200/30/61 -> 26.338798 | X5: =G5-I5-J5-K5-L5-M5-N5-O5-P5-Q5-R5-S5-U5-V5-W5-T5-H5 -> 1118.7837
A6: 4 | B6: 赣J00607D | C6: 桂LD396挂 | D6: =$Y$2 -> 46201 | E6: =COUNTIFS(磅单!E:E,B:B,磅单!B:B,D:D) -> 0 | F6: =SUMIFS(磅单!L:L,磅单!F:F,B:B,磅单!B:B,D:D) -> 0 | G6: =SUMIFS(磅单!O:O,磅单!F:F,B6,磅单!B:B,D6) -> 0 | H6: =SUMIFS(磅单!P:P,磅单!F:F,B:B,磅单!B:B,D:D) -> 0 | I6: =SUMIFS(现金充电明细!L:L,现金充电明细!B:B,B:B,现金充电明细!A:A,D:D)+SUMIFS('华瑞-曙光，大水井，老水井充电站'!L:L,'华瑞-曙光，大水井，老水井充电站'!B:B,B:B,'华瑞-曙光，大水井，老水井充电站'!A:A,D:D)+SUMIFS('银盛-青龙坪充电站'!L:L,'银盛-青龙坪充电站'!B:B,B:B,'银盛-青龙坪充电站'!A:A,D:D)+SUMIFS('砚山锦佳-砚山充电站'!K:K,'砚山锦佳-砚山充电站'!B:B,B:B,'砚山锦佳-砚山充电站'!A:A,D:D)+SUMIFS(中石油广西百色靖西市龙临加油充电站!K:K,中石油广西百色靖西市龙临加油充电站!B:B,B:B,中石油广西百色靖西市龙临加油充电站!A:A,D:D)+SUMIFS(德保众擎充电站!L:L,德保众擎充电站!B:B,B:B,德保众擎充电站!A:A,D:D)+SUMIFS(南网八宝充电站!K:K,南网八宝充电站!B:B,B:B,南网八宝充电站!A:A,D:D)+SUMIFS(南屏充电站!K:K,南屏充电站!B:B,B:B,南屏充电站!A:A,D:D)+SUMIFS(鑫鸿充电站!K:K,鑫鸿充电站!B:B,B:B,鑫鸿充电站!A:A,D:D)+SUMIFS('锦田-百色田东充电站'!K:K,'锦田-百色田东充电站'!B:B,C:C,'锦田-百色田东充电站'!A:A,D:D)+SUMIFS(平远充电站!K:K,平远充电站!B:B,B6,平远充电站!A:A,D6) -> 0 | J6: =SUMIFS(付款明细!G:G,付款明细!D:D,B:B,付款明细!A:A,D:D,付款明细!B:B,J5) -> 0 | K6: =SUMIFS(轮胎!H:H,轮胎!C:C,B:B,轮胎!A:A,D:D) -> 0 | L6: 0 | M6: =SUMIFS(维修费!E:E,维修费!C:C,B:B,维修费!A:A,D:D) -> 0 | N6: =SUMIFS(磅单!R:R,磅单!F:F,B:B,磅单!B:B,D:D) -> 0 | O6: 0 | P6: =SUMIFS(付款明细!G:G,付款明细!D:D,B:B,付款明细!A:A,D:D,付款明细!B:B,"车队-罚款") -> 0 | Q6: =SUMIFS(付款明细!G:G,付款明细!D:D,B:B,付款明细!A:A,D:D,付款明细!B:B,"车辆费用") -> 0 | R6: =SUMIFS(付款明细!G:G,付款明细!A:A,D:D,付款明细!B:B,"综合费用")/61 -> 0 | S6: =32000/12/30 -> 88.888889 | T6: =3800/30 -> 126.66667 | U6: =10600/30 -> 353.33333 | V6: =G6*0.07 -> 0 | W6: =48200/30/61 -> 26.338798 | X6: =G6-I6-J6-K6-L6-M6-N6-O6-P6-Q6-R6-S6-U6-V6-W6-T6-H6 -> -595.22769
A7: 5 | B7: 赣J00677D | C7: 桂LB829挂 | D7: =$Y$2 -> 46201 | E7: =COUNTIFS(磅单!E:E,B:B,磅单!B:B,D:D) -> 0 | F7: =SUMIFS(磅单!L:L,磅单!F:F,B:B,磅单!B:B,D:D) -> 0 | G7: =SUMIFS(磅单!O:O,磅单!F:F,B7,磅单!B:B,D7) -> 0 | H7: =SUMIFS(磅单!P:P,磅单!F:F,B:B,磅单!B:B,D:D) -> 0 | I7: =SUMIFS(现金充电明细!L:L,现金充电明细!B:B,B:B,现金充电明细!A:A,D:D)+SUMIFS('华瑞-曙光，大水井，老水井充电站'!L:L,'华瑞-曙光，大水井，老水井充电站'!B:B,B:B,'华瑞-曙光，大水井，老水井充电站'!A:A,D:D)+SUMIFS('银盛-青龙坪充电站'!L:L,'银盛-青龙坪充电站'!B:B,B:B,'银盛-青龙坪充电站'!A:A,D:D)+SUMIFS('砚山锦佳-砚山充电站'!K:K,'砚山锦佳-砚山充电站'!B:B,B:B,'砚山锦佳-砚山充电站'!A:A,D:D)+SUMIFS(中石油广西百色靖西市龙临加油充电站!K:K,中石油广西百色靖西市龙临加油充电站!B:B,B:B,中石油广西百色靖西市龙临加油充电站!A:A,D:D)+SUMIFS(德保众擎充电站!L:L,德保众擎充电站!B:B,B:B,德保众擎充电站!A:A,D:D)+SUMIFS(南网八宝充电站!K:K,南网八宝充电站!B:B,B:B,南网八宝充电站!A:A,D:D)+SUMIFS(南屏充电站!K:K,南屏充电站!B:B,B:B,南屏充电站!A:A,D:D)+SUMIFS(鑫鸿充电站!K:K,鑫鸿充电站!B:B,B:B,鑫鸿充电站!A:A,D:D)+SUMIFS('锦田-百色田东充电站'!K:K,'锦田-百色田东充电站'!B:B,C:C,'锦田-百色田东充电站'!A:A,D:D)+SUMIFS(平远充电站!K:K,平远充电站!B:B,B7,平远充电站!A:A,D7) -> 672.3 | J7: =SUMIFS(付款明细!G:G,付款明细!D:D,B:B,付款明细!A:A,D:D,付款明细!B:B,J6) -> 0 | K7: =SUMIFS(轮胎!H:H,轮胎!C:C,B:B,轮胎!A:A,D:D) -> 0 | L7: 0 | M7: =SUMIFS(维修费!E:E,维修费!C:C,B:B,维修费!A:A,D:D) -> 0 | N7: =SUMIFS(磅单!R:R,磅单!F:F,B:B,磅单!B:B,D:D) -> 0 | O7: 0 | P7: =SUMIFS(付款明细!G:G,付款明细!D:D,B:B,付款明细!A:A,D:D,付款明细!B:B,"车队-罚款") -> 0 | Q7: =SUMIFS(付款明细!G:G,付款明细!D:D,B:B,付款明细!A:A,D:D,付款明细!B:B,"车辆费用") -> 0 | R7: =SUMIFS(付款明细!G:G,付款明细!A:A,D:D,付款明细!B:B,"综合费用")/61 -> 0 | S7: =32000/12/30 -> 88.888889 | T7: =3800/30 -> 126.66667 | U7: =10600/30 -> 353.33333 | V7: =G7*0.07 -> 0 | W7: =48200/30/61 -> 26.338798 | X7: =G7-I7-J7-K7-L7-M7-N7-O7-P7-Q7-R7-S7-U7-V7-W7-T7-H7 -> -1267.5277
A8: 6 | B8: 赣J01095D | C8: 桂LC705挂 | D8: =$Y$2 -> 46201 | E8: =COUNTIFS(磅单!E:E,B:B,磅单!B:B,D:D) -> 1 | F8: =SUMIFS(磅单!L:L,磅单!F:F,B:B,磅单!B:B,D:D) -> 37.96 | G8: =SUMIFS(磅单!O:O,磅单!F:F,B8,磅单!B:B,D8) -> 2881.28 | H8: =SUMIFS(磅单!P:P,磅单!F:F,B:B,磅单!B:B,D:D) -> 15 | I8: =SUMIFS(现金充电明细!L:L,现金充电明细!B:B,B:B,现金充电明细!A:A,D:D)+SUMIFS('华瑞-曙光，大水井，老水井充电站'!L:L,'华瑞-曙光，大水井，老水井充电站'!B:B,B:B,'华瑞-曙光，大水井，老水井充电站'!A:A,D:D)+SUMIFS('银盛-青龙坪充电站'!L:L,'银盛-青龙坪充电站'!B:B,B:B,'银盛-青龙坪充电站'!A:A,D:D)+SUMIFS('砚山锦佳-砚山充电站'!K:K,'砚山锦佳-砚山充电站'!B:B,B:B,'砚山锦佳-砚山充电站'!A:A,D:D)+SUMIFS(中石油广西百色靖西市龙临加油充电站!K:K,中石油广西百色靖西市龙临加油充电站!B:B,B:B,中石油广西百色靖西市龙临加油充电站!A:A,D:D)+SUMIFS(德保众擎充电站!L:L,德保众擎充电站!B:B,B:B,德保众擎充电站!A:A,D:D)+SUMIFS(南网八宝充电站!K:K,南网八宝充电站!B:B,B:B,南网八宝充电站!A:A,D:D)+SUMIFS(南屏充电站!K:K,南屏充电站!B:B,B:B,南屏充电站!A:A,D:D)+SUMIFS(鑫鸿充电站!K:K,鑫鸿充电站!B:B,B:B,鑫鸿充电站!A:A,D:D)+SUMIFS('锦田-百色田东充电站'!K:K,'锦田-百色田东充电站'!B:B,C:C,'锦田-百色田东充电站'!A:A,D:D)+SUMIFS(平远充电站!K:K,平远充电站!B:B,B8,平远充电站!A:A,D8) -> 488.52 | J8: =SUMIFS(付款明细!G:G,付款明细!D:D,B:B,付款明细!A:A,D:D,付款明细!B:B,J7) -> 0 | K8: =SUMIFS(轮胎!H:H,轮胎!C:C,B:B,轮胎!A:A,D:D) -> 0 | L8: 0 | M8: =SUMIFS(维修费!E:E,维修费!C:C,B:B,维修费!A:A,D:D) -> 0 | N8: =SUMIFS(磅单!R:R,磅单!F:F,B:B,磅单!B:B,D:D) -> 800 | O8: 0 | P8: =SUMIFS(付款明细!G:G,付款明细!D:D,B:B,付款明细!A:A,D:D,付款明细!B:B,"车队-罚款") -> 0 | Q8: =SUMIFS(付款明细!G:G,付款明细!D:D,B:B,付款明细!A:A,D:D,付款明细!B:B,"车辆费用") -> 10 | R8: =SUMIFS(付款明细!G:G,付款明细!A:A,D:D,付款明细!B:B,"综合费用")/61 -> 0 | S8: =32000/12/30 -> 88.888889 | T8: =3800/30 -> 126.66667 | U8: =10600/30 -> 353.33333 | V8: =G8*0.07 -> 201.6896 | W8: =48200/30/61 -> 26.338798 | X8: =G8-I8-J8-K8-L8-M8-N8-O8-P8-Q8-R8-S8-U8-V8-W8-T8-H8 -> 770.84271
A9: 7 | B9: 赣J03136D | C9: 桂L9856挂 | D9: =$Y$2 -> 46201 | E9: =COUNTIFS(磅单!E:E,B:B,磅单!B:B,D:D) -> 0 | F9: =SUMIFS(磅单!L:L,磅单!F:F,B:B,磅单!B:B,D:D) -> 0 | G9: =SUMIFS(磅单!O:O,磅单!F:F,B9,磅单!B:B,D9) -> 0 | H9: =SUMIFS(磅单!P:P,磅单!F:F,B:B,磅单!B:B,D:D) -> 0 | I9: =SUMIFS(现金充电明细!L:L,现金充电明细!B:B,B:B,现金充电明细!A:A,D:D)+SUMIFS('华瑞-曙光，大水井，老水井充电站'!L:L,'华瑞-曙光，大水井，老水井充电站'!B:B,B:B,'华瑞-曙光，大水井，老水井充电站'!A:A,D:D)+SUMIFS('银盛-青龙坪充电站'!L:L,'银盛-青龙坪充电站'!B:B,B:B,'银盛-青龙坪充电站'!A:A,D:D)+SUMIFS('砚山锦佳-砚山充电站'!K:K,'砚山锦佳-砚山充电站'!B:B,B:B,'砚山锦佳-砚山充电站'!A:A,D:D)+SUMIFS(中石油广西百色靖西市龙临加油充电站!K:K,中石油广西百色靖西市龙临加油充电站!B:B,B:B,中石油广西百色靖西市龙临加油充电站!A:A,D:D)+SUMIFS(德保众擎充电站!L:L,德保众擎充电站!B:B,B:B,德保众擎充电站!A:A,D:D)+SUMIFS(南网八宝充电站!K:K,南网八宝充电站!B:B,B:B,南网八宝充电站!A:A,D:D)+SUMIFS(南屏充电站!K:K,南屏充电站!B:B,B:B,南屏充电站!A:A,D:D)+SUMIFS(鑫鸿充电站!K:K,鑫鸿充电站!B:B,B:B,鑫鸿充电站!A:A,D:D)+SUMIFS('锦田-百色田东充电站'!K:K,'锦田-百色田东充电站'!B:B,C:C,'锦田-百色田东充电站'!A:A,D:D)+SUMIFS(平远充电站!K:K,平远充电站!B:B,B9,平远充电站!A:A,D9) -> 175.15 | J9: =SUMIFS(付款明细!G:G,付款明细!D:D,B:B,付款明细!A:A,D:D,付款明细!B:B,J8) -> 0 | K9: =SUMIFS(轮胎!H:H,轮胎!C:C,B:B,轮胎!A:A,D:D) -> 0 | L9: 0 | M9: =SUMIFS(维修费!E:E,维修费!C:C,B:B,维修费!A:A,D:D) -> 0 | N9: =SUMIFS(磅单!R:R,磅单!F:F,B:B,磅单!B:B,D:D) -> 0 | O9: 0 | P9: =SUMIFS(付款明细!G:G,付款明细!D:D,B:B,付款明细!A:A,D:D,付款明细!B:B,"车队-罚款") -> 0 | Q9: =SUMIFS(付款明细!G:G,付款明细!D:D,B:B,付款明细!A:A,D:D,付款明细!B:B,"车辆费用") -> 0 | R9: =SUMIFS(付款明细!G:G,付款明细!A:A,D:D,付款明细!B:B,"综合费用")/61 -> 0 | S9: =32000/12/30 -> 88.888889 | T9: =3800/30 -> 126.66667 | U9: =10600/30 -> 353.33333 | V9: =G9*0.07 -> 0 | W9: =48200/30/61 -> 26.338798 | X9: =G9-I9-J9-K9-L9-M9-N9-O9-P9-Q9-R9-S9-U9-V9-W9-T9-H9 -> -770.37769
A10: 8 | B10: 赣J03688D | C10: 桂LA935挂 | D10: =$Y$2 -> 46201 | E10: =COUNTIFS(磅单!E:E,B:B,磅单!B:B,D:D) -> 1 | F10: =SUMIFS(磅单!L:L,磅单!F:F,B:B,磅单!B:B,D:D) -> 40.04 | G10: =SUMIFS(磅单!O:O,磅单!F:F,B10,磅单!B:B,D10) -> 3022.72 | H10: =SUMIFS(磅单!P:P,磅单!F:F,B:B,磅单!B:B,D:D) -> 15 | I10: =SUMIFS(现金充电明细!L:L,现金充电明细!B:B,B:B,现金充电明细!A:A,D:D)+SUMIFS('华瑞-曙光，大水井，老水井充电站'!L:L,'华瑞-曙光，大水井，老水井充电站'!B:B,B:B,'华瑞-曙光，大水井，老水井充电站'!A:A,D:D)+SUMIFS('银盛-青龙坪充电站'!L:L,'银盛-青龙坪充电站'!B:B,B:B,'银盛-青龙坪充电站'!A:A,D:D)+SUMIFS('砚山锦佳-砚山充电站'!K:K,'砚山锦佳-砚山充电站'!B:B,B:B,'砚山锦佳-砚山充电站'!A:A,D:D)+SUMIFS(中石油广西百色靖西市龙临加油充电站!K:K,中石油广西百色靖西市龙临加油充电站!B:B,B:B,中石油广西百色靖西市龙临加油充电站!A:A,D:D)+SUMIFS(德保众擎充电站!L:L,德保众擎充电站!B:B,B:B,德保众擎充电站!A:A,D:D)+SUMIFS(南网八宝充电站!K:K,南网八宝充电站!B:B,B:B,南网八宝充电站!A:A,D:D)+SUMIFS(南屏充电站!K:K,南屏充电站!B:B,B:B,南屏充电站!A:A,D:D)+SUMIFS(鑫鸿充电站!K:K,鑫鸿充电站!B:B,B:B,鑫鸿充电站!A:A,D:D)+SUMIFS('锦田-百色田东充电站'!K:K,'锦田-百色田东充电站'!B:B,C:C,'锦田-百色田东充电站'!A:A,D:D)+SUMIFS(平远充电站!K:K,平远充电站!B:B,B10,平远充电站!A:A,D10) -> 649.934 | J10: =SUMIFS(付款明细!G:G,付款明细!D:D,B:B,付款明细!A:A,D:D,付款明细!B:B,J9) -> 0 | K10: =SUMIFS(轮胎!H:H,轮胎!C:C,B:B,轮胎!A:A,D:D) -> 0 | L10: 0 | M10: =SUMIFS(维修费!E:E,维修费!C:C,B:B,维修费!A:A,D:D) -> 0 | N10: =SUMIFS(磅单!R:R,磅单!F:F,B:B,磅单!B:B,D:D) -> 800 | O10: 0 | P10: =SUMIFS(付款明细!G:G,付款明细!D:D,B:B,付款明细!A:A,D:D,付款明细!B:B,"车队-罚款") -> 0 | Q10: =SUMIFS(付款明细!G:G,付款明细!D:D,B:B,付款明细!A:A,D:D,付款明细!B:B,"车辆费用") -> 15 | R10: =SUMIFS(付款明细!G:G,付款明细!A:A,D:D,付款明细!B:B,"综合费用")/61 -> 0 | S10: =32000/12/30 -> 88.888889 | T10: =3800/30 -> 126.66667 | U10: =10600/30 -> 353.33333 | V10: =G10*0.07 -> 211.5904 | W10: =48200/30/61 -> 26.338798 | X10: =G10-I10-J10-K10-L10-M10-N10-O10-P10-Q10-R10-S10-U10-V10-W10-T10-H10 -> 735.96791
A11: 9 | B11: 赣J07535D | C11: 桂LB307挂 | D11: =$Y$2 -> 46201 | E11: =COUNTIFS(磅单!E:E,B:B,磅单!B:B,D:D) -> 1 | F11: =SUMIFS(磅单!L:L,磅单!F:F,B:B,磅单!B:B,D:D) -> 40.22 | G11: =SUMIFS(磅单!O:O,磅单!F:F,B11,磅单!B:B,D11) -> 3034.96 | H11: =SUMIFS(磅单!P:P,磅单!F:F,B:B,磅单!B:B,D:D) -> 15 | I11: =SUMIFS(现金充电明细!L:L,现金充电明细!B:B,B:B,现金充电明细!A:A,D:D)+SUMIFS('华瑞-曙光，大水井，老水井充电站'!L:L,'华瑞-曙光，大水井，老水井充电站'!B:B,B:B,'华瑞-曙光，大水井，老水井充电站'!A:A,D:D)+SUMIFS('银盛-青龙坪充电站'!L:L,'银盛-青龙坪充电站'!B:B,B:B,'银盛-青龙坪充电站'!A:A,D:D)+SUMIFS('砚山锦佳-砚山充电站'!K:K,'砚山锦佳-砚山充电站'!B:B,B:B,'砚山锦佳-砚山充电站'!A:A,D:D)+SUMIFS(中石油广西百色靖西市龙临加油充电站!K:K,中石油广西百色靖西市龙临加油充电站!B:B,B:B,中石油广西百色靖西市龙临加油充电站!A:A,D:D)+SUMIFS(德保众擎充电站!L:L,德保众擎充电站!B:B,B:B,德保众擎充电站!A:A,D:D)+SUMIFS(南网八宝充电站!K:K,南网八宝充电站!B:B,B:B,南网八宝充电站!A:A,D:D)+SUMIFS(南屏充电站!K:K,南屏充电站!B:B,B:B,南屏充电站!A:A,D:D)+SUMIFS(鑫鸿充电站!K:K,鑫鸿充电站!B:B,B:B,鑫鸿充电站!A:A,D:D)+SUMIFS('锦田-百色田东充电站'!K:K,'锦田-百色田东充电站'!B:B,C:C,'锦田-百色田东充电站'!A:A,D:D)+SUMIFS(平远充电站!K:K,平远充电站!B:B,B11,平远充电站!A:A,D11) -> 775.03 | J11: =SUMIFS(付款明细!G:G,付款明细!D:D,B:B,付款明细!A:A,D:D,付款明细!B:B,J10) -> 0 | K11: =SUMIFS(轮胎!H:H,轮胎!C:C,B:B,轮胎!A:A,D:D) -> 0 | L11: 0 | M11: =SUMIFS(维修费!E:E,维修费!C:C,B:B,维修费!A:A,D:D) -> 0 | N11: =SUMIFS(磅单!R:R,磅单!F:F,B:B,磅单!B:B,D:D) -> 800 | O11: 0 | P11: =SUMIFS(付款明细!G:G,付款明细!D:D,B:B,付款明细!A:A,D:D,付款明细!B:B,"车队-罚款") -> 0 | Q11: =SUMIFS(付款明细!G:G,付款明细!D:D,B:B,付款明细!A:A,D:D,付款明细!B:B,"车辆费用") -> 0 | R11: =SUMIFS(付款明细!G:G,付款明细!A:A,D:D,付款明细!B:B,"综合费用")/61 -> 0 | S11: =32000/12/30 -> 88.888889 | T11: =3800/30 -> 126.66667 | U11: =10600/30 -> 353.33333 | V11: =G11*0.07 -> 212.4472 | W11: =48200/30/61 -> 26.338798 | X11: =G11-I11-J11-K11-L11-M11-N11-O11-P11-Q11-R11-S11-U11-V11-W11-T11-H11 -> 637.25511
A12: 10 | B12: 赣J08536D | C12: 桂LD179挂 | D12: =$Y$2 -> 46201 | E12: =COUNTIFS(磅单!E:E,B:B,磅单!B:B,D:D) -> 0 | F12: =SUMIFS(磅单!L:L,磅单!F:F,B:B,磅单!B:B,D:D) -> 0 | G12: =SUMIFS(磅单!O:O,磅单!F:F,B12,磅单!B:B,D12) -> 0 | H12: =SUMIFS(磅单!P:P,磅单!F:F,B:B,磅单!B:B,D:D) -> 0 | I12: =SUMIFS(现金充电明细!L:L,现金充电明细!B:B,B:B,现金充电明细!A:A,D:D)+SUMIFS('华瑞-曙光，大水井，老水井充电站'!L:L,'华瑞-曙光，大水井，老水井充电站'!B:B,B:B,'华瑞-曙光，大水井，老水井充电站'!A:A,D:D)+SUMIFS('银盛-青龙坪充电站'!L:L,'银盛-青龙坪充电站'!B:B,B:B,'银盛-青龙坪充电站'!A:A,D:D)+SUMIFS('砚山锦佳-砚山充电站'!K:K,'砚山锦佳-砚山充电站'!B:B,B:B,'砚山锦佳-砚山充电站'!A:A,D:D)+SUMIFS(中石油广西百色靖西市龙临加油充电站!K:K,中石油广西百色靖西市龙临加油充电站!B:B,B:B,中石油广西百色靖西市龙临加油充电站!A:A,D:D)+SUMIFS(德保众擎充电站!L:L,德保众擎充电站!B:B,B:B,德保众擎充电站!A:A,D:D)+SUMIFS(南网八宝充电站!K:K,南网八宝充电站!B:B,B:B,南网八宝充电站!A:A,D:D)+SUMIFS(南屏充电站!K:K,南屏充电站!B:B,B:B,南屏充电站!A:A,D:D)+SUMIFS(鑫鸿充电站!K:K,鑫鸿充电站!B:B,B:B,鑫鸿充电站!A:A,D:D)+SUMIFS('锦田-百色田东充电站'!K:K,'锦田-百色田东充电站'!B:B,C:C,'锦田-百色田东充电站'!A:A,D:D)+SUMIFS(平远充电站!K:K,平远充电站!B:B,B12,平远充电站!A:A,D12) -> 704.22 | J12: =SUMIFS(付款明细!G:G,付款明细!D:D,B:B,付款明细!A:A,D:D,付款明细!B:B,J11) -> 0 | K12: =SUMIFS(轮胎!H:H,轮胎!C:C,B:B,轮胎!A:A,D:D) -> 0 | L12: 0 | M12: =SUMIFS(维修费!E:E,维修费!C:C,B:B,维修费!A:A,D:D) -> 0 | N12: =SUMIFS(磅单!R:R,磅单!F:F,B:B,磅单!B:B,D:D) -> 0 | O12: 0 | P12: =SUMIFS(付款明细!G:G,付款明细!D:D,B:B,付款明细!A:A,D:D,付款明细!B:B,"车队-罚款") -> 0 | Q12: =SUMIFS(付款明细!G:G,付款明细!D:D,B:B,付款明细!A:A,D:D,付款明细!B:B,"车辆费用") -> 0 | R12: =SUMIFS(付款明细!G:G,付款明细!A:A,D:D,付款明细!B:B,"综合费用")/61 -> 0 | S12: =32000/12/30 -> 88.888889 | T12: =3800/30 -> 126.66667 | U12: =10600/30 -> 353.33333 | V12: =G12*0.07 -> 0 | W12: =48200/30/61 -> 26.338798 | X12: =G12-I12-J12-K12-L12-M12-N12-O12-P12-Q12-R12-S12-U12-V12-W12-T12-H12 -> -1299.4477
A13: 11 | B13: 赣J05857D | C13: 桂LB659挂 | D13: =$Y$2 -> 46201 | E13: =COUNTIFS(磅单!E:E,B:B,磅单!B:B,D:D) -> 0 | F13: =SUMIFS(磅单!L:L,磅单!F:F,B:B,磅单!B:B,D:D) -> 0 | G13: =SUMIFS(磅单!O:O,磅单!F:F,B13,磅单!B:B,D13) -> 0 | H13: =SUMIFS(磅单!P:P,磅单!F:F,B:B,磅单!B:B,D:D) -> 0 | I13: =SUMIFS(现金充电明细!L:L,现金充电明细!B:B,B:B,现金充电明细!A:A,D:D)+SUMIFS('华瑞-曙光，大水井，老水井充电站'!L:L,'华瑞-曙光，大水井，老水井充电站'!B:B,B:B,'华瑞-曙光，大水井，老水井充电站'!A:A,D:D)+SUMIFS('银盛-青龙坪充电站'!L:L,'银盛-青龙坪充电站'!B:B,B:B,'银盛-青龙坪充电站'!A:A,D:D)+SUMIFS('砚山锦佳-砚山充电站'!K:K,'砚山锦佳-砚山充电站'!B:B,B:B,'砚山锦佳-砚山充电站'!A:A,D:D)+SUMIFS(中石油广西百色靖西市龙临加油充电站!K:K,中石油广西百色靖西市龙临加油充电站!B:B,B:B,中石油广西百色靖西市龙临加油充电站!A:A,D:D)+SUMIFS(德保众擎充电站!L:L,德保众擎充电站!B:B,B:B,德保众擎充电站!A:A,D:D)+SUMIFS(南网八宝充电站!K:K,南网八宝充电站!B:B,B:B,南网八宝充电站!A:A,D:D)+SUMIFS(南屏充电站!K:K,南屏充电站!B:B,B:B,南屏充电站!A:A,D:D)+SUMIFS(鑫鸿充电站!K:K,鑫鸿充电站!B:B,B:B,鑫鸿充电站!A:A,D:D)+SUMIFS('锦田-百色田东充电站'!K:K,'锦田-百色田东充电站'!B:B,C:C,'锦田-百色田东充电站'!A:A,D:D)+SUMIFS(平远充电站!K:K,平远充电站!B:B,B13,平远充电站!A:A,D13) -> 451.2 | J13: =SUMIFS(付款明细!G:G,付款明细!D:D,B:B,付款明细!A:A,D:D,付款明细!B:B,J12) -> 0 | K13: =SUMIFS(轮胎!H:H,轮胎!C:C,B:B,轮胎!A:A,D:D) -> 0 | L13: 0 | M13: =SUMIFS(维修费!E:E,维修费!C:C,B:B,维修费!A:A,D:D) -> 0 | N13: =SUMIFS(磅单!R:R,磅单!F:F,B:B,磅单!B:B,D:D) -> 0 | O13: 0 | P13: =SUMIFS(付款明细!G:G,付款明细!D:D,B:B,付款明细!A:A,D:D,付款明细!B:B,"车队-罚款") -> 0 | Q13: =SUMIFS(付款明细!G:G,付款明细!D:D,B:B,付款明细!A:A,D:D,付款明细!B:B,"车辆费用") -> 0 | R13: =SUMIFS(付款明细!G:G,付款明细!A:A,D:D,付款明细!B:B,"综合费用")/61 -> 0 | S13: =32000/12/30 -> 88.888889 | T13: =3800/30 -> 126.66667 | U13: =10600/30 -> 353.33333 | V13: =G13*0.07 -> 0 | W13: =48200/30/61 -> 26.338798 | X13: =G13-I13-J13-K13-L13-M13-N13-O13-P13-Q13-R13-S13-U13-V13-W13-T13-H13 -> -1046.4277
A14: 12 | B14: 赣J06519D | C14: 桂L5759挂 | D14: =$Y$2 -> 46201 | E14: =COUNTIFS(磅单!E:E,B:B,磅单!B:B,D:D) -> 1 | F14: =SUMIFS(磅单!L:L,磅单!F:F,B:B,磅单!B:B,D:D) -> 40.48 | G14: =SUMIFS(磅单!O:O,磅单!F:F,B14,磅单!B:B,D14) -> 3012.16 | H14: =SUMIFS(磅单!P:P,磅单!F:F,B:B,磅单!B:B,D:D) -> 15 | I14: =SUMIFS(现金充电明细!L:L,现金充电明细!B:B,B:B,现金充电明细!A:A,D:D)+SUMIFS('华瑞-曙光，大水井，老水井充电站'!L:L,'华瑞-曙光，大水井，老水井充电站'!B:B,B:B,'华瑞-曙光，大水井，老水井充电站'!A:A,D:D)+SUMIFS('银盛-青龙坪充电站'!L:L,'银盛-青龙坪充电站'!B:B,B:B,'银盛-青龙坪充电站'!A:A,D:D)+SUMIFS('砚山锦佳-砚山充电站'!K:K,'砚山锦佳-砚山充电站'!B:B,B:B,'砚山锦佳-砚山充电站'!A:A,D:D)+SUMIFS(中石油广西百色靖西市龙临加油充电站!K:K,中石油广西百色靖西市龙临加油充电站!B:B,B:B,中石油广西百色靖西市龙临加油充电站!A:A,D:D)+SUMIFS(德保众擎充电站!L:L,德保众擎充电站!B:B,B:B,德保众擎充电站!A:A,D:D)+SUMIFS(南网八宝充电站!K:K,南网八宝充电站!B:B,B:B,南网八宝充电站!A:A,D:D)+SUMIFS(南屏充电站!K:K,南屏充电站!B:B,B:B,南屏充电站!A:A,D:D)+SUMIFS(鑫鸿充电站!K:K,鑫鸿充电站!B:B,B:B,鑫鸿充电站!A:A,D:D)+SUMIFS('锦田-百色田东充电站'!K:K,'锦田-百色田东充电站'!B:B,C:C,'锦田-百色田东充电站'!A:A,D:D)+SUMIFS(平远充电站!K:K,平远充电站!B:B,B14,平远充电站!A:A,D14) -> 849.5 | J14: =SUMIFS(付款明细!G:G,付款明细!D:D,B:B,付款明细!A:A,D:D,付款明细!B:B,J13) -> 0 | K14: =SUMIFS(轮胎!H:H,轮胎!C:C,B:B,轮胎!A:A,D:D) -> 0 | L14: 0 | M14: =SUMIFS(维修费!E:E,维修费!C:C,B:B,维修费!A:A,D:D) -> 0 | N14: =SUMIFS(磅单!R:R,磅单!F:F,B:B,磅单!B:B,D:D) -> 800 | O14: 0 | P14: =SUMIFS(付款明细!G:G,付款明细!D:D,B:B,付款明细!A:A,D:D,付款明细!B:B,"车队-罚款") -> 0 | Q14: =SUMIFS(付款明细!G:G,付款明细!D:D,B:B,付款明细!A:A,D:D,付款明细!B:B,"车辆费用") -> 15 | R14: =SUMIFS(付款明细!G:G,付款明细!A:A,D:D,付款明细!B:B,"综合费用")/61 -> 0 | S14: =32000/12/30 -> 88.888889 | T14: =3800/30 -> 126.66667 | U14: =10600/30 -> 353.33333 | V14: =G14*0.07 -> 210.8512 | W14: =48200/30/61 -> 26.338798 | X14: =G14-I14-J14-K14-L14-M14-N14-O14-P14-Q14-R14-S14-U14-V14-W14-T14-H14 -> 526.58111
